Workbook

Sheet 360
A2: ក្រុមហ៊ុន ហ្រ្តេតហ្វ៊ូល សឹលូសិន (ខេមបូឌា) ឯ.ក | J2: ក្រុមហ៊ុន ហ្រ្តេតហ្វ៊ូល សឹលូសិន (ខេមបូឌា) ឯ.ក
A3: GRATEFUL SOLUTIONS (CAMBODIA) CO.,LTD. | J3: GRATEFUL SOLUTIONS (CAMBODIA) CO.,LTD.
C4: លេខអត្តសញ្ញាណកម្ម អតប ( VATTIN ) : K008-902404873 | L4: លេខអត្តសញ្ញាណកម្ម អតប ( VATTIN ) : K008-902404873
A5: អាស័យដ្ឋាន : # 7E0 ផ្លូវបេតុង ក្រុម 7 ភូមិទួលថ្ងាន់ សង្កាត់ទួលសង្កែទី2 ខណ្ឌឬស្សីកែវ រាជធានីភ្នំពេញ | J5: អាស័យដ្ឋាន : # 7E0 ផ្លូវបេតុង ក្រុម 7 ភូមិទួលថ្ងាន់ សង្កាត់ទួលសង្កែទី2 ខណ្ឌឬស្សីកែវ រាជធានីភ្នំពេញ
A6: លេខទូរស័ព្ទ:​098​ 484 ​414 | J6: លេខទូរស័ព្ទ:​098​ 484 ​414
A9: វិក្កយបត្រអាករ | J9: វិក្កយបត្របង់ជំនួស
A10: TAX INVOICE | J10: DISBURSEMENT
A12: ឈ្មោះអតិថិជន /Customer: ជេអ អឹភែរឹល ឯ.ក | F12: លេខវិក័យប័ត្រ: /Invoice No: | I12: GS26-360 | J12: =A12 -> ឈ្មោះអតិថិជន /Customer: ជេអ អឹភែរឹល ឯ.ក | O12: លេខវិក័យប័ត្រ: /DIS-No: | R12: DIS403 | S12: E 264562
A13: JR APPAREL CO.,LTD | E13: ការបរិច្ឆេទវិក្កយបត្រ/Invoice Date: | I13: 46268 | J13: =A13 -> JR APPAREL CO.,LTD | N13: ការបរិច្ឆេទវិក្កយបត្រ/DIS-Date: | R13: =I13 -> 46268
A14: អាស័យដ្ឋាន/Address: KAOH KNOR VILLAGE PREAEK ROKA COMMUNE KANDAL | J14: =A14 -> អាស័យដ្ឋាន/Address: KAOH KNOR VILLAGE PREAEK ROKA COMMUNE KANDAL
A15: STUENG DISTRICT, KANDAL STUENG, KANDAL, CAMBODIA | J15: =A15 -> STUENG DISTRICT, KANDAL STUENG, KANDAL, CAMBODIA
A16: លេខ អ ត ប (VATTIN) : L001-902501613 | J16: =A16 -> លេខ អ ត ប (VATTIN) : L001-902501613
A17: SHIPPER: | C17: JR APPAREL CO., LTD. | J17: =A17 -> SHIPPER: | L17: =C17 -> JR APPAREL CO., LTD.
A18: CONSIGNEE : | C18: CHAPTERONE SPORTSWEAR | G18: GROSS WEIGHT: | I18: 16864.8 | J18: =A18 -> CONSIGNEE : | L18: =C18 -> CHAPTERONE SPORTSWEAR | P18: =G18 -> GROSS WEIGHT: | R18: =I18 -> 16864.8
A19: HBL: | B19: COSU6464276980 | D19: VOLUME: | E19: 1X45'HQ | H19: POL: | I19: PNH PORT | J19: =A19 -> HBL: | K19: =B19 -> COSU6464276980 | M19: VOLUME: | N19: =E19 -> 1X45'HQ | Q19: POL: | R19: =I19 -> PNH PORT
A20: PKGS: | B20: 1,150 CTNS | D20: CTNR No: | E20: CXDU2223299 | H20: POD: | I20: USA | J20: =A20 -> PKGS: | K20: =B20 -> 1,150 CTNS | M20: CTNR No: | N20: =E20 -> CXDU2223299 | Q20: POD: | R20: =I20 -> USA
G21: 4047 | P21: =G21 -> 4047
A22: ល.រ | B22: បរិយាយមុខទំនិញ | D22: បរិមាណ | E22: ឯកតា | F22: ថ្លៃឯកតា | G22: សរុប | H22: អាករ10% | I22: ថ្លៃទំនិញ | J22: ល.រ | K22: បរិយាយមុខទំនិញ | M22: បរិមាណ | N22: ឯកតា | O22: ថ្លៃឯកតា | P22: សរុប | Q22: អាករ 0% | R22: ថ្លៃទំនិញ
A23: No | B23: Description | D23: Quatity | E23: Unit | F23: Unit Price | G23: Sub. Total | H23: VAT ( 10%) | I23: Amount | J23: No | K23: Description | M23: Quatity | N23: Unit | O23: Unit Price | P23: Sub. Total | Q23: VAT ( 0%) | R23: Amount
A25: 1 | B25: កំរៃសេវាបំពេញបែបបទនាំចេញ / EXPORT PROCESSING FEE | D25: 1 | E25: 45H | F25: 242 | G25: =ROUND(F25*D25,2) -> 242 | H25: =G25*10% -> 24.2 | I25: =H25+G25 -> 266.2 | J25: 1 | K25: LOLO AT PORT | M25: 1 | N25: 45H | O25: 77 | P25: =O25*M25 -> 77 | Q25: 0 | R25: =Q25+P25 -> 77
J26: 2 | K26: CUSTOM PROCESSING FEE | M26: 1 | N26: 45H | O26: 21.25 | P26: =O26*M26 -> 21.25 | Q26: 0 | R26: =Q26+P26 -> 21.25
J27: 3 | K27: HBL FEE | M27: 1 | N27: 45H | O27: 539 | P27: =O27*M27 -> 539 | Q27: 0 | R27: =Q27+P27 -> 539
C29: សរុប SUB TOTAL | E29: KHR | F29: =$I$29*G21 -> 979374 | H29: USD | I29: =SUM(G25:G28) -> 242 | L29: សរុប SUB TOTAL | Q29: USD | R29: =SUM(R24:R28) -> 637.25
C30: អារករលើតម្លៃបន្ថែម (VAT 10%) | E30: KHR | F30: =$I$30*$G$21 -> 97937.4 | H30: USD | I30: =ROUND(SUM(H25:H28),2) -> 24.2 | L30: អារករលើតម្លៃបន្ថែម (VAT 0%) | Q30: USD | R30: 0
C31: សរុបរួម GRAND TOTAL | E31: KHR | F31: =I31*$G$21 -> 1077311.4 | H31: USD | I31: =$I$29+$I$30 -> 266.2 | L31: សរុបរួម GRAND TOTAL | Q31: USD | R31: =SUM(R29:R30) -> 637.25 | S31: =SUM(I31+R31) -> 903.45
A33: Note: Can make payment by cross cheque to: | J33: Note: Can make payment by cross cheque to:
A34: GRATEFUL SOLUTIONS (CAMBODIA) CO.,LTD. | J34: GRATEFUL SOLUTIONS (CAMBODIA) CO.,LTD.
A35: or Deposit Cash/Cheque payment to bank as below: | J35: or Deposit Cash/Cheque payment to bank as below:
A36: KB BRASAC BANK PLC | J36: KB BRASAC BANK PLC
A37: A/NAME: GRATEFUL SOLUTIONS (CAMBODIA) CO.,LTD. | J37: A/NAME: GRATEFUL SOLUTIONS (CAMBODIA) CO.,LTD.
A38: AC/NO: 033 754 230 001 | J38: AC/NO: 033 754 230 001
A47: ________________________ | G47: _______________________________ | J47: ________________________ | P47: _______________________________
A48: ហត្ថលេខា និង ឈ្មោះអ្នកទិញ | G48: ​​​​​​​​​​​ ហត្ថលេខា និង ឈ្មោះអ្នកលក់ | J48: ហត្ថលេខា និង ឈ្មោះអ្នកទិញ | P48: ​​​​​​​​​​​ ហត្ថលេខា និង ឈ្មោះអ្នកលក់
A49: សម្គាល់ច្បាប់ដើមសំរាប់អ្នកទិញច្បាប់ចំលងសំរាប់អ្នកលក់ | J49: សម្គាល់ច្បាប់ដើមសំរាប់អ្នកទិញច្បាប់ចំលងសំរាប់អ្នកលក់
A50: Note ÷ Original invoice for customer , copies invoice for seller | J50: Note ÷ Original invoice for customer , copies invoice for seller

Sheet D001
A1: DEBIT NOTE
A4: CUSTOMER | B4: : | C4: JR APPAREL CO.,LTD | F4: DN NO | G4: JR2609001
A5: ADDRESS | B5: : | C5: KAOH KNOR VILLAGE PREAEK ROKA | F5: DATE | G5: ='360'!$I$13 -> 46268
C6: COMMUNE KANDALSTUENG DISTRICT,
C7: KANDAL STUENG, KANDAL, CAMBODIA
A9: HBL NO | B9: : | C9: ='360'!$B$19 -> COSU6464276980
A10: G.W | B10: : | C10: ='360'!$I$18 -> 16864.8 | F10: POL: | G10: ='360'!$I$19 -> PNH PORT
A11: VOLUME: | B11: : | C11: ='360'!$E$19 -> 1X45'HQ | F11: POD: | G11: ='360'!$I$20 -> USA
A12: CTNR No: | B12: : | C12: ='360'!$E$20 -> CXDU2223299 | F12: PKGS: | G12: ='360'!B20 -> 1,150 CTNS
A13: Shipper | B13: : | C13: ='360'!$C$17 -> JR APPAREL CO., LTD.
A14: Consignee | B14: : | C14: ='360'!$C$18 -> CHAPTERONE SPORTSWEAR
A16: NO | C16: DESCRIPTION | D16: Q'TY | E16: U/M | F16: PRICE | G16: TOTAL | H16: ='360'!S12 -> E 264562
A17: 1 | C17: TRUCKING FEE | D17: 1 | E17: 45H | F17: 260 | G17: =ROUND(F17*D17,2) -> 260
A18: 2 | C18: HANDLING FEE | D18: 1 | E18: 45H | F18: 35 | G18: =ROUND(F18*D18,2) -> 35
A19: 3 | C19: INCREASE TRUCKING FEE(65%) | D19: 1 | E19: TRUCK | F19: 169 | G19: =ROUND(F19*D19,2) -> 169 | H19: =G17*65% -> 169
A20: 4 | C20: DOCUMENT FEE | D20: 1 | E20: SET | F20: 25 | G20: =ROUND(F20*D20,2) -> 25
A21: 5 | C21: SERVICE TAXATION | D21: 1 | E21: SHIP | F21: 20 | G21: =ROUND(F21*D21,2) -> 20
A22: 6 | C22: PETROLL ALLOWANCE FEE | D22: 1 | E22: TIME | F22: 69 | G22: =ROUND(F22*D22,2) -> 69
A23: 7 | C23: FUEL SURCHARGE | D23: 1 | E23: 45H | F23: 40 | G23: =ROUND(F23*D23,2) -> 40
A24: 8 | C24: APPLY CO FOR INV: JRA26051 | D24: 1 | E24: INV | F24: 40 | G24: =ROUND(F24*D24,2) -> 40
A25: 9 | C25: LOLO EMPTY CONTAINER | D25: 1 | E25: 45H | F25: 49.5 | G25: =ROUND(F25*D25,2) -> 49.5
D26: GRAND TOTAL: | F26: USD | G26: =SUM(G17:G25) -> 707.5
A51: Thank you for your supporting | E51: AUTHORIZED SIGNATURE

Sheet 366
A2: ក្រុមហ៊ុន ហ្រ្តេតហ្វ៊ូល សឹលូសិន (ខេមបូឌា) ឯ.ក | J2: ក្រុមហ៊ុន ហ្រ្តេតហ្វ៊ូល សឹលូសិន (ខេមបូឌា) ឯ.ក
A3: GRATEFUL SOLUTIONS (CAMBODIA) CO.,LTD. | J3: GRATEFUL SOLUTIONS (CAMBODIA) CO.,LTD.
C4: លេខអត្តសញ្ញាណកម្ម អតប ( VATTIN ) : K008-902404873 | L4: លេខអត្តសញ្ញាណកម្ម អតប ( VATTIN ) : K008-902404873
A5: អាស័យដ្ឋាន : # 7E0 ផ្លូវបេតុង ក្រុម 7 ភូមិទួលថ្ងាន់ សង្កាត់ទួលសង្កែទី2 ខណ្ឌឬស្សីកែវ រាជធានីភ្នំពេញ | J5: អាស័យដ្ឋាន : # 7E0 ផ្លូវបេតុង ក្រុម 7 ភូមិទួលថ្ងាន់ សង្កាត់ទួលសង្កែទី2 ខណ្ឌឬស្សីកែវ រាជធានីភ្នំពេញ
A6: លេខទូរស័ព្ទ:​098​ 484 ​414 | J6: លេខទូរស័ព្ទ:​098​ 484 ​414
A9: វិក្កយបត្រអាករ | J9: វិក្កយបត្របង់ជំនួស
A10: TAX INVOICE | J10: DISBURSEMENT
A12: ឈ្មោះអតិថិជន /Customer: ជេអ អឹភែរឹល ឯ.ក | F12: លេខវិក័យប័ត្រ: /Invoice No: | I12: GS26-366 | J12: =A12 -> ឈ្មោះអតិថិជន /Customer: ជេអ អឹភែរឹល ឯ.ក | O12: លេខវិក័យប័ត្រ: /DIS-No: | R12: DIS409 | S12: E 272714
A13: JR APPAREL CO.,LTD | E13: ការបរិច្ឆេទវិក្កយបត្រ/Invoice Date: | I13: 46275 | J13: =A13 -> JR APPAREL CO.,LTD | N13: ការបរិច្ឆេទវិក្កយបត្រ/DIS-Date: | R13: =I13 -> 46275
A14: អាស័យដ្ឋាន/Address: KAOH KNOR VILLAGE PREAEK ROKA COMMUNE KANDAL | J14: =A14 -> អាស័យដ្ឋាន/Address: KAOH KNOR VILLAGE PREAEK ROKA COMMUNE KANDAL
A15: STUENG DISTRICT, KANDAL STUENG, KANDAL, CAMBODIA | J15: =A15 -> STUENG DISTRICT, KANDAL STUENG, KANDAL, CAMBODIA
A16: លេខ អ ត ប (VATTIN) : L001-902501613 | J16: =A16 -> លេខ អ ត ប (VATTIN) : L001-902501613
A17: SHIPPER: | C17: JR APPAREL CO., LTD. | J17: =A17 -> SHIPPER: | L17: =C17 -> JR APPAREL CO., LTD.
A18: CONSIGNEE : | C18: CHAPTERONE SPORTSWEAR | G18: GROSS WEIGHT: | I18: 16194.3 | J18: =A18 -> CONSIGNEE : | L18: =C18 -> CHAPTERONE SPORTSWEAR | P18: =G18 -> GROSS WEIGHT: | R18: =I18 -> 16194.3
A19: HBL: | B19: COSU6464270110 | D19: VOLUME: | E19: 1X45'HQ | H19: POL: | I19: PNH PORT | J19: =A19 -> HBL: | K19: =B19 -> COSU6464270110 | M19: VOLUME: | N19: =E19 -> 1X45'HQ | Q19: POL: | R19: =I19 -> PNH PORT
A20: PKGS: | B20: 982 CTNS | D20: CTNR No: | E20: CSNU9538620 | H20: POD: | I20: USA | J20: =A20 -> PKGS: | K20: =B20 -> 982 CTNS | M20: CTNR No: | N20: =E20 -> CSNU9538620 | Q20: POD: | R20: =I20 -> USA
G21: 4052 | P21: =G21 -> 4052
A22: ល.រ | B22: បរិយាយមុខទំនិញ | D22: បរិមាណ | E22: ឯកតា | F22: ថ្លៃឯកតា | G22: សរុប | H22: អាករ10% | I22: ថ្លៃទំនិញ | J22: ល.រ | K22: បរិយាយមុខទំនិញ | M22: បរិមាណ | N22: ឯកតា | O22: ថ្លៃឯកតា | P22: សរុប | Q22: អាករ 0% | R22: ថ្លៃទំនិញ
A23: No | B23: Description | D23: Quatity | E23: Unit | F23: Unit Price | G23: Sub. Total | H23: VAT ( 10%) | I23: Amount | J23: No | K23: Description | M23: Quatity | N23: Unit | O23: Unit Price | P23: Sub. Total | Q23: VAT ( 0%) | R23: Amount
A25: 1 | B25: កំរៃសេវាបំពេញបែបបទនាំចេញ / EXPORT PROCESSING FEE | D25: 1 | E25: 45H | F25: 242 | G25: =ROUND(F25*D25,2) -> 242 | H25: =G25*10% -> 24.2 | I25: =H25+G25 -> 266.2 | J25: 1 | K25: LOLO AT PORT | M25: 1 | N25: 45H | O25: 77 | P25: =O25*M25 -> 77 | Q25: 0 | R25: =Q25+P25 -> 77
J26: 2 | K26: CUSTOM PROCESSING FEE | M26: 1 | N26: 45H | O26: 21.25 | P26: =O26*M26 -> 21.25 | Q26: 0 | R26: =Q26+P26 -> 21.25
J27: 3 | K27: HBL FEE | M27: 1 | N27: 45H | O27: 539 | P27: =O27*M27 -> 539 | Q27: 0 | R27: =Q27+P27 -> 539
C29: សរុប SUB TOTAL | E29: KHR | F29: =$I$29*G21 -> 980584 | H29: USD | I29: =SUM(G25:G28) -> 242 | L29: សរុប SUB TOTAL | Q29: USD | R29: =SUM(R24:R28) -> 637.25
C30: អារករលើតម្លៃបន្ថែម (VAT 10%) | E30: KHR | F30: =$I$30*$G$21 -> 98058.4 | H30: USD | I30: =ROUND(SUM(H25:H28),2) -> 24.2 | L30: អារករលើតម្លៃបន្ថែម (VAT 0%) | Q30: USD | R30: 0
C31: សរុបរួម GRAND TOTAL | E31: KHR | F31: =I31*$G$21 -> 1078642.4 | H31: USD | I31: =$I$29+$I$30 -> 266.2 | L31: សរុបរួម GRAND TOTAL | Q31: USD | R31: =SUM(R29:R30) -> 637.25 | S31: =SUM(I31+R31) -> 903.45
A33: Note: Can make payment by cross cheque to: | J33: Note: Can make payment by cross cheque to:
A34: GRATEFUL SOLUTIONS (CAMBODIA) CO.,LTD. | J34: GRATEFUL SOLUTIONS (CAMBODIA) CO.,LTD.
A35: or Deposit Cash/Cheque payment to bank as below: | J35: or Deposit Cash/Cheque payment to bank as below:
A36: KB BRASAC BANK PLC | J36: KB BRASAC BANK PLC
A37: A/NAME: GRATEFUL SOLUTIONS (CAMBODIA) CO.,LTD. | J37: A/NAME: GRATEFUL SOLUTIONS (CAMBODIA) CO.,LTD.
A38: AC/NO: 033 754 230 001 | J38: AC/NO: 033 754 230 001
A49: ________________________ | G49: _______________________________ | J49: ________________________ | P49: _______________________________
A50: ហត្ថលេខា និង ឈ្មោះអ្នកទិញ | G50: ​​​​​​​​​​​ ហត្ថលេខា និង ឈ្មោះអ្នកលក់ | J50: ហត្ថលេខា និង ឈ្មោះអ្នកទិញ | P50: ​​​​​​​​​​​ ហត្ថលេខា និង ឈ្មោះអ្នកលក់
A51: សម្គាល់ច្បាប់ដើមសំរាប់អ្នកទិញច្បាប់ចំលងសំរាប់អ្នកលក់ | J51: សម្គាល់ច្បាប់ដើមសំរាប់អ្នកទិញច្បាប់ចំលងសំរាប់អ្នកលក់
A52: Note ÷ Original invoice for customer , copies invoice for seller | J52: Note ÷ Original invoice for customer , copies invoice for seller

Sheet D002
A1: DEBIT NOTE
A4: CUSTOMER | B4: : | C4: JR APPAREL CO.,LTD | F4: DN NO | G4: JR2609002
A5: ADDRESS | B5: : | C5: KAOH KNOR VILLAGE PREAEK ROKA | F5: DATE | G5: ='366'!$I$13 -> 46275
C6: COMMUNE KANDALSTUENG DISTRICT,
C7: KANDAL STUENG, KANDAL, CAMBODIA
A9: HBL NO | B9: : | C9: ='366'!$B$19 -> COSU6464270110
A10: G.W | B10: : | C10: ='366'!$I$18 -> 16194.3 | F10: POL: | G10: ='366'!$I$19 -> PNH PORT
A11: VOLUME: | B11: : | C11: ='366'!$E$19 -> 1X45'HQ | F11: POD: | G11: ='366'!$I$20 -> USA
A12: CTNR No: | B12: : | C12: ='366'!$E$20 -> CSNU9538620 | F12: PKGS: | G12: ='366'!$B$20 -> 982 CTNS
A13: Shipper | B13: : | C13: ='366'!$C$17 -> JR APPAREL CO., LTD.
A14: Consignee | B14: : | C14: ='366'!$C$18 -> CHAPTERONE SPORTSWEAR
A16: NO | C16: DESCRIPTION | D16: Q'TY | E16: U/M | F16: PRICE | G16: TOTAL | H16: ='366'!S12 -> E 272714
A17: 1 | C17: TRUCKING FEE | D17: 1 | E17: 45H | F17: 260 | G17: =ROUND(F17*D17,2) -> 260
A18: 2 | C18: HANDLING FEE | D18: 1 | E18: 45H | F18: 35 | G18: =ROUND(F18*D18,2) -> 35
A19: 3 | C19: INCREASE TRUCKING FEE(65%) | D19: 1 | E19: TRUCK | F19: 169 | G19: =ROUND(F19*D19,2) -> 169 | H19: =G17*65% -> 169
A20: 4 | C20: DOCUMENT FEE | D20: 1 | E20: SET | F20: 25 | G20: =ROUND(F20*D20,2) -> 25
A21: 5 | C21: SERVICE TAXATION | D21: 1 | E21: SHIP | F21: 20 | G21: =ROUND(F21*D21,2) -> 20
A22: 6 | C22: PETROLL ALLOWANCE FEE | D22: 1 | E22: TIME | F22: 69 | G22: =ROUND(F22*D22,2) -> 69
A23: 7 | C23: FUEL SURCHARGE | D23: 1 | E23: 45H | F23: 40 | G23: =ROUND(F23*D23,2) -> 40
A24: 8 | C24: APPLY CO FOR INV: JRA26053 | D24: 1 | E24: INV | F24: 40 | G24: =ROUND(F24*D24,2) -> 40
A25: 9 | C25: LOLO EMPTY CONTAINER | D25: 1 | E25: 45H | F25: 49.5 | G25: =ROUND(F25*D25,2) -> 49.5
D26: GRAND TOTAL: | F26: USD | G26: =SUM(G17:G25) -> 707.5
A51: Thank you for your supporting | E51: AUTHORIZED SIGNATURE

Sheet 370
A2: ក្រុមហ៊ុន ហ្រ្តេតហ្វ៊ូល សឹលូសិន (ខេមបូឌា) ឯ.ក | J2: ក្រុមហ៊ុន ហ្រ្តេតហ្វ៊ូល សឹលូសិន (ខេមបូឌា) ឯ.ក
A3: GRATEFUL SOLUTIONS (CAMBODIA) CO.,LTD. | J3: GRATEFUL SOLUTIONS (CAMBODIA) CO.,LTD.
C4: លេខអត្តសញ្ញាណកម្ម អតប ( VATTIN ) : K008-902404873 | L4: លេខអត្តសញ្ញាណកម្ម អតប ( VATTIN ) : K008-902404873
A5: អាស័យដ្ឋាន : # 7E0 ផ្លូវបេតុង ក្រុម 7 ភូមិទួលថ្ងាន់ សង្កាត់ទួលសង្កែទី2 ខណ្ឌឬស្សីកែវ រាជធានីភ្នំពេញ | J5: អាស័យដ្ឋាន : # 7E0 ផ្លូវបេតុង ក្រុម 7 ភូមិទួលថ្ងាន់ សង្កាត់ទួលសង្កែទី2 ខណ្ឌឬស្សីកែវ រាជធានីភ្នំពេញ
A6: លេខទូរស័ព្ទ:​098​ 484 ​414 | J6: លេខទូរស័ព្ទ:​098​ 484 ​414
A9: វិក្កយបត្រអាករ | J9: វិក្កយបត្របង់ជំនួស
A10: TAX INVOICE | J10: DISBURSEMENT
A12: ឈ្មោះអតិថិជន /Customer: ជេអ អឹភែរឹល ឯ.ក | F12: លេខវិក័យប័ត្រ: /Invoice No: | I12: GS26-370 | J12: =A12 -> ឈ្មោះអតិថិជន /Customer: ជេអ អឹភែរឹល ឯ.ក | O12: លេខវិក័យប័ត្រ: /DIS-No: | R12: DIS413 | S12: E 275226
A13: JR APPAREL CO.,LTD | E13: ការបរិច្ឆេទវិក្កយបត្រ/Invoice Date: | I13: 46279 | J13: =A13 -> JR APPAREL CO.,LTD | N13: ការបរិច្ឆេទវិក្កយបត្រ/DIS-Date: | R13: =I13 -> 46279
A14: អាស័យដ្ឋាន/Address: KAOH KNOR VILLAGE PREAEK ROKA COMMUNE KANDAL | J14: =A14 -> អាស័យដ្ឋាន/Address: KAOH KNOR VILLAGE PREAEK ROKA COMMUNE KANDAL
A15: STUENG DISTRICT, KANDAL STUENG, KANDAL, CAMBODIA | J15: =A15 -> STUENG DISTRICT, KANDAL STUENG, KANDAL, CAMBODIA
A16: លេខ អ ត ប (VATTIN) : L001-902501613 | J16: =A16 -> លេខ អ ត ប (VATTIN) : L001-902501613
A17: SHIPPER: | C17: JR APPAREL CO., LTD. | J17: =A17 -> SHIPPER: | L17: =C17 -> JR APPAREL CO., LTD.
A18: CONSIGNEE : | C18: CHAPTERONE SPORTSWEAR | G18: GROSS WEIGHT: | I18: 12454 | J18: =A18 -> CONSIGNEE : | L18: =C18 -> CHAPTERONE SPORTSWEAR | P18: =G18 -> GROSS WEIGHT: | R18: =I18 -> 12454
A19: HBL: | B19: COSU6464270310 | D19: VOLUME: | E19: 1X40'HC | H19: POL: | I19: PNH PORT | J19: =A19 -> HBL: | K19: =B19 -> COSU6464270310 | M19: VOLUME: | N19: =E19 -> 1X40'HC | Q19: POL: | R19: =I19 -> PNH PORT
A20: PKGS: | B20: 729 CTNS | D20: CTNR No: | E20: CSNU6351548 | H20: POD: | I20: USA | J20: =A20 -> PKGS: | K20: =B20 -> 729 CTNS | M20: CTNR No: | N20: =E20 -> CSNU6351548 | Q20: POD: | R20: =I20 -> USA
G21: 4052 | P21: =G21 -> 4052
A22: ល.រ | B22: បរិយាយមុខទំនិញ | D22: បរិមាណ | E22: ឯកតា | F22: ថ្លៃឯកតា | G22: សរុប | H22: អាករ10% | I22: ថ្លៃទំនិញ | J22: ល.រ | K22: បរិយាយមុខទំនិញ | M22: បរិមាណ | N22: ឯកតា | O22: ថ្លៃឯកតា | P22: សរុប | Q22: អាករ 0% | R22: ថ្លៃទំនិញ
A23: No | B23: Description | D23: Quatity | E23: Unit | F23: Unit Price | G23: Sub. Total | H23: VAT ( 10%) | I23: Amount | J23: No | K23: Description | M23: Quatity | N23: Unit | O23: Unit Price | P23: Sub. Total | Q23: VAT ( 0%) | R23: Amount
A25: 1 | B25: កំរៃសេវាបំពេញបែបបទនាំចេញ / EXPORT PROCESSING FEE | D25: 1 | E25: 40H | F25: 242 | G25: =ROUND(F25*D25,2) -> 242 | H25: =G25*10% -> 24.2 | I25: =H25+G25 -> 266.2 | J25: 1 | K25: LOLO AT PORT | M25: 1 | N25: 40H | O25: 77 | P25: =O25*M25 -> 77 | Q25: 0 | R25: =Q25+P25 -> 77 | S25: TBA
J26: 2 | K26: CUSTOM PROCESSING FEE | M26: 1 | N26: 40H | O26: 21.25 | P26: =O26*M26 -> 21.25 | Q26: 0 | R26: =Q26+P26 -> 21.25
J27: 3 | K27: HBL FEE | M27: 1 | N27: 40H | O27: 539 | P27: =O27*M27 -> 539 | Q27: 0 | R27: =Q27+P27 -> 539
C29: សរុប SUB TOTAL | E29: KHR | F29: =$I$29*G21 -> 980584 | H29: USD | I29: =SUM(G25:G28) -> 242 | L29: សរុប SUB TOTAL | Q29: USD | R29: =SUM(R25:R28) -> 637.25
C30: អារករលើតម្លៃបន្ថែម (VAT 10%) | E30: KHR | F30: =$I$30*$G$21 -> 98058.4 | H30: USD | I30: =ROUND(SUM(H25:H28),2) -> 24.2 | L30: អារករលើតម្លៃបន្ថែម (VAT 0%) | Q30: USD | R30: 0
C31: សរុបរួម GRAND TOTAL | E31: KHR | F31: =I31*$G$21 -> 1078642.4 | H31: USD | I31: =$I$29+$I$30 -> 266.2 | L31: សរុបរួម GRAND TOTAL | Q31: USD | R31: =SUM(R29:R30) -> 637.25 | S31: =SUM(I31+R31) -> 903.45
A33: Note: Can make payment by cross cheque to: | J33: Note: Can make payment by cross cheque to:
A34: GRATEFUL SOLUTIONS (CAMBODIA) CO.,LTD. | J34: GRATEFUL SOLUTIONS (CAMBODIA) CO.,LTD.
A35: or Deposit Cash/Cheque payment to bank as below: | J35: or Deposit Cash/Cheque payment to bank as below:
A36: KB BRASAC BANK PLC | J36: KB BRASAC BANK PLC
A37: A/NAME: GRATEFUL SOLUTIONS (CAMBODIA) CO.,LTD. | J37: A/NAME: GRATEFUL SOLUTIONS (CAMBODIA) CO.,LTD.
A38: AC/NO: 033 754 230 001 | J38: AC/NO: 033 754 230 001
A48: ________________________ | G48: _______________________________ | J48: ________________________ | P48: _______________________________
A49: ហត្ថលេខា និង ឈ្មោះអ្នកទិញ | G49: ​​​​​​​​​​​ ហត្ថលេខា និង ឈ្មោះអ្នកលក់ | J49: ហត្ថលេខា និង ឈ្មោះអ្នកទិញ | P49: ​​​​​​​​​​​ ហត្ថលេខា និង ឈ្មោះអ្នកលក់
A50: សម្គាល់ច្បាប់ដើមសំរាប់អ្នកទិញច្បាប់ចំលងសំរាប់អ្នកលក់ | J50: សម្គាល់ច្បាប់ដើមសំរាប់អ្នកទិញច្បាប់ចំលងសំរាប់អ្នកលក់
A51: Note ÷ Original invoice for customer , copies invoice for seller | J51: Note ÷ Original invoice for customer , copies invoice for seller

Sheet D003
A1: DEBIT NOTE
A4: CUSTOMER | B4: : | C4: JR APPAREL CO.,LTD | F4: DN NO | G4: JR2609003
A5: ADDRESS | B5: : | C5: KAOH KNOR VILLAGE PREAEK ROKA | F5: DATE | G5: ='370'!$I$13 -> 46279
C6: COMMUNE KANDALSTUENG DISTRICT,
C7: KANDAL STUENG, KANDAL, CAMBODIA
A9: HBL NO | B9: : | C9: ='370'!$B$19 -> COSU6464270310
A10: G.W | B10: : | C10: ='370'!$I$18 -> 12454 | F10: POL: | G10: ='370'!$I$19 -> PNH PORT
A11: VOLUME: | B11: : | C11: ='370'!$E$19 -> 1X40'HC | F11: POD: | G11: ='370'!$I$20 -> USA
A12: CTNR No: | B12: : | C12: ='370'!$E$20 -> CSNU6351548 | F12: PKGS: | G12: ='370'!$B$20 -> 729 CTNS
A13: Shipper | B13: : | C13: ='370'!$C$17 -> JR APPAREL CO., LTD.
A14: Consignee | B14: : | C14: ='370'!$C$18 -> CHAPTERONE SPORTSWEAR
A16: NO | C16: DESCRIPTION | D16: Q'TY | E16: U/M | F16: PRICE | G16: TOTAL | H16: ='370'!S12 -> E 275226
A17: 1 | C17: TRUCKING FEE | D17: 1 | E17: 45H | F17: 260 | G17: =ROUND(F17*D17,2) -> 260
A18: 2 | C18: HANDLING FEE | D18: 1 | E18: 45H | F18: 35 | G18: =ROUND(F18*D18,2) -> 35
A19: 3 | C19: INCREASE TRUCKING FEE(65%) | D19: 1 | E19: TRUCK | F19: 169 | G19: =ROUND(F19*D19,2) -> 169 | H19: =G17*65% -> 169
A20: 4 | C20: DOCUMENT FEE | D20: 1 | E20: SET | F20: 25 | G20: =ROUND(F20*D20,2) -> 25
A21: 5 | C21: SERVICE TAXATION | D21: 1 | E21: SHIP | F21: 20 | G21: =ROUND(F21*D21,2) -> 20
A22: 6 | C22: PETROLL ALLOWANCE FEE | D22: 1 | E22: TIME | F22: 69 | G22: =ROUND(F22*D22,2) -> 69
A23: 7 | C23: FUEL SURCHARGE | D23: 1 | E23: 45H | F23: 40 | G23: =ROUND(F23*D23,2) -> 40
A24: 8 | C24: APPLY CO FOR INV: JRA26054 | D24: 1 | E24: INV | F24: 40 | G24: =ROUND(F24*D24,2) -> 40
A25: 9 | C25: LOLO EMPTY CONTAINER | D25: 1 | E25: 45H | F25: 49.5 | G25: =ROUND(F25*D25,2) -> 49.5
D26: GRAND TOTAL: | F26: USD | G26: =SUM(G17:G25) -> 707.5
A51: Thank you for your supporting | E51: AUTHORIZED SIGNATURE

Sheet 375
A2: ក្រុមហ៊ុន ហ្រ្តេតហ្វ៊ូល សឹលូសិន (ខេមបូឌា) ឯ.ក | J2: ក្រុមហ៊ុន ហ្រ្តេតហ្វ៊ូល សឹលូសិន (ខេមបូឌា) ឯ.ក
A3: GRATEFUL SOLUTIONS (CAMBODIA) CO.,LTD. | J3: GRATEFUL SOLUTIONS (CAMBODIA) CO.,LTD.
C4: លេខអត្តសញ្ញាណកម្ម អតប ( VATTIN ) : K008-902404873 | L4: លេខអត្តសញ្ញាណកម្ម អតប ( VATTIN ) : K008-902404873
A5: អាស័យដ្ឋាន : # 7E0 ផ្លូវបេតុង ក្រុម 7 ភូមិទួលថ្ងាន់ សង្កាត់ទួលសង្កែទី2 ខណ្ឌឬស្សីកែវ រាជធានីភ្នំពេញ | J5: អាស័យដ្ឋាន : # 7E0 ផ្លូវបេតុង ក្រុម 7 ភូមិទួលថ្ងាន់ សង្កាត់ទួលសង្កែទី2 ខណ្ឌឬស្សីកែវ រាជធានីភ្នំពេញ
A6: លេខទូរស័ព្ទ:​098​ 484 ​414 | J6: លេខទូរស័ព្ទ:​098​ 484 ​414
A9: វិក្កយបត្រអាករ | J9: វិក្កយបត្របង់ជំនួស
A10: TAX INVOICE | J10: DISBURSEMENT
A12: ឈ្មោះអតិថិជន /Customer: ជេអ អឹភែរឹល ឯ.ក | F12: លេខវិក័យប័ត្រ: /Invoice No: | I12: GS26-375 | J12: =A12 -> ឈ្មោះអតិថិជន /Customer: ជេអ អឹភែរឹល ឯ.ក | O12: លេខវិក័យប័ត្រ: /DIS-No: | R12: DIS418 | S12: E 284067
A13: JR APPAREL CO.,LTD | E13: ការបរិច្ឆេទវិក្កយបត្រ/Invoice Date: | I13: 46286 | J13: =A13 -> JR APPAREL CO.,LTD | N13: ការបរិច្ឆេទវិក្កយបត្រ/DIS-Date: | R13: =I13 -> 46286
A14: អាស័យដ្ឋាន/Address: KAOH KNOR VILLAGE PREAEK ROKA COMMUNE KANDAL | J14: =A14 -> អាស័យដ្ឋាន/Address: KAOH KNOR VILLAGE PREAEK ROKA COMMUNE KANDAL
A15: STUENG DISTRICT, KANDAL STUENG, KANDAL, CAMBODIA | J15: =A15 -> STUENG DISTRICT, KANDAL STUENG, KANDAL, CAMBODIA
A16: លេខ អ ត ប (VATTIN) : L001-902501613 | J16: =A16 -> លេខ អ ត ប (VATTIN) : L001-902501613
A17: SHIPPER: | C17: JR APPAREL CO., LTD. | J17: =A17 -> SHIPPER: | L17: =C17 -> JR APPAREL CO., LTD.
A18: CONSIGNEE : | C18: CHAPTERONE SPORTSWEAR | G18: GROSS WEIGHT: | I18: 14952.5 | J18: =A18 -> CONSIGNEE : | L18: =C18 -> CHAPTERONE SPORTSWEAR | P18: =G18 -> GROSS WEIGHT: | R18: =I18 -> 14952.5
A19: HBL: | B19: COSU6464808450 | D19: VOLUME: | E19: 1X45'HQ | H19: POL: | I19: PNH PORT | J19: =A19 -> HBL: | K19: =B19 -> COSU6464808450 | M19: VOLUME: | N19: =E19 -> 1X45'HQ | Q19: POL: | R19: =I19 -> PNH PORT
A20: PKGS: | B20: 977 CTNS | D20: CTNR No: | E20: TEMU8045497 | H20: POD: | I20: USA | J20: =A20 -> PKGS: | K20: =B20 -> 977 CTNS | M20: CTNR No: | N20: =E20 -> TEMU8045497 | Q20: POD: | R20: =I20 -> USA
G21: 4054 | P21: =G21 -> 4054
A22: ល.រ | B22: បរិយាយមុខទំនិញ | D22: បរិមាណ | E22: ឯកតា | F22: ថ្លៃឯកតា | G22: សរុប | H22: អាករ10% | I22: ថ្លៃទំនិញ | J22: ល.រ | K22: បរិយាយមុខទំនិញ | M22: បរិមាណ | N22: ឯកតា | O22: ថ្លៃឯកតា | P22: សរុប | Q22: អាករ 0% | R22: ថ្លៃទំនិញ
A23: No | B23: Description | D23: Quatity | E23: Unit | F23: Unit Price | G23: Sub. Total | H23: VAT ( 10%) | I23: Amount | J23: No | K23: Description | M23: Quatity | N23: Unit | O23: Unit Price | P23: Sub. Total | Q23: VAT ( 0%) | R23: Amount
A25: 1 | B25: កំរៃសេវាបំពេញបែបបទនាំចេញ / EXPORT PROCESSING FEE | D25: 1 | E25: 45H | F25: 242 | G25: =ROUND(F25*D25,2) -> 242 | H25: =G25*10% -> 24.2 | I25: =H25+G25 -> 266.2 | J25: 1 | K25: LOLO AT PORT | M25: 1 | N25: 45H | O25: 77 | P25: =O25*M25 -> 77 | Q25: 0 | R25: =Q25+P25 -> 77
J26: 2 | K26: CUSTOM PROCESSING FEE | M26: 1 | N26: 45H | O26: 21.25 | P26: =O26*M26 -> 21.25 | Q26: 0 | R26: =Q26+P26 -> 21.25
J27: 3 | K27: STORAGE FEE | M27: 1 | N27: 45H | O27: 13.2 | P27: =O27*M27 -> 13.2 | Q27: 0 | R27: =Q27+P27 -> 13.2
J28: 4 | K28: HBL FEE | M28: 1 | N28: 45H | O28: 539 | P28: =O28*M28 -> 539 | Q28: 0 | R28: =Q28+P28 -> 539
C30: សរុប SUB TOTAL | E30: KHR | F30: =$I$30*G21 -> 981068 | H30: USD | I30: =SUM(G25:G29) -> 242 | L30: សរុប SUB TOTAL | Q30: USD | R30: =SUM(R24:R29) -> 650.45
C31: អារករលើតម្លៃបន្ថែម (VAT 10%) | E31: KHR | F31: =$I$31*$G$21 -> 98106.8 | H31: USD | I31: =ROUND(SUM(H25:H29),2) -> 24.2 | L31: អារករលើតម្លៃបន្ថែម (VAT 0%) | Q31: USD | R31: 0
C32: សរុបរួម GRAND TOTAL | E32: KHR | F32: =I32*$G$21 -> 1079174.8 | H32: USD | I32: =$I$30+$I$31 -> 266.2 | L32: សរុបរួម GRAND TOTAL | Q32: USD | R32: =SUM(R30:R31) -> 650.45 | S32: =SUM(I32,R32) -> 916.65
A34: Note: Can make payment by cross cheque to: | J34: Note: Can make payment by cross cheque to:
A35: GRATEFUL SOLUTIONS (CAMBODIA) CO.,LTD. | J35: GRATEFUL SOLUTIONS (CAMBODIA) CO.,LTD.
A36: or Deposit Cash/Cheque payment to bank as below: | J36: or Deposit Cash/Cheque payment to bank as below:
A37: KB BRASAC BANK PLC | J37: KB BRASAC BANK PLC
A38: A/NAME: GRATEFUL SOLUTIONS (CAMBODIA) CO.,LTD. | J38: A/NAME: GRATEFUL SOLUTIONS (CAMBODIA) CO.,LTD.
A39: AC/NO: 033 754 230 001 | J39: AC/NO: 033 754 230 001
A48: ________________________ | G48: _______________________________ | J48: ________________________ | P48: _______________________________
A49: ហត្ថលេខា និង ឈ្មោះអ្នកទិញ | G49: ​​​​​​​​​​​ ហត្ថលេខា និង ឈ្មោះអ្នកលក់ | J49: ហត្ថលេខា និង ឈ្មោះអ្នកទិញ | P49: ​​​​​​​​​​​ ហត្ថលេខា និង ឈ្មោះអ្នកលក់
A50: សម្គាល់ច្បាប់ដើមសំរាប់អ្នកទិញច្បាប់ចំលងសំរាប់អ្នកលក់ | J50: សម្គាល់ច្បាប់ដើមសំរាប់អ្នកទិញច្បាប់ចំលងសំរាប់អ្នកលក់
A51: Note ÷ Original invoice for customer , copies invoice for seller | J51: Note ÷ Original invoice for customer , copies invoice for seller

Sheet D004
A1: DEBIT NOTE
A4: CUSTOMER | B4: : | C4: JR APPAREL CO.,LTD | F4: DN NO | G4: JR2609004
A5: ADDRESS | B5: : | C5: KAOH KNOR VILLAGE PREAEK ROKA | F5: DATE | G5: ='375'!I13 -> 46286
C6: COMMUNE KANDALSTUENG DISTRICT,
C7: KANDAL STUENG, KANDAL, CAMBODIA
A9: HBL NO | B9: : | C9: ='375'!B19 -> COSU6464808450
A10: G.W | B10: : | C10: ='375'!I18 -> 14952.5 | F10: POL: | G10: ='375'!I19 -> PNH PORT
A11: VOLUME: | B11: : | C11: ='375'!E19 -> 1X45'HQ | F11: POD: | G11: ='375'!I20 -> USA
A12: CTNR No: | B12: : | C12: ='375'!E20 -> TEMU8045497 | F12: PKGS: | G12: ='375'!B20 -> 977 CTNS
A13: Shipper | B13: : | C13: ='375'!C17 -> JR APPAREL CO., LTD.
A14: Consignee | B14: : | C14: ='375'!C18 -> CHAPTERONE SPORTSWEAR
A16: NO | C16: DESCRIPTION | D16: Q'TY | E16: U/M | F16: PRICE | G16: TOTAL | H16: ='375'!S12 -> E 284067
A17: 1 | C17: TRUCKING FEE | D17: 1 | E17: 45H | F17: 260 | G17: =ROUND(F17*D17,2) -> 260
A18: 2 | C18: HANDLING FEE | D18: 1 | E18: 45H | F18: 35 | G18: =ROUND(F18*D18,2) -> 35
A19: 3 | C19: INCREASE TRUCKING FEE(65%) | D19: 1 | E19: TRUCK | F19: 169 | G19: =ROUND(F19*D19,2) -> 169 | H19: =G17*65% -> 169
A20: 4 | C20: INSPECTION AT DRYPORT | D20: 1 | E20: TIME | F20: 57.5 | G20: =ROUND(F20*D20,2) -> 57.5
A21: 5 | C21: DOCUMENT FEE | D21: 1 | E21: SET | F21: 25 | G21: =ROUND(F21*D21,2) -> 25
A22: 6 | C22: SERVICE TAXATION | D22: 1 | E22: SHIP | F22: 20 | G22: =ROUND(F22*D22,2) -> 20
A23: 7 | C23: FUEL SURCHARGE | D23: 1 | E23: 45H | F23: 40 | G23: =ROUND(F23*D23,2) -> 40
A24: 8 | C24: OT INSPECTION | D24: 1 | E24: 45H | F24: 80 | G24: =ROUND(F24*D24,2) -> 80
A25: 9 | C25: OT AT PORT | D25: 1 | E25: 45H | F25: 60 | G25: =ROUND(F25*D25,2) -> 60
A26: 10 | C26: LOLO EMPTY CONTAINER | D26: 1 | E26: 45H | F26: 49.5 | G26: =ROUND(F26*D26,2) -> 49.5
A27: 11 | C27: GATE FEE AT DRY PORT | D27: 1 | E27: 45H | F27: 15 | G27: =ROUND(F27*D27,2) -> 15
A28: 12 | C28: APPLY CO FOR INV: JRA26055 | D28: 1 | E28: INV | F28: 40 | G28: =ROUND(F28*D28,2) -> 40
D29: GRAND TOTAL: | F29: USD | G29: =SUM(G17:G28) -> 851
A51: Thank you for your supporting | E51: AUTHORIZED SIGNATURE

Sheet 377
A2: ក្រុមហ៊ុន ហ្រ្តេតហ្វ៊ូល សឹលូសិន (ខេមបូឌា) ឯ.ក | J2: ក្រុមហ៊ុន ហ្រ្តេតហ្វ៊ូល សឹលូសិន (ខេមបូឌា) ឯ.ក
A3: GRATEFUL SOLUTIONS (CAMBODIA) CO.,LTD. | J3: GRATEFUL SOLUTIONS (CAMBODIA) CO.,LTD.
C4: លេខអត្តសញ្ញាណកម្ម អតប ( VATTIN ) : K008-902404873 | L4: លេខអត្តសញ្ញាណកម្ម អតប ( VATTIN ) : K008-902404873
A5: អាស័យដ្ឋាន : # 7E0 ផ្លូវបេតុង ក្រុម 7 ភូមិទួលថ្ងាន់ សង្កាត់ទួលសង្កែទី2 ខណ្ឌឬស្សីកែវ រាជធានីភ្នំពេញ | J5: អាស័យដ្ឋាន : # 7E0 ផ្លូវបេតុង ក្រុម 7 ភូមិទួលថ្ងាន់ សង្កាត់ទួលសង្កែទី2 ខណ្ឌឬស្សីកែវ រាជធានីភ្នំពេញ
A6: លេខទូរស័ព្ទ:​098​ 484 ​414 | J6: លេខទូរស័ព្ទ:​098​ 484 ​414
A9: វិក្កយបត្រអាករ | J9: វិក្កយបត្របង់ជំនួស
A10: TAX INVOICE | J10: DISBURSEMENT
A12: ឈ្មោះអតិថិជន /Customer: ជេអ អឹភែរឹល ឯ.ក | F12: លេខវិក័យប័ត្រ: /Invoice No: | I12: GS26-377 | J12: =A12 -> ឈ្មោះអតិថិជន /Customer: ជេអ អឹភែរឹល ឯ.ក | O12: លេខវិក័យប័ត្រ: /DIS-No: | R12: DIS420 | S12: I 136252
A13: JR APPAREL CO.,LTD | E13: ការបរិច្ឆេទវិក្កយបត្រ/Invoice Date: | I13: 46286 | J13: =A13 -> JR APPAREL CO.,LTD | N13: ការបរិច្ឆេទវិក្កយបត្រ/DIS-Date: | R13: =I13 -> 46286
A14: អាស័យដ្ឋាន/Address: KAOH KNOR VILLAGE PREAEK ROKA COMMUNE KANDAL | J14: =A14 -> អាស័យដ្ឋាន/Address: KAOH KNOR VILLAGE PREAEK ROKA COMMUNE KANDAL
A15: STUENG DISTRICT, KANDAL STUENG, KANDAL, CAMBODIA | J15: =A15 -> STUENG DISTRICT, KANDAL STUENG, KANDAL, CAMBODIA
A16: លេខ អ ត ប (VATTIN) : L001-902501613 | J16: =A16 -> លេខ អ ត ប (VATTIN) : L001-902501613
A17: SHIPPER: | C17: SHANGHAI YONGYUE IMP. &EXP. TRADING CO., LTD. | J17: =A17 -> SHIPPER: | L17: =C17 -> SHANGHAI YONGYUE IMP. &EXP. TRADING CO., LTD.
A18: CONSIGNEE : | C18: JR APPAREL CO., LTD. | G18: GROSS WEIGHT: | I18: 24300 | J18: =A18 -> CONSIGNEE : | L18: =C18 -> JR APPAREL CO., LTD. | P18: =G18 -> GROSS WEIGHT: | R18: =I18 -> 24300
A19: HBL: | B19: SHSIN6090083 | D19: VOLUME: | E19: 1X40'HQ | H19: POL: | I19: CHINA | J19: =A19 -> HBL: | K19: =B19 -> SHSIN6090083 | M19: VOLUME: | N19: =E19 -> 1X40'HQ | Q19: POL: | R19: =I19 -> CHINA
A20: PKGS: | B20: 797 ROLLS | D20: CTNR No: | E20: OOCU7012318 | H20: POD: | I20: SHV PORT | J20: =A20 -> PKGS: | K20: =B20 -> 797 ROLLS | M20: CTNR No: | N20: =E20 -> OOCU7012318 | Q20: POD: | R20: =I20 -> SHV PORT
G21: 4054 | P21: =G21 -> 4054
A22: ល.រ | B22: បរិយាយមុខទំនិញ | D22: បរិមាណ | E22: ឯកតា | F22: ថ្លៃឯកតា | G22: សរុប | H22: អាករ10% | I22: ថ្លៃទំនិញ | J22: ល.រ | K22: បរិយាយមុខទំនិញ | M22: បរិមាណ | N22: ឯកតា | O22: ថ្លៃឯកតា | P22: សរុប | Q22: អាករ 0% | R22: ថ្លៃទំនិញ
A23: No | B23: Description | D23: Quatity | E23: Unit | F23: Unit Price | G23: Sub. Total | H23: VAT ( 10%) | I23: Amount | J23: No | K23: Description | M23: Quatity | N23: Unit | O23: Unit Price | P23: Sub. Total | Q23: VAT ( 0%) | R23: Amount
A25: 1 | B25: កំរៃសេវាបំពេញបែបបទនាំចូល / IMPORT PROCESSING FEE | D25: 1 | E25: 40H | F25: 200 | G25: =ROUND(F25*D25,2) -> 200 | H25: =G25*10% -> 20 | I25: =H25+G25 -> 220 | J25: 1 | K25: LOLO AT PORT | M25: 1 | N25: 40H | O25: 95.7 | P25: =O25*M25 -> 95.7 | Q25: 0 | R25: =Q25+P25 -> 95.7
J26: 2 | K26: CUSTOM PROCESSING FEE | M26: 1 | N26: 40H | O26: 18.75 | P26: =O26*M26 -> 18.75 | Q26: 0 | R26: =Q26+P26 -> 18.75
J27: 3 | K27: THC FEE | M27: 1 | N27: 40H | O27: 691.5 | P27: =O27*M27 -> 691.5 | Q27: 0 | R27: =Q27+P27 -> 691.5
C29: សរុប SUB TOTAL | E29: KHR | F29: =$I$29*G21 -> 810800 | H29: USD | I29: =SUM(G25:G28) -> 200 | L29: សរុប SUB TOTAL | Q29: USD | R29: =SUM(R25:R28) -> 805.95
C30: អារករលើតម្លៃបន្ថែម (VAT 10%) | E30: KHR | F30: =$I$30*$G$21 -> 81080 | H30: USD | I30: =ROUND(SUM(H25:H28),2) -> 20 | L30: អារករលើតម្លៃបន្ថែម (VAT 0%) | Q30: USD | R30: 0
C31: សរុបរួម GRAND TOTAL | E31: KHR | F31: =I31*$G$21 -> 891880 | H31: USD | I31: =$I$29+$I$30 -> 220 | L31: សរុបរួម GRAND TOTAL | Q31: USD | R31: =SUM(R29:R30) -> 805.95 | S31: =SUM(I31,R31) -> 1025.95
A33: Note: Can make payment by cross cheque to: | J33: Note: Can make payment by cross cheque to:
A34: GRATEFUL SOLUTIONS (CAMBODIA) CO.,LTD. | J34: GRATEFUL SOLUTIONS (CAMBODIA) CO.,LTD.
A35: or Deposit Cash/Cheque payment to bank as below: | J35: or Deposit Cash/Cheque payment to bank as below:
A36: KB BRASAC BANK PLC | J36: KB BRASAC BANK PLC
A37: A/NAME: GRATEFUL SOLUTIONS (CAMBODIA) CO.,LTD. | J37: A/NAME: GRATEFUL SOLUTIONS (CAMBODIA) CO.,LTD.
A38: AC/NO: 033 754 230 001 | J38: AC/NO: 033 754 230 001
A50: ________________________ | G50: _______________________________ | J50: ________________________ | P50: _______________________________
A51: ហត្ថលេខា និង ឈ្មោះអ្នកទិញ | G51: ​​​​​​​​​​​ ហត្ថលេខា និង ឈ្មោះអ្នកលក់ | J51: ហត្ថលេខា និង ឈ្មោះអ្នកទិញ | P51: ​​​​​​​​​​​ ហត្ថលេខា និង ឈ្មោះអ្នកលក់
A52: សម្គាល់ច្បាប់ដើមសំរាប់អ្នកទិញច្បាប់ចំលងសំរាប់អ្នកលក់ | J52: សម្គាល់ច្បាប់ដើមសំរាប់អ្នកទិញច្បាប់ចំលងសំរាប់អ្នកលក់
A53: Note ÷ Original invoice for customer , copies invoice for seller | J53: Note ÷ Original invoice for customer , copies invoice for seller

Sheet D005
A1: DEBIT NOTE
A4: CUSTOMER | B4: : | C4: JR APPAREL CO.,LTD | F4: DN NO | G4: JR2609005
A5: ADDRESS | B5: : | C5: KAOH KNOR VILLAGE PREAEK ROKA | F5: DATE | G5: ='377'!I13 -> 46286
C6: COMMUNE KANDALSTUENG DISTRICT,
C7: KANDAL STUENG, KANDAL, CAMBODIA
A9: HBL NO | B9: : | C9: ='377'!B19 -> SHSIN6090083
A10: G.W | B10: : | C10: ='377'!I18 -> 24300 | F10: POL: | G10: ='377'!I19 -> CHINA
A11: VOLUME: | B11: : | C11: ='377'!E19 -> 1X40'HQ | F11: POD: | G11: ='377'!I20 -> SHV PORT
A12: CTNR No: | B12: : | C12: ='377'!E20 -> OOCU7012318 | F12: PKGS: | G12: ='377'!B20 -> 797 ROLLS
A13: Shipper | B13: : | C13: ='377'!C17 -> SHANGHAI YONGYUE IMP. &EXP. TRADING CO., LTD.
A14: Consignee | B14: : | C14: ='377'!C18 -> JR APPAREL CO., LTD.
A16: NO | C16: DESCRIPTION | D16: Q'TY | E16: U/M | F16: PRICE | G16: TOTAL | H16: ='377'!S12 -> I 136252
A17: 1 | C17: TRUCKING FEE | D17: 1 | E17: 40H | F17: 360 | G17: =ROUND(F17*D17,2) -> 360
A18: 2 | C18: HANDLING FEE | D18: 1 | E18: 40H | F18: 35 | G18: =ROUND(F18*D18,2) -> 35
A19: 3 | C19: INCREASE TRUCKING FEE(65%) | D19: 1 | E19: TRUCK | F19: 234 | G19: =ROUND(F19*D19,2) -> 234 | H19: =F17*65% -> 234
A20: 4 | C20: MISSING INSURANCE | D20: 1 | E20: SET | F20: 20 | G20: =ROUND(F20*D20,2) -> 20
A21: 5 | C21: DOCUMENT FEE | D21: 1 | E21: SET | F21: 25 | G21: =ROUND(F21*D21,2) -> 25
A22: 6 | C22: SERVICE TAXATION | D22: 1 | E22: SHIP | F22: 20 | G22: =ROUND(F22*D22,2) -> 20
A23: 7 | C23: PERMIT FEE | D23: 1 | E23: SET | F23: 45 | G23: =ROUND(F23*D23,2) -> 45
A24: 8 | C24: FUEL SURCHARGE | D24: 1 | E24: 40H | F24: 50 | G24: =ROUND(F24*D24,2) -> 50
A25: 9 | C25: OVER WEIGHT | D25: 3.3 | E25: TON | F25: 50 | G25: =ROUND(F25*D25,2) -> 165
A26: 10 | C26: TRUCKING TO SECOND PLACE | D26: 1 | E26: 40H | F26: 60 | G26: =ROUND(F26*D26,2) -> 60
A27: 11 | C27: LOLO EMPTY DROP DOWN | D27: 1 | E27: 40H | F27: 24.75 | G27: =ROUND(F27*D27,2) -> 24.75
D28: GRAND TOTAL: | F28: USD | G28: =SUM(G17:G27) -> 1038.75
A51: Thank you for your supporting | E51: AUTHORIZED SIGNATURE

Sheet 379
A2: ក្រុមហ៊ុន ហ្រ្តេតហ្វ៊ូល សឹលូសិន (ខេមបូឌា) ឯ.ក | J2: ក្រុមហ៊ុន ហ្រ្តេតហ្វ៊ូល សឹលូសិន (ខេមបូឌា) ឯ.ក
A3: GRATEFUL SOLUTIONS (CAMBODIA) CO.,LTD. | J3: GRATEFUL SOLUTIONS (CAMBODIA) CO.,LTD.
C4: លេខអត្តសញ្ញាណកម្ម អតប ( VATTIN ) : K008-902404873 | L4: លេខអត្តសញ្ញាណកម្ម អតប ( VATTIN ) : K008-902404873
A5: អាស័យដ្ឋាន : # 7E0 ផ្លូវបេតុង ក្រុម 7 ភូមិទួលថ្ងាន់ សង្កាត់ទួលសង្កែទី2 ខណ្ឌឬស្សីកែវ រាជធានីភ្នំពេញ | J5: អាស័យដ្ឋាន : # 7E0 ផ្លូវបេតុង ក្រុម 7 ភូមិទួលថ្ងាន់ សង្កាត់ទួលសង្កែទី2 ខណ្ឌឬស្សីកែវ រាជធានីភ្នំពេញ
A6: លេខទូរស័ព្ទ:​098​ 484 ​414 | J6: លេខទូរស័ព្ទ:​098​ 484 ​414
A9: វិក្កយបត្រអាករ | J9: វិក្កយបត្របង់ជំនួស
A10: TAX INVOICE | J10: DISBURSEMENT
A12: ឈ្មោះអតិថិជន /Customer: ជេអ អឹភែរឹល ឯ.ក | F12: លេខវិក័យប័ត្រ: /Invoice No: | I12: GS26-379 | J12: =A12 -> ឈ្មោះអតិថិជន /Customer: ជេអ អឹភែរឹល ឯ.ក | O12: លេខវិក័យប័ត្រ: /DIS-No: | R12: DIS422 | S12: I 136243
A13: JR APPAREL CO.,LTD | E13: ការបរិច្ឆេទវិក្កយបត្រ/Invoice Date: | I13: 46286 | J13: =A13 -> JR APPAREL CO.,LTD | N13: ការបរិច្ឆេទវិក្កយបត្រ/DIS-Date: | R13: =I13 -> 46286
A14: អាស័យដ្ឋាន/Address: KAOH KNOR VILLAGE PREAEK ROKA COMMUNE KANDAL | J14: =A14 -> អាស័យដ្ឋាន/Address: KAOH KNOR VILLAGE PREAEK ROKA COMMUNE KANDAL
A15: STUENG DISTRICT, KANDAL STUENG, KANDAL, CAMBODIA | J15: =A15 -> STUENG DISTRICT, KANDAL STUENG, KANDAL, CAMBODIA
A16: លេខ អ ត ប (VATTIN) : L001-902501613 | J16: =A16 -> លេខ អ ត ប (VATTIN) : L001-902501613
A17: SHIPPER: | C17: SHANGHAI YONGYUE IMP. &EXP. TRADING CO., LTD. | J17: =A17 -> SHIPPER: | L17: =C17 -> SHANGHAI YONGYUE IMP. &EXP. TRADING CO., LTD.
A18: CONSIGNEE : | C18: JR APPAREL CO., LTD. | G18: GROSS WEIGHT: | I18: 24996.9 | J18: =A18 -> CONSIGNEE : | L18: =C18 -> JR APPAREL CO., LTD. | P18: =G18 -> GROSS WEIGHT: | R18: =I18 -> 24996.9
A19: HBL: | B19: SHSIN6090084 | D19: VOLUME: | E19: 1X40'HQ | H19: POL: | I19: CHINA | J19: =A19 -> HBL: | K19: =B19 -> SHSIN6090084 | M19: VOLUME: | N19: =E19 -> 1X40'HQ | Q19: POL: | R19: =I19 -> CHINA
A20: PKGS: | B20: 688 ROLLS | D20: CTNR No: | E20: CSNU6862609 | H20: POD: | I20: SHV PORT | J20: =A20 -> PKGS: | K20: =B20 -> 688 ROLLS | M20: CTNR No: | N20: =E20 -> CSNU6862609 | Q20: POD: | R20: =I20 -> SHV PORT
G21: 4054 | P21: =G21 -> 4054
A22: ល.រ | B22: បរិយាយមុខទំនិញ | D22: បរិមាណ | E22: ឯកតា | F22: ថ្លៃឯកតា | G22: សរុប | H22: អាករ10% | I22: ថ្លៃទំនិញ | J22: ល.រ | K22: បរិយាយមុខទំនិញ | M22: បរិមាណ | N22: ឯកតា | O22: ថ្លៃឯកតា | P22: សរុប | Q22: អាករ 0% | R22: ថ្លៃទំនិញ
A23: No | B23: Description | D23: Quatity | E23: Unit | F23: Unit Price | G23: Sub. Total | H23: VAT ( 10%) | I23: Amount | J23: No | K23: Description | M23: Quatity | N23: Unit | O23: Unit Price | P23: Sub. Total | Q23: VAT ( 0%) | R23: Amount
A25: 1 | B25: កំរៃសេវាបំពេញបែបបទនាំចូល / IMPORT PROCESSING FEE | D25: 1 | E25: 40H | F25: 200 | G25: =ROUND(F25*D25,2) -> 200 | H25: =G25*10% -> 20 | I25: =H25+G25 -> 220 | J25: 1 | K25: LOLO AT PORT | M25: 1 | N25: 40H | O25: 95.7 | P25: =O25*M25 -> 95.7 | Q25: 0 | R25: =Q25+P25 -> 95.7
J26: 2 | K26: CUSTOM PROCESSING FEE | M26: 1 | N26: 40H | O26: 18.75 | P26: =O26*M26 -> 18.75 | Q26: 0 | R26: =Q26+P26 -> 18.75
J27: 3 | K27: THC FEE | M27: 1 | N27: 40H | O27: 691.5 | P27: =O27*M27 -> 691.5 | Q27: 0 | R27: =Q27+P27 -> 691.5
C29: សរុប SUB TOTAL | E29: KHR | F29: =$I$29*G21 -> 810800 | H29: USD | I29: =SUM(G25:G28) -> 200 | L29: សរុប SUB TOTAL | Q29: USD | R29: =SUM(R25:R28) -> 805.95
C30: អារករលើតម្លៃបន្ថែម (VAT 10%) | E30: KHR | F30: =$I$30*$G$21 -> 81080 | H30: USD | I30: =ROUND(SUM(H25:H28),2) -> 20 | L30: អារករលើតម្លៃបន្ថែម (VAT 0%) | Q30: USD | R30: 0
C31: សរុបរួម GRAND TOTAL | E31: KHR | F31: =I31*$G$21 -> 891880 | H31: USD | I31: =$I$29+$I$30 -> 220 | L31: សរុបរួម GRAND TOTAL | Q31: USD | R31: =SUM(R29:R30) -> 805.95 | S31: =SUM(I31,R31) -> 1025.95
A33: Note: Can make payment by cross cheque to: | J33: Note: Can make payment by cross cheque to:
A34: GRATEFUL SOLUTIONS (CAMBODIA) CO.,LTD. | J34: GRATEFUL SOLUTIONS (CAMBODIA) CO.,LTD.
A35: or Deposit Cash/Cheque payment to bank as below: | J35: or Deposit Cash/Cheque payment to bank as below:
A36: KB BRASAC BANK PLC | J36: KB BRASAC BANK PLC
A37: A/NAME: GRATEFUL SOLUTIONS (CAMBODIA) CO.,LTD. | J37: A/NAME: GRATEFUL SOLUTIONS (CAMBODIA) CO.,LTD.
A38: AC/NO: 033 754 230 001 | J38: AC/NO: 033 754 230 001
A49: ________________________ | G49: _______________________________ | J49: ________________________ | P49: _______________________________
A50: ហត្ថលេខា និង ឈ្មោះអ្នកទិញ | G50: ​​​​​​​​​​​ ហត្ថលេខា និង ឈ្មោះអ្នកលក់ | J50: ហត្ថលេខា និង ឈ្មោះអ្នកទិញ | P50: ​​​​​​​​​​​ ហត្ថលេខា និង ឈ្មោះអ្នកលក់
A51: សម្គាល់ច្បាប់ដើមសំរាប់អ្នកទិញច្បាប់ចំលងសំរាប់អ្នកលក់ | J51: សម្គាល់ច្បាប់ដើមសំរាប់អ្នកទិញច្បាប់ចំលងសំរាប់អ្នកលក់
A52: Note ÷ Original invoice for customer , copies invoice for seller | J52: Note ÷ Original invoice for customer , copies invoice for seller

Sheet D006
A1: DEBIT NOTE
A4: CUSTOMER | B4: : | C4: JR APPAREL CO.,LTD | F4: DN NO | G4: JR2609006
A5: ADDRESS | B5: : | C5: KAOH KNOR VILLAGE PREAEK ROKA | F5: DATE | G5: ='379'!I13 -> 46286
C6: COMMUNE KANDALSTUENG DISTRICT,
C7: KANDAL STUENG, KANDAL, CAMBODIA
A9: HBL NO | B9: : | C9: ='379'!B19 -> SHSIN6090084
A10: G.W | B10: : | C10: ='379'!I18 -> 24996.9 | F10: POL: | G10: ='379'!I19 -> CHINA
A11: VOLUME: | B11: : | C11: ='379'!E19 -> 1X40'HQ | F11: POD: | G11: ='379'!I20 -> SHV PORT
A12: CTNR No: | B12: : | C12: ='379'!E20 -> CSNU6862609 | F12: PKGS: | G12: ='379'!B20 -> 688 ROLLS
A13: Shipper | B13: : | C13: ='379'!C17 -> SHANGHAI YONGYUE IMP. &EXP. TRADING CO., LTD.
A14: Consignee | B14: : | C14: ='379'!C18 -> JR APPAREL CO., LTD.
A16: NO | C16: DESCRIPTION | D16: Q'TY | E16: U/M | F16: PRICE | G16: TOTAL | H16: ='379'!S12 -> I 136243
A17: 1 | C17: TRUCKING FEE | D17: 1 | E17: 40H | F17: 360 | G17: =ROUND(F17*D17,2) -> 360
A18: 2 | C18: HANDLING FEE | D18: 1 | E18: 40H | F18: 35 | G18: =ROUND(F18*D18,2) -> 35
A19: 3 | C19: INCREASE TRUCKING FEE(65%) | D19: 1 | E19: TRUCK | F19: 234 | G19: =ROUND(F19*D19,2) -> 234 | H19: =F17*65% -> 234
A20: 4 | C20: EXTRA TRUCKING FEE (TO PREK LEAP) | D20: 1 | E20: 40H | F20: 50 | G20: =ROUND(F20*D20,2) -> 50
A21: 5 | C21: MISSING INSURANCE | D21: 1 | E21: SET | F21: 20 | G21: =ROUND(F21*D21,2) -> 20
A22: 6 | C22: DOCUMENT FEE | D22: 1 | E22: SET | F22: 25 | G22: =ROUND(F22*D22,2) -> 25
A23: 7 | C23: SERVICE TAXATION | D23: 1 | E23: SHIP | F23: 20 | G23: =ROUND(F23*D23,2) -> 20
A24: 8 | C24: PERMIT FEE | D24: 1 | E24: SET | F24: 45 | G24: =ROUND(F24*D24,2) -> 45
A25: 9 | C25: FUEL SURCHARE | D25: 1 | E25: 40H | F25: 50 | G25: =ROUND(F25*D25,2) -> 50
A26: 10 | C26: TRUCKING DETENTION CHARGE | D26: 1 | E26: NIGHT | F26: 70 | G26: =ROUND(F26*D26,2) -> 70
A27: 11 | C27: OVER WEIGHT | D27: 4.99 | E27: TON | F27: 50 | G27: =ROUND(F27*D27,2) -> 249.5
A28: 12 | C28: LOLO EMPTY DROP DOWN | D28: 1 | E28: 40H | F28: 24.75 | G28: =ROUND(F28*D28,2) -> 24.75
D29: GRAND TOTAL: | F29: USD | G29: =SUM(G17:G28) -> 1183.25
A51: Thank you for your supporting | E51: AUTHORIZED SIGNATURE

Sheet 387
A2: ក្រុមហ៊ុន ហ្រ្តេតហ្វ៊ូល សឹលូសិន (ខេមបូឌា) ឯ.ក | J2: ក្រុមហ៊ុន ហ្រ្តេតហ្វ៊ូល សឹលូសិន (ខេមបូឌា) ឯ.ក
A3: GRATEFUL SOLUTIONS (CAMBODIA) CO.,LTD. | J3: GRATEFUL SOLUTIONS (CAMBODIA) CO.,LTD.
C4: លេខអត្តសញ្ញាណកម្ម អតប ( VATTIN ) : K008-902404873 | L4: លេខអត្តសញ្ញាណកម្ម អតប ( VATTIN ) : K008-902404873
A5: អាស័យដ្ឋាន : # 7E0 ផ្លូវបេតុង ក្រុម 7 ភូមិទួលថ្ងាន់ សង្កាត់ទួលសង្កែទី2 ខណ្ឌឬស្សីកែវ រាជធានីភ្នំពេញ | J5: អាស័យដ្ឋាន : # 7E0 ផ្លូវបេតុង ក្រុម 7 ភូមិទួលថ្ងាន់ សង្កាត់ទួលសង្កែទី2 ខណ្ឌឬស្សីកែវ រាជធានីភ្នំពេញ
A6: លេខទូរស័ព្ទ:​098​ 484 ​414 | J6: លេខទូរស័ព្ទ:​098​ 484 ​414
A9: វិក្កយបត្រអាករ | J9: វិក្កយបត្របង់ជំនួស
A10: TAX INVOICE | J10: DISBURSEMENT
A12: ឈ្មោះអតិថិជន /Customer: ជេអ អឹភែរឹល ឯ.ក | F12: លេខវិក័យប័ត្រ: /Invoice No: | I12: GS26-387 | J12: =A12 -> ឈ្មោះអតិថិជន /Customer: ជេអ អឹភែរឹល ឯ.ក | O12: លេខវិក័យប័ត្រ: /DIS-No: | R12: DIS430 | S12: E 291340
A13: JR APPAREL CO.,LTD | E13: ការបរិច្ឆេទវិក្កយបត្រ/Invoice Date: | I13: 46293 | J13: =A13 -> JR APPAREL CO.,LTD | N13: ការបរិច្ឆេទវិក្កយបត្រ/DIS-Date: | R13: =I13 -> 46293
A14: អាស័យដ្ឋាន/Address: KAOH KNOR VILLAGE PREAEK ROKA COMMUNE KANDAL | J14: =A14 -> អាស័យដ្ឋាន/Address: KAOH KNOR VILLAGE PREAEK ROKA COMMUNE KANDAL
A15: STUENG DISTRICT, KANDAL STUENG, KANDAL, CAMBODIA | J15: =A15 -> STUENG DISTRICT, KANDAL STUENG, KANDAL, CAMBODIA
A16: លេខ អ ត ប (VATTIN) : L001-902501613 | J16: =A16 -> លេខ អ ត ប (VATTIN) : L001-902501613
A17: SHIPPER: | C17: JR APPAREL CO., LTD. | J17: =A17 -> SHIPPER: | L17: =C17 -> JR APPAREL CO., LTD.
A18: CONSIGNEE : | C18: CHAPTERONE SPORTSWEAR | G18: GROSS WEIGHT: | I18: 14112.8 | J18: =A18 -> CONSIGNEE : | L18: =C18 -> CHAPTERONE SPORTSWEAR | P18: =G18 -> GROSS WEIGHT: | R18: =I18 -> 14112.8
A19: HBL: | B19: COSU6464270740 | D19: VOLUME: | E19: 1X45'HQ | H19: POL: | I19: PNH PORT | J19: =A19 -> HBL: | K19: =B19 -> COSU6464270740 | M19: VOLUME: | N19: =E19 -> 1X45'HQ | Q19: POL: | R19: =I19 -> PNH PORT
A20: PKGS: | B20: 814 CTNS | D20: CTNR No: | E20: CSNU6327198 | H20: POD: | I20: USA | J20: =A20 -> PKGS: | K20: =B20 -> 814 CTNS | M20: CTNR No: | N20: =E20 -> CSNU6327198 | Q20: POD: | R20: =I20 -> USA
G21: 4057 | P21: =G21 -> 4057
A22: ល.រ | B22: បរិយាយមុខទំនិញ | D22: បរិមាណ | E22: ឯកតា | F22: ថ្លៃឯកតា | G22: សរុប | H22: អាករ10% | I22: ថ្លៃទំនិញ | J22: ល.រ | K22: បរិយាយមុខទំនិញ | M22: បរិមាណ | N22: ឯកតា | O22: ថ្លៃឯកតា | P22: សរុប | Q22: អាករ 0% | R22: ថ្លៃទំនិញ
A23: No | B23: Description | D23: Quatity | E23: Unit | F23: Unit Price | G23: Sub. Total | H23: VAT ( 10%) | I23: Amount | J23: No | K23: Description | M23: Quatity | N23: Unit | O23: Unit Price | P23: Sub. Total | Q23: VAT ( 0%) | R23: Amount
A25: 1 | B25: កំរៃសេវាបំពេញបែបបទនាំចេញ / EXPORT PROCESSING FEE | D25: 1 | E25: 45H | F25: 242 | G25: =ROUND(F25*D25,2) -> 242 | H25: =G25*10% -> 24.2 | I25: =H25+G25 -> 266.2 | J25: 1 | K25: LOLO AT PORT | M25: 1 | N25: 45H | O25: 77 | P25: =O25*M25 -> 77 | Q25: 0 | R25: =Q25+P25 -> 77
J26: 2 | K26: CUSTOM PROCESSING FEE | M26: 1 | N26: 45H | O26: 21.25 | P26: =O26*M26 -> 21.25 | Q26: 0 | R26: =Q26+P26 -> 21.25
J27: 3 | K27: HBL FEE | M27: 1 | N27: 45H | O27: 539 | P27: =O27*M27 -> 539 | Q27: 0 | R27: =Q27+P27 -> 539
C29: សរុប SUB TOTAL | E29: KHR | F29: =$I$29*G21 -> 981794 | H29: USD | I29: =SUM(G25:G28) -> 242 | L29: សរុប SUB TOTAL | Q29: USD | R29: =SUM(R25:R28) -> 637.25
C30: អារករលើតម្លៃបន្ថែម (VAT 10%) | E30: KHR | F30: =$I$30*$G$21 -> 98179.4 | H30: USD | I30: =ROUND(SUM(H25:H28),2) -> 24.2 | L30: អារករលើតម្លៃបន្ថែម (VAT 0%) | Q30: USD | R30: 0
C31: សរុបរួម GRAND TOTAL | E31: KHR | F31: =I31*$G$21 -> 1079973.4 | H31: USD | I31: =$I$29+$I$30 -> 266.2 | L31: សរុបរួម GRAND TOTAL | Q31: USD | R31: =SUM(R29:R30) -> 637.25 | S31: =SUM(I31,R31) -> 903.45
A33: Note: Can make payment by cross cheque to: | J33: Note: Can make payment by cross cheque to:
A34: GRATEFUL SOLUTIONS (CAMBODIA) CO.,LTD. | J34: GRATEFUL SOLUTIONS (CAMBODIA) CO.,LTD.
A35: or Deposit Cash/Cheque payment to bank as below: | J35: or Deposit Cash/Cheque payment to bank as below:
A36: KB BRASAC BANK PLC | J36: KB BRASAC BANK PLC
A37: A/NAME: GRATEFUL SOLUTIONS (CAMBODIA) CO.,LTD. | J37: A/NAME: GRATEFUL SOLUTIONS (CAMBODIA) CO.,LTD.
A38: AC/NO: 033 754 230 001 | J38: AC/NO: 033 754 230 001
A49: ________________________ | G49: _______________________________ | J49: ________________________ | P49: _______________________________
A50: ហត្ថលេខា និង ឈ្មោះអ្នកទិញ | G50: ​​​​​​​​​​​ ហត្ថលេខា និង ឈ្មោះអ្នកលក់ | J50: ហត្ថលេខា និង ឈ្មោះអ្នកទិញ | P50: ​​​​​​​​​​​ ហត្ថលេខា និង ឈ្មោះអ្នកលក់
A51: សម្គាល់ច្បាប់ដើមសំរាប់អ្នកទិញច្បាប់ចំលងសំរាប់អ្នកលក់ | J51: សម្គាល់ច្បាប់ដើមសំរាប់អ្នកទិញច្បាប់ចំលងសំរាប់អ្នកលក់
A52: Note ÷ Original invoice for customer , copies invoice for seller | J52: Note ÷ Original invoice for customer , copies invoice for seller

Sheet D007
A1: DEBIT NOTE
A4: CUSTOMER | B4: : | C4: JR APPAREL CO.,LTD | F4: DN NO | G4: JR2609007
A5: ADDRESS | B5: : | C5: KAOH KNOR VILLAGE PREAEK ROKA | F5: DATE | G5: ='387'!I13 -> 46293
C6: COMMUNE KANDALSTUENG DISTRICT,
C7: KANDAL STUENG, KANDAL, CAMBODIA
A9: HBL NO | B9: : | C9: ='387'!B19 -> COSU6464270740
A10: G.W | B10: : | C10: ='387'!I18 -> 14112.8 | F10: POL: | G10: ='387'!I19 -> PNH PORT
A11: VOLUME: | B11: : | C11: ='387'!E19 -> 1X45'HQ | F11: POD: | G11: ='387'!I20 -> USA
A12: CTNR No: | B12: : | C12: ='387'!E20 -> CSNU6327198 | F12: PKGS: | G12: ='387'!B20 -> 814 CTNS
A13: Shipper | B13: : | C13: ='387'!C17 -> JR APPAREL CO., LTD.
A14: Consignee | B14: : | C14: ='387'!C18 -> CHAPTERONE SPORTSWEAR
A16: NO | C16: DESCRIPTION | D16: Q'TY | E16: U/M | F16: PRICE | G16: TOTAL | H16: ='387'!S12 -> E 291340
A17: 1 | C17: TRUCKING FEE | D17: 1 | E17: 45H | F17: 260 | G17: =ROUND(F17*D17,2) -> 260
A18: 2 | C18: HANDLING FEE | D18: 1 | E18: 45H | F18: 35 | G18: =ROUND(F18*D18,2) -> 35
A19: 3 | C19: INCREASE TRUCKING FEE(65%) | D19: 1 | E19: TRUCK | F19: 169 | G19: =ROUND(F19*D19,2) -> 169
A20: 4 | C20: INSPECTION AT DRYPORT | D20: 1 | E20: TIME | F20: 57.5 | G20: =ROUND(F20*D20,2) -> 57.5
A21: 5 | C21: DOCUMENT FEE | D21: 1 | E21: SET | F21: 25 | G21: =ROUND(F21*D21,2) -> 25
A22: 6 | C22: SERVICE TAXATION | D22: 1 | E22: SHIP | F22: 20 | G22: =ROUND(F22*D22,2) -> 20
A23: 7 | C23: FUEL SURCHARGE | D23: 1 | E23: 45H | F23: 40 | G23: =ROUND(F23*D23,2) -> 40
A24: 8 | C24: TRUCKING TO SECOND PLACE | D24: 1 | E24: 45H | F24: 60 | G24: =ROUND(F24*D24,2) -> 60
A25: 9 | C25: LOLO EMPTY CONTAINER | D25: 1 | E25: 45H | F25: 49.5 | G25: =ROUND(F25*D25,2) -> 49.5
A26: 10 | C26: GATE FEE AT DRY PORT | D26: 1 | E26: 45H | F26: 15 | G26: =ROUND(F26*D26,2) -> 15
A27: 11 | C27: APPLY CO FOR INV: JRA26057 | D27: 1 | E27: INV | F27: 40 | G27: =ROUND(F27*D27,2) -> 40
D28: GRAND TOTAL: | F28: USD | G28: =SUM(G17:G27) -> 771
A51: Thank you for your supporting | E51: AUTHORIZED SIGNATURE

Sheet 388
A2: ក្រុមហ៊ុន ហ្រ្តេតហ្វ៊ូល សឹលូសិន (ខេមបូឌា) ឯ.ក | J2: ក្រុមហ៊ុន ហ្រ្តេតហ្វ៊ូល សឹលូសិន (ខេមបូឌា) ឯ.ក
A3: GRATEFUL SOLUTIONS (CAMBODIA) CO.,LTD. | J3: GRATEFUL SOLUTIONS (CAMBODIA) CO.,LTD.
C4: លេខអត្តសញ្ញាណកម្ម អតប ( VATTIN ) : K008-902404873 | L4: លេខអត្តសញ្ញាណកម្ម អតប ( VATTIN ) : K008-902404873
A5: អាស័យដ្ឋាន : # 7E0 ផ្លូវបេតុង ក្រុម 7 ភូមិទួលថ្ងាន់ សង្កាត់ទួលសង្កែទី2 ខណ្ឌឬស្សីកែវ រាជធានីភ្នំពេញ | J5: អាស័យដ្ឋាន : # 7E0 ផ្លូវបេតុង ក្រុម 7 ភូមិទួលថ្ងាន់ សង្កាត់ទួលសង្កែទី2 ខណ្ឌឬស្សីកែវ រាជធានីភ្នំពេញ
A6: លេខទូរស័ព្ទ:​098​ 484 ​414 | J6: លេខទូរស័ព្ទ:​098​ 484 ​414
A9: វិក្កយបត្រអាករ | J9: វិក្កយបត្របង់ជំនួស
A10: TAX INVOICE | J10: DISBURSEMENT
A12: ឈ្មោះអតិថិជន /Customer: ជេអ អឹភែរឹល ឯ.ក | F12: លេខវិក័យប័ត្រ: /Invoice No: | I12: GS26-388 | J12: =A12 -> ឈ្មោះអតិថិជន /Customer: ជេអ អឹភែរឹល ឯ.ក | O12: លេខវិក័យប័ត្រ: /DIS-No: | R12: DIS431 | S12: I 138725
A13: JR APPAREL CO.,LTD | E13: ការបរិច្ឆេទវិក្កយបត្រ/Invoice Date: | I13: 46293 | J13: =A13 -> JR APPAREL CO.,LTD | N13: ការបរិច្ឆេទវិក្កយបត្រ/DIS-Date: | R13: =I13 -> 46293
A14: អាស័យដ្ឋាន/Address: KAOH KNOR VILLAGE PREAEK ROKA COMMUNE KANDAL | J14: =A14 -> អាស័យដ្ឋាន/Address: KAOH KNOR VILLAGE PREAEK ROKA COMMUNE KANDAL
A15: STUENG DISTRICT, KANDAL STUENG, KANDAL, CAMBODIA | J15: =A15 -> STUENG DISTRICT, KANDAL STUENG, KANDAL, CAMBODIA
A16: លេខ អ ត ប (VATTIN) : L001-902501613 | J16: =A16 -> លេខ អ ត ប (VATTIN) : L001-902501613
A17: SHIPPER: | C17: SHANGHAI YONGYUE IMP. &EXP. TRADING CO., LTD. | J17: =A17 -> SHIPPER: | L17: =C17 -> SHANGHAI YONGYUE IMP. &EXP. TRADING CO., LTD.
A18: CONSIGNEE : | C18: JR APPAREL CO., LTD. | G18: GROSS WEIGHT: | I18: 11104.1 | J18: =A18 -> CONSIGNEE : | L18: =C18 -> JR APPAREL CO., LTD. | P18: =G18 -> GROSS WEIGHT: | R18: =I18 -> 11104.1
A19: HBL: | B19: SHSIN6090113 | D19: VOLUME: | E19: 1X20'GP | H19: POL: | I19: CHINA | J19: =A19 -> HBL: | K19: =B19 -> SHSIN6090113 | M19: VOLUME: | N19: =E19 -> 1X20'GP | Q19: POL: | R19: =I19 -> CHINA
A20: PKGS: | B20: 306 ROLLS | D20: CTNR No: | E20: SEKU1756681 | H20: POD: | I20: SHV PORT | J20: =A20 -> PKGS: | K20: =B20 -> 306 ROLLS | M20: CTNR No: | N20: =E20 -> SEKU1756681 | Q20: POD: | R20: =I20 -> SHV PORT
G21: 4057 | P21: =G21 -> 4057
A22: ល.រ | B22: បរិយាយមុខទំនិញ | D22: បរិមាណ | E22: ឯកតា | F22: ថ្លៃឯកតា | G22: សរុប | H22: អាករ10% | I22: ថ្លៃទំនិញ | J22: ល.រ | K22: បរិយាយមុខទំនិញ | M22: បរិមាណ | N22: ឯកតា | O22: ថ្លៃឯកតា | P22: សរុប | Q22: អាករ 0% | R22: ថ្លៃទំនិញ
A23: No | B23: Description | D23: Quatity | E23: Unit | F23: Unit Price | G23: Sub. Total | H23: VAT ( 10%) | I23: Amount | J23: No | K23: Description | M23: Quatity | N23: Unit | O23: Unit Price | P23: Sub. Total | Q23: VAT ( 0%) | R23: Amount
A25: 1 | B25: កំរៃសេវាបំពេញបែបបទនាំចូល / IMPORT PROCESSING FEE | D25: 1 | E25: 20G | F25: 180 | G25: =ROUND(F25*D25,2) -> 180 | H25: =G25*10% -> 18 | I25: =H25+G25 -> 198 | J25: 1 | K25: LOLO AT PORT | M25: 1 | N25: 20G | O25: 62.7 | P25: =O25*M25 -> 62.7 | Q25: 0 | R25: =Q25+P25 -> 62.7
J26: 2 | K26: CUSTOM PROCESSING FEE | M26: 1 | N26: 20G | O26: 18.75 | P26: =O26*M26 -> 18.75 | Q26: 0 | R26: =Q26+P26 -> 18.75
J27: 3 | K27: THC FEE | M27: 1 | N27: 20G | O27: 479.5 | P27: =O27*M27 -> 479.5 | Q27: 0 | R27: =Q27+P27 -> 479.5
C29: សរុប SUB TOTAL | E29: KHR | F29: =$I$29*G21 -> 730260 | H29: USD | I29: =SUM(G25:G28) -> 180 | L29: សរុប SUB TOTAL | Q29: USD | R29: =SUM(R24:R28) -> 560.95
C30: អារករលើតម្លៃបន្ថែម (VAT 10%) | E30: KHR | F30: =$I$30*$G$21 -> 73026 | H30: USD | I30: =ROUND(SUM(H25:H28),2) -> 18 | L30: អារករលើតម្លៃបន្ថែម (VAT 0%) | Q30: USD | R30: 0
C31: សរុបរួម GRAND TOTAL | E31: KHR | F31: =I31*$G$21 -> 803286 | H31: USD | I31: =$I$29+$I$30 -> 198 | L31: សរុបរួម GRAND TOTAL | Q31: USD | R31: =SUM(R29:R30) -> 560.95 | S31: =SUM(I31,R31) -> 758.95
A33: Note: Can make payment by cross cheque to: | J33: Note: Can make payment by cross cheque to:
A34: GRATEFUL SOLUTIONS (CAMBODIA) CO.,LTD. | J34: GRATEFUL SOLUTIONS (CAMBODIA) CO.,LTD.
A35: or Deposit Cash/Cheque payment to bank as below: | J35: or Deposit Cash/Cheque payment to bank as below:
A36: KB BRASAC BANK PLC | J36: KB BRASAC BANK PLC
A37: A/NAME: GRATEFUL SOLUTIONS (CAMBODIA) CO.,LTD. | J37: A/NAME: GRATEFUL SOLUTIONS (CAMBODIA) CO.,LTD.
A38: AC/NO: 033 754 230 001 | J38: AC/NO: 033 754 230 001
A48: ________________________ | G48: _______________________________ | J48: ________________________ | P48: _______________________________
A49: ហត្ថលេខា និង ឈ្មោះអ្នកទិញ | G49: ​​​​​​​​​​​ ហត្ថលេខា និង ឈ្មោះអ្នកលក់ | J49: ហត្ថលេខា និង ឈ្មោះអ្នកទិញ | P49: ​​​​​​​​​​​ ហត្ថលេខា និង ឈ្មោះអ្នកលក់
A50: សម្គាល់ច្បាប់ដើមសំរាប់អ្នកទិញច្បាប់ចំលងសំរាប់អ្នកលក់ | J50: សម្គាល់ច្បាប់ដើមសំរាប់អ្នកទិញច្បាប់ចំលងសំរាប់អ្នកលក់
A51: Note ÷ Original invoice for customer , copies invoice for seller | J51: Note ÷ Original invoice for customer , copies invoice for seller

Sheet D008
A1: DEBIT NOTE
A4: CUSTOMER | B4: : | C4: JR APPAREL CO.,LTD | F4: DN NO | G4: JR2609008
A5: ADDRESS | B5: : | C5: KAOH KNOR VILLAGE PREAEK ROKA | F5: DATE | G5: ='388'!R13 -> 46293
C6: COMMUNE KANDALSTUENG DISTRICT,
C7: KANDAL STUENG, KANDAL, CAMBODIA
A9: HBL NO | B9: : | C9: ='388'!B19 -> SHSIN6090113
A10: G.W | B10: : | C10: ='388'!I18 -> 11104.1 | F10: POL: | G10: ='388'!I19 -> CHINA
A11: VOLUME: | B11: : | C11: ='388'!E19 -> 1X20'GP | F11: POD: | G11: ='388'!I20 -> SHV PORT
A12: CTNR No: | B12: : | C12: ='388'!E20 -> SEKU1756681 | F12: PKGS: | G12: ='388'!B20 -> 306 ROLLS
A13: Shipper | B13: : | C13: ='388'!C17 -> SHANGHAI YONGYUE IMP. &EXP. TRADING CO., LTD.
A14: Consignee | B14: : | C14: ='388'!C18 -> JR APPAREL CO., LTD.
A16: NO | C16: DESCRIPTION | D16: Q'TY | E16: U/M | F16: PRICE | G16: TOTAL | H16: ='388'!S12 -> I 138725
A17: 1 | C17: TRUCKING FEE | D17: 1 | E17: 20G | F17: 280 | G17: =ROUND(F17*D17,2) -> 280
A18: 2 | C18: HANDLING FEE | D18: 1 | E18: 20G | F18: 35 | G18: =ROUND(F18*D18,2) -> 35
A19: 3 | C19: INCREASE TRUCKING FEE(65%) | D19: 1 | E19: TRUCK | F19: 182 | G19: =ROUND(F19*D19,2) -> 182 | H19: =F17*65% -> 182
A20: 4 | C20: EXTRA TRUCKING FEE (TO PREK LEAP) | D20: 1 | E20: 20G | F20: 50 | G20: =ROUND(F20*D20,2) -> 50
A21: 5 | C21: PERMIT FEE | D21: 1 | E21: SET | F21: 45 | G21: =ROUND(F21*D21,2) -> 45
A22: 4 | C22: DOCUMENT FEE | D22: 1 | E22: SET | F22: 25 | G22: =ROUND(F22*D22,2) -> 25
A23: 5 | C23: SERVICE TAXATION | D23: 1 | E23: SHIP | F23: 20 | G23: =ROUND(F23*D23,2) -> 20
A24: 6 | C24: MISSING INSURANCE | D24: 1 | E24: SET | F24: 20 | G24: =ROUND(F24*D24,2) -> 20
A25: 7 | C25: FUEL SURCHARGE | D25: 1 | E25: 20G | F25: 30 | G25: =ROUND(F25*D25,2) -> 30
A26: 9 | C26: LOLO EMPTY DROP DOWN | D26: 1 | E26: 20G | F26: 16.5 | G26: =ROUND(F26*D26,2) -> 16.5
D27: GRAND TOTAL: | F27: USD | G27: =SUM(G17:G26) -> 703.5
A51: Thank you for your supporting | E51: AUTHORIZED SIGNATURE

Sheet 389
A2: ក្រុមហ៊ុន ហ្រ្តេតហ្វ៊ូល សឹលូសិន (ខេមបូឌា) ឯ.ក | J2: ក្រុមហ៊ុន ហ្រ្តេតហ្វ៊ូល សឹលូសិន (ខេមបូឌា) ឯ.ក
A3: GRATEFUL SOLUTIONS (CAMBODIA) CO.,LTD. | J3: GRATEFUL SOLUTIONS (CAMBODIA) CO.,LTD.
C4: លេខអត្តសញ្ញាណកម្ម អតប ( VATTIN ) : K008-902404873 | L4: លេខអត្តសញ្ញាណកម្ម អតប ( VATTIN ) : K008-902404873
A5: អាស័យដ្ឋាន : # 7E0 ផ្លូវបេតុង ក្រុម 7 ភូមិទួលថ្ងាន់ សង្កាត់ទួលសង្កែទី2 ខណ្ឌឬស្សីកែវ រាជធានីភ្នំពេញ | J5: អាស័យដ្ឋាន : # 7E0 ផ្លូវបេតុង ក្រុម 7 ភូមិទួលថ្ងាន់ សង្កាត់ទួលសង្កែទី2 ខណ្ឌឬស្សីកែវ រាជធានីភ្នំពេញ
A6: លេខទូរស័ព្ទ:​098​ 484 ​414 | J6: លេខទូរស័ព្ទ:​098​ 484 ​414
A9: វិក្កយបត្រអាករ | J9: វិក្កយបត្របង់ជំនួស
A10: TAX INVOICE | J10: DISBURSEMENT
A12: ឈ្មោះអតិថិជន /Customer: ជេអ អឹភែរឹល ឯ.ក | F12: លេខវិក័យប័ត្រ: /Invoice No: | I12: GS26-389 | J12: =A12 -> ឈ្មោះអតិថិជន /Customer: ជេអ អឹភែរឹល ឯ.ក | O12: លេខវិក័យប័ត្រ: /DIS-No: | R12: DIS432 | S12: I 138735
A13: JR APPAREL CO.,LTD | E13: ការបរិច្ឆេទវិក្កយបត្រ/Invoice Date: | I13: 46293 | J13: =A13 -> JR APPAREL CO.,LTD | N13: ការបរិច្ឆេទវិក្កយបត្រ/DIS-Date: | R13: =I13 -> 46293
A14: អាស័យដ្ឋាន/Address: KAOH KNOR VILLAGE PREAEK ROKA COMMUNE KANDAL | J14: =A14 -> អាស័យដ្ឋាន/Address: KAOH KNOR VILLAGE PREAEK ROKA COMMUNE KANDAL
A15: STUENG DISTRICT, KANDAL STUENG, KANDAL, CAMBODIA | J15: =A15 -> STUENG DISTRICT, KANDAL STUENG, KANDAL, CAMBODIA
A16: លេខ អ ត ប (VATTIN) : L001-902501613 | J16: =A16 -> លេខ អ ត ប (VATTIN) : L001-902501613
A17: SHIPPER: | C17: SHANGHAI YONGYUE IMP. &EXP. TRADING CO., LTD. | J17: =A17 -> SHIPPER: | L17: =C17 -> SHANGHAI YONGYUE IMP. &EXP. TRADING CO., LTD.
A18: CONSIGNEE : | C18: JR APPAREL CO., LTD. | G18: GROSS WEIGHT: | I18: 18809.5 | J18: =A18 -> CONSIGNEE : | L18: =C18 -> JR APPAREL CO., LTD. | P18: =G18 -> GROSS WEIGHT: | R18: =I18 -> 18809.5
A19: HBL: | B19: SHSIN6090031 | D19: VOLUME: | E19: 1X40'HQ | H19: POL: | I19: CHINA | J19: =A19 -> HBL: | K19: =B19 -> SHSIN6090031 | M19: VOLUME: | N19: =E19 -> 1X40'HQ | O19: =F19 -> 0 | Q19: POL: | R19: =I19 -> CHINA
A20: PKGS: | B20: 635 ROLLS | D20: CTNR No: | E20: ZCSU7954124 | H20: POD: | I20: SHV PORT | J20: =A20 -> PKGS: | K20: =B20 -> 635 ROLLS | M20: CTNR No: | N20: =E20 -> ZCSU7954124 | Q20: POD: | R20: =I20 -> SHV PORT
G21: 4057 | P21: =G21 -> 4057
A22: ល.រ | B22: បរិយាយមុខទំនិញ | D22: បរិមាណ | E22: ឯកតា | F22: ថ្លៃឯកតា | G22: សរុប | H22: អាករ10% | I22: ថ្លៃទំនិញ | J22: ល.រ | K22: បរិយាយមុខទំនិញ | M22: បរិមាណ | N22: ឯកតា | O22: ថ្លៃឯកតា | P22: សរុប | Q22: អាករ 0% | R22: ថ្លៃទំនិញ
A23: No | B23: Description | D23: Quatity | E23: Unit | F23: Unit Price | G23: Sub. Total | H23: VAT ( 10%) | I23: Amount | J23: No | K23: Description | M23: Quatity | N23: Unit | O23: Unit Price | P23: Sub. Total | Q23: VAT ( 0%) | R23: Amount
A25: 1 | B25: កំរៃសេវាបំពេញបែបបទនាំចូល / IMPORT PROCESSING FEE | D25: 1 | E25: 40H | F25: 200 | G25: =ROUND(F25*D25,2) -> 200 | H25: =G25*10% -> 20 | I25: =H25+G25 -> 220 | J25: 1 | K25: LOLO AT PORT | M25: 1 | N25: 40H | O25: 95.7 | P25: =O25*M25 -> 95.7 | Q25: 0 | R25: =Q25+P25 -> 95.7
J26: 2 | K26: CUSTOM PROCESSING FEE | M26: 1 | N26: 40H | O26: 18.75 | P26: =O26*M26 -> 18.75 | Q26: 0 | R26: =Q26+P26 -> 18.75
J27: 3 | K27: THC FEE | M27: 1 | N27: 40H | O27: 599.5 | P27: =O27*M27 -> 599.5 | Q27: 0 | R27: =Q27+P27 -> 599.5
C29: សរុប SUB TOTAL | E29: KHR | F29: =$I$29*G21 -> 811400 | H29: USD | I29: =SUM(G25:G28) -> 200 | L29: សរុប SUB TOTAL | Q29: USD | R29: =SUM(R24:R28) -> 713.95
C30: អារករលើតម្លៃបន្ថែម (VAT 10%) | E30: KHR | F30: =$I$30*$G$21 -> 81140 | H30: USD | I30: =ROUND(SUM(H25:H28),2) -> 20 | L30: អារករលើតម្លៃបន្ថែម (VAT 0%) | Q30: USD | R30: 0
C31: សរុបរួម GRAND TOTAL | E31: KHR | F31: =I31*$G$21 -> 892540 | H31: USD | I31: =$I$29+$I$30 -> 220 | L31: សរុបរួម GRAND TOTAL | Q31: USD | R31: =SUM(R29:R30) -> 713.95 | S31: =SUM(I31,R31) -> 933.95
A33: Note: Can make payment by cross cheque to: | J33: Note: Can make payment by cross cheque to:
A34: GRATEFUL SOLUTIONS (CAMBODIA) CO.,LTD. | J34: GRATEFUL SOLUTIONS (CAMBODIA) CO.,LTD.
A35: or Deposit Cash/Cheque payment to bank as below: | J35: or Deposit Cash/Cheque payment to bank as below:
A36: KB BRASAC BANK PLC | J36: KB BRASAC BANK PLC
A37: A/NAME: GRATEFUL SOLUTIONS (CAMBODIA) CO.,LTD. | J37: A/NAME: GRATEFUL SOLUTIONS (CAMBODIA) CO.,LTD.
A38: AC/NO: 033 754 230 001 | J38: AC/NO: 033 754 230 001
A48: ________________________ | G48: _______________________________ | J48: ________________________ | P48: _______________________________
A49: ហត្ថលេខា និង ឈ្មោះអ្នកទិញ | G49: ​​​​​​​​​​​ ហត្ថលេខា និង ឈ្មោះអ្នកលក់ | J49: ហត្ថលេខា និង ឈ្មោះអ្នកទិញ | P49: ​​​​​​​​​​​ ហត្ថលេខា និង ឈ្មោះអ្នកលក់
A50: សម្គាល់ច្បាប់ដើមសំរាប់អ្នកទិញច្បាប់ចំលងសំរាប់អ្នកលក់ | J50: សម្គាល់ច្បាប់ដើមសំរាប់អ្នកទិញច្បាប់ចំលងសំរាប់អ្នកលក់
A51: Note ÷ Original invoice for customer , copies invoice for seller | J51: Note ÷ Original invoice for customer , copies invoice for seller

Sheet D009
A1: DEBIT NOTE
A4: CUSTOMER | B4: : | C4: JR APPAREL CO.,LTD | F4: DN NO | G4: JR2609009
A5: ADDRESS | B5: : | C5: KAOH KNOR VILLAGE PREAEK ROKA | F5: DATE | G5: ='389'!R13 -> 46293
C6: COMMUNE KANDALSTUENG DISTRICT,
C7: KANDAL STUENG, KANDAL, CAMBODIA
A9: HBL NO | B9: : | C9: ='389'!B19 -> SHSIN6090031
A10: G.W | B10: : | C10: ='389'!I18 -> 18809.5 | F10: POL: | G10: ='389'!I19 -> CHINA
A11: VOLUME: | B11: : | C11: ='389'!E19 -> 1X40'HQ | F11: POD: | G11: ='389'!I20 -> SHV PORT
A12: CTNR No: | B12: : | C12: ='389'!E20 -> ZCSU7954124 | F12: PKGS: | G12: ='389'!B20 -> 635 ROLLS
A13: Shipper | B13: : | C13: ='389'!C17 -> SHANGHAI YONGYUE IMP. &EXP. TRADING CO., LTD.
A14: Consignee | B14: : | C14: ='389'!C18 -> JR APPAREL CO., LTD.
A16: NO | C16: DESCRIPTION | D16: Q'TY | E16: U/M | F16: PRICE | G16: TOTAL | H16: ='389'!S12 -> I 138735
A17: 1 | C17: TRUCKING FEE | D17: 1 | E17: 40H | F17: 360 | G17: =ROUND(F17*D17,2) -> 360
A18: 2 | C18: HANDLING FEE | D18: 1 | E18: 40H | F18: 35 | G18: =ROUND(F18*D18,2) -> 35
A19: 3 | C19: INCREASE TRUCKING FEE(65%) | D19: 1 | E19: TRUCK | F19: 234 | G19: =ROUND(F19*D19,2) -> 234
A20: 4 | C20: MISSING INSURANCE | D20: 1 | E20: SET | F20: 20 | G20: =ROUND(F20*D20,2) -> 20
A21: 5 | C21: DOCUMENT FEE | D21: 1 | E21: SET | F21: 25 | G21: =ROUND(F21*D21,2) -> 25
A22: 6 | C22: SERVICE TAXATION | D22: 1 | E22: SHIP | F22: 20 | G22: =ROUND(F22*D22,2) -> 20
A23: 7 | C23: PERMIT FEE | D23: 1 | E23: SET | F23: 45 | G23: =ROUND(F23*D23,2) -> 45
A24: 8 | C24: FUEL SURCHARE | D24: 1 | E24: 40H | F24: 50 | G24: =ROUND(F24*D24,2) -> 50
A25: 9 | C25: RETURN EMPTY | D25: 1 | E25: 40H | F25: 100 | G25: =ROUND(F25*D25,2) -> 100
A26: 10 | C26: LOLO EMPTY DROP DOWN | D26: 1 | E26: 40H | F26: 24.75 | G26: =ROUND(F26*D26,2) -> 24.75
D27: GRAND TOTAL: | F27: USD | G27: =SUM(G17:G26) -> 913.75
A51: Thank you for your supporting | E51: AUTHORIZED SIGNATURE

Sheet 393
A2: ក្រុមហ៊ុន ហ្រ្តេតហ្វ៊ូល សឹលូសិន (ខេមបូឌា) ឯ.ក | J2: ក្រុមហ៊ុន ហ្រ្តេតហ្វ៊ូល សឹលូសិន (ខេមបូឌា) ឯ.ក
A3: GRATEFUL SOLUTIONS (CAMBODIA) CO.,LTD. | J3: GRATEFUL SOLUTIONS (CAMBODIA) CO.,LTD.
C4: លេខអត្តសញ្ញាណកម្ម អតប ( VATTIN ) : K008-902404873 | L4: លេខអត្តសញ្ញាណកម្ម អតប ( VATTIN ) : K008-902404873
A5: អាស័យដ្ឋាន : # 7E0 ផ្លូវបេតុង ក្រុម 7 ភូមិទួលថ្ងាន់ សង្កាត់ទួលសង្កែទី2 ខណ្ឌឬស្សីកែវ រាជធានីភ្នំពេញ | J5: អាស័យដ្ឋាន : # 7E0 ផ្លូវបេតុង ក្រុម 7 ភូមិទួលថ្ងាន់ សង្កាត់ទួលសង្កែទី2 ខណ្ឌឬស្សីកែវ រាជធានីភ្នំពេញ
A6: លេខទូរស័ព្ទ:​098​ 484 ​414 | J6: លេខទូរស័ព្ទ:​098​ 484 ​414
A9: វិក្កយបត្រអាករ | J9: វិក្កយបត្របង់ជំនួស
A10: TAX INVOICE | J10: DISBURSEMENT
A12: ឈ្មោះអតិថិជន /Customer: ជេអ អឹភែរឹល ឯ.ក | F12: លេខវិក័យប័ត្រ: /Invoice No: | I12: GS26-393 | J12: =A12 -> ឈ្មោះអតិថិជន /Customer: ជេអ អឹភែរឹល ឯ.ក | O12: លេខវិក័យប័ត្រ: /DIS-No: | R12: DIS436
A13: JR APPAREL CO.,LTD | E13: ការបរិច្ឆេទវិក្កយបត្រ/Invoice Date: | I13: 46295 | J13: =A13 -> JR APPAREL CO.,LTD | N13: ការបរិច្ឆេទវិក្កយបត្រ/DIS-Date: | R13: =I13 -> 46295
A14: អាស័យដ្ឋាន/Address: KAOH KNOR VILLAGE PREAEK ROKA COMMUNE KANDAL | J14: =A14 -> អាស័យដ្ឋាន/Address: KAOH KNOR VILLAGE PREAEK ROKA COMMUNE KANDAL
A15: STUENG DISTRICT, KANDAL STUENG, KANDAL, CAMBODIA | J15: =A15 -> STUENG DISTRICT, KANDAL STUENG, KANDAL, CAMBODIA
A16: លេខ អ ត ប (VATTIN) : L001-902501613 | J16: =A16 -> លេខ អ ត ប (VATTIN) : L001-902501613
A17: SHIPPER: | C17: JR APPAREL CO., LTD. | J17: =A17 -> SHIPPER: | L17: =C17 -> JR APPAREL CO., LTD.
A18: CONSIGNEE : | C18: CHAPTERONE SPORTSWEAR | G18: GROSS WEIGHT: | I18: 3577.5 | J18: =A18 -> CONSIGNEE : | L18: =C18 -> CHAPTERONE SPORTSWEAR | P18: =G18 -> GROSS WEIGHT: | R18: =I18 -> 3577.5
A19: HBL: | B19: KHS2609038 | D19: VOLUME: | E19: 15.17 | F19: CBM | H19: POL: | I19: PNH PORT | J19: =A19 -> HBL: | K19: =B19 -> KHS2609038 | M19: VOLUME: | N19: =E19 -> 15.17 | O19: =F19 -> CBM | Q19: POL: | R19: =I19 -> PNH PORT
A20: PKGS: | B20: 195 CTNS | D20: CTNR No: | E20: LCL | H20: POD: | I20: CANADA | J20: =A20 -> PKGS: | K20: =B20 -> 195 CTNS | M20: CTNR No: | N20: =E20 -> LCL | Q20: POD: | R20: =I20 -> CANADA
G21: 4055 | P21: =G21 -> 4055
A22: ល.រ | B22: បរិយាយមុខទំនិញ | D22: បរិមាណ | E22: ឯកតា | F22: ថ្លៃឯកតា | G22: សរុប | H22: អាករ10% | I22: ថ្លៃទំនិញ | J22: ល.រ | K22: បរិយាយមុខទំនិញ | M22: បរិមាណ | N22: ឯកតា | O22: ថ្លៃឯកតា | P22: សរុប | Q22: អាករ 0% | R22: ថ្លៃទំនិញ
A23: No | B23: Description | D23: Quatity | E23: Unit | F23: Unit Price | G23: Sub. Total | H23: VAT ( 10%) | I23: Amount | J23: No | K23: Description | M23: Quatity | N23: Unit | O23: Unit Price | P23: Sub. Total | Q23: VAT ( 0%) | R23: Amount
A25: 1 | B25: កំរៃសេវាបំពេញបែបបទនាំចូល / IMPORT PROCESSING FEE | D25: 1 | E25: 20G | F25: 180 | G25: =ROUND(F25*D25,2) -> 180 | H25: =G25*10% -> 18 | I25: =H25+G25 -> 198 | J25: 1 | K25: HBL FEE | M25: 1 | N25: SHIP | O25: 703.26 | P25: =O25*M25 -> 703.26 | Q25: 0 | R25: =Q25+P25 -> 703.26 | S25: =235+231 -> 466
C27: សរុប SUB TOTAL | E27: KHR | F27: =$I$27*G21 -> 729900 | H27: USD | I27: =SUM(G25:G26) -> 180 | L27: សរុប SUB TOTAL | Q27: USD | R27: =SUM(R24:R26) -> 703.26
C28: អារករលើតម្លៃបន្ថែម (VAT 10%) | E28: KHR | F28: =$I$28*$G$21 -> 72990 | H28: USD | I28: =ROUND(SUM(H25:H26),2) -> 18 | L28: អារករលើតម្លៃបន្ថែម (VAT 0%) | Q28: USD | R28: 0
C29: សរុបរួម GRAND TOTAL | E29: KHR | F29: =I29*$G$21 -> 802890 | H29: USD | I29: =$I$27+$I$28 -> 198 | L29: សរុបរួម GRAND TOTAL | Q29: USD | R29: =SUM(R27:R28) -> 703.26 | S29: =SUM(I29,R29) -> 901.26
A31: Note: Can make payment by cross cheque to: | J31: Note: Can make payment by cross cheque to:
A32: GRATEFUL SOLUTIONS (CAMBODIA) CO.,LTD. | J32: GRATEFUL SOLUTIONS (CAMBODIA) CO.,LTD.
A33: or Deposit Cash/Cheque payment to bank as below: | J33: or Deposit Cash/Cheque payment to bank as below:
A34: KB BRASAC BANK PLC | J34: KB BRASAC BANK PLC
A35: A/NAME: GRATEFUL SOLUTIONS (CAMBODIA) CO.,LTD. | J35: A/NAME: GRATEFUL SOLUTIONS (CAMBODIA) CO.,LTD.
A36: AC/NO: 033 754 230 001 | J36: AC/NO: 033 754 230 001
A49: ________________________ | G49: _______________________________ | J49: ________________________ | P49: _______________________________
A50: ហត្ថលេខា និង ឈ្មោះអ្នកទិញ | G50: ​​​​​​​​​​​ ហត្ថលេខា និង ឈ្មោះអ្នកលក់ | J50: ហត្ថលេខា និង ឈ្មោះអ្នកទិញ | P50: ​​​​​​​​​​​ ហត្ថលេខា និង ឈ្មោះអ្នកលក់
A51: សម្គាល់ច្បាប់ដើមសំរាប់អ្នកទិញច្បាប់ចំលងសំរាប់អ្នកលក់ | J51: សម្គាល់ច្បាប់ដើមសំរាប់អ្នកទិញច្បាប់ចំលងសំរាប់អ្នកលក់
A52: Note ÷ Original invoice for customer , copies invoice for seller | J52: Note ÷ Original invoice for customer , copies invoice for seller

Sheet D010
A1: DEBIT NOTE
A4: CUSTOMER | B4: : | C4: JR APPAREL CO.,LTD | F4: DN NO | G4: JR2609010
A5: ADDRESS | B5: : | C5: KAOH KNOR VILLAGE PREAEK ROKA | F5: DATE | G5: ='393'!R13 -> 46295
C6: COMMUNE KANDALSTUENG DISTRICT,
C7: KANDAL STUENG, KANDAL, CAMBODIA
A9: HBL NO | B9: : | C9: ='393'!B19 -> KHS2609038
A10: G.W | B10: : | C10: ='393'!I18 -> 3577.5 | F10: POL: | G10: ='393'!I19 -> PNH PORT
A11: VOLUME: | B11: : | C11: ='393'!E19 -> 15.17 | F11: POD: | G11: ='393'!I20 -> CANADA
A12: CTNR No: | B12: : | C12: ='393'!E20 -> LCL | F12: PKGS: | G12: ='393'!B20 -> 195 CTNS
A13: Shipper | B13: : | C13: ='393'!C17 -> JR APPAREL CO., LTD.
A14: Consignee | B14: : | C14: ='393'!C18 -> CHAPTERONE SPORTSWEAR
A16: NO | C16: DESCRIPTION | D16: Q'TY | E16: U/M | F16: PRICE | G16: TOTAL | H16: ='393'!S12 -> 0
A17: 1 | C17: DOCUMENT FEE | D17: 1 | E17: SHIP | F17: 25 | G17: =ROUND(F17*D17,2) -> 25
A18: =A17+1 -> 2 | C18: HANDLING FEE | D18: 1 | E18: SHIP | F18: 35 | G18: =ROUND(F18*D18,2) -> 35
A19: =A18+1 -> 3 | C19: APPLY CO FOR INV: JRA26052 | D19: 1 | E19: INV | F19: 40 | G19: =ROUND(F19*D19,2) -> 40
A20: =A19+1 -> 4 | C20: EQMC FOR INV: JRA26052 | D20: 1 | E20: INV | F20: 54 | G20: =ROUND(F20*D20,2) -> 54
A21: =A20+1 -> 5 | C21: SERVICE TAXATION | D21: 1 | E21: SET | F21: 20 | G21: =ROUND(F21*D21,2) -> 20
D22: GRAND TOTAL: | F22: USD | G22: =SUM(G17:G21) -> 174
A51: Thank you for your supporting | E51: AUTHORIZED SIGNATURE

Sheet D011
A1: DEBIT NOTE
A4: CUSTOMER | B4: : | C4: JR APPAREL CO.,LTD | F4: DN NO | G4: JR2609011
A5: ADDRESS | B5: : | C5: KAOH KNOR VILLAGE PREAEK ROKA | F5: DATE | G5: 46295
C6: COMMUNE KANDALSTUENG DISTRICT,
C7: KANDAL STUENG, KANDAL, CAMBODIA
A10: CHARGE | B10: : | C10: MIH CHARGE AND PAYROLL FEE
A16: NO | C16: DESCRIPTION | D16: Q'TY | E16: U/M | F16: PRICE | G16: TOTAL
A17: 1 | C17: MIH FEE FOR SEP | D17: 1 | E17: MONTH | F17: 30 | G17: =ROUND(F17*D17,2) -> 30
A18: 2 | C18: PAYROLL FEE FROM AUG TO SEP | D18: 2 | E18: MONTH | F18: 25 | G18: =ROUND(F18*D18,2) -> 50
D19: GRAND TOTAL: | F19: USD | G19: =SUM(G17:G18) -> 80
A51: Thank you for your supporting | E51: AUTHORIZED SIGNATURE

Sheet ST-INV
B2: ក្រុមហ៊ុន ហ្រ្តេតហ្វ៊ូល សឹលូសិន (ខេមបូឌា) ឯ.ក
B3: GRATEFUL SOLUTIONS (CAMBODIA) CO.,LTD.
B4: លេខអត្តសញ្ញាណកម្ម អតប ( VATTIN ) : K008-902404873
A6: Account Statement
A8: Date: 01-09-2026 ~ 30-09-2026
A10: ='360'!A13:D13 -> JR APPAREL CO.,LTD
A11: KAOH KNOR VILLAGE PREAEK ROKA COMMUNE KANDAL
A12: STUENG DISTRICT, KANDAL STUENG, KANDAL,
A13: PHNOM PENH, CAMBODIA
A16: No: | B16: Date | C16: INV Number | D16: DISBURSEMENT | E16: REF # | F16: Currency | G16: Amount
A18: 1 | B18: ='360'!I13 -> 46268 | C18: ='360'!I12 -> GS26-360 | D18: ='360'!R12 -> DIS403 | E18: ='360'!B19 -> COSU6464276980 | F18: USD | G18: =SUM('360'!I31,'360'!R31) -> 903.45 | J18: =G18-H18-I18 -> 903.45
A19: =A18+1 -> 2 | B19: ='366'!I13 -> 46275 | C19: ='366'!I12 -> GS26-366 | D19: ='366'!R12 -> DIS409 | E19: ='366'!B19 -> COSU6464270110 | F19: USD | G19: =SUM('366'!I31,'366'!R31) -> 903.45 | J19: =G19-H19-I19 -> 903.45
A20: =A19+1 -> 3 | B20: ='370'!I13 -> 46279 | C20: ='370'!I12 -> GS26-370 | D20: ='370'!R12 -> DIS413 | E20: ='370'!B19 -> COSU6464270310 | F20: USD | G20: =SUM('370'!I31,'370'!R31) -> 903.45 | J20: =G20-H20-I20 -> 903.45
A21: =A20+1 -> 4 | B21: ='375'!I13 -> 46286 | C21: ='375'!I12 -> GS26-375 | D21: ='375'!R12 -> DIS418 | E21: ='375'!B19 -> COSU6464808450 | F21: USD | G21: =SUM('375'!I32,'375'!R32) -> 916.65 | J21: =G21-H21-I21 -> 916.65
A22: =A21+1 -> 5 | B22: ='377'!I13 -> 46286 | C22: ='377'!I12 -> GS26-377 | D22: ='377'!R12 -> DIS420 | E22: ='377'!B19 -> SHSIN6090083 | F22: USD | G22: =SUM('377'!I31,'377'!R31) -> 1025.95 | J22: =G22-H22-I22 -> 1025.95
A23: =A22+1 -> 6 | B23: ='379'!I13 -> 46286 | C23: ='379'!I12 -> GS26-379 | D23: ='379'!R12 -> DIS422 | E23: ='379'!B19 -> SHSIN6090084 | F23: USD | G23: =SUM('379'!I31,'379'!R31) -> 1025.95 | J23: =G23-H23-I23 -> 1025.95
A24: =A23+1 -> 7 | B24: ='387'!I13 -> 46293 | C24: ='387'!I12 -> GS26-387 | D24: ='387'!R12 -> DIS430 | E24: ='387'!B19 -> COSU6464270740 | F24: USD | G24: =SUM('387'!I31,'387'!R31) -> 903.45 | J24: =G24-H24-I24 -> 903.45
A25: =A24+1 -> 8 | B25: ='388'!I13 -> 46293 | C25: ='388'!I12 -> GS26-388 | D25: ='388'!R12 -> DIS431 | E25: ='388'!B19 -> SHSIN6090113 | F25: USD | G25: =SUM('388'!I31,'388'!R31) -> 758.95 | J25: =G25-H25-I25 -> 758.95
A26: =A25+1 -> 9 | B26: ='389'!I13 -> 46293 | C26: ='389'!I12 -> GS26-389 | D26: ='389'!R12 -> DIS432 | E26: ='389'!B19 -> SHSIN6090031 | F26: USD | G26: =SUM('389'!I31,'389'!R31) -> 933.95 | J26: =G26-H26-I26 -> 933.95
A27: =A26+1 -> 10 | B27: ='393'!I13 -> 46295 | C27: ='393'!I12 -> GS26-393 | D27: ='393'!R12 -> DIS436 | E27: ='393'!B19 -> KHS2609038 | F27: USD | G27: =SUM('393'!R29) -> 703.26 | J27: =G27-H27-I27 -> 703.26
B29: BALANCE AS | C29: SEP-2026 | G29: =SUM(G18:G28) -> 8978.51 | H29: =SUM(H18:H28) -> 0 | I29: =SUM(I18:I28) -> 0 | J29: =SUM(H29:I29) -> 0

Sheet STA-DN
A2: Account Statement
A3: ='ST-INV'!A8:G8 -> Date: 01-09-2026 ~ 30-09-2026
A6: ='ST-INV'!A10 -> JR APPAREL CO.,LTD
A7: KAOH KNOR VILLAGE PREAEK ROKA COMMUNE KANDAL
A8: STUENG DISTRICT, KANDAL STUENG, KANDAL,
A9: PHNOM PENH, CAMBODIA
A12: NO: | B12: DATE | C12: DN NUMBER | D12: REF NO: | E12: CURRENCY | F12: AMOUNT
A14: 1 | B14: ='ST-INV'!B18 -> 46268 | C14: ='D001'!G4 -> JR2609001 | D14: ='ST-INV'!E18 -> COSU6464276980 | E14: USD | F14: ='D001'!G26 -> 707.5 | G14: 921.5 | H14: =G14-F14 -> 214
A15: 2 | B15: ='ST-INV'!B19 -> 46275 | C15: ='D002'!G4 -> JR2609002 | D15: ='ST-INV'!E19 -> COSU6464270110 | E15: USD | F15: ='D002'!G26 -> 707.5 | G15: 950.5 | H15: =G15-F15 -> 243
A16: 3 | B16: ='ST-INV'!B20 -> 46279 | C16: ='D003'!G4 -> JR2609003 | D16: ='ST-INV'!E20 -> COSU6464270310 | E16: USD | F16: ='D003'!G26 -> 707.5 | G16: 939 | H16: =G16-F16 -> 231.5
A17: 4 | B17: ='ST-INV'!B21 -> 46286 | C17: ='D004'!G4 -> JR2609004 | D17: ='ST-INV'!E21 -> COSU6464808450 | E17: USD | F17: ='D004'!G29 -> 851 | G17: 899 | H17: =G17-F17 -> 48
A18: 5 | B18: ='ST-INV'!B22 -> 46286 | C18: ='D005'!G4 -> JR2609005 | D18: ='ST-INV'!E22 -> SHSIN6090083 | E18: USD | F18: ='D005'!G28 -> 1038.75 | G18: 871.5 | H18: =G18-F18 -> -167.25
A19: 6 | B19: ='ST-INV'!B23 -> 46286 | C19: ='D006'!G4 -> JR2609006 | D19: ='ST-INV'!E23 -> SHSIN6090084 | E19: USD | F19: ='D006'!G29 -> 1183.25 | G19: 174 | H19: =G19-F19 -> -1009.25
A20: 7 | B20: ='ST-INV'!B24 -> 46293 | C20: ='D007'!G4 -> JR2609007 | D20: ='ST-INV'!E24 -> COSU6464270740 | E20: USD | F20: ='D007'!G28 -> 771 | G20: 174 | H20: =G20-F20 -> -597
A21: 8 | B21: ='ST-INV'!B25 -> 46293 | C21: ='D008'!G4 -> JR2609008 | D21: ='ST-INV'!E25 -> SHSIN6090113 | E21: USD | F21: ='D008'!G27 -> 703.5 | G21: 141.5 | H21: =G21-F21 -> -562
A22: 9 | B22: ='ST-INV'!B26 -> 46293 | C22: ='D009'!G4 -> JR2609009 | D22: ='ST-INV'!E26 -> SHSIN6090031 | E22: USD | F22: ='D009'!G27 -> 913.75 | G22: 141.5 | H22: =G22-F22 -> -772.25
A23: 10 | B23: ='ST-INV'!B27 -> 46295 | C23: ='D010'!G4 -> JR2609010 | D23: ='ST-INV'!E27 -> KHS2609038 | E23: USD | F23: ='D010'!G22 -> 174
A24: 11 | B24: ='D011'!G5 -> 46295 | C24: ='D011'!G4 -> JR2609011 | D24: NON | E24: USD | F24: ='D011'!G19 -> 80
B26: BALANCE AS | C26: ='ST-INV'!$C$29 -> SEP-2026 | F26: =SUM(F14:F25) -> 7837.75 | G26: =SUM(G13:G25) -> 5212.5

Sheet OR-INV
C1: GRATEFUL SOLUTIONS (CAMBODIA) CO.,LTD.
C3: ( VATTIN ): K008-902404873
A5: OFFICIAL RECEIPT
A7: Received from | B7: : | C7: ='ST-INV'!A10 -> JR APPAREL CO.,LTD | H7: Date: | I7: 46295
A8: Amount | B8: : | C8: ='ST-INV'!G29 -> 8978.51
A9: Amount in word | B9: : | C9: TWELVE THOUSAND SEVEN HUNDRED NINETY DOLLARS AND EIGHTY NINE CENTS.
A11: Received for | B11: : | C11: ='ST-INV'!C29 -> SEP-2026
A13: Payment Method | B13: :
H17: Received by:
H23: Authorized Signature
A24: OFFICIAL RECEIPT
A27: Received from | B27: : | C27: =C7 -> JR APPAREL CO.,LTD | H27: Date: | I27: =I7 -> 46295
A28: Amount | B28: : | C28: ='STA-DN'!F26 -> 7837.75 | D28: 3576.02
A29: Amount in word | B29: : | C29: SIX THOUSAND FIVE HUNDRED FORTY DOLLARS AND TWENTY FIVE CENTS.
A31: Received for | B31: : | C31: =C11 -> SEP-2026
A33: Payment Method | B33: :
H37: Received by:
H44: Authorized Signature

Sheet Check list 1
A2: From: GRATEFUL SOLUTIONS (CAMBODIA) CO., LTD.
A4: To: JR APPAREL CO., LTD
A7: Subject: IMP & EXP SHIPMENT-CHECKING LIST | E7: 46276
A9: No | B9: DOX NO | C9: DECLARE NO | D9: DATE | E9: REMARK
A10: 1 | B10: GS26-347 | C10: ='360'!S12 -> E 264562 | D10: 46254 | E10: ORIGINAL
A11: =A10+1 -> 2 | B11: GS26-348 | C11: ='366'!S12 -> E 272714 | D11: 46255 | E11: ORIGINAL
A12: =A11+1 -> 3 | B12: GS26-349 | C12: ='370'!S12 -> E 275226 | D12: 46258 | E12: ORIGINAL
A13: =A12+1 -> 4 | B13: GS26-352 | C13: ='375'!S12 -> E 284067 | D13: 46260 | E13: ORIGINAL
A14: =A13+1 -> 5 | B14: DIS397 | C14: ='377'!S12 -> I 136252 | D14: 46265 | E14: ORIGINAL
A15: =A14+1 -> 6 | B15: DIS398 | C15: ='379'!S12 -> I 136243 | D15: 46265 | E15: ORIGINAL
A16: =A15+1 -> 7 | B16: DIS399 | C16: ='387'!S12 -> E 291340 | D16: 46265 | E16: ORIGINAL
A17: =A16+1 -> 8 | B17: DIS400 | C17: ='388'!S12 -> I 138725 | D17: 46265 | E17: ORIGINAL
A18: =A17+1 -> 9 | B18: JR2608009 | C18: MIH AND MOC PAYROLL | D18: 46265 | E18: ORIGINAL
A19: =A18+1 -> 10 | B19: DIS364 | C19: E 225809 | D19: 46234 | E19: ORIGINAL
A20: =A19+1 -> 11 | B20: JUN&JUL-STATEMENT | E20: ORIGINAL
A21: 12 | B21: CPF PAYMENT RECEIPT | C21: I 107653 | E21: ORIGINAL
C22: I 105712 | E22: ORIGINAL
C23: I 105711 | E23: ORIGINAL
C24: I 96707 | E24: ORIGINAL
E25: ORIGINAL
E26: ORIGINAL
E27: WASTED
A31: TOTAL: | B31: =SUBTOTAL(3,B10:B30) -> 12
A35: PREPARED BY: | D35: =A4 -> To: JR APPAREL CO., LTD
A36: NAME: | B36: Lycheng | D36: RECEIVE BY : | E36: Kendy
A37: DATE: | B37: 46276

Sheet 证书
A1: ព្រះរាជាណាចក្រកម្ពុជា | F1: KINGDOM OF CAMBODIA
A2: ជាតិ​ សាសានា ព្រះមហាក្សត្រ | F2: NATION KING RELIGION
A4: ខ្ញុំបាទ / នាងខ្ញុំឈ្មោះ : សំ វណ្ណនី | D4: សញ្ជាតិ : ខ្មែរ
A5: I / Name: | D5: Nationality :
A6: អាយុ : | B6: 35​ ឆ្នាំ | D6: កាន់អត្តសញ្ញាណប័ណ្ណ / លិខិតឆ្លងដែន លេខ : 010111826
A7: Age : | D7: Identification card/Passport number :
A8: ចេញដោយ: សាលារាជធានីភ្នំពេញ | D8: ជា : គណនេយ្យករ | J8: =23*6 -> 138
A9: Issued by: | D9: Is………belong to
A10: របស់ក្រុមហ៊ុន : ROO HSING GARMENT CO., LTD | F10: លេខអត្តសញ្ញាណកម្មសារពើពន្ធ: L001-100051030
A11: Campany: | F11: VAT-TIN:
A12: អស័យដ្ឋាន : ផ្លូវថ្មី សង្កាត់ទួលសង្កែ ខណ្ឌឫស្សីកែវ រាជធានីភ្នំពេញ
A13: Address: No.
A14: បានទិញ PURCHASED
A15: ល.រ No. | B15: វិក័យប័ត្រ Invoice No. | D15: ផលិតផលឬសេវា Produce/Service | F15: ឯកតា Unit Price | G15: បរិមាណ Quantity (Pcs) | H15: ថ្លៃសរុប Total Amount
A16: 1 | B16: 0001 | D16: សេវាកែច្នៃ ម៉ូតខោខូវប៊យ | F16: =H16/G16 -> #DIV/0! | G16: ='360'!C25 -> 0 | H16: ='360'!G25 -> 242
A17: =+A16+1 -> 2 | B17: 0001 | D17: សេវាកែច្នៃ ម៉ូតខោខូវប៊យ | F17: =H17/G17 -> #REF! | G17: ='360'!#REF! -> #REF! | H17: ='360'!#REF! -> #REF!
A18: =+A17+1 -> 3 | B18: 0001 | D18: សេវាកែច្នៃ ម៉ូតខោខូវប៊យ | F18: =H18/G18 -> #REF! | G18: ='360'!#REF! -> #REF! | H18: ='360'!#REF! -> #REF!
A19: =+A18+1 -> 4 | B19: 0001 | D19: សេវាកែច្នៃ ម៉ូតខោខូវប៊យ | F19: =H19/G19 -> #REF! | G19: ='360'!#REF! -> #REF! | H19: ='360'!#REF! -> #REF!
A20: =+A19+1 -> 5 | B20: 0001 | D20: សេវាកែច្នៃ ម៉ូតខោខូវប៊យ | F20: =H20/G20 -> #REF! | G20: ='360'!#REF! -> #REF! | H20: ='360'!#REF! -> #REF!
A21: =+A20+1 -> 6 | B21: 0001 | D21: សេវាកែច្នៃ ម៉ូតខោខូវប៊យ | F21: =H21/G21 -> #REF! | G21: ='360'!#REF! -> #REF! | H21: ='360'!#REF! -> #REF!
A22: =+A21+1 -> 7 | B22: 0001 | D22: សេវាកែច្នៃ ម៉ូតខោខូវប៊យ | F22: =H22/G22 -> #REF! | G22: ='360'!#REF! -> #REF! | H22: ='360'!#REF! -> #REF!
A23: =+A22+1 -> 8 | B23: 0001 | D23: សេវាកែច្នៃ ម៉ូតខោខូវប៊យ | F23: =H23/G23 -> #REF! | G23: ='360'!#REF! -> #REF! | H23: ='360'!#REF! -> #REF!
A24: =+A23+1 -> 9 | B24: 0001 | D24: សេវាកែច្នៃ ម៉ូតខោខូវប៊យ | F24: =H24/G24 -> #REF! | G24: ='360'!#REF! -> #REF! | H24: ='360'!#REF! -> #REF!
A25: =+A24+1 -> 10 | B25: 0001 | D25: សេវាកែច្នៃ ម៉ូតខោខូវប៊យ | F25: =H25/G25 -> #REF! | G25: ='360'!#REF! -> #REF! | H25: ='360'!#REF! -> #REF!
A26: =+A25+1 -> 11 | B26: 0001 | D26: សេវាកែច្នៃ ម៉ូតខោខូវប៊យ | F26: =H26/G26 -> #REF! | G26: ='360'!#REF! -> #REF! | H26: ='360'!#REF! -> #REF!
A27: =+A26+1 -> 12 | B27: 0001 | D27: សេវាកែច្នៃ ម៉ូតខោខូវប៊យ | F27: =H27/G27 -> #REF! | G27: ='360'!#REF! -> #REF! | H27: ='360'!#REF! -> #REF!
A28: =+A27+1 -> 13 | B28: 0001 | D28: សេវាកែច្នៃ ម៉ូតខោខូវប៊យ | F28: =H28/G28 -> #REF! | G28: ='360'!#REF! -> #REF! | H28: ='360'!#REF! -> #REF!
... A116: =+A115+1 -> 101 | B116: 0001 | D116: សេវាកែច្នៃ ម៉ូតខោខូវប៊យ | F116: =H116/G116 -> #REF! | G116: ='360'!#REF! -> #REF! | H116: ='360'!#REF! -> #REF!
D118: SUB TOTAL | H118: =SUM(H16:H117) -> #REF!
D120: TOTAL | H120: =H118-H119 -> #REF!
A121: ពីក្រុមហ៊ុន : JIN LOUN AGRICULTURE Co., Ltd​ លេខអត្តសញ្ញាណកម្មសារពើពន្ធ : K008-103016015
A122: អាស័យដ្ឋាន : #01EoE1 ភូមិ ទួលគោក ខណ្ឌ ឬស្សីកែវ រាជធានីភ្នំពេញ
A123: ខ្ញុំបាទ / នាងខ្ញុំ សូមសន្យាថានឹងធ្វើការនាំចេញ ផលិតផល /​ សេវា ខាងលើនេះទៅបរទេស ។​ ប្រសិនបើក្រុមហ៊ុនរបស់ខ្ញុំបាទ/នាងខ្ញុំ
A124: មិនបាននាំចេញឬបង្វែទិសដៅប្រើប្រាស់ ផលិតផល /​ សេវា ខាងលើនេះ ផ្សេងវិញ ខ្ញុំបាទ / នាងខ្ញុំ សូមទទួលខុសត្រូវទាំងស្រុងក្នុងការ
A125: បង់អាករលើតំលៃបន្ថែមរួមទាំងទោសទណ្ឌទាំងអស់ទៅតាមច្បាប់ជាធរមាន។
A126: From Company: ​​​​​​​​​​​ VAT-TIN:
A127: Address of business :
A128: I promise that I will do the export of my above produce/service to foreign countries.
A129: If my company do not export or diversity the utilization of the above products/services,
A130: I am unconditionally responsible for paying VAT including receiving any penalty.
F139: ធ្វើនៅភ្នំពេញ ថ្ងៃទី​ 31 ខែ 01 ឆ្នាំ​ 2019
F140: Phnom Penh, Date:…… Month…… Year……
F141: ហត្ថលេខា Signature

Sheet Contract
A1: RBHraCaNacRkkm<úCa
A2: Cati sasna RBHmhakSRt
A3: hcc ddf
A4: kic©snüaCYlesvaesvaEkexa
A5: kic©snüaenHeFIVeLIg nig cuHehtßelxaenAéf¶TI 01-01-2019 eday ³
A6: ¬k ¦ PaKICUleFVI esvaEkexa ³ | C6: Rkumh‘un JIN LOUN AGRICULTURE Co., Ltd
A7: VAT TIN : K008-103016015
A8: Gas½ydæan ³ #០១E0E1, ភូមិគោក សង្កាត់ទួលសង្កែ ​ខណ្ឌឫស្សីកែវ រាជធានីភ្នំពេញ
A9: TUrs½BÞelx ³
A10: tMNageday ³ Mr. ZHANG, JIEZHAO | D10: tYnaTI ³ naykRkumh‘un
A11: ¬x ¦ PaKITTYl esvaEkexa ³ | C11: Rkumh‘un ROO HSING GARMENT CO., LTD
A12: VAT TIN : 100051030
A13: Gas½ydæan ³ ភូមិទួលសង្កែ សង្កាត់ទួលសង្កែ ខណ្ឌឫស្សីកែវ រាជធានី ភ្នំពេញ
A14: TUrs½BÞelx ³ 023 430 151
A15: tMNageday ³ Mr. HSU MING SONG | D15: tYnaTI ³ naykRkumh‘un
A16: muxTMnijCYledr
A17: No. | B17: Description | C17: Style | D17: P.O No | E17: Unit Price/PCS | F17: Qty.(PCS) | G17: AMOUNT($) | J17: Qty.(PCS)
A18: 1 | B18: សេវាកែខោ | C18: ='360'!B25 -> កំរៃសេវាបំពេញបែបបទនាំចេញ / EXPORT PROCESSING FEE | E18: =G18/F18 -> #DIV/0! | F18: ='360'!C25 -> 0 | G18: ='360'!G25 -> 242
A19: =+A18+1 -> 2 | B19: សេវាកែខោ | C19: ='360'!#REF! -> #REF! | E19: =G19/F19 -> #REF! | F19: ='360'!#REF! -> #REF! | G19: ='360'!#REF! -> #REF!
A20: =+A19+1 -> 3 | B20: សេវាកែខោ | C20: ='360'!#REF! -> #REF! | E20: =G20/F20 -> #REF! | F20: ='360'!#REF! -> #REF! | G20: ='360'!#REF! -> #REF!
A21: =+A20+1 -> 4 | B21: សេវាកែខោ | C21: ='360'!#REF! -> #REF! | E21: =G21/F21 -> #REF! | F21: ='360'!#REF! -> #REF! | G21: ='360'!#REF! -> #REF!
A22: =+A21+1 -> 5 | B22: សេវាកែខោ | C22: ='360'!#REF! -> #REF! | E22: =G22/F22 -> #REF! | F22: ='360'!#REF! -> #REF! | G22: ='360'!#REF! -> #REF!
A23: =+A22+1 -> 6 | B23: សេវាកែខោ | C23: ='360'!#REF! -> #REF! | E23: =G23/F23 -> #REF! | F23: ='360'!#REF! -> #REF! | G23: ='360'!#REF! -> #REF!
A24: =+A23+1 -> 7 | B24: សេវាកែខោ | C24: ='360'!#REF! -> #REF! | E24: =G24/F24 -> #REF! | F24: ='360'!#REF! -> #REF! | G24: ='360'!#REF! -> #REF!
A25: =+A24+1 -> 8 | B25: សេវាកែខោ | C25: ='360'!#REF! -> #REF! | E25: =G25/F25 -> #REF! | F25: ='360'!#REF! -> #REF! | G25: ='360'!#REF! -> #REF!
A26: =+A25+1 -> 9 | B26: សេវាកែខោ | C26: ='360'!#REF! -> #REF! | E26: =G26/F26 -> #REF! | F26: ='360'!#REF! -> #REF! | G26: ='360'!#REF! -> #REF!
A27: =+A26+1 -> 10 | B27: សេវាកែខោ | C27: ='360'!#REF! -> #REF! | E27: =G27/F27 -> #REF! | F27: ='360'!#REF! -> #REF! | G27: ='360'!#REF! -> #REF!
A28: =+A27+1 -> 11 | B28: សេវាកែខោ | C28: ='360'!#REF! -> #REF! | E28: =G28/F28 -> #REF! | F28: ='360'!#REF! -> #REF! | G28: ='360'!#REF! -> #REF!
A29: =+A28+1 -> 12 | B29: សេវាកែខោ | C29: ='360'!#REF! -> #REF! | E29: =G29/F29 -> #REF! | F29: ='360'!#REF! -> #REF! | G29: ='360'!#REF! -> #REF!
A30: =+A29+1 -> 13 | B30: សេវាកែខោ | C30: ='360'!#REF! -> #REF! | E30: =G30/F30 -> #REF! | F30: ='360'!#REF! -> #REF! | G30: ='360'!#REF! -> #REF!
... A118: =+A117+1 -> 101 | B118: សេវាកែខោ | C118: ='360'!#REF! -> #REF! | E118: =G118/F118 -> #REF! | F118: ='360'!#REF! -> #REF! | G118: ='360'!#REF! -> #REF!
A120: TOTAL | G120: =SUM(G18:G119) -> #REF!
A122: SUB TOTAL | G122: =G120-G121 -> #REF!
A123: lkçx½NÐCYledrsMelokbMBak;³
A124: PaKI {x} RtUveFIVesvaeGay PaKI {k} eGay)anrYcral;kñúgry³eBl 1Ex bnÞab;BI)anTTYlbBa¢arTij (Order) eTAtam Style RtUvb¤ P.O nImYy².
A125: karTUrTat;R)ak;eFIVeLIgbnÞab;BIpÁt;pÁg;esvarYcral;.
A127: PaKITTYlesvaEkexa | F127: PaKICYlesvaEkexa
A128: htßelxa nig Rta | F128: htßelxa nig Rta
A133: Mr. ZHANG,JIEZHAO | F133: Mr. HSU MING SONG
