Workbook

Sheet 1-JAN
B1: ព្រះរាជាណាចក្រកម្ពុជា
B2: ជាត​ សានា ព្រះមហាក្សត្រ
G3: 
B4: របាយការណ៍ជូនក្រសួងឧស្សាហកម្ម វិទ្យាសាស្ត្រ បច្ចេកវិទ្យា និងនវានុវត្តន៍
B5: Report for Ministry of Industry, Science, Technology & Innovation
G6: ទិន្នន័យប្រចាំខែ | I6: មករា | J6: ឆ្នាំ 2026
G7: Monthly Data In ........... 202…
A9: ឈ្មោះរោងចក្រ:​​​​​​​​​​ ជេអ អឹភែរឹល ឯ.ក អាស័យដ្ឋានរោងចក្រៈ # ផ្លូវលំ ភូមិ កោះខ្នុរ ឃុំ ព្រែករកា ស្រុក កណ្ដាលស្ទឹង ខេត្ត កណ្ដាល ប្រកាសលេខៈ៤១៧ ឧស.កឧ.ប្រក១២ ចុះថ្ងៃទី ២៤​​ ខែ ធ្នូ ឆ្នាំ ២០១៨
A10: Name of Factory: JR APPAREL CO., LTD Factory Address: #LOM ROAD,KAOH KNOR PREAEK ROKA KANDAL STUENG​ KANDAL PROVINCE Prakas Number : 417
A11: ឈ្មោះអ្នកគ្រប់គ្រងរោងចក្រ NI, CUNLAN ទូរស័ព្ទៈ 855-85 441 621 ទូរសារ:.............................. អ៊ីម៉ែលៈ sanashipping8@gmail.com
A12: Manager Name: NI, CUNLAN Tel: 855-85 441 621 Fax:……………………… E-mail: sanashipping8@gmail.com
A13: ចំនួនពលកម្មសរុបៈ​​​ | C13: 168 | E13: ក្នុងនោះមានស្រីៈ | F13: 111 | H13: បៀរវត្សសរុបប្រចាំខែៈ | J13: 45784.38 | L13: USD
A14: Total Number of Employees: Persons Number of Females: Persons Total Salary & Wage of Monthly USD
A15: ទុនសរុបមិនគិតដីធ្លី Total Asset(Land exclude) | D15: 1000000 | F15: ទុនអចលនទ្រព្យមិនគិតដីធ្លី Total Fixed Asset (Land exclude) | J15: 1000000
A16: មុខផលិតផល Products | C16: ឯកតាUnit | D16: បរិមាណ និងតម្លៃផលិតផល Total Output
D17: ឆ្នាំមុន (Data Last Year) | H17: ទិន្នន័យប្រចាំខែ (Monthly Data) | L17: សរុបពីដើមឆ្នាំ (From beginning of the Year )
D18: ​ បរិមាណ Quantity | F18: តម្លៃ Value(USD) | H18: បរិមាណផលិតផល Product Quantity | J18: តម្លៃផលិតផល Product Value(USD) | L18: បរិមាណផលិតផល Product Quantity | N18: តម្លៃផលិតផល Product Value(USD)
D19: ក្នុងស្រុក Domestic | E19: នាំចេញ Export | F19: ក្នុងស្រុក Domestic | G19: នាំចេញ Export | H19: ក្នុងស្រុក Domestic | I19: នាំចេញ Export | J19: ក្នុងស្រុក Domestic | K19: នាំចេញ Export | L19: ក្នុងស្រុក Domestic | M19: នាំចេញ Export | N19: ក្នុងស្រុក Domestic | O19: នាំចេញ Export
A20: LADIES | B20: PAJAMAS | C20: PCS | I20: 25768 | K20: 27190 | M20: =I20 -> 25768 | O20: =K20 -> 27190 | Q20: =M20+I20 -> 51536 | S20: =O20+K20 -> 54380
A21: LADIES | B21: PANTS | C21: PCS | I21: 60216 | K21: 53155.36 | M21: =I21 -> 60216 | O21: =K21 -> 53155.36 | Q21: =M21+I21 -> 120432 | S21: =O21+K21 -> 106310.72
A22: LADIES | B22: NIGHT GOWN | C22: PCS | I22: 2080 | K22: 155240 | M22: =I22 -> 2080 | O22: =K22 -> 155240 | Q22: =M22+I22 -> 4160 | S22: =O22+K22 -> 310480
A23: LADIES | B23: TANK | C23: PCS | O23: =K23 -> 0
A24: LADIES | B24: SKIRT | C24: PCS | O24: =K24 -> 0
A25: LADIES | B25: SHORT | C25: PCS | M25: 0 | O25: =K25 -> 0 | Q25: =M25+I25 -> 0 | S25: =O25+K25 -> 0
A26: LADIES | B26: DRESS | C26: PCS | M26: 0 | O26: =K26 -> 0 | Q26: =M26+I26 -> 0 | S26: =O26+K26 -> 0
A27: Total | E27: =SUM(E20:E26) -> 0 | G27: =SUM(G20:G26) -> 0 | I27: =SUM(I20:I26) -> 88064 | K27: =SUM(K20:K26) -> 235585.36 | M27: =SUM(M20:M26) -> 88064 | O27: =SUM(O20:O26) -> 235585.36
A28: សំគាល់ :​ ទិន្នន័យនៃរបាយការណ៍នេះត្រូវបានប្រើប្រាស់តែក្នុងគោលបំណង ស្ថិតិឧស្សាហកម្មតែប៉ុណ្ណោះ មិនត្រូវបានយកទៅចែកចាយដើម្បីប្រើប្រាស់
A29: ក្នុងគោលបំណងពាណិជ្ជកម្ម ឬក្នុងការគណនាបង់ពន្ធដារទេ។ | K29: ថ្ងៃទី 15 ខែ មករា ឆ្នាំ2026 | N29: =K29 -> ថ្ងៃទី 15 ខែ មករា ឆ្នាំ2026
A30: Remark: This report is used for industrial statistic only,​ not for commercial or tax purpose | J30: ​​​​​​​​​​​​​​​​​​​ | K30: Date:……./……../…… | N30: Date:……./……../……
A31: ទុនអចលនទ្រព្យមិនគិតដីធ្លី រួមមាន៖ អគារ និងឧបករណ៍បរិក្ខារដែលភ្ជាប់នឹងអគារ | K31: នាយក | N31: អ្នកធ្វើរបាយការណ៍
A32: Total asset excluding land comprises of : building & material attached.
A33: ទុនសរុបមិនគិតដីធ្លី រួមមាន៖ ទុនអចលនទ្រព្យមិនគិតដីធ្លី, មធ្យោបាយដឹកជញ្ជូន, គ្រឿងចក្រ-ម៉ាស៊ីន និងឧបករណ៍សម្ភារប្រើប្រាស់ក្នុងផលិតកម្ម, សង្ហារឹម និងសម្ភារការិយាល័យ | K33: Director | N33: Reportor
A34: Total fixed asset excluding land comprises of : real estate capital excluding land, transportation, machinery, and instrument utilised in the production line,
A35: furniture and office equiment.
A36: ទំនាក់ទំនង : Tel 077 330 279/090 922 237 E-mail : industryaffair.mih@gmail.com : TELEGRAM :077 330 279
K40: NI, CUNLAN | N40: THNIN
B41: ឈ្មោះរោងចក្រ ជេអ​ អឹភែរឹល ឯ.ក
A42: ទីផ្សារលក់ផលិតផលប្រចាំខែ | J42: =I6 -> មករា | K42: ឆ្នាំ២០២៦ (USD)
A43: ល.រ | B43: ឈ្មោះផលិតផល | D43: ឯកតា (Unit) | E43: ឈ្មោះប្រទេសនាំចេញផលិតផល | O43: សរុបពីដើមឆ្នាំ
E44: USA | G44: CANADA | I44: CHINA | K44: EU GROUP | M44: ផ្សេងៗ
E45: បរិមាណ | F45: តម្លៃ | G45: បរិមាណ | H45: តម្លៃ | I45: បរិមាណ | J45: តម្លៃ | K45: បរិមាណ | L45: តម្លៃ | M45: បរិមាណ | N45: តម្លៃ | O45: បរិមាណ | P45: តម្លៃ
A46: 1 | B46: =A20 -> LADIES | C46: =B20 -> PAJAMAS | D46: PCS | G46: 2719 | H46: 27190 | O46: =M20 -> 25768 | P46: =O20 -> 27190
A47: =A46+1 -> 2 | B47: =A21 -> LADIES | C47: =B21 -> PANTS | D47: PCS | G47: 6536 | H47: 53155.36 | O47: =M21 -> 60216 | P47: =O21 -> 53155.36
A48: =A47+1 -> 3 | B48: =A22 -> LADIES | C48: =B22 -> NIGHT GOWN | D48: PCS | G48: 7762 | H48: 155240 | O48: =M22 -> 2080 | P48: =O22 -> 155240
A49: =A48+1 -> 4 | B49: =A23 -> LADIES | C49: =B23 -> TANK | D49: PCS | O49: =M23 -> 0 | P49: =O23 -> 0
A50: =A49+1 -> 5 | B50: =A24 -> LADIES | C50: =B24 -> SKIRT | D50: PCS | O50: =M24 -> 0 | P50: =O24 -> 0
A51: =A50+1 -> 6 | B51: =A25 -> LADIES | C51: =B25 -> SHORT | D51: PCS | O51: =M25 -> 0 | P51: =O25 -> 0
A52: =A51+1 -> 7 | B52: =A26 -> LADIES | C52: =B26 -> DRESS | D52: PCS | O52: =M26 -> 0 | P52: =O26 -> 0
B53: សរុប | E53: =SUM(E46:E52) -> 0 | F53: =SUM(F46:F52) -> 0 | G53: =SUM(G46:G52) -> 17017 | H53: =SUM(H46:H52) -> 235585.36 | I53: =SUM(I46:I52) -> 0 | J53: =SUM(J46:J52) -> 0 | K53: =SUM(K46:K52) -> 0 | L53: =SUM(L46:L52) -> 0 | ... P53: =SUM(P46:P52) -> 235585.36
A55: ប្រភពដើមទំនិញ (វត្ថុធាតុដើម)ប្រចាំខែ | J55: =$I$6 -> មករា | K55: =$K$42 -> ឆ្នាំ២០២៦ (USD)
A56: ល.រ | B56: ឈ្មោះវត្ថុធាតុដើម | D56: ឯកតា (Unit) | E56: ឈ្មោះប្រទេសនាំចូលវត្ថុធាតុដើម | O56: សរុបពីដើមឆ្នាំ
E57: ចិន | G57: តៃវ៉ាន់ | I57: ហុងកុង | K57: វៀតណាម | M57: ផ្សេងៗ
E58: បរិមាណ | F58: តម្លៃ | G58: បរិមាណ | H58: តម្លៃ | I58: បរិមាណ | J58: តម្លៃ | K58: បរិមាណ | L58: តម្លៃ | M58: បរិមាណ | N58: តម្លៃ | O58: បរិមាណ | P58: តម្លៃ
A59: 1 | B59: I. MACHINERIES &. EQUIPMENTS | Q59: =E59+G59+I59+K59+M59 -> 0 | R59: =F59+H59+J59+L59+N59 -> 0 | S59: =Q59+O59 -> 0 | T59: =R59+P59 -> 0
A60: 3 | B60: II. RAW MATERIAL | D60: MTR | E60: 96774.8 | F60: 160385.04 | O60: =E60 -> 96774.8 | P60: =F60 -> 160385.04 | Q60: =E60+G60+I60+K60+M60 -> 96774.8 | R60: =F60+H60+J60+L60+N60 -> 160385.04 | S60: =Q60+O60 -> 193549.6 | T60: =R60+P60 -> 320770.08
A61: 4 | B61: III. ACCESSORY | D61: DZN | E61: 380 | F61: 380 | O61: =E61 -> 380 | P61: =F61 -> 380 | Q61: =E61+G61+I61+K61+M61 -> 380 | R61: =F61+H61+J61+L61+N61 -> 380 | S61: =Q61+O61 -> 760 | T61: =R61+P61 -> 760
B62: សរុប | E62: =SUM(E59:E61) -> 97154.8 | F62: =SUM(F59:F61) -> 160765.04 | G62: =SUM(G59:G61) -> 0 | H62: =SUM(H59:H61) -> 0 | I62: =SUM(I59:I61) -> 0 | J62: =SUM(J59:J61) -> 0 | K62: =SUM(K59:K61) -> 0 | L62: =SUM(L59:L61) -> 0 | ... P62: =SUM(P59:P61) -> 160765.04
B64: =A36 -> ទំនាក់ទំនង : Tel 077 330 279/090 922 237 E-mail : industryaffair.mih@gmail.com : TELEGRAM :077 330 279 | K64: =K29 -> ថ្ងៃទី 15 ខែ មករា ឆ្នាំ2026 | N64: =N29 -> ថ្ងៃទី 15 ខែ មករា ឆ្នាំ2026
K65: =K30 -> Date:……./……../…… | N65: =N30 -> Date:……./……../……
K66: =K31 -> នាយក | N66: =N31 -> អ្នកធ្វើរបាយការណ៍
K67: =K33 -> Director | N67: =N33 -> Reportor
K73: =K40 -> NI, CUNLAN | N73: =N40 -> THNIN
B74: ឈ្មោះរោងចក្រ ជេអ​ អឹភែរឹល ឯ.ក
B75: បរិមាណការប្រើប្រាស់ថាមពល ប្រចាំខែ | J75: =$I$6 -> មករា | K75: =$K$42 -> ឆ្នាំ២០២៦ (USD)
A76: ល.រ | B76: ប្រភេទថាមពល | E76: ឯកតា (Unit) | G76: ឆ្នាំមុន | I76: ប្រចាំខែ......... | K76: សរុបពីដើមឆ្នាំ | O76: ផ្សេងៗ
G77: បរិមាណ | H77: តម្លៃ $ | I77: បរិមាណ | J77: តម្លៃ $ | K77: បរិមាណ | M77: តម្លៃ $
A78: 1 | B78: EDC | E78: KW | I78: 11368 | J78: =0.137*I78 -> 1557.416 | K78: =I78 -> 11368 | M78: =J78 -> 1557.416 | Q78: =K78+I78 -> 22736 | R78: =M78+J78 -> 3114.832
B79: សរុប | G79: =SUM(G78) -> 0 | H79: =SUM(H78) -> 0 | I79: =SUM(I78) -> 11368 | J79: =SUM(J78) -> 1557.416 | K79: =SUM(K78) -> 11368 | M79: =SUM(M78) -> 1557.416
B81: បរិមាណការប្រើប្រាស់ទឹក​ ប្រចាំខែ | J81: =J75 -> មករា
A82: ល.រ | B82: ប្រភពទឹក | E82: ឯកតា (Unit) | G82: ឆ្នាំមុន | I82: ប្រចាំខែ......... | K82: សរុបពីដើមឆ្នាំ | O82: ផ្សេងៗ
G83: បរិមាណ | H83: តម្លៃ $ | I83: បរិមាណ | J83: តម្លៃ $ | K83: បរិមាណ | M83: តម្លៃ $
A84: 1 | B84: PPWSA | E84: M3 | I84: 83 | J84: =0.55*I84 -> 45.65 | K84: =I84 -> 83 | M84: =J84 -> 45.65 | Q84: =K84+I84 -> 166 | R84: =M84+J84 -> 91.3
B85: សរុប | G85: =SUM(G84) -> 0 | H85: =SUM(H84) -> 0 | I85: =SUM(I84) -> 83 | J85: =SUM(J84) -> 45.65 | K85: =SUM(K84) -> 83 | M85: =SUM(M84) -> 45.65
B87: ​ ​បរិមាណសំណល់ ពីដំណើរការខ្សែសង្វាក់ផលិតកម្ម ប្រចាំខែ | J87: =$I$6 -> មករា | K87: =$K$42 -> ឆ្នាំ២០២៦ (USD)
A88: ល.រ | B88: ប្រភេទសំណល់ | D88: ឯកតា (Unit) | E88: បរិមាណសំណល់សរុប ពីឆ្នាំមុន | G88: បរិមាណសំណល់ប្រចាំខែ......... | K88: បរិមាណសំណល់សរុបពីដើមឆ្នាំ | O88: ផ្សេងៗ
A89: 1 | B89: សំណល់រឹង
A90: 2 | B90: សំណល់រាវ
A91: 3 | B91: សំណល់(ឧស្ម័ន)
A92: 4 | B92: សរុប
A94: =A36 -> ទំនាក់ទំនង : Tel 077 330 279/090 922 237 E-mail : industryaffair.mih@gmail.com : TELEGRAM :077 330 279 | K94: =K29 -> ថ្ងៃទី 15 ខែ មករា ឆ្នាំ2026 | N94: =N29 -> ថ្ងៃទី 15 ខែ មករា ឆ្នាំ2026
K95: =K30 -> Date:……./……../…… | N95: =N30 -> Date:……./……../……
K96: =K31 -> នាយក | N96: =N31 -> អ្នកធ្វើរបាយការណ៍
K97: =K33 -> Director | N97: =N67 -> Reportor
K105: =K40 -> NI, CUNLAN | N105: =N73 -> THNIN
K228: =K145 -> 0 | N228: =N188 -> 0

Sheet 2-FEB
B1: ព្រះរាជាណាចក្រកម្ពុជា
B2: ជាត​ សានា ព្រះមហាក្សត្រ
G3: 
B4: របាយការណ៍ជូនក្រសួងឧស្សាហកម្ម វិទ្យាសាស្ត្រ បច្ចេកវិទ្យា និងនវានុវត្តន៍
B5: Report for Ministry of Industry, Science, Technology & Innovation
G6: ទិន្នន័យប្រចាំខែ | I6: កុម្ភៈ | J6: ឆ្នាំ 2026
G7: Monthly Data In ........... 202…
A9: ឈ្មោះរោងចក្រ:​​​​​​​​​​ ជេអ អឹភែរឹល ឯ.ក អាស័យដ្ឋានរោងចក្រៈ # ផ្លូវលំ ភូមិ កោះខ្នុរ ឃុំ ព្រែករកា ស្រុក កណ្ដាលស្ទឹង ខេត្ត កណ្ដាល ប្រកាសលេខៈ៤១៧ ឧស.កឧ.ប្រក១២ ចុះថ្ងៃទី ២៤​​ ខែ ធ្នូ ឆ្នាំ ២០១៨
A10: Name of Factory: JR APPAREL CO., LTD Factory Address: #LOM ROAD,KAOH KNOR PREAEK ROKA KANDAL STUENG​ KANDAL PROVINCE Prakas Number : 417
A11: ឈ្មោះអ្នកគ្រប់គ្រងរោងចក្រ NI, CUNLAN ទូរស័ព្ទៈ 855-85 441 621 ទូរសារ:.............................. អ៊ីម៉ែលៈ sanashipping8@gmail.com
A12: Manager Name: NI, CUNLAN Tel: 855-85 441 621 Fax:……………………… E-mail: sanashipping8@gmail.com
A13: ចំនួនពលកម្មសរុបៈ​​​ | C13: 175 | E13: ក្នុងនោះមានស្រីៈ | F13: 117 | H13: បៀរវត្សសរុបប្រចាំខែៈ | J13: 58602.51 | L13: USD
A14: Total Number of Employees: Persons Number of Females: Persons Total Salary & Wage of Monthly USD
A15: ទុនសរុបមិនគិតដីធ្លី Total Asset(Land exclude) | D15: 1000000 | F15: ទុនអចលនទ្រព្យមិនគិតដីធ្លី Total Fixed Asset (Land exclude) | J15: 1000000
A16: មុខផលិតផល Products | C16: ឯកតាUnit | D16: បរិមាណ និងតម្លៃផលិតផល Total Output
D17: ឆ្នាំមុន (Data Last Year) | H17: ទិន្នន័យប្រចាំខែ (Monthly Data) | L17: សរុបពីដើមឆ្នាំ (From beginning of the Year )
D18: ​ បរិមាណ Quantity | F18: តម្លៃ Value(USD) | H18: បរិមាណផលិតផល Product Quantity | J18: តម្លៃផលិតផល Product Value(USD) | L18: បរិមាណផលិតផល Product Quantity | N18: តម្លៃផលិតផល Product Value(USD)
D19: ក្នុងស្រុក Domestic | E19: នាំចេញ Export | F19: ក្នុងស្រុក Domestic | G19: នាំចេញ Export | H19: ក្នុងស្រុក Domestic | I19: នាំចេញ Export | J19: ក្នុងស្រុក Domestic | K19: នាំចេញ Export | L19: ក្នុងស្រុក Domestic | M19: នាំចេញ Export | N19: ក្នុងស្រុក Domestic | O19: នាំចេញ Export
A20: LADIES | B20: PANTS | C20: PCS | I20: 22549 | K20: =ROUND(I20*2.03594837908555,2) -> 45908.6 | M20: =I20+'1-JAN'!M21 -> 82765 | O20: ='2-FEB'!K20+'1-JAN'!O21 -> 99063.96 | Q20: =M20+I20 -> 105314 | S20: =O20+K20 -> 144972.56
A21: LADIES | B21: TANK | C21: PCS | I21: 3396 | K21: =ROUND(I21*0.669257950530035,2) -> 2272.8 | M21: =I21 -> 3396 | O21: =K21 -> 2272.8 | Q21: =M21+I21 -> 6792 | S21: =O21+K21 -> 4545.6
A22: LADIES | B22: SKIRT | C22: PCS | I22: 1635 | K22: =ROUND(I22*1.5,2) -> 2452.5 | M22: =I22 -> 1635 | O22: =K22 -> 2452.5
A23: LADIES | B23: SHORT | C23: PCS | I23: 1848 | K23: =ROUND(I23*1.41,2) -> 2605.68 | M23: =I23 -> 1848 | O23: =K23 -> 2605.68 | Q23: =M23+I23 -> 3696 | S23: =O23+K23 -> 5211.36
A24: LADIES | B24: PAJAMAS | C24: PCS | I24: 4026 | K24: =ROUND(I24*2.04,2) -> 8213.04 | M24: ='1-JAN'!M20 -> 25768 | O24: =K24+'1-JAN'!O22 -> 163453.04
A25: LADIES | B25: NIGHT GOWN | C25: PCS | M25: ='1-JAN'!M22 -> 2080 | O25: ='1-JAN'!O22 -> 155240
A26: LADIES | B26: DRESS | C26: PCS | M26: 0 | O26: 0 | Q26: =M26+I26 -> 0 | S26: =O26+K26 -> 0
A27: Total | E27: =SUM(E20:E26) -> 0 | G27: =SUM(G20:G26) -> 0 | I27: =SUM(I20:I26) -> 33454 | K27: =SUM(K20:K26) -> 61452.62 | M27: =SUM(M20:M26) -> 117492 | O27: =SUM(O20:O26) -> 425087.98
A28: សំគាល់ :​ ទិន្នន័យនៃរបាយការណ៍នេះត្រូវបានប្រើប្រាស់តែក្នុងគោលបំណង ស្ថិតិឧស្សាហកម្មតែប៉ុណ្ណោះ មិនត្រូវបានយកទៅចែកចាយដើម្បីប្រើប្រាស់
A29: ក្នុងគោលបំណងពាណិជ្ជកម្ម ឬក្នុងការគណនាបង់ពន្ធដារទេ។ | K29: ថ្ងៃទី 15 ខែ កុម្ភៈ ឆ្នាំ2026 | N29: =K29 -> ថ្ងៃទី 15 ខែ កុម្ភៈ ឆ្នាំ2026
A30: Remark: This report is used for industrial statistic only,​ not for commercial or tax purpose | J30: ​​​​​​​​​​​​​​​​​​​ | K30: Date:……./……../…… | N30: Date:……./……../……
A31: ទុនអចលនទ្រព្យមិនគិតដីធ្លី រួមមាន៖ អគារ និងឧបករណ៍បរិក្ខារដែលភ្ជាប់នឹងអគារ | K31: នាយក | N31: អ្នកធ្វើរបាយការណ៍
A32: Total asset excluding land comprises of : building & material attached.
A33: ទុនសរុបមិនគិតដីធ្លី រួមមាន៖ ទុនអចលនទ្រព្យមិនគិតដីធ្លី, មធ្យោបាយដឹកជញ្ជូន, គ្រឿងចក្រ-ម៉ាស៊ីន និងឧបករណ៍សម្ភារប្រើប្រាស់ក្នុងផលិតកម្ម, សង្ហារឹម និងសម្ភារការិយាល័យ | K33: Director | N33: Reportor
A34: Total fixed asset excluding land comprises of : real estate capital excluding land, transportation, machinery, and instrument utilised in the production line,
A35: furniture and office equiment.
A36: ទំនាក់ទំនង : Tel 077 330 279/090 922 237 E-mail : industryaffair.mih@gmail.com : TELEGRAM :077 330 279
K40: NI, CUNLAN | N40: THNIN
B41: ឈ្មោះរោងចក្រ ជេអ​ អឹភែរឹល ឯ.ក
A42: ទីផ្សារលក់ផលិតផលប្រចាំខែ | J42: =I6 -> កុម្ភៈ | K42: ឆ្នាំ២០២៦ (USD)
A43: ល.រ | B43: ឈ្មោះផលិតផល | D43: ឯកតា (Unit) | E43: ឈ្មោះប្រទេសនាំចេញផលិតផល | O43: សរុបពីដើមឆ្នាំ
E44: USA | G44: CANADA | I44: CHINA | K44: EU GROUP | M44: ផ្សេងៗ
E45: បរិមាណ | F45: តម្លៃ | G45: បរិមាណ | H45: តម្លៃ | I45: បរិមាណ | J45: តម្លៃ | K45: បរិមាណ | L45: តម្លៃ | M45: បរិមាណ | N45: តម្លៃ | O45: បរិមាណ | P45: តម្លៃ
A46: 1 | B46: =A20 -> LADIES | C46: =B20 -> PANTS | D46: PCS | E46: 17949 | F46: 36321.4 | G46: 4600 | H46: 9587.2 | O46: =M20 -> 82765 | P46: =O20 -> 99063.96
A47: =A46+1 -> 2 | B47: =A21 -> LADIES | C47: =B21 -> TANK | D47: PCS | E47: 2196 | F47: 1317.6 | G47: 1200 | H47: 955.2 | O47: =M21 -> 3396 | P47: =O21 -> 2272.8
A48: =A47+1 -> 3 | B48: =A22 -> LADIES | C48: =B22 -> SKIRT | D48: PCS | E48: 1635 | F48: 2452.5 | O48: =M22 -> 1635 | P48: =O22 -> 2452.5
A49: =A48+1 -> 4 | B49: =A23 -> LADIES | C49: =B23 -> SHORT | D49: PCS | E49: 1848 | F49: 2605.48 | O49: =M23 -> 1848 | P49: =O23 -> 2605.68
A50: =A49+1 -> 5 | B50: =A24 -> LADIES | C50: =B24 -> PAJAMAS | D50: PCS | E50: 4026 | F50: 8213.04 | O50: =M24 -> 25768 | P50: =O24 -> 163453.04
A51: =A50+1 -> 6 | B51: =A25 -> LADIES | C51: =B25 -> NIGHT GOWN | D51: PCS | O51: =M25 -> 2080 | P51: =O25 -> 155240
A52: =A51+1 -> 7 | B52: =A26 -> LADIES | C52: =B26 -> DRESS | D52: PCS | O52: =M26 -> 0 | P52: =O26 -> 0
B53: សរុប | E53: =SUM(E46:E52) -> 27654 | F53: =SUM(F46:F52) -> 50910.02 | G53: =SUM(G46:G52) -> 5800 | H53: =SUM(H46:H52) -> 10542.4 | I53: =SUM(I46:I52) -> 0 | J53: =SUM(J46:J52) -> 0 | K53: =SUM(K46:K52) -> 0 | L53: =SUM(L46:L52) -> 0 | ... P53: =SUM(P46:P52) -> 425087.98
A55: ប្រភពដើមទំនិញ (វត្ថុធាតុដើម)ប្រចាំខែ | J55: =$I$6 -> កុម្ភៈ | K55: =$K$42 -> ឆ្នាំ២០២៦ (USD)
A56: ល.រ | B56: ឈ្មោះវត្ថុធាតុដើម | D56: ឯកតា (Unit) | E56: ឈ្មោះប្រទេសនាំចូលវត្ថុធាតុដើម | O56: សរុបពីដើមឆ្នាំ
E57: ចិន | G57: តៃវ៉ាន់ | I57: ហុងកុង | K57: វៀតណាម | M57: ផ្សេងៗ
E58: បរិមាណ | F58: តម្លៃ | G58: បរិមាណ | H58: តម្លៃ | I58: បរិមាណ | J58: តម្លៃ | K58: បរិមាណ | L58: តម្លៃ | M58: បរិមាណ | N58: តម្លៃ | O58: បរិមាណ | P58: តម្លៃ
A59: 1 | B59: I. MACHINERIES &. EQUIPMENTS | Q59: =E59+G59+I59+K59+M59 -> 0 | R59: =F59+H59+J59+L59+N59 -> 0 | S59: =Q59+O59 -> 0 | T59: =R59+P59 -> 0
A60: 3 | B60: II. RAW MATERIAL | E60: 81187.7 | F60: 81187.7 | O60: =E60+'1-JAN'!O60 -> 177962.5 | P60: ='1-JAN'!P60 -> 160385.04 | Q60: =E60+G60+I60+K60+M60 -> 81187.7 | R60: =F60+H60+J60+L60+N60 -> 81187.7 | S60: =Q60+O60 -> 259150.2 | T60: =R60+P60 -> 241572.74
A61: 4 | B61: III. ACCESSORY | O61: ='1-JAN'!O61 -> 380 | P61: ='1-JAN'!P61 -> 380 | Q61: =E61+G61+I61+K61+M61 -> 0 | R61: =F61+H61+J61+L61+N61 -> 0 | S61: =Q61+O61 -> 380 | T61: =R61+P61 -> 380
B62: សរុប | E62: =SUM(E59:E61) -> 81187.7 | F62: =SUM(F59:F61) -> 81187.7 | G62: =SUM(G59:G61) -> 0 | H62: =SUM(H59:H61) -> 0 | I62: =SUM(I59:I61) -> 0 | J62: =SUM(J59:J61) -> 0 | K62: =SUM(K59:K61) -> 0 | L62: =SUM(L59:L61) -> 0 | ... P62: =SUM(P59:P61) -> 160765.04
B64: =A36 -> ទំនាក់ទំនង : Tel 077 330 279/090 922 237 E-mail : industryaffair.mih@gmail.com : TELEGRAM :077 330 279 | K64: =K29 -> ថ្ងៃទី 15 ខែ កុម្ភៈ ឆ្នាំ2026 | N64: =N29 -> ថ្ងៃទី 15 ខែ កុម្ភៈ ឆ្នាំ2026
K65: =K30 -> Date:……./……../…… | N65: =N30 -> Date:……./……../……
K66: =K31 -> នាយក | N66: =N31 -> អ្នកធ្វើរបាយការណ៍
K67: =K33 -> Director | N67: =N33 -> Reportor
K73: =K40 -> NI, CUNLAN | N73: =N40 -> THNIN
B74: ឈ្មោះរោងចក្រ ជេអ​ អឹភែរឹល ឯ.ក
B75: បរិមាណការប្រើប្រាស់ថាមពល ប្រចាំខែ | J75: =$I$6 -> កុម្ភៈ | K75: =$K$42 -> ឆ្នាំ២០២៦ (USD)
A76: ល.រ | B76: ប្រភេទថាមពល | E76: ឯកតា (Unit) | G76: ឆ្នាំមុន | I76: ប្រចាំខែ......... | K76: សរុបពីដើមឆ្នាំ | O76: ផ្សេងៗ
G77: បរិមាណ | H77: តម្លៃ $ | I77: បរិមាណ | J77: តម្លៃ $ | K77: បរិមាណ | M77: តម្លៃ $
A78: 1 | B78: EDC | E78: KW | I78: 11368 | J78: =0.137*I78 -> 1557.416 | K78: =I78+'1-JAN'!K78:L78 -> 22736 | M78: =J78+'1-JAN'!M78:N78 -> 3114.832 | Q78: =K78+I78 -> 34104 | R78: =M78+J78 -> 4672.248
B79: សរុប | G79: =SUM(G78) -> 0 | H79: =SUM(H78) -> 0 | I79: =SUM(I78) -> 11368 | J79: =SUM(J78) -> 1557.416 | K79: =SUM(K78) -> 22736 | M79: =SUM(M78) -> 3114.832
B81: បរិមាណការប្រើប្រាស់ទឹក​ ប្រចាំខែ | J81: =J75 -> កុម្ភៈ
A82: ល.រ | B82: ប្រភពទឹក | E82: ឯកតា (Unit) | G82: ឆ្នាំមុន | I82: ប្រចាំខែ......... | K82: សរុបពីដើមឆ្នាំ | O82: ផ្សេងៗ
G83: បរិមាណ | H83: តម្លៃ $ | I83: បរិមាណ | J83: តម្លៃ $ | K83: បរិមាណ | M83: តម្លៃ $
A84: 1 | B84: PPWSA | E84: M3 | I84: 83 | J84: =0.55*I84 -> 45.65 | K84: =I84+'1-JAN'!K84:L84 -> 166 | M84: =J84+'1-JAN'!M84:N84 -> 91.3 | Q84: =K84+I84 -> 249 | R84: =M84+J84 -> 136.95
B85: សរុប | G85: =SUM(G84) -> 0 | H85: =SUM(H84) -> 0 | I85: =SUM(I84) -> 83 | J85: =SUM(J84) -> 45.65 | K85: =SUM(K84) -> 166 | M85: =SUM(M84) -> 91.3
B87: ​ ​បរិមាណសំណល់ ពីដំណើរការខ្សែសង្វាក់ផលិតកម្ម ប្រចាំខែ | J87: =$I$6 -> កុម្ភៈ | K87: =$K$42 -> ឆ្នាំ២០២៦ (USD)
A88: ល.រ | B88: ប្រភេទសំណល់ | D88: ឯកតា (Unit) | E88: បរិមាណសំណល់សរុប ពីឆ្នាំមុន | G88: បរិមាណសំណល់ប្រចាំខែ......... | K88: បរិមាណសំណល់សរុបពីដើមឆ្នាំ | O88: ផ្សេងៗ
A89: 1 | B89: សំណល់រឹង
A90: 2 | B90: សំណល់រាវ
A91: 3 | B91: សំណល់(ឧស្ម័ន)
A92: 4 | B92: សរុប
A94: =A36 -> ទំនាក់ទំនង : Tel 077 330 279/090 922 237 E-mail : industryaffair.mih@gmail.com : TELEGRAM :077 330 279 | K94: =K29 -> ថ្ងៃទី 15 ខែ កុម្ភៈ ឆ្នាំ2026 | N94: =N29 -> ថ្ងៃទី 15 ខែ កុម្ភៈ ឆ្នាំ2026
K95: =K30 -> Date:……./……../…… | N95: =N30 -> Date:……./……../……
K96: =K31 -> នាយក | N96: =N31 -> អ្នកធ្វើរបាយការណ៍
K97: =K33 -> Director | N97: =N67 -> Reportor
K105: =K40 -> NI, CUNLAN | N105: =N73 -> THNIN

Sheet 3-MAR
B1: ព្រះរាជាណាចក្រកម្ពុជា
B2: ជាត​ សានា ព្រះមហាក្សត្រ
G3: 
B4: របាយការណ៍ជូនក្រសួងឧស្សាហកម្ម វិទ្យាសាស្ត្រ បច្ចេកវិទ្យា និងនវានុវត្តន៍
B5: Report for Ministry of Industry, Science, Technology & Innovation
G6: ទិន្នន័យប្រចាំខែ | I6: មីនា | J6: ឆ្នាំ 2026
G7: Monthly Data In ........... 202…
A9: ឈ្មោះរោងចក្រ:​​​​​​​​​​ ជេអ អឹភែរឹល ឯ.ក អាស័យដ្ឋានរោងចក្រៈ # ផ្លូវលំ ភូមិ កោះខ្នុរ ឃុំ ព្រែករកា ស្រុក កណ្ដាលស្ទឹង ខេត្ត កណ្ដាល ប្រកាសលេខៈ៤១៧ ឧស.កឧ.ប្រក១២ ចុះថ្ងៃទី ២៤​​ ខែ ធ្នូ ឆ្នាំ ២០១៨
A10: Name of Factory: JR APPAREL CO., LTD Factory Address: #LOM ROAD,KAOH KNOR PREAEK ROKA KANDAL STUENG​ KANDAL PROVINCE Prakas Number : 417
A11: ឈ្មោះអ្នកគ្រប់គ្រងរោងចក្រ NI, CUNLAN ទូរស័ព្ទៈ 855-85 441 621 ទូរសារ:.............................. អ៊ីម៉ែលៈ sanashipping8@gmail.com
A12: Manager Name: NI, CUNLAN Tel: 855-85 441 621 Fax:……………………… E-mail: sanashipping8@gmail.com
A13: ចំនួនពលកម្មសរុបៈ​​​ | C13: 179 | E13: ក្នុងនោះមានស្រីៈ | F13: 122 | H13: បៀរវត្សសរុបប្រចាំខែៈ | J13: 63192.24 | L13: USD
A14: Total Number of Employees: Persons Number of Females: Persons Total Salary & Wage of Monthly USD
A15: ទុនសរុបមិនគិតដីធ្លី Total Asset(Land exclude) | D15: 1000000 | F15: ទុនអចលនទ្រព្យមិនគិតដីធ្លី Total Fixed Asset (Land exclude) | J15: 1000000
A16: មុខផលិតផល Products | C16: ឯកតាUnit | D16: បរិមាណ និងតម្លៃផលិតផល Total Output
D17: ឆ្នាំមុន (Data Last Year) | H17: ទិន្នន័យប្រចាំខែ (Monthly Data) | L17: សរុបពីដើមឆ្នាំ (From beginning of the Year )
D18: ​ បរិមាណ Quantity | F18: តម្លៃ Value(USD) | H18: បរិមាណផលិតផល Product Quantity | J18: តម្លៃផលិតផល Product Value(USD) | L18: បរិមាណផលិតផល Product Quantity | N18: តម្លៃផលិតផល Product Value(USD)
D19: ក្នុងស្រុក Domestic | E19: នាំចេញ Export | F19: ក្នុងស្រុក Domestic | G19: នាំចេញ Export | H19: ក្នុងស្រុក Domestic | I19: នាំចេញ Export | J19: ក្នុងស្រុក Domestic | K19: នាំចេញ Export | L19: ក្នុងស្រុក Domestic | M19: នាំចេញ Export | N19: ក្នុងស្រុក Domestic | O19: នាំចេញ Export
A20: LADIES | B20: PANTS | C20: PCS | I20: 60139 | K20: =ROUND(I20*1.9865772626748,2) -> 119470.77 | M20: =I20+'2-FEB'!M20 -> 142904 | O20: =K20+'2-FEB'!O20 -> 218534.73 | Q20: =M20+I20 -> 203043 | S20: =O20+K20 -> 338005.5
A21: LADIES | B21: NIGHT GOWN | C21: PCS | I21: 2004 | K21: =ROUND(I21*2.04,2) -> 4088.16 | M21: =I21+'2-FEB'!M25 -> 4084 | O21: =K21+'1-JAN'!O22 -> 159328.16 | Q21: =M21+I21 -> 6088 | S21: =O21+K21 -> 163416.32
A22: LADIES | B22: PAJAMAS | C22: PCS | I22: 19680 | K22: =ROUND(I22*2.13887804878049,2) -> 42093.12 | M22: =I22+'2-FEB'!M24 -> 45448 | O22: =K22+'2-FEB'!O24 -> 205546.16
A23: LADIES | B23: TANK | C23: PCS | M23: ='2-FEB'!M21 -> 3396 | O23: ='2-FEB'!O21 -> 2272.8
A24: LADIES | B24: SKIRT | C24: PCS | M24: ='2-FEB'!M22 -> 1635 | O24: ='2-FEB'!O22 -> 2452.5 | Q24: =M24+I24 -> 1635 | S24: =O24+K24 -> 2452.5
A25: LADIES | B25: SHORT | C25: PCS | M25: ='2-FEB'!M23 -> 1848 | O25: ='2-FEB'!O23 -> 2605.68 | Q25: =M25+I25 -> 1848 | S25: =O25+K25 -> 2605.68
A26: LADIES | B26: DRESS | C26: PCS | M26: 0 | O26: 0 | Q26: =M26+I26 -> 0 | S26: =O26+K26 -> 0
A27: Total | E27: =SUM(E20:E26) -> 0 | G27: =SUM(G20:G26) -> 0 | I27: =SUM(I20:I26) -> 81823 | K27: =SUM(K20:K26) -> 165652.05 | M27: =SUM(M20:M26) -> 199315 | O27: =SUM(O20:O26) -> 590740.03
A28: សំគាល់ :​ ទិន្នន័យនៃរបាយការណ៍នេះត្រូវបានប្រើប្រាស់តែក្នុងគោលបំណង ស្ថិតិឧស្សាហកម្មតែប៉ុណ្ណោះ មិនត្រូវបានយកទៅចែកចាយដើម្បីប្រើប្រាស់
A29: ក្នុងគោលបំណងពាណិជ្ជកម្ម ឬក្នុងការគណនាបង់ពន្ធដារទេ។ | K29: ថ្ងៃទី 15 ខែ មីនា ឆ្នាំ2026 | N29: =K29 -> ថ្ងៃទី 15 ខែ មីនា ឆ្នាំ2026
A30: Remark: This report is used for industrial statistic only,​ not for commercial or tax purpose | J30: ​​​​​​​​​​​​​​​​​​​ | K30: Date:……./……../…… | N30: Date:……./……../……
A31: ទុនអចលនទ្រព្យមិនគិតដីធ្លី រួមមាន៖ អគារ និងឧបករណ៍បរិក្ខារដែលភ្ជាប់នឹងអគារ | K31: នាយក | N31: អ្នកធ្វើរបាយការណ៍
A32: Total asset excluding land comprises of : building & material attached.
A33: ទុនសរុបមិនគិតដីធ្លី រួមមាន៖ ទុនអចលនទ្រព្យមិនគិតដីធ្លី, មធ្យោបាយដឹកជញ្ជូន, គ្រឿងចក្រ-ម៉ាស៊ីន និងឧបករណ៍សម្ភារប្រើប្រាស់ក្នុងផលិតកម្ម, សង្ហារឹម និងសម្ភារការិយាល័យ | K33: Director | N33: Reportor
A34: Total fixed asset excluding land comprises of : real estate capital excluding land, transportation, machinery, and instrument utilised in the production line,
A35: furniture and office equiment.
A36: ទំនាក់ទំនង : Tel 077 330 279/090 922 237 E-mail : industryaffair.mih@gmail.com : TELEGRAM :077 330 279
K40: NI, CUNLAN | N40: THNIN
B41: ឈ្មោះរោងចក្រ ជេអ​ អឹភែរឹល ឯ.ក
A42: ទីផ្សារលក់ផលិតផលប្រចាំខែ | J42: =I6 -> មីនា | K42: ឆ្នាំ២០២៦ (USD)
A43: ល.រ | B43: ឈ្មោះផលិតផល | D43: ឯកតា (Unit) | E43: ឈ្មោះប្រទេសនាំចេញផលិតផល | O43: សរុបពីដើមឆ្នាំ
E44: USA | G44: CANADA | I44: CHINA | K44: EU GROUP | M44: ផ្សេងៗ
E45: បរិមាណ | F45: តម្លៃ | G45: បរិមាណ | H45: តម្លៃ | I45: បរិមាណ | J45: តម្លៃ | K45: បរិមាណ | L45: តម្លៃ | M45: បរិមាណ | N45: តម្លៃ | O45: បរិមាណ | P45: តម្លៃ
A46: 1 | B46: =A20 -> LADIES | C46: =B20 -> PANTS | D46: PCS | E46: 33344 | F46: 65144.85 | G46: 26795 | H46: 54325.92 | O46: =M20 -> 142904 | P46: =O20 -> 218534.73
A47: 2 | B47: =A21 -> LADIES | C47: =B21 -> NIGHT GOWN | D47: PCS | G47: 2004 | H47: 4088.16 | O47: =M21 -> 4084 | P47: =O21 -> 159328.16
A48: 3 | B48: =A22 -> LADIES | C48: =B22 -> PAJAMAS | D48: PCS | E48: 11652 | F48: 24274.56 | G48: 8028 | H48: 17818.56 | O48: =M22 -> 45448 | P48: =O22 -> 205546.16
A49: 4 | B49: =A23 -> LADIES | C49: =B23 -> TANK | D49: PCS | O49: =M23 -> 3396 | P49: =O23 -> 2272.8
A50: 5 | B50: =A24 -> LADIES | C50: =B24 -> SKIRT | D50: PCS | O50: =M24 -> 1635 | P50: =O24 -> 2452.5
A51: 6 | B51: =A25 -> LADIES | C51: =B25 -> SHORT | D51: PCS | O51: =M25 -> 1848 | P51: =O25 -> 2605.68
A52: 7 | B52: =A26 -> LADIES | C52: =B26 -> DRESS | D52: PCS | O52: =M26 -> 0 | P52: =O26 -> 0
B53: សរុប | E53: =SUM(E46:E52) -> 44996 | F53: =SUM(F46:F52) -> 89419.41 | G53: =SUM(G46:G52) -> 36827 | H53: =SUM(H46:H52) -> 76232.64 | I53: =SUM(I46:I52) -> 0 | J53: =SUM(J46:J52) -> 0 | K53: =SUM(K46:K52) -> 0 | L53: =SUM(L46:L52) -> 0 | ... P53: =SUM(P46:P52) -> 590740.03
A55: ប្រភពដើមទំនិញ (វត្ថុធាតុដើម)ប្រចាំខែ | J55: =$I$6 -> មីនា | K55: =$K$42 -> ឆ្នាំ២០២៦ (USD)
A56: ល.រ | B56: ឈ្មោះវត្ថុធាតុដើម | D56: ឯកតា (Unit) | E56: ឈ្មោះប្រទេសនាំចូលវត្ថុធាតុដើម | O56: សរុបពីដើមឆ្នាំ
E57: ចិន | G57: តៃវ៉ាន់ | I57: ហុងកុង | K57: វៀតណាម | M57: ផ្សេងៗ
E58: បរិមាណ | F58: តម្លៃ | G58: បរិមាណ | H58: តម្លៃ | I58: បរិមាណ | J58: តម្លៃ | K58: បរិមាណ | L58: តម្លៃ | M58: បរិមាណ | N58: តម្លៃ | O58: បរិមាណ | P58: តម្លៃ
A59: 1 | B59: I. MACHINERIES &. EQUIPMENTS | Q59: =E59+G59+I59+K59+M59 -> 0 | R59: =F59+H59+J59+L59+N59 -> 0 | S59: =Q59+O59 -> 0 | T59: =R59+P59 -> 0
A60: 3 | B60: II. RAW MATERIAL | D60: MTR | E60: 155861.9 | F60: 162964.68 | O60: =E60+'2-FEB'!O60 -> 333824.4 | P60: =F60+'2-FEB'!P60 -> 323349.72 | Q60: =E60+G60+I60+K60+M60 -> 155861.9 | R60: =F60+H60+J60+L60+N60 -> 162964.68 | S60: =Q60+O60 -> 489686.3 | T60: =R60+P60 -> 486314.4
A61: 4 | B61: III. ACCESSORY | D61: DZN | E61: 234 | F61: 234 | O61: =E61+'2-FEB'!O61 -> 614 | P61: =F61+'2-FEB'!P61 -> 614 | Q61: =E61+G61+I61+K61+M61 -> 234 | R61: =F61+H61+J61+L61+N61 -> 234 | S61: =Q61+O61 -> 848 | T61: =R61+P61 -> 848
B62: សរុប | E62: =SUM(E59:E61) -> 156095.9 | F62: =SUM(F59:F61) -> 163198.68 | G62: =SUM(G59:G61) -> 0 | H62: =SUM(H59:H61) -> 0 | I62: =SUM(I59:I61) -> 0 | J62: =SUM(J59:J61) -> 0 | K62: =SUM(K59:K61) -> 0 | L62: =SUM(L59:L61) -> 0 | ... P62: =SUM(P59:P61) -> 323963.72
B64: =A36 -> ទំនាក់ទំនង : Tel 077 330 279/090 922 237 E-mail : industryaffair.mih@gmail.com : TELEGRAM :077 330 279 | K64: =K29 -> ថ្ងៃទី 15 ខែ មីនា ឆ្នាំ2026 | N64: =N29 -> ថ្ងៃទី 15 ខែ មីនា ឆ្នាំ2026
K65: =K30 -> Date:……./……../…… | N65: =N30 -> Date:……./……../……
K66: =K31 -> នាយក | N66: =N31 -> អ្នកធ្វើរបាយការណ៍
K67: =K33 -> Director | N67: =N33 -> Reportor
K73: =K40 -> NI, CUNLAN | N73: =N40 -> THNIN
B74: ឈ្មោះរោងចក្រ ជេអ​ អឹភែរឹល ឯ.ក
B75: បរិមាណការប្រើប្រាស់ថាមពល ប្រចាំខែ | J75: =$I$6 -> មីនា | K75: =$K$42 -> ឆ្នាំ២០២៦ (USD)
A76: ល.រ | B76: ប្រភេទថាមពល | E76: ឯកតា (Unit) | G76: ឆ្នាំមុន | I76: ប្រចាំខែ......... | K76: សរុបពីដើមឆ្នាំ | O76: ផ្សេងៗ
G77: បរិមាណ | H77: តម្លៃ $ | I77: បរិមាណ | J77: តម្លៃ $ | K77: បរិមាណ | M77: តម្លៃ $
A78: 1 | B78: EDC | E78: KW | I78: 11368 | J78: =0.137*I78 -> 1557.416 | K78: =I78+'2-FEB'!K78:L78 -> 34104 | M78: =J78+'2-FEB'!M78:N78 -> 4672.248 | Q78: =K78+I78 -> 45472 | R78: =M78+J78 -> 6229.664
B79: សរុប | G79: =SUM(G78) -> 0 | H79: =SUM(H78) -> 0 | I79: =SUM(I78) -> 11368 | J79: =SUM(J78) -> 1557.416 | K79: =SUM(K78) -> 34104 | M79: =SUM(M78) -> 4672.248
B81: បរិមាណការប្រើប្រាស់ទឹក​ ប្រចាំខែ | J81: =J75 -> មីនា
A82: ល.រ | B82: ប្រភពទឹក | E82: ឯកតា (Unit) | G82: ឆ្នាំមុន | I82: ប្រចាំខែ......... | K82: សរុបពីដើមឆ្នាំ | O82: ផ្សេងៗ
G83: បរិមាណ | H83: តម្លៃ $ | I83: បរិមាណ | J83: តម្លៃ $ | K83: បរិមាណ | M83: តម្លៃ $
A84: 1 | B84: PPWSA | E84: M3 | I84: 83 | J84: =0.55*I84 -> 45.65 | K84: =I84+'2-FEB'!K84:L84 -> 249 | M84: =J84+'2-FEB'!M84:N84 -> 136.95 | Q84: =K84+I84 -> 332 | R84: =M84+J84 -> 182.6
B85: សរុប | G85: =SUM(G84) -> 0 | H85: =SUM(H84) -> 0 | I85: =SUM(I84) -> 83 | J85: =SUM(J84) -> 45.65 | K85: =SUM(K84) -> 249 | M85: =SUM(M84) -> 136.95
B87: ​ ​បរិមាណសំណល់ ពីដំណើរការខ្សែសង្វាក់ផលិតកម្ម ប្រចាំខែ | J87: =$I$6 -> មីនា | K87: =$K$42 -> ឆ្នាំ២០២៦ (USD)
A88: ល.រ | B88: ប្រភេទសំណល់ | D88: ឯកតា (Unit) | E88: បរិមាណសំណល់សរុប ពីឆ្នាំមុន | G88: បរិមាណសំណល់ប្រចាំខែ......... | K88: បរិមាណសំណល់សរុបពីដើមឆ្នាំ | O88: ផ្សេងៗ
A89: 1 | B89: សំណល់រឹង
A90: 2 | B90: សំណល់រាវ
A91: 3 | B91: សំណល់(ឧស្ម័ន)
A92: 4 | B92: សរុប
A94: =A36 -> ទំនាក់ទំនង : Tel 077 330 279/090 922 237 E-mail : industryaffair.mih@gmail.com : TELEGRAM :077 330 279 | K94: =K29 -> ថ្ងៃទី 15 ខែ មីនា ឆ្នាំ2026 | N94: =N29 -> ថ្ងៃទី 15 ខែ មីនា ឆ្នាំ2026
K95: =K30 -> Date:……./……../…… | N95: =N30 -> Date:……./……../……
K96: =K31 -> នាយក | N96: =N31 -> អ្នកធ្វើរបាយការណ៍
K97: =K33 -> Director | N97: =N67 -> Reportor
K105: =K40 -> NI, CUNLAN | N105: =N73 -> THNIN

Sheet 4-APR
B1: ព្រះរាជាណាចក្រកម្ពុជា
B2: ជាត​ សានា ព្រះមហាក្សត្រ
G3: 
B4: របាយការណ៍ជូនក្រសួងឧស្សាហកម្ម វិទ្យាសាស្ត្រ បច្ចេកវិទ្យា និងនវានុវត្តន៍
B5: Report for Ministry of Industry, Science, Technology & Innovation
G6: ទិន្នន័យប្រចាំខែ | I6: មេសា | J6: ឆ្នាំ 2026
G7: Monthly Data In ........... 202…
A9: ឈ្មោះរោងចក្រ:​​​​​​​​​​ ជេអ អឹភែរឹល ឯ.ក អាស័យដ្ឋានរោងចក្រៈ # ផ្លូវលំ ភូមិ កោះខ្នុរ ឃុំ ព្រែករកា ស្រុក កណ្ដាលស្ទឹង ខេត្ត កណ្ដាល ប្រកាសលេខៈ៤១៧ ឧស.កឧ.ប្រក១២ ចុះថ្ងៃទី ២៤​​ ខែ ធ្នូ ឆ្នាំ ២០១៨
A10: Name of Factory: JR APPAREL CO., LTD Factory Address: #LOM ROAD,KAOH KNOR PREAEK ROKA KANDAL STUENG​ KANDAL PROVINCE Prakas Number : 417
A11: ឈ្មោះអ្នកគ្រប់គ្រងរោងចក្រ NI, CUNLAN ទូរស័ព្ទៈ 855-85 441 621 ទូរសារ:.............................. អ៊ីម៉ែលៈ sanashipping8@gmail.com
A12: Manager Name: NI, CUNLAN Tel: 855-85 441 621 Fax:……………………… E-mail: sanashipping8@gmail.com
A13: ចំនួនពលកម្មសរុបៈ​​​ | C13: 169 | E13: ក្នុងនោះមានស្រីៈ | F13: 116 | H13: បៀរវត្សសរុបប្រចាំខែៈ | J13: 56704.61 | L13: USD
A14: Total Number of Employees: Persons Number of Females: Persons Total Salary & Wage of Monthly USD
A15: ទុនសរុបមិនគិតដីធ្លី Total Asset(Land exclude) | D15: 1000000 | F15: ទុនអចលនទ្រព្យមិនគិតដីធ្លី Total Fixed Asset (Land exclude) | J15: 1000000
A16: មុខផលិតផល Products | C16: ឯកតាUnit | D16: បរិមាណ និងតម្លៃផលិតផល Total Output
D17: ឆ្នាំមុន (Data Last Year) | H17: ទិន្នន័យប្រចាំខែ (Monthly Data) | L17: សរុបពីដើមឆ្នាំ (From beginning of the Year )
D18: ​ បរិមាណ Quantity | F18: តម្លៃ Value(USD) | H18: បរិមាណផលិតផល Product Quantity | J18: តម្លៃផលិតផល Product Value(USD) | L18: បរិមាណផលិតផល Product Quantity | N18: តម្លៃផលិតផល Product Value(USD)
D19: ក្នុងស្រុក Domestic | E19: នាំចេញ Export | F19: ក្នុងស្រុក Domestic | G19: នាំចេញ Export | H19: ក្នុងស្រុក Domestic | I19: នាំចេញ Export | J19: ក្នុងស្រុក Domestic | K19: នាំចេញ Export | L19: ក្នុងស្រុក Domestic | M19: នាំចេញ Export | N19: ក្នុងស្រុក Domestic | O19: នាំចេញ Export
A20: LADIES | B20: PANTS | C20: PCS | I20: 26583 | K20: =ROUND(I20*1.96772561411428,2) -> 52308.05 | M20: =I20+'3-MAR'!M20 -> 169487 | O20: =K20+'3-MAR'!O20 -> 270842.78 | Q20: =M20+I20 -> 196070 | S20: =O20+K20 -> 323150.83
A21: LADIES | B21: DRESS | C21: PCS | I21: 576 | K21: =ROUND(I21*2.66,2) -> 1532.16 | M21: =I21 -> 576 | O21: =K21 -> 1532.16 | Q21: =M21+I21 -> 1152 | S21: =O21+K21 -> 3064.32
A22: LADIES | B22: PAJAMAS | C22: PCS | I22: 35832 | K22: =ROUND(I22*1.73571667782987,2) -> 62194.2 | M22: =I22+'3-MAR'!M22 -> 81280 | O22: =K22+'3-MAR'!O22 -> 267740.36
A23: LADIES | B23: NIGHT GOWN | C23: PCS | M23: ='3-MAR'!M21 -> 4084 | O23: ='3-MAR'!O21 -> 159328.16
A24: LADIES | B24: TANK | C24: PCS | M24: ='3-MAR'!M23 -> 3396 | O24: ='3-MAR'!O23 -> 2272.8 | Q24: =M24+I24 -> 3396 | S24: =O24+K24 -> 2272.8
A25: LADIES | B25: SKIRT | C25: PCS | M25: ='3-MAR'!M24 -> 1635 | O25: ='3-MAR'!O24 -> 2452.5 | Q25: =M25+I25 -> 1635 | S25: =O25+K25 -> 2452.5
A26: LADIES | B26: SHORT | C26: PCS | M26: ='3-MAR'!M25 -> 1848 | O26: ='3-MAR'!O25 -> 2605.68 | Q26: =M26+I26 -> 1848 | S26: =O26+K26 -> 2605.68
A27: Total | E27: =SUM(E20:E26) -> 0 | G27: =SUM(G20:G26) -> 0 | I27: =SUM(I20:I26) -> 62991 | K27: =SUM(K20:K26) -> 116034.41 | M27: =SUM(M20:M26) -> 262306 | O27: =SUM(O20:O26) -> 706774.44
A28: សំគាល់ :​ ទិន្នន័យនៃរបាយការណ៍នេះត្រូវបានប្រើប្រាស់តែក្នុងគោលបំណង ស្ថិតិឧស្សាហកម្មតែប៉ុណ្ណោះ មិនត្រូវបានយកទៅចែកចាយដើម្បីប្រើប្រាស់
A29: ក្នុងគោលបំណងពាណិជ្ជកម្ម ឬក្នុងការគណនាបង់ពន្ធដារទេ។ | K29: ថ្ងៃទី 15 ខែ មេសា ឆ្នាំ2026 | N29: =K29 -> ថ្ងៃទី 15 ខែ មេសា ឆ្នាំ2026
A30: Remark: This report is used for industrial statistic only,​ not for commercial or tax purpose | J30: ​​​​​​​​​​​​​​​​​​​ | K30: Date:……./……../…… | N30: Date:……./……../……
A31: ទុនអចលនទ្រព្យមិនគិតដីធ្លី រួមមាន៖ អគារ និងឧបករណ៍បរិក្ខារដែលភ្ជាប់នឹងអគារ | K31: នាយក | N31: អ្នកធ្វើរបាយការណ៍
A32: Total asset excluding land comprises of : building & material attached.
A33: ទុនសរុបមិនគិតដីធ្លី រួមមាន៖ ទុនអចលនទ្រព្យមិនគិតដីធ្លី, មធ្យោបាយដឹកជញ្ជូន, គ្រឿងចក្រ-ម៉ាស៊ីន និងឧបករណ៍សម្ភារប្រើប្រាស់ក្នុងផលិតកម្ម, សង្ហារឹម និងសម្ភារការិយាល័យ | K33: Director | N33: Reportor
A34: Total fixed asset excluding land comprises of : real estate capital excluding land, transportation, machinery, and instrument utilised in the production line,
A35: furniture and office equiment.
A36: ទំនាក់ទំនង : Tel 077 330 279/090 922 237 E-mail : industryaffair.mih@gmail.com : TELEGRAM :077 330 279
K40: NI, CUNLAN | N40: THNIN
B41: ឈ្មោះរោងចក្រ ជេអ​ អឹភែរឹល ឯ.ក
A42: ទីផ្សារលក់ផលិតផលប្រចាំខែ | J42: =I6 -> មេសា | K42: ឆ្នាំ២០២៦ (USD)
A43: ល.រ | B43: ឈ្មោះផលិតផល | D43: ឯកតា (Unit) | E43: ឈ្មោះប្រទេសនាំចេញផលិតផល | O43: សរុបពីដើមឆ្នាំ
E44: USA | G44: CANADA | I44: CHINA | K44: EU GROUP | M44: ផ្សេងៗ
E45: បរិមាណ | F45: តម្លៃ | G45: បរិមាណ | H45: តម្លៃ | I45: បរិមាណ | J45: តម្លៃ | K45: បរិមាណ | L45: តម្លៃ | M45: បរិមាណ | N45: តម្លៃ | O45: បរិមាណ | P45: តម្លៃ
A46: 1 | B46: =A20 -> LADIES | C46: =B20 -> PANTS | D46: PCS | E46: 26583 | F46: 52308.05 | O46: =M20 -> 169487 | P46: =O20 -> 270842.78
A47: 2 | B47: =A21 -> LADIES | C47: =B21 -> DRESS | D47: PCS | E47: 576 | F47: 1532.16 | O47: =M21 -> 576 | P47: =O21 -> 1532.16
A48: 3 | B48: =A22 -> LADIES | C48: =B22 -> PAJAMAS | D48: PCS | E48: 17916 | F48: 38199.6 | G48: 17916 | H48: 23994.6 | O48: =M22 -> 81280 | P48: =O22 -> 267740.36
A49: 4 | B49: =A23 -> LADIES | C49: =B23 -> NIGHT GOWN | D49: PCS | O49: =M23 -> 4084 | P49: =O23 -> 159328.16
A50: 5 | B50: =A24 -> LADIES | C50: =B24 -> TANK | D50: PCS | O50: =M24 -> 3396 | P50: =O24 -> 2272.8
A51: 6 | B51: =A25 -> LADIES | C51: =B25 -> SKIRT | D51: PCS | O51: =M25 -> 1635 | P51: =O25 -> 2452.5
A52: 7 | B52: =A26 -> LADIES | C52: =B26 -> SHORT | D52: PCS | O52: =M26 -> 1848 | P52: =O26 -> 2605.68
B53: សរុប | E53: =SUM(E46:E52) -> 45075 | F53: =SUM(F46:F52) -> 92039.81 | G53: =SUM(G46:G52) -> 17916 | H53: =SUM(H46:H52) -> 23994.6 | I53: =SUM(I46:I52) -> 0 | J53: =SUM(J46:J52) -> 0 | K53: =SUM(K46:K52) -> 0 | L53: =SUM(L46:L52) -> 0 | ... P53: =SUM(P46:P52) -> 706774.44
A55: ប្រភពដើមទំនិញ (វត្ថុធាតុដើម)ប្រចាំខែ | J55: =$I$6 -> មេសា | K55: =$K$42 -> ឆ្នាំ២០២៦ (USD)
A56: ល.រ | B56: ឈ្មោះវត្ថុធាតុដើម | D56: ឯកតា (Unit) | E56: ឈ្មោះប្រទេសនាំចូលវត្ថុធាតុដើម | O56: សរុបពីដើមឆ្នាំ
E57: ចិន | G57: តៃវ៉ាន់ | I57: ហុងកុង | K57: វៀតណាម | M57: ផ្សេងៗ
E58: បរិមាណ | F58: តម្លៃ | G58: បរិមាណ | H58: តម្លៃ | I58: បរិមាណ | J58: តម្លៃ | K58: បរិមាណ | L58: តម្លៃ | M58: បរិមាណ | N58: តម្លៃ | O58: បរិមាណ | P58: តម្លៃ
A59: 1 | B59: I. MACHINERIES &. EQUIPMENTS | Q59: =E59+G59+I59+K59+M59 -> 0 | R59: =F59+H59+J59+L59+N59 -> 0 | S59: =Q59+O59 -> 0 | T59: =R59+P59 -> 0
A60: 3 | B60: II. RAW MATERIAL | E60: 116399 | F60: 119687.88 | O60: =E60+'3-MAR'!O60 -> 450223.4 | P60: =F60+'3-MAR'!P60 -> 443037.6 | Q60: =E60+G60+I60+K60+M60 -> 116399 | R60: =F60+H60+J60+L60+N60 -> 119687.88 | S60: =Q60+O60 -> 566622.4 | T60: =R60+P60 -> 562725.48
A61: 4 | B61: III. ACCESSORY | E61: 142 | F61: 142 | O61: =E61+'3-MAR'!O61 -> 756 | P61: =F61+'3-MAR'!P61 -> 756 | Q61: =E61+G61+I61+K61+M61 -> 142 | R61: =F61+H61+J61+L61+N61 -> 142 | S61: =Q61+O61 -> 898 | T61: =R61+P61 -> 898
B62: សរុប | E62: =SUM(E59:E61) -> 116541 | F62: =SUM(F59:F61) -> 119829.88 | G62: =SUM(G59:G61) -> 0 | H62: =SUM(H59:H61) -> 0 | I62: =SUM(I59:I61) -> 0 | J62: =SUM(J59:J61) -> 0 | K62: =SUM(K59:K61) -> 0 | L62: =SUM(L59:L61) -> 0 | ... P62: =SUM(P59:P61) -> 443793.6
B64: =A36 -> ទំនាក់ទំនង : Tel 077 330 279/090 922 237 E-mail : industryaffair.mih@gmail.com : TELEGRAM :077 330 279 | K64: =K29 -> ថ្ងៃទី 15 ខែ មេសា ឆ្នាំ2026 | N64: =N29 -> ថ្ងៃទី 15 ខែ មេសា ឆ្នាំ2026
K65: =K30 -> Date:……./……../…… | N65: =N30 -> Date:……./……../……
K66: =K31 -> នាយក | N66: =N31 -> អ្នកធ្វើរបាយការណ៍
K67: =K33 -> Director | N67: =N33 -> Reportor
K73: =K40 -> NI, CUNLAN | N73: =N40 -> THNIN
B74: ឈ្មោះរោងចក្រ ជេអ​ អឹភែរឹល ឯ.ក
B75: បរិមាណការប្រើប្រាស់ថាមពល ប្រចាំខែ | J75: =$I$6 -> មេសា | K75: =$K$42 -> ឆ្នាំ២០២៦ (USD)
A76: ល.រ | B76: ប្រភេទថាមពល | E76: ឯកតា (Unit) | G76: ឆ្នាំមុន | I76: ប្រចាំខែ......... | K76: សរុបពីដើមឆ្នាំ | O76: ផ្សេងៗ
G77: បរិមាណ | H77: តម្លៃ $ | I77: បរិមាណ | J77: តម្លៃ $ | K77: បរិមាណ | M77: តម្លៃ $
A78: 1 | B78: EDC | E78: KW | I78: 11368 | J78: =0.137*I78 -> 1557.416 | K78: =I78+'3-MAR'!K78:L78 -> 45472 | M78: =J78+'3-MAR'!M78:N78 -> 6229.664 | Q78: =K78+I78 -> 56840 | R78: =M78+J78 -> 7787.08
B79: សរុប | G79: =SUM(G78) -> 0 | H79: =SUM(H78) -> 0 | I79: =SUM(I78) -> 11368 | J79: =SUM(J78) -> 1557.416 | K79: =SUM(K78) -> 45472 | M79: =SUM(M78) -> 6229.664
B81: បរិមាណការប្រើប្រាស់ទឹក​ ប្រចាំខែ | J81: =J75 -> មេសា
A82: ល.រ | B82: ប្រភពទឹក | E82: ឯកតា (Unit) | G82: ឆ្នាំមុន | I82: ប្រចាំខែ......... | K82: សរុបពីដើមឆ្នាំ | O82: ផ្សេងៗ
G83: បរិមាណ | H83: តម្លៃ $ | I83: បរិមាណ | J83: តម្លៃ $ | K83: បរិមាណ | M83: តម្លៃ $
A84: 1 | B84: PPWSA | E84: M3 | I84: 83 | J84: =0.55*I84 -> 45.65 | K84: =I84+'3-MAR'!K84:L84 -> 332 | M84: =J84+'3-MAR'!M84:N84 -> 182.6 | Q84: =K84+I84 -> 415 | R84: =M84+J84 -> 228.25
B85: សរុប | G85: =SUM(G84) -> 0 | H85: =SUM(H84) -> 0 | I85: =SUM(I84) -> 83 | J85: =SUM(J84) -> 45.65 | K85: =SUM(K84) -> 332 | M85: =SUM(M84) -> 182.6
B87: ​ ​បរិមាណសំណល់ ពីដំណើរការខ្សែសង្វាក់ផលិតកម្ម ប្រចាំខែ | J87: =$I$6 -> មេសា | K87: =$K$42 -> ឆ្នាំ២០២៦ (USD)
A88: ល.រ | B88: ប្រភេទសំណល់ | D88: ឯកតា (Unit) | E88: បរិមាណសំណល់សរុប ពីឆ្នាំមុន | G88: បរិមាណសំណល់ប្រចាំខែ......... | K88: បរិមាណសំណល់សរុបពីដើមឆ្នាំ | O88: ផ្សេងៗ
A89: 1 | B89: សំណល់រឹង
A90: 2 | B90: សំណល់រាវ
A91: 3 | B91: សំណល់(ឧស្ម័ន)
A92: 4 | B92: សរុប
A94: =A36 -> ទំនាក់ទំនង : Tel 077 330 279/090 922 237 E-mail : industryaffair.mih@gmail.com : TELEGRAM :077 330 279 | K94: =K29 -> ថ្ងៃទី 15 ខែ មេសា ឆ្នាំ2026 | N94: =N29 -> ថ្ងៃទី 15 ខែ មេសា ឆ្នាំ2026
K95: =K30 -> Date:……./……../…… | N95: =N30 -> Date:……./……../……
K96: =K31 -> នាយក | N96: =N31 -> អ្នកធ្វើរបាយការណ៍
K97: =K33 -> Director | N97: =N67 -> Reportor
K105: =K40 -> NI, CUNLAN | N105: =N73 -> THNIN

Sheet 5-MAY
B1: ព្រះរាជាណាចក្រកម្ពុជា
B2: ជាត​ សានា ព្រះមហាក្សត្រ
G3: 
B4: របាយការណ៍ជូនក្រសួងឧស្សាហកម្ម វិទ្យាសាស្ត្រ បច្ចេកវិទ្យា និងនវានុវត្តន៍
B5: Report for Ministry of Industry, Science, Technology & Innovation
G6: ទិន្នន័យប្រចាំខែ | I6: ឧសភា | J6: ឆ្នាំ 2026
G7: Monthly Data In ........... 202…
A9: ឈ្មោះរោងចក្រ:​​​​​​​​​​ ជេអ អឹភែរឹល ឯ.ក អាស័យដ្ឋានរោងចក្រៈ # ផ្លូវលំ ភូមិ កោះខ្នុរ ឃុំ ព្រែករកា ស្រុក កណ្ដាលស្ទឹង ខេត្ត កណ្ដាល ប្រកាសលេខៈ៤១៧ ឧស.កឧ.ប្រក១២ ចុះថ្ងៃទី ២៤​​ ខែ ធ្នូ ឆ្នាំ ២០១៨
A10: Name of Factory: JR APPAREL CO., LTD Factory Address: #LOM ROAD,KAOH KNOR PREAEK ROKA KANDAL STUENG​ KANDAL PROVINCE Prakas Number : 417
A11: ឈ្មោះអ្នកគ្រប់គ្រងរោងចក្រ NI, CUNLAN ទូរស័ព្ទៈ 855-85 441 621 ទូរសារ:.............................. អ៊ីម៉ែលៈ sanashipping8@gmail.com
A12: Manager Name: NI, CUNLAN Tel: 855-85 441 621 Fax:……………………… E-mail: sanashipping8@gmail.com
A13: ចំនួនពលកម្មសរុបៈ​​​ | C13: 151 | E13: ក្នុងនោះមានស្រីៈ | F13: 105 | H13: បៀរវត្សសរុបប្រចាំខែៈ | J13: 55620.7 | L13: USD
A14: Total Number of Employees: Persons Number of Females: Persons Total Salary & Wage of Monthly USD
A15: ទុនសរុបមិនគិតដីធ្លី Total Asset(Land exclude) | D15: 1000000 | F15: ទុនអចលនទ្រព្យមិនគិតដីធ្លី Total Fixed Asset (Land exclude) | J15: 1000000
A16: មុខផលិតផល Products | C16: ឯកតាUnit | D16: បរិមាណ និងតម្លៃផលិតផល Total Output
D17: ឆ្នាំមុន (Data Last Year) | H17: ទិន្នន័យប្រចាំខែ (Monthly Data) | L17: សរុបពីដើមឆ្នាំ (From beginning of the Year )
D18: ​ បរិមាណ Quantity | F18: តម្លៃ Value(USD) | H18: បរិមាណផលិតផល Product Quantity | J18: តម្លៃផលិតផល Product Value(USD) | L18: បរិមាណផលិតផល Product Quantity | N18: តម្លៃផលិតផល Product Value(USD)
D19: ក្នុងស្រុក Domestic | E19: នាំចេញ Export | F19: ក្នុងស្រុក Domestic | G19: នាំចេញ Export | H19: ក្នុងស្រុក Domestic | I19: នាំចេញ Export | J19: ក្នុងស្រុក Domestic | K19: នាំចេញ Export | L19: ក្នុងស្រុក Domestic | M19: នាំចេញ Export | N19: ក្នុងស្រុក Domestic | O19: នាំចេញ Export
A20: LADIES | B20: PANTS | C20: PCS | I20: 45756 | K20: =ROUND(I20*2.13575268817204,2) -> 97723.5 | M20: =I20+'4-APR'!M20 -> 215243 | O20: =K20+'4-APR'!O20 -> 368566.28 | Q20: =M20+I20 -> 260999 | S20: =O20+K20 -> 466289.78
A21: LADIES | B21: SKIRT | C21: PCS | I21: 175 | K21: =ROUND(I21*2.3,2) -> 402.5 | M21: =I21+'2-FEB'!M22 -> 1810 | O21: =K21+'2-FEB'!O22 -> 2855 | Q21: =M21+I21 -> 1985 | S21: =O21+K21 -> 3257.5
A22: LADIES | B22: PAJAMAS | C22: PCS | I22: 38268 | K22: =ROUND(I22*1.34513954217623,2) -> 51475.8 | M22: =I22+'4-APR'!M22 -> 119548 | O22: =K22+'4-APR'!O22 -> 319216.16
A23: LADIES | B23: DRESS | C23: PCS | M23: ='4-APR'!M22 -> 81280 | O23: ='4-APR'!O22 -> 267740.36
A24: LADIES | B24: NIGHT GOWN | C24: PCS | M24: ='4-APR'!M21 -> 576 | O24: ='4-APR'!O21 -> 1532.16 | Q24: =M24+I24 -> 576 | S24: =O24+K24 -> 1532.16
A25: LADIES | B25: TANK | C25: PCS | M25: ='4-APR'!M24 -> 3396 | O25: ='4-APR'!O24 -> 2272.8 | Q25: =M25+I25 -> 3396 | S25: =O25+K25 -> 2272.8
A26: LADIES | B26: SHORT | C26: PCS | M26: ='4-APR'!M26 -> 1848 | O26: ='4-APR'!O26 -> 2605.68 | Q26: =M26+I26 -> 1848 | S26: =O26+K26 -> 2605.68
A27: Total | E27: =SUM(E20:E26) -> 0 | G27: =SUM(G20:G26) -> 0 | I27: =SUM(I20:I26) -> 84199 | K27: =SUM(K20:K26) -> 149601.8 | M27: =SUM(M20:M26) -> 423701 | O27: =SUM(O20:O26) -> 964788.44
A28: សំគាល់ :​ ទិន្នន័យនៃរបាយការណ៍នេះត្រូវបានប្រើប្រាស់តែក្នុងគោលបំណង ស្ថិតិឧស្សាហកម្មតែប៉ុណ្ណោះ មិនត្រូវបានយកទៅចែកចាយដើម្បីប្រើប្រាស់
A29: ក្នុងគោលបំណងពាណិជ្ជកម្ម ឬក្នុងការគណនាបង់ពន្ធដារទេ។ | K29: ថ្ងៃទី 15 ខែ ឧសភា ឆ្នាំ2026 | N29: =K29 -> ថ្ងៃទី 15 ខែ ឧសភា ឆ្នាំ2026
A30: Remark: This report is used for industrial statistic only,​ not for commercial or tax purpose | J30: ​​​​​​​​​​​​​​​​​​​ | K30: Date:……./……../…… | N30: Date:……./……../……
A31: ទុនអចលនទ្រព្យមិនគិតដីធ្លី រួមមាន៖ អគារ និងឧបករណ៍បរិក្ខារដែលភ្ជាប់នឹងអគារ | K31: នាយក | N31: អ្នកធ្វើរបាយការណ៍
A32: Total asset excluding land comprises of : building & material attached.
A33: ទុនសរុបមិនគិតដីធ្លី រួមមាន៖ ទុនអចលនទ្រព្យមិនគិតដីធ្លី, មធ្យោបាយដឹកជញ្ជូន, គ្រឿងចក្រ-ម៉ាស៊ីន និងឧបករណ៍សម្ភារប្រើប្រាស់ក្នុងផលិតកម្ម, សង្ហារឹម និងសម្ភារការិយាល័យ | K33: Director | N33: Reportor
A34: Total fixed asset excluding land comprises of : real estate capital excluding land, transportation, machinery, and instrument utilised in the production line,
A35: furniture and office equiment.
A36: ទំនាក់ទំនង : Tel 077 330 279/090 922 237 E-mail : industryaffair.mih@gmail.com : TELEGRAM :077 330 279
K40: NI, CUNALN | N40: THNIN
B41: ឈ្មោះរោងចក្រ ជេអ​ អឹភែរឹល ឯ.ក
A42: ទីផ្សារលក់ផលិតផលប្រចាំខែ | J42: =I6 -> ឧសភា | K42: ឆ្នាំ២០២៦ (USD)
A43: ល.រ | B43: ឈ្មោះផលិតផល | D43: ឯកតា (Unit) | E43: ឈ្មោះប្រទេសនាំចេញផលិតផល | O43: សរុបពីដើមឆ្នាំ
E44: USA | G44: CANADA | I44: CHINA | K44: EU GROUP | M44: ផ្សេងៗ
E45: បរិមាណ | F45: តម្លៃ | G45: បរិមាណ | H45: តម្លៃ | I45: បរិមាណ | J45: តម្លៃ | K45: បរិមាណ | L45: តម្លៃ | M45: បរិមាណ | N45: តម្លៃ | O45: បរិមាណ | P45: តម្លៃ
A46: 1 | B46: =A20 -> LADIES | C46: =B20 -> PANTS | D46: PCS | E46: 28491 | F46: 56882 | G46: 16545 | H46: 39444.7 | M46: 720 | N46: 1396.8 | O46: =M20 -> 215243 | P46: =O20 -> 368566.28
A47: 2 | B47: =A21 -> LADIES | C47: =B21 -> SKIRT | D47: PCS | G47: 175 | H47: 402.5 | O47: =M21 -> 1810 | P47: =O21 -> 2855
A48: 3 | B48: =A22 -> LADIES | C48: =B22 -> PAJAMAS | D48: PCS | E48: 33444 | F48: 44682.6 | G48: 4824 | H48: 6793.2 | O48: =M22 -> 119548 | P48: =O22 -> 319216.16
A49: 4 | B49: =A23 -> LADIES | C49: =B23 -> DRESS | D49: PCS | O49: =M23 -> 81280 | P49: =O23 -> 267740.36
A50: 5 | B50: =A24 -> LADIES | C50: =B24 -> NIGHT GOWN | D50: PCS | O50: =M24 -> 576 | P50: =O24 -> 1532.16
A51: 6 | B51: =A25 -> LADIES | C51: =B25 -> TANK | D51: PCS | O51: =M25 -> 3396 | P51: =O25 -> 2272.8
A52: 7 | B52: =A26 -> LADIES | C52: =B26 -> SHORT | D52: PCS | O52: =M26 -> 1848 | P52: =O26 -> 2605.68
B53: សរុប | E53: =SUM(E46:E52) -> 61935 | F53: =SUM(F46:F52) -> 101564.6 | G53: =SUM(G46:G52) -> 21544 | H53: =SUM(H46:H52) -> 46640.4 | I53: =SUM(I46:I52) -> 0 | J53: =SUM(J46:J52) -> 0 | K53: =SUM(K46:K52) -> 0 | L53: =SUM(L46:L52) -> 0 | ... P53: =SUM(P46:P52) -> 964788.44
A55: ប្រភពដើមទំនិញ (វត្ថុធាតុដើម)ប្រចាំខែ | J55: =$I$6 -> ឧសភា | K55: =$K$42 -> ឆ្នាំ២០២៦ (USD)
A56: ល.រ | B56: ឈ្មោះវត្ថុធាតុដើម | D56: ឯកតា (Unit) | E56: ឈ្មោះប្រទេសនាំចូលវត្ថុធាតុដើម | O56: សរុបពីដើមឆ្នាំ
E57: ចិន | G57: តៃវ៉ាន់ | I57: ហុងកុង | K57: វៀតណាម | M57: ផ្សេងៗ
E58: បរិមាណ | F58: តម្លៃ | G58: បរិមាណ | H58: តម្លៃ | I58: បរិមាណ | J58: តម្លៃ | K58: បរិមាណ | L58: តម្លៃ | M58: បរិមាណ | N58: តម្លៃ | O58: បរិមាណ | P58: តម្លៃ
A59: 1 | B59: I. MACHINERIES &. EQUIPMENTS | Q59: =E59+G59+I59+K59+M59 -> 0 | R59: =F59+H59+J59+L59+N59 -> 0 | S59: =Q59+O59 -> 0 | T59: =R59+P59 -> 0
A60: 3 | B60: II. RAW MATERIAL | O60: ='4-APR'!O60 -> 450223.4 | P60: ='4-APR'!P60 -> 443037.6 | Q60: =E60+G60+I60+K60+M60 -> 0 | R60: =F60+H60+J60+L60+N60 -> 0 | S60: =Q60+O60 -> 450223.4 | T60: =R60+P60 -> 443037.6
A61: 4 | B61: III. ACCESSORY | O61: ='4-APR'!O61 -> 756 | P61: ='4-APR'!P61 -> 756 | Q61: =E61+G61+I61+K61+M61 -> 0 | R61: =F61+H61+J61+L61+N61 -> 0 | S61: =Q61+O61 -> 756 | T61: =R61+P61 -> 756
B62: សរុប | E62: =SUM(E59:E61) -> 0 | F62: =SUM(F59:F61) -> 0 | G62: =SUM(G59:G61) -> 0 | H62: =SUM(H59:H61) -> 0 | I62: =SUM(I59:I61) -> 0 | J62: =SUM(J59:J61) -> 0 | K62: =SUM(K59:K61) -> 0 | L62: =SUM(L59:L61) -> 0 | ... P62: =SUM(P59:P61) -> 443793.6
B64: =A36 -> ទំនាក់ទំនង : Tel 077 330 279/090 922 237 E-mail : industryaffair.mih@gmail.com : TELEGRAM :077 330 279 | K64: =K29 -> ថ្ងៃទី 15 ខែ ឧសភា ឆ្នាំ2026 | N64: =N29 -> ថ្ងៃទី 15 ខែ ឧសភា ឆ្នាំ2026
K65: =K30 -> Date:……./……../…… | N65: =N30 -> Date:……./……../……
K66: =K31 -> នាយក | N66: =N31 -> អ្នកធ្វើរបាយការណ៍
K67: =K33 -> Director | N67: =N33 -> Reportor
K73: =K40 -> NI, CUNALN | N73: =N40 -> THNIN
B74: ឈ្មោះរោងចក្រ ជេអ​ អឹភែរឹល ឯ.ក
B75: បរិមាណការប្រើប្រាស់ថាមពល ប្រចាំខែ | J75: =$I$6 -> ឧសភា | K75: =$K$42 -> ឆ្នាំ២០២៦ (USD)
A76: ល.រ | B76: ប្រភេទថាមពល | E76: ឯកតា (Unit) | G76: ឆ្នាំមុន | I76: ប្រចាំខែ......... | K76: សរុបពីដើមឆ្នាំ | O76: ផ្សេងៗ
G77: បរិមាណ | H77: តម្លៃ $ | I77: បរិមាណ | J77: តម្លៃ $ | K77: បរិមាណ | M77: តម្លៃ $
A78: 1 | B78: EDC | E78: KW | I78: 11368 | J78: =0.137*I78 -> 1557.416 | K78: =I78+'4-APR'!K78:L78 -> 56840 | M78: =J78+'4-APR'!M78:N78 -> 7787.08 | Q78: =K78+I78 -> 68208 | R78: =M78+J78 -> 9344.496
B79: សរុប | G79: =SUM(G78) -> 0 | H79: =SUM(H78) -> 0 | I79: =SUM(I78) -> 11368 | J79: =SUM(J78) -> 1557.416 | K79: =SUM(K78) -> 56840 | M79: =SUM(M78) -> 7787.08
B81: បរិមាណការប្រើប្រាស់ទឹក​ ប្រចាំខែ | J81: =J75 -> ឧសភា
A82: ល.រ | B82: ប្រភពទឹក | E82: ឯកតា (Unit) | G82: ឆ្នាំមុន | I82: ប្រចាំខែ......... | K82: សរុបពីដើមឆ្នាំ | O82: ផ្សេងៗ
G83: បរិមាណ | H83: តម្លៃ $ | I83: បរិមាណ | J83: តម្លៃ $ | K83: បរិមាណ | M83: តម្លៃ $
A84: 1 | B84: PPWSA | E84: M3 | I84: 83 | J84: =0.55*I84 -> 45.65 | K84: =I84+'4-APR'!K84:L84 -> 415 | M84: =J84+'4-APR'!M84:N84 -> 228.25 | Q84: =K84+I84 -> 498 | R84: =M84+J84 -> 273.9
B85: សរុប | G85: =SUM(G84) -> 0 | H85: =SUM(H84) -> 0 | I85: =SUM(I84) -> 83 | J85: =SUM(J84) -> 45.65 | K85: =SUM(K84) -> 415 | M85: =SUM(M84) -> 228.25
B87: ​ ​បរិមាណសំណល់ ពីដំណើរការខ្សែសង្វាក់ផលិតកម្ម ប្រចាំខែ | J87: =$I$6 -> ឧសភា | K87: =$K$42 -> ឆ្នាំ២០២៦ (USD)
A88: ល.រ | B88: ប្រភេទសំណល់ | D88: ឯកតា (Unit) | E88: បរិមាណសំណល់សរុប ពីឆ្នាំមុន | G88: បរិមាណសំណល់ប្រចាំខែ......... | K88: បរិមាណសំណល់សរុបពីដើមឆ្នាំ | O88: ផ្សេងៗ
A89: 1 | B89: សំណល់រឹង
A90: 2 | B90: សំណល់រាវ
A91: 3 | B91: សំណល់(ឧស្ម័ន)
A92: 4 | B92: សរុប
A94: =A36 -> ទំនាក់ទំនង : Tel 077 330 279/090 922 237 E-mail : industryaffair.mih@gmail.com : TELEGRAM :077 330 279 | K94: =K29 -> ថ្ងៃទី 15 ខែ ឧសភា ឆ្នាំ2026 | N94: =N29 -> ថ្ងៃទី 15 ខែ ឧសភា ឆ្នាំ2026
K95: =K30 -> Date:……./……../…… | N95: =N30 -> Date:……./……../……
K96: =K31 -> នាយក | N96: =N31 -> អ្នកធ្វើរបាយការណ៍
K97: =K33 -> Director | N97: =N67 -> Reportor
K105: =K40 -> NI, CUNALN | N105: =N73 -> THNIN

Sheet 6-JUN
B1: ព្រះរាជាណាចក្រកម្ពុជា
B2: ជាត​ សានា ព្រះមហាក្សត្រ
G3: 
B4: របាយការណ៍ជូនក្រសួងឧស្សាហកម្ម វិទ្យាសាស្ត្រ បច្ចេកវិទ្យា និងនវានុវត្តន៍
B5: Report for Ministry of Industry, Science, Technology & Innovation
G6: ទិន្នន័យប្រចាំខែ | I6: មិថុនា | J6: ឆ្នាំ 2026
G7: Monthly Data In ........... 202…
A9: ឈ្មោះរោងចក្រ:​​​​​​​​​​ ជេអ អឹភែរឹល ឯ.ក អាស័យដ្ឋានរោងចក្រៈ # ផ្លូវលំ ភូមិ កោះខ្នុរ ឃុំ ព្រែករកា ស្រុក កណ្ដាលស្ទឹង ខេត្ត កណ្ដាល ប្រកាសលេខៈ៤១៧ ឧស.កឧ.ប្រក១២ ចុះថ្ងៃទី ២៤​​ ខែ ធ្នូ ឆ្នាំ ២០១៨
A10: Name of Factory: JR APPAREL CO., LTD Factory Address: #LOM ROAD,KAOH KNOR PREAEK ROKA KANDAL STUENG​ KANDAL PROVINCE Prakas Number : 417
A11: ឈ្មោះអ្នកគ្រប់គ្រងរោងចក្រ NI, CUNLAN ទូរស័ព្ទៈ 855-85 441 621 ទូរសារ:.............................. អ៊ីម៉ែលៈ sanashipping8@gmail.com
A12: Manager Name: NI, CUNLAN Tel: 855-85 441 621 Fax:……………………… E-mail: sanashipping8@gmail.com
A13: ចំនួនពលកម្មសរុបៈ​​​ | C13: 186 | E13: ក្នុងនោះមានស្រីៈ | F13: 125 | H13: បៀរវត្សសរុបប្រចាំខែៈ | J13: 65896.2 | L13: USD
A14: Total Number of Employees: Persons Number of Females: Persons Total Salary & Wage of Monthly USD
A15: ទុនសរុបមិនគិតដីធ្លី Total Asset(Land exclude) | D15: 1000000 | F15: ទុនអចលនទ្រព្យមិនគិតដីធ្លី Total Fixed Asset (Land exclude) | J15: 1000000
A16: មុខផលិតផល Products | C16: ឯកតាUnit | D16: បរិមាណ និងតម្លៃផលិតផល Total Output
D17: ឆ្នាំមុន (Data Last Year) | H17: ទិន្នន័យប្រចាំខែ (Monthly Data) | L17: សរុបពីដើមឆ្នាំ (From beginning of the Year )
D18: ​ បរិមាណ Quantity | F18: តម្លៃ Value(USD) | H18: បរិមាណផលិតផល Product Quantity | J18: តម្លៃផលិតផល Product Value(USD) | L18: បរិមាណផលិតផល Product Quantity | N18: តម្លៃផលិតផល Product Value(USD)
D19: ក្នុងស្រុក Domestic | E19: នាំចេញ Export | F19: ក្នុងស្រុក Domestic | G19: នាំចេញ Export | H19: ក្នុងស្រុក Domestic | I19: នាំចេញ Export | J19: ក្នុងស្រុក Domestic | K19: នាំចេញ Export | L19: ក្នុងស្រុក Domestic | M19: នាំចេញ Export | N19: ក្នុងស្រុក Domestic | O19: នាំចេញ Export
A20: LADIES | B20: PANTS | C20: PCS | I20: 136526 | K20: =ROUND(I20*2.05938099702621,2) -> 281159.05 | M20: =I20+'5-MAY'!M20 -> 351769 | O20: =K20+'5-MAY'!O20 -> 649725.33 | Q20: =M20+I20 -> 488295 | S20: =O20+K20 -> 930884.38
A21: LADIES | B21: PAJAMAS | C21: PCS | I21: 5424 | K21: =ROUND(I21*1.325,2) -> 7186.8 | M21: =I21+'5-MAY'!M22 -> 124972 | O21: =K21+'5-MAY'!O22 -> 326402.96
A22: LADIES | B22: SKIRT | C22: PCS | M22: ='5-MAY'!M21 -> 1810 | O22: ='5-MAY'!O21 -> 2855
A23: LADIES | B23: DRESS | C23: PCS | M23: ='5-MAY'!M23 -> 81280 | O23: ='5-MAY'!O23 -> 267740.36 | Q23: =M23+I23 -> 81280 | S23: =O23+K23 -> 267740.36
A24: LADIES | B24: NIGHT GOWN | C24: PCS | M24: ='5-MAY'!M24 -> 576 | O24: ='5-MAY'!O24 -> 1532.16 | Q24: =M24+I24 -> 576 | S24: =O24+K24 -> 1532.16
A25: LADIES | B25: TANK | C25: PCS | M25: ='5-MAY'!M25 -> 3396 | O25: ='5-MAY'!O25 -> 2272.8 | Q25: =M25+I25 -> 3396 | S25: =O25+K25 -> 2272.8
A26: LADIES | B26: SHORT | C26: PCS | M26: ='5-MAY'!M26 -> 1848 | O26: ='5-MAY'!O26 -> 2605.68 | Q26: =M26+I26 -> 1848 | S26: =O26+K26 -> 2605.68
A27: Total | E27: =SUM(E20:E26) -> 0 | G27: =SUM(G20:G26) -> 0 | I27: =SUM(I20:I26) -> 141950 | K27: =SUM(K20:K26) -> 288345.85 | M27: =SUM(M20:M26) -> 565651 | O27: =SUM(O20:O26) -> 1253134.3
A28: សំគាល់ :​ ទិន្នន័យនៃរបាយការណ៍នេះត្រូវបានប្រើប្រាស់តែក្នុងគោលបំណង ស្ថិតិឧស្សាហកម្មតែប៉ុណ្ណោះ មិនត្រូវបានយកទៅចែកចាយដើម្បីប្រើប្រាស់
A29: ក្នុងគោលបំណងពាណិជ្ជកម្ម ឬក្នុងការគណនាបង់ពន្ធដារទេ។ | K29: ថ្ងៃទី 15 ខែ មិថុនា ឆ្នាំ2026 | N29: =K29 -> ថ្ងៃទី 15 ខែ មិថុនា ឆ្នាំ2026
A30: Remark: This report is used for industrial statistic only,​ not for commercial or tax purpose | J30: ​​​​​​​​​​​​​​​​​​​ | K30: Date:……./……../…… | N30: Date:……./……../……
A31: ទុនអចលនទ្រព្យមិនគិតដីធ្លី រួមមាន៖ អគារ និងឧបករណ៍បរិក្ខារដែលភ្ជាប់នឹងអគារ | K31: នាយក | N31: អ្នកធ្វើរបាយការណ៍
A32: Total asset excluding land comprises of : building & material attached.
A33: ទុនសរុបមិនគិតដីធ្លី រួមមាន៖ ទុនអចលនទ្រព្យមិនគិតដីធ្លី, មធ្យោបាយដឹកជញ្ជូន, គ្រឿងចក្រ-ម៉ាស៊ីន និងឧបករណ៍សម្ភារប្រើប្រាស់ក្នុងផលិតកម្ម, សង្ហារឹម និងសម្ភារការិយាល័យ | K33: Director | N33: Reportor
A34: Total fixed asset excluding land comprises of : real estate capital excluding land, transportation, machinery, and instrument utilised in the production line,
A35: furniture and office equiment.
A36: ទំនាក់ទំនង : Tel 077 330 279/090 922 237 E-mail : industryaffair.mih@gmail.com : TELEGRAM :077 330 279
K40: NI, CUNLAN | N40: THNIN
B41: ឈ្មោះរោងចក្រ ជេអ​ អឹភែរឹល ឯ.ក
A42: ទីផ្សារលក់ផលិតផលប្រចាំខែ | J42: =I6 -> មិថុនា | K42: ឆ្នាំ២០២៦ (USD)
A43: ល.រ | B43: ឈ្មោះផលិតផល | D43: ឯកតា (Unit) | E43: ឈ្មោះប្រទេសនាំចេញផលិតផល | O43: សរុបពីដើមឆ្នាំ
E44: USA | G44: CANADA | I44: CHINA | K44: EU GROUP | M44: ផ្សេងៗ
E45: បរិមាណ | F45: តម្លៃ | G45: បរិមាណ | H45: តម្លៃ | I45: បរិមាណ | J45: តម្លៃ | K45: បរិមាណ | L45: តម្លៃ | M45: បរិមាណ | N45: តម្លៃ | O45: បរិមាណ | P45: តម្លៃ
A46: 1 | B46: =A20 -> LADIES | C46: =B20 -> PANTS | D46: PCS | E46: 67245 | F46: 132927.75 | G46: 63821 | H46: 137422.3 | K46: 2160 | L46: 4272 | M46: 3300 | N46: 6537 | O46: =M20 -> 351769 | P46: =O20 -> 649725.33
A47: 2 | B47: =A21 -> LADIES | C47: =B21 -> PAJAMAS | D47: PCS | E47: 3432 | F47: 4547.4 | G47: 1992 | H47: 2639.4 | O47: =M21 -> 124972 | P47: =O21 -> 326402.96
A48: 3 | B48: =A22 -> LADIES | C48: =B22 -> SKIRT | D48: PCS | O48: =M22 -> 1810 | P48: =O22 -> 2855
A49: 4 | B49: =A23 -> LADIES | C49: =B23 -> DRESS | D49: PCS | O49: =M23 -> 81280 | P49: =O23 -> 267740.36
A50: 5 | B50: =A24 -> LADIES | C50: =B24 -> NIGHT GOWN | D50: PCS | O50: =M24 -> 576 | P50: =O24 -> 1532.16
A51: 6 | B51: =A25 -> LADIES | C51: =B25 -> TANK | D51: PCS | O51: =M25 -> 3396 | P51: =O25 -> 2272.8
A52: 7 | B52: =A26 -> LADIES | C52: =B26 -> SHORT | D52: PCS | O52: =M26 -> 1848 | P52: =O26 -> 2605.68
B53: សរុប | E53: =SUM(E46:E52) -> 70677 | F53: =SUM(F46:F52) -> 137475.15 | G53: =SUM(G46:G52) -> 65813 | H53: =SUM(H46:H52) -> 140061.7 | I53: =SUM(I46:I52) -> 0 | J53: =SUM(J46:J52) -> 0 | K53: =SUM(K46:K52) -> 2160 | L53: =SUM(L46:L52) -> 4272 | ... P53: =SUM(P46:P52) -> 1253134.3
A55: ប្រភពដើមទំនិញ (វត្ថុធាតុដើម)ប្រចាំខែ | J55: =$I$6 -> មិថុនា | K55: =$K$42 -> ឆ្នាំ២០២៦ (USD)
A56: ល.រ | B56: ឈ្មោះវត្ថុធាតុដើម | D56: ឯកតា (Unit) | E56: ឈ្មោះប្រទេសនាំចូលវត្ថុធាតុដើម | O56: សរុបពីដើមឆ្នាំ
E57: ចិន | G57: តៃវ៉ាន់ | I57: ហុងកុង | K57: វៀតណាម | M57: ផ្សេងៗ
E58: បរិមាណ | F58: តម្លៃ | G58: បរិមាណ | H58: តម្លៃ | I58: បរិមាណ | J58: តម្លៃ | K58: បរិមាណ | L58: តម្លៃ | M58: បរិមាណ | N58: តម្លៃ | O58: បរិមាណ | P58: តម្លៃ
A59: 1 | B59: I. MACHINERIES &. EQUIPMENTS | Q59: =E59+G59+I59+K59+M59 -> 0 | R59: =F59+H59+J59+L59+N59 -> 0 | S59: =Q59+O59 -> 0 | T59: =R59+P59 -> 0
A60: 3 | B60: II. RAW MATERIAL | O60: ='5-MAY'!O60 -> 450223.4 | P60: ='5-MAY'!P60 -> 443037.6 | Q60: =E60+G60+I60+K60+M60 -> 0 | R60: =F60+H60+J60+L60+N60 -> 0 | S60: =Q60+O60 -> 450223.4 | T60: =R60+P60 -> 443037.6
A61: 4 | B61: III. ACCESSORY | O61: ='5-MAY'!O61 -> 756 | P61: ='5-MAY'!P61 -> 756 | Q61: =E61+G61+I61+K61+M61 -> 0 | R61: =F61+H61+J61+L61+N61 -> 0 | S61: =Q61+O61 -> 756 | T61: =R61+P61 -> 756
B62: សរុប | E62: =SUM(E59:E61) -> 0 | F62: =SUM(F59:F61) -> 0 | G62: =SUM(G59:G61) -> 0 | H62: =SUM(H59:H61) -> 0 | I62: =SUM(I59:I61) -> 0 | J62: =SUM(J59:J61) -> 0 | K62: =SUM(K59:K61) -> 0 | L62: =SUM(L59:L61) -> 0 | ... P62: =SUM(P59:P61) -> 443793.6
B64: =A36 -> ទំនាក់ទំនង : Tel 077 330 279/090 922 237 E-mail : industryaffair.mih@gmail.com : TELEGRAM :077 330 279 | K64: =K29 -> ថ្ងៃទី 15 ខែ មិថុនា ឆ្នាំ2026 | N64: =N29 -> ថ្ងៃទី 15 ខែ មិថុនា ឆ្នាំ2026
K65: =K30 -> Date:……./……../…… | N65: =N30 -> Date:……./……../……
K66: =K31 -> នាយក | N66: =N31 -> អ្នកធ្វើរបាយការណ៍
K67: =K33 -> Director | N67: =N33 -> Reportor
K73: =K40 -> NI, CUNLAN | N73: =N40 -> THNIN
B74: ឈ្មោះរោងចក្រ ជេអ​ អឹភែរឹល ឯ.ក
B75: បរិមាណការប្រើប្រាស់ថាមពល ប្រចាំខែ | J75: =$I$6 -> មិថុនា | K75: =$K$42 -> ឆ្នាំ២០២៦ (USD)
A76: ល.រ | B76: ប្រភេទថាមពល | E76: ឯកតា (Unit) | G76: ឆ្នាំមុន | I76: ប្រចាំខែ......... | K76: សរុបពីដើមឆ្នាំ | O76: ផ្សេងៗ
G77: បរិមាណ | H77: តម្លៃ $ | I77: បរិមាណ | J77: តម្លៃ $ | K77: បរិមាណ | M77: តម្លៃ $
A78: 1 | B78: EDC | E78: KW | I78: 11368 | J78: =0.137*I78 -> 1557.416 | K78: =I78+'5-MAY'!K78:L78 -> 68208 | M78: =J78+'5-MAY'!M78:N78 -> 9344.496 | Q78: =K78+I78 -> 79576 | R78: =M78+J78 -> 10901.912
B79: សរុប | G79: =SUM(G78) -> 0 | H79: =SUM(H78) -> 0 | I79: =SUM(I78) -> 11368 | J79: =SUM(J78) -> 1557.416 | K79: =SUM(K78) -> 68208 | M79: =SUM(M78) -> 9344.496
B81: បរិមាណការប្រើប្រាស់ទឹក​ ប្រចាំខែ | J81: =J75 -> មិថុនា
A82: ល.រ | B82: ប្រភពទឹក | E82: ឯកតា (Unit) | G82: ឆ្នាំមុន | I82: ប្រចាំខែ......... | K82: សរុបពីដើមឆ្នាំ | O82: ផ្សេងៗ
G83: បរិមាណ | H83: តម្លៃ $ | I83: បរិមាណ | J83: តម្លៃ $ | K83: បរិមាណ | M83: តម្លៃ $
A84: 1 | B84: PPWSA | E84: M3 | I84: 83 | J84: =0.55*I84 -> 45.65 | K84: =I84+'5-MAY'!K84:L84 -> 498 | M84: =J84+'5-MAY'!M84:N84 -> 273.9 | Q84: =K84+I84 -> 581 | R84: =M84+J84 -> 319.55
B85: សរុប | G85: =SUM(G84) -> 0 | H85: =SUM(H84) -> 0 | I85: =SUM(I84) -> 83 | J85: =SUM(J84) -> 45.65 | K85: =SUM(K84) -> 498 | M85: =SUM(M84) -> 273.9
B87: ​ ​បរិមាណសំណល់ ពីដំណើរការខ្សែសង្វាក់ផលិតកម្ម ប្រចាំខែ | J87: =$I$6 -> មិថុនា | K87: =$K$42 -> ឆ្នាំ២០២៦ (USD)
A88: ល.រ | B88: ប្រភេទសំណល់ | D88: ឯកតា (Unit) | E88: បរិមាណសំណល់សរុប ពីឆ្នាំមុន | G88: បរិមាណសំណល់ប្រចាំខែ......... | K88: បរិមាណសំណល់សរុបពីដើមឆ្នាំ | O88: ផ្សេងៗ
A89: 1 | B89: សំណល់រឹង
A90: 2 | B90: សំណល់រាវ
A91: 3 | B91: សំណល់(ឧស្ម័ន)
A92: 4 | B92: សរុប
A94: =A36 -> ទំនាក់ទំនង : Tel 077 330 279/090 922 237 E-mail : industryaffair.mih@gmail.com : TELEGRAM :077 330 279 | K94: =K29 -> ថ្ងៃទី 15 ខែ មិថុនា ឆ្នាំ2026 | N94: =N29 -> ថ្ងៃទី 15 ខែ មិថុនា ឆ្នាំ2026
K95: =K30 -> Date:……./……../…… | N95: =N30 -> Date:……./……../……
K96: =K31 -> នាយក | N96: =N31 -> អ្នកធ្វើរបាយការណ៍
K97: =K33 -> Director | N97: =N67 -> Reportor
K105: =K40 -> NI, CUNLAN | N105: =N73 -> THNIN

Sheet 7-JUL
B1: ព្រះរាជាណាចក្រកម្ពុជា
B2: ជាត​ សានា ព្រះមហាក្សត្រ
G3: 
B4: របាយការណ៍ជូនក្រសួងឧស្សាហកម្ម វិទ្យាសាស្ត្រ បច្ចេកវិទ្យា និងនវានុវត្តន៍
B5: Report for Ministry of Industry, Science, Technology & Innovation
G6: ទិន្នន័យប្រចាំខែ | I6: កក្កដា | J6: ឆ្នាំ 2026
G7: Monthly Data In ........... 202…
A9: ឈ្មោះរោងចក្រ:​​​​​​​​​​ ជេអ អឹភែរឹល ឯ.ក អាស័យដ្ឋានរោងចក្រៈ # ផ្លូវលំ ភូមិ កោះខ្នុរ ឃុំ ព្រែករកា ស្រុក កណ្ដាលស្ទឹង ខេត្ត កណ្ដាល ប្រកាសលេខៈ៤១៧ ឧស.កឧ.ប្រក១២ ចុះថ្ងៃទី ២៤​​ ខែ ធ្នូ ឆ្នាំ ២០១៨
A10: Name of Factory: JR APPAREL CO., LTD Factory Address: #LOM ROAD,KAOH KNOR PREAEK ROKA KANDAL STUENG​ KANDAL PROVINCE Prakas Number : 417
A11: ឈ្មោះអ្នកគ្រប់គ្រងរោងចក្រ NI, CUNLAN ទូរស័ព្ទៈ 855-85 441 621 ទូរសារ:.............................. អ៊ីម៉ែលៈ sanashipping8@gmail.com
A12: Manager Name: NI, CUNLAN Tel: 855-85 441 621 Fax:……………………… E-mail: sanashipping8@gmail.com
A13: ចំនួនពលកម្មសរុបៈ​​​ | C13: 169 | E13: ក្នុងនោះមានស្រីៈ | F13: 113 | H13: បៀរវត្សសរុបប្រចាំខែៈ | J13: 59031.34 | L13: USD
A14: Total Number of Employees: Persons Number of Females: Persons Total Salary & Wage of Monthly USD
A15: ទុនសរុបមិនគិតដីធ្លី Total Asset(Land exclude) | D15: 1000000 | F15: ទុនអចលនទ្រព្យមិនគិតដីធ្លី Total Fixed Asset (Land exclude) | J15: 1000000
A16: មុខផលិតផល Products | C16: ឯកតាUnit | D16: បរិមាណ និងតម្លៃផលិតផល Total Output
D17: ឆ្នាំមុន (Data Last Year) | H17: ទិន្នន័យប្រចាំខែ (Monthly Data) | L17: សរុបពីដើមឆ្នាំ (From beginning of the Year )
D18: ​ បរិមាណ Quantity | F18: តម្លៃ Value(USD) | H18: បរិមាណផលិតផល Product Quantity | J18: តម្លៃផលិតផល Product Value(USD) | L18: បរិមាណផលិតផល Product Quantity | N18: តម្លៃផលិតផល Product Value(USD)
D19: ក្នុងស្រុក Domestic | E19: នាំចេញ Export | F19: ក្នុងស្រុក Domestic | G19: នាំចេញ Export | H19: ក្នុងស្រុក Domestic | I19: នាំចេញ Export | J19: ក្នុងស្រុក Domestic | K19: នាំចេញ Export | L19: ក្នុងស្រុក Domestic | M19: នាំចេញ Export | N19: ក្នុងស្រុក Domestic | O19: នាំចេញ Export
A20: LADIES | B20: PANTS | C20: PCS | I20: 22486 | K20: 56774.5 | M20: 374255 | O20: =K20+'6-JUN'!O20 -> 706499.83 | Q20: =M20+I20 -> 396741 | S20: =O20+K20 -> 763274.33
A21: LADIES | B21: PAJAMAS | C21: PCS | I21: 8484 | K21: 10918.8 | M21: 10294 | O21: =K21+'6-JUN'!O21 -> 337321.76
A22: LADIES | B22: SKIRT | C22: PCS | M22: 81280 | O22: =K22+'6-JUN'!O22 -> 2855
A23: LADIES | B23: DRESS | C23: PCS | M23: 576 | O23: =K23+'6-JUN'!O23 -> 267740.36 | Q23: =M23+I23 -> 576 | S23: =O23+K23 -> 267740.36
A24: LADIES | B24: NIGHT GOWN | C24: PCS | M24: 3396 | O24: =K24+'6-JUN'!O24 -> 1532.16 | Q24: =M24+I24 -> 3396 | S24: =O24+K24 -> 1532.16
A25: LADIES | B25: TANK | C25: PCS | M25: 1848 | O25: =K25+'6-JUN'!O25 -> 2272.8 | Q25: =M25+I25 -> 1848 | S25: =O25+K25 -> 2272.8
A26: LADIES | B26: SHORT | C26: PCS | M26: 565651 | O26: =K26+'6-JUN'!O26 -> 2605.68 | Q26: =M26+I26 -> 565651 | S26: =O26+K26 -> 2605.68
A27: LADIES | B27: SKORT | C27: PCS | I27: 1000 | K27: 1950 | M27: 1000 | O27: =K27 -> 1950
A28: Total | E28: =SUM(E20:E26) -> 0 | G28: =SUM(G20:G26) -> 0 | I28: =SUM(I20:I27) -> 31970 | K28: =SUM(K20:K27) -> 69643.3 | M28: =SUM(M20:M27) -> 1038300 | O28: =SUM(O20:O27) -> 1322777.6
A29: សំគាល់ :​ ទិន្នន័យនៃរបាយការណ៍នេះត្រូវបានប្រើប្រាស់តែក្នុងគោលបំណង ស្ថិតិឧស្សាហកម្មតែប៉ុណ្ណោះ មិនត្រូវបានយកទៅចែកចាយដើម្បីប្រើប្រាស់
A30: ក្នុងគោលបំណងពាណិជ្ជកម្ម ឬក្នុងការគណនាបង់ពន្ធដារទេ។ | K30: ថ្ងៃទី 15 ខែ កក្កដា ឆ្នាំ2026 | N30: =K30 -> ថ្ងៃទី 15 ខែ កក្កដា ឆ្នាំ2026
A31: Remark: This report is used for industrial statistic only,​ not for commercial or tax purpose | J31: ​​​​​​​​​​​​​​​​​​​ | K31: Date:……./……../…… | N31: Date:……./……../……
A32: ទុនអចលនទ្រព្យមិនគិតដីធ្លី រួមមាន៖ អគារ និងឧបករណ៍បរិក្ខារដែលភ្ជាប់នឹងអគារ | K32: នាយក | N32: អ្នកធ្វើរបាយការណ៍
A33: Total asset excluding land comprises of : building & material attached.
A34: ទុនសរុបមិនគិតដីធ្លី រួមមាន៖ ទុនអចលនទ្រព្យមិនគិតដីធ្លី, មធ្យោបាយដឹកជញ្ជូន, គ្រឿងចក្រ-ម៉ាស៊ីន និងឧបករណ៍សម្ភារប្រើប្រាស់ក្នុងផលិតកម្ម, សង្ហារឹម និងសម្ភារការិយាល័យ | K34: Director | N34: Reportor
A35: Total fixed asset excluding land comprises of : real estate capital excluding land, transportation, machinery, and instrument utilised in the production line,
A36: furniture and office equiment.
A37: ទំនាក់ទំនង : Tel 077 330 279/090 922 237 E-mail : industryaffair.mih@gmail.com : TELEGRAM :077 330 279
K41: NI, CUNLAN | N41: THNIN
B42: ឈ្មោះរោងចក្រ ជេអ​ អឹភែរឹល ឯ.ក
A43: ទីផ្សារលក់ផលិតផលប្រចាំខែ | J43: =I6 -> កក្កដា | K43: ឆ្នាំ២០២៦ (USD)
A44: ល.រ | B44: ឈ្មោះផលិតផល | D44: ឯកតា (Unit) | E44: ឈ្មោះប្រទេសនាំចេញផលិតផល | O44: សរុបពីដើមឆ្នាំ
E45: USA | G45: CANADA | I45: CHINA | K45: EU GROUP | M45: ផ្សេងៗ
E46: បរិមាណ | F46: តម្លៃ | G46: បរិមាណ | H46: តម្លៃ | I46: បរិមាណ | J46: តម្លៃ | K46: បរិមាណ | L46: តម្លៃ | M46: បរិមាណ | N46: តម្លៃ | O46: បរិមាណ | P46: តម្លៃ
A47: 1 | B47: =A20 -> LADIES | C47: =B20 -> PANTS | D47: PCS | E47: 12556 | F47: 28331.5 | G47: 9930 | H47: 28443 | O47: =M20 -> 374255 | P47: =O20 -> 706499.83
A48: 2 | B48: =A21 -> LADIES | C48: =B21 -> PAJAMAS | D48: PCS | E48: 8484 | F48: 10919.8 | O48: =M21 -> 10294 | P48: =O21 -> 337321.76
A49: 3 | B49: =A22 -> LADIES | C49: =B22 -> SKIRT | D49: PCS | O49: =M22 -> 81280 | P49: =O22 -> 2855
A50: 4 | B50: =A23 -> LADIES | C50: =B23 -> DRESS | D50: PCS | O50: =M23 -> 576 | P50: =O23 -> 267740.36
A51: 5 | B51: =A24 -> LADIES | C51: =B24 -> NIGHT GOWN | D51: PCS | O51: =M24 -> 3396 | P51: =O24 -> 1532.16
A52: 6 | B52: =A25 -> LADIES | C52: =B25 -> TANK | D52: PCS | O52: =M25 -> 1848 | P52: =O25 -> 2272.8
A53: 7 | B53: =A26 -> LADIES | C53: =B26 -> SHORT | D53: PCS | G53: 1000 | H53: 1950 | O53: =M26 -> 565651 | P53: =O26 -> 2605.68
A54: 8 | B54: =A27 -> LADIES | C54: =B27 -> SKORT | D54: PCS | O54: 1000 | P54: 1950
B55: សរុប | E55: =SUM(E47:E53) -> 21040 | F55: =SUM(F47:F53) -> 39251.3 | G55: =SUM(G47:G53) -> 10930 | H55: =SUM(H47:H53) -> 30393 | I55: =SUM(I47:I53) -> 0 | J55: =SUM(J47:J53) -> 0 | K55: =SUM(K47:K53) -> 0 | L55: =SUM(L47:L53) -> 0 | ... N55: =SUM(N47:N53) -> 0 | O55: =SUM(O47:O54) -> 1038300 | P55: =SUM(P47:P54) -> 1322777.6
A57: ប្រភពដើមទំនិញ (វត្ថុធាតុដើម)ប្រចាំខែ | J57: =$I$6 -> កក្កដា | K57: =$K$43 -> ឆ្នាំ២០២៦ (USD)
A58: ល.រ | B58: ឈ្មោះវត្ថុធាតុដើម | D58: ឯកតា (Unit) | E58: ឈ្មោះប្រទេសនាំចូលវត្ថុធាតុដើម | O58: សរុបពីដើមឆ្នាំ
E59: ចិន | G59: តៃវ៉ាន់ | I59: ហុងកុង | K59: វៀតណាម | M59: ផ្សេងៗ
E60: បរិមាណ | F60: តម្លៃ | G60: បរិមាណ | H60: តម្លៃ | I60: បរិមាណ | J60: តម្លៃ | K60: បរិមាណ | L60: តម្លៃ | M60: បរិមាណ | N60: តម្លៃ | O60: បរិមាណ | P60: តម្លៃ
A61: 1 | B61: I. MACHINERIES &. EQUIPMENTS | Q61: =E61+G61+I61+K61+M61 -> 0 | R61: =F61+H61+J61+L61+N61 -> 0 | S61: =Q61+O61 -> 0 | T61: =R61+P61 -> 0
A62: 3 | B62: II. RAW MATERIAL | D62: MTR | E62: 169738.7 | F62: 169738.7 | O62: =E62+'6-JUN'!O60 -> 619962.1 | P62: =F62+'6-JUN'!P60 -> 612776.3 | Q62: =E62+G62+I62+K62+M62 -> 169738.7 | R62: =F62+H62+J62+L62+N62 -> 169738.7 | S62: =Q62+O62 -> 789700.8 | T62: =R62+P62 -> 782515
A63: 4 | B63: III. ACCESSORY | D63: DZN | E63: 26881 | F63: 5832.45 | O63: =E63+'6-JUN'!O61 -> 27637 | P63: =F63+'6-JUN'!P61 -> 6588.45 | Q63: =E63+G63+I63+K63+M63 -> 26881 | R63: =F63+H63+J63+L63+N63 -> 5832.45 | S63: =Q63+O63 -> 54518 | T63: =R63+P63 -> 12420.9
B64: សរុប | E64: =SUM(E61:E63) -> 196619.7 | F64: =SUM(F61:F63) -> 175571.15 | G64: =SUM(G61:G63) -> 0 | H64: =SUM(H61:H63) -> 0 | I64: =SUM(I61:I63) -> 0 | J64: =SUM(J61:J63) -> 0 | K64: =SUM(K61:K63) -> 0 | L64: =SUM(L61:L63) -> 0 | ... P64: =SUM(P61:P63) -> 619364.75
B66: =A37 -> ទំនាក់ទំនង : Tel 077 330 279/090 922 237 E-mail : industryaffair.mih@gmail.com : TELEGRAM :077 330 279 | K66: =K30 -> ថ្ងៃទី 15 ខែ កក្កដា ឆ្នាំ2026 | N66: =N30 -> ថ្ងៃទី 15 ខែ កក្កដា ឆ្នាំ2026
K67: =K31 -> Date:……./……../…… | N67: =N31 -> Date:……./……../……
K68: =K32 -> នាយក | N68: =N32 -> អ្នកធ្វើរបាយការណ៍
K69: =K34 -> Director | N69: =N34 -> Reportor
K75: =K41 -> NI, CUNLAN | N75: =N41 -> THNIN
B76: ឈ្មោះរោងចក្រ ជេអ​ អឹភែរឹល ឯ.ក
B77: បរិមាណការប្រើប្រាស់ថាមពល ប្រចាំខែ | J77: =$I$6 -> កក្កដា | K77: =$K$43 -> ឆ្នាំ២០២៦ (USD)
A78: ល.រ | B78: ប្រភេទថាមពល | E78: ឯកតា (Unit) | G78: ឆ្នាំមុន | I78: ប្រចាំខែ......... | K78: សរុបពីដើមឆ្នាំ | O78: ផ្សេងៗ
G79: បរិមាណ | H79: តម្លៃ $ | I79: បរិមាណ | J79: តម្លៃ $ | K79: បរិមាណ | M79: តម្លៃ $
A80: 1 | B80: EDC | E80: KW | I80: 11368 | J80: =0.137*I80 -> 1557.416 | K80: =I80+'6-JUN'!K78:L78 -> 79576 | M80: =J80+'6-JUN'!M78:N78 -> 10901.912 | Q80: =K80+I80 -> 90944 | R80: =M80+J80 -> 12459.328
B81: សរុប | G81: =SUM(G80) -> 0 | H81: =SUM(H80) -> 0 | I81: =SUM(I80) -> 11368 | J81: =SUM(J80) -> 1557.416 | K81: =SUM(K80) -> 79576 | M81: =SUM(M80) -> 10901.912
B83: បរិមាណការប្រើប្រាស់ទឹក​ ប្រចាំខែ | J83: =J77 -> កក្កដា
A84: ល.រ | B84: ប្រភពទឹក | E84: ឯកតា (Unit) | G84: ឆ្នាំមុន | I84: ប្រចាំខែ......... | K84: សរុបពីដើមឆ្នាំ | O84: ផ្សេងៗ
G85: បរិមាណ | H85: តម្លៃ $ | I85: បរិមាណ | J85: តម្លៃ $ | K85: បរិមាណ | M85: តម្លៃ $
A86: 1 | B86: PPWSA | E86: M3 | I86: 83 | J86: =0.55*I86 -> 45.65 | K86: =I86+'6-JUN'!K85:L85 -> 581 | M86: =J86+'6-JUN'!M85:N85 -> 319.55 | Q86: =K86+I86 -> 664 | R86: =M86+J86 -> 365.2
B87: សរុប | G87: =SUM(G86) -> 0 | H87: =SUM(H86) -> 0 | I87: =SUM(I86) -> 83 | J87: =SUM(J86) -> 45.65 | K87: =SUM(K86) -> 581 | M87: =SUM(M86) -> 319.55
B89: ​ ​បរិមាណសំណល់ ពីដំណើរការខ្សែសង្វាក់ផលិតកម្ម ប្រចាំខែ | J89: =$I$6 -> កក្កដា | K89: =$K$43 -> ឆ្នាំ២០២៦ (USD)
A90: ល.រ | B90: ប្រភេទសំណល់ | D90: ឯកតា (Unit) | E90: បរិមាណសំណល់សរុប ពីឆ្នាំមុន | G90: បរិមាណសំណល់ប្រចាំខែ......... | K90: បរិមាណសំណល់សរុបពីដើមឆ្នាំ | O90: ផ្សេងៗ
A91: 1 | B91: សំណល់រឹង
A92: 2 | B92: សំណល់រាវ
A93: 3 | B93: សំណល់(ឧស្ម័ន)
A94: 4 | B94: សរុប
A96: =A37 -> ទំនាក់ទំនង : Tel 077 330 279/090 922 237 E-mail : industryaffair.mih@gmail.com : TELEGRAM :077 330 279 | K96: =K30 -> ថ្ងៃទី 15 ខែ កក្កដា ឆ្នាំ2026 | N96: =N30 -> ថ្ងៃទី 15 ខែ កក្កដា ឆ្នាំ2026
K97: =K31 -> Date:……./……../…… | N97: =N31 -> Date:……./……../……
K98: =K32 -> នាយក | N98: =N32 -> អ្នកធ្វើរបាយការណ៍
K99: =K34 -> Director | N99: =N69 -> Reportor
K107: =K41 -> NI, CUNLAN | N107: =N75 -> THNIN

Sheet 8-AUG
B1: ព្រះរាជាណាចក្រកម្ពុជា
B2: ជាត​ សានា ព្រះមហាក្សត្រ
G3: 
B4: របាយការណ៍ជូនក្រសួងឧស្សាហកម្ម វិទ្យាសាស្ត្រ បច្ចេកវិទ្យា និងនវានុវត្តន៍
B5: Report for Ministry of Industry, Science, Technology & Innovation
G6: ទិន្នន័យប្រចាំខែ | I6: សីហា | J6: ឆ្នាំ 2026
G7: Monthly Data In August 2026
A9: ឈ្មោះរោងចក្រ:​​​​​​​​​​ ជេអ អឹភែរឹល ឯ.ក អាស័យដ្ឋានរោងចក្រៈ # ផ្លូវលំ ភូមិ កោះខ្នុរ ឃុំ ព្រែករកា ស្រុក កណ្ដាលស្ទឹង ខេត្ត កណ្ដាល ប្រកាសលេខៈ៤១៧ ឧស.កឧ.ប្រក១២ ចុះថ្ងៃទី ២៤​​ ខែ ធ្នូ ឆ្នាំ ២០១៨
A10: Name of Factory: JR APPAREL CO., LTD Factory Address: #LOM ROAD,KAOH KNOR PREAEK ROKA KANDAL STUENG​ KANDAL PROVINCE Prakas Number : 417
A11: ឈ្មោះអ្នកគ្រប់គ្រងរោងចក្រ NI, CUNLAN ទូរស័ព្ទៈ 855-85 441 621 ទូរសារ:.............................. អ៊ីម៉ែលៈ sanashipping8@gmail.com
A12: Manager Name: NI, CUNLAN Tel: 855-85 441 621 Fax:……………………… E-mail: sanashipping8@gmail.com
A13: ចំនួនពលកម្មសរុបៈ​​​ | C13: 168 | D13: ក្នុងនោះមានស្រីៈ | F13: 113 | H13: បៀរវត្សសរុបប្រចាំខែៈ | J13: 61010.34 | L13: USD
A14: Total Number of Employees: Persons Number of Females: Persons Total Salary & Wage of Monthly USD
A15: ទុនសរុបមិនគិតដីធ្លី Total Asset(Land exclude) | D15: 1000000 | F15: ទុនអចលនទ្រព្យមិនគិតដីធ្លី Total Fixed Asset (Land exclude) | J15: 1000000
A16: មុខផលិតផល Products | C16: ឯកតាUnit | D16: បរិមាណ និងតម្លៃផលិតផល Total Output
D17: ឆ្នាំមុន (Data Last Year) | H17: ទិន្នន័យប្រចាំខែ (Monthly Data) | L17: សរុបពីដើមឆ្នាំ (From beginning of the Year )
D18: ​ បរិមាណ Quantity | F18: តម្លៃ Value(USD) | H18: បរិមាណផលិតផល Product Quantity | J18: តម្លៃផលិតផល Product Value(USD) | L18: បរិមាណផលិតផល Product Quantity | N18: តម្លៃផលិតផល Product Value(USD)
D19: ក្នុងស្រុក Domestic | E19: នាំចេញ Export | F19: ក្នុងស្រុក Domestic | G19: នាំចេញ Export | H19: ក្នុងស្រុក Domestic | I19: នាំចេញ Export | J19: ក្នុងស្រុក Domestic | K19: នាំចេញ Export | L19: ក្នុងស្រុក Domestic | M19: នាំចេញ Export | N19: ក្នុងស្រុក Domestic | O19: នាំចេញ Export
A20: LADIES | B20: PANTS | C20: PCS | I20: 41078 | K20: =ROUND(I20*2.25345562101368,2) -> 92567.45 | M20: =I20+'7-JUL'!M20 -> 415333 | O20: =K20+'7-JUL'!O20 -> 799067.28 | Q20: =M20+I20 -> 456411 | S20: =O20+K20 -> 891634.73
A21: LADIES | B21: PAJAMAS | C21: PCS | I21: 13404 | K21: =ROUND(I21*1.38028200537153,2) -> 18501.3 | M21: =I21+'7-JUL'!M21 -> 23698 | O21: =K21+'6-JUN'!O21 -> 344904.26
A22: LADIES | B22: SKIRT | C22: PCS | M22: 81280 | O22: =K22+'6-JUN'!O22 -> 2855
A23: LADIES | B23: DRESS | C23: PCS | M23: 576 | O23: =K23+'6-JUN'!O23 -> 267740.36 | Q23: =M23+I23 -> 576 | S23: =O23+K23 -> 267740.36
A24: LADIES | B24: NIGHT GOWN | C24: PCS | M24: 3396 | O24: =K24+'6-JUN'!O24 -> 1532.16 | Q24: =M24+I24 -> 3396 | S24: =O24+K24 -> 1532.16
A25: LADIES | B25: TANK | C25: PCS | M25: 1848 | O25: =K25+'6-JUN'!O25 -> 2272.8 | Q25: =M25+I25 -> 1848 | S25: =O25+K25 -> 2272.8
A26: LADIES | B26: SHORT | C26: PCS | M26: 565651 | O26: =K26+'6-JUN'!O26 -> 2605.68 | Q26: =M26+I26 -> 565651 | S26: =O26+K26 -> 2605.68
A27: LADIES | B27: SKORT | C27: PCS | M27: ='7-JUL'!M27 -> 1000 | O27: ='7-JUL'!O27 -> 1950
A28: Total | E28: =SUM(E20:E26) -> 0 | G28: =SUM(G20:G26) -> 0 | I28: =SUM(I20:I27) -> 54482 | K28: =SUM(K20:K27) -> 111068.75 | M28: =SUM(M20:M27) -> 1092782 | O28: =SUM(O20:O27) -> 1422927.5
A29: សំគាល់ :​ ទិន្នន័យនៃរបាយការណ៍នេះត្រូវបានប្រើប្រាស់តែក្នុងគោលបំណង ស្ថិតិឧស្សាហកម្មតែប៉ុណ្ណោះ មិនត្រូវបានយកទៅចែកចាយដើម្បីប្រើប្រាស់
A30: ក្នុងគោលបំណងពាណិជ្ជកម្ម ឬក្នុងការគណនាបង់ពន្ធដារទេ។ | K30: ថ្ងៃទី 15 ខែ សីហា ឆ្នាំ2026 | N30: =K30 -> ថ្ងៃទី 15 ខែ សីហា ឆ្នាំ2026
A31: Remark: This report is used for industrial statistic only,​ not for commercial or tax purpose | J31: ​​​​​​​​​​​​​​​​​​​ | K31: Date:……./……../…… | N31: Date:……./……../……
A32: ទុនអចលនទ្រព្យមិនគិតដីធ្លី រួមមាន៖ អគារ និងឧបករណ៍បរិក្ខារដែលភ្ជាប់នឹងអគារ | K32: នាយក | N32: អ្នកធ្វើរបាយការណ៍
A33: Total asset excluding land comprises of : building & material attached.
A34: ទុនសរុបមិនគិតដីធ្លី រួមមាន៖ ទុនអចលនទ្រព្យមិនគិតដីធ្លី, មធ្យោបាយដឹកជញ្ជូន, គ្រឿងចក្រ-ម៉ាស៊ីន និងឧបករណ៍សម្ភារប្រើប្រាស់ក្នុងផលិតកម្ម, សង្ហារឹម និងសម្ភារការិយាល័យ | K34: Director | N34: Reportor
A35: Total fixed asset excluding land comprises of : real estate capital excluding land, transportation, machinery, and instrument utilised in the production line,
A36: furniture and office equiment.
A37: ទំនាក់ទំនង : Tel 077 330 279/090 922 237 E-mail : industryaffair.mih@gmail.com : TELEGRAM :077 330 279
K41: NI, CUNLAN | N41: THNIN
B42: ឈ្មោះរោងចក្រ ជេអ​ អឹភែរឹល ឯ.ក
A43: ទីផ្សារលក់ផលិតផលប្រចាំខែ | J43: =I6 -> សីហា | K43: ឆ្នាំ២០២៦ (USD)
A44: ល.រ | B44: ឈ្មោះផលិតផល | D44: ឯកតា (Unit) | E44: ឈ្មោះប្រទេសនាំចេញផលិតផល | O44: សរុបពីដើមឆ្នាំ
E45: USA | G45: CANADA | I45: CHINA | K45: EU GROUP | M45: ផ្សេងៗ
E46: បរិមាណ | F46: តម្លៃ | G46: បរិមាណ | H46: តម្លៃ | I46: បរិមាណ | J46: តម្លៃ | K46: បរិមាណ | L46: តម្លៃ | M46: បរិមាណ | N46: តម្លៃ | O46: បរិមាណ | P46: តម្លៃ
A47: 1 | B47: =A20 -> LADIES | C47: =B20 -> PANTS | D47: PCS | E47: 26427 | F47: =ROUND(E47*2.25345562101368,2) -> 59552.07 | G47: 12675 | H47: =ROUND(G47*2.25345562101368,2) -> 28562.55 | M47: 1976 | N47: =ROUND(M47*2.25345562101368,2) -> 4452.83 | O47: =M20 -> 415333 | P47: =O20 -> 799067.28
A48: 2 | B48: =A21 -> LADIES | C48: =B21 -> PAJAMAS | D48: PCS | E48: 7908 | F48: =ROUND(E48*1.38028200537153,2) -> 10915.27 | G48: 5496 | H48: =ROUND(G48*1.38028200537153,2) -> 7586.03 | O48: =M21 -> 23698 | P48: =O21 -> 344904.26
A49: 3 | B49: =A22 -> LADIES | C49: =B22 -> SKIRT | D49: PCS | O49: =M22 -> 81280 | P49: =O22 -> 2855
A50: 4 | B50: =A23 -> LADIES | C50: =B23 -> DRESS | D50: PCS | O50: =M23 -> 576 | P50: =O23 -> 267740.36
A51: 5 | B51: =A24 -> LADIES | C51: =B24 -> NIGHT GOWN | D51: PCS | O51: =M24 -> 3396 | P51: =O24 -> 1532.16
A52: 6 | B52: =A25 -> LADIES | C52: =B25 -> TANK | D52: PCS | O52: =M25 -> 1848 | P52: =O25 -> 2272.8
A53: 7 | B53: =A26 -> LADIES | C53: =B26 -> SHORT | D53: PCS | O53: =M26 -> 565651 | P53: =O26 -> 2605.68
A54: 8 | B54: =A27 -> LADIES | C54: =B27 -> SKORT | D54: PCS | O54: 1000 | P54: 1950
B55: សរុប | E55: =SUM(E47:E53) -> 34335 | F55: =SUM(F47:F53) -> 70467.34 | G55: =SUM(G47:G53) -> 18171 | H55: =SUM(H47:H53) -> 36148.58 | I55: =SUM(I47:I53) -> 0 | J55: =SUM(J47:J53) -> 0 | K55: =SUM(K47:K53) -> 0 | L55: =SUM(L47:L53) -> 0 | ... N55: =SUM(N47:N53) -> 4452.83 | O55: =SUM(O47:O54) -> 1092782 | P55: =SUM(P47:P54) -> 1422927.5
A57: ប្រភពដើមទំនិញ (វត្ថុធាតុដើម)ប្រចាំខែ | J57: =$I$6 -> សីហា | K57: =$K$43 -> ឆ្នាំ២០២៦ (USD)
A58: ល.រ | B58: ឈ្មោះវត្ថុធាតុដើម | D58: ឯកតា (Unit) | E58: ឈ្មោះប្រទេសនាំចូលវត្ថុធាតុដើម | O58: សរុបពីដើមឆ្នាំ
E59: ចិន | G59: តៃវ៉ាន់ | I59: ហុងកុង | K59: វៀតណាម | M59: ផ្សេងៗ
E60: បរិមាណ | F60: តម្លៃ | G60: បរិមាណ | H60: តម្លៃ | I60: បរិមាណ | J60: តម្លៃ | K60: បរិមាណ | L60: តម្លៃ | M60: បរិមាណ | N60: តម្លៃ | O60: បរិមាណ | P60: តម្លៃ
A61: 1 | B61: I. MACHINERIES &. EQUIPMENTS | D61: SET | E61: 1 | F61: 11000 | O61: =E61 -> 1 | P61: =F61 -> 11000 | Q61: =E61+G61+I61+K61+M61 -> 1 | R61: =F61+H61+J61+L61+N61 -> 11000 | S61: =Q61+O61 -> 2 | T61: =R61+P61 -> 22000
A62: 3 | B62: II. RAW MATERIAL | D62: MTR | E62: 39071.9 | F62: 39071.9 | O62: =E62+'7-JUL'!O62 -> 659034 | P62: =F62+'7-JUL'!P62 -> 651848.2 | Q62: =E62+G62+I62+K62+M62 -> 39071.9 | R62: =F62+H62+J62+L62+N62 -> 39071.9 | S62: =Q62+O62 -> 698105.9 | T62: =R62+P62 -> 690920.1
A63: 4 | B63: III. ACCESSORY | D63: DZN | O63: =E63+'7-JUL'!O63 -> 27637 | P63: =F63+'7-JUL'!P63 -> 6588.45 | Q63: =E63+G63+I63+K63+M63 -> 0 | R63: =F63+H63+J63+L63+N63 -> 0 | S63: =Q63+O63 -> 27637 | T63: =R63+P63 -> 6588.45
B64: សរុប | E64: =SUM(E61:E63) -> 39072.9 | F64: =SUM(F61:F63) -> 50071.9 | G64: =SUM(G61:G63) -> 0 | H64: =SUM(H61:H63) -> 0 | I64: =SUM(I61:I63) -> 0 | J64: =SUM(J61:J63) -> 0 | K64: =SUM(K61:K63) -> 0 | L64: =SUM(L61:L63) -> 0 | ... P64: =SUM(P61:P63) -> 669436.65
B66: =A37 -> ទំនាក់ទំនង : Tel 077 330 279/090 922 237 E-mail : industryaffair.mih@gmail.com : TELEGRAM :077 330 279 | K66: =K30 -> ថ្ងៃទី 15 ខែ សីហា ឆ្នាំ2026 | N66: =N30 -> ថ្ងៃទី 15 ខែ សីហា ឆ្នាំ2026
K67: =K31 -> Date:……./……../…… | N67: =N31 -> Date:……./……../……
K68: =K32 -> នាយក | N68: =N32 -> អ្នកធ្វើរបាយការណ៍
K69: =K34 -> Director | N69: =N34 -> Reportor
K75: =K41 -> NI, CUNLAN | N75: =N41 -> THNIN
B76: ឈ្មោះរោងចក្រ ជេអ​ អឹភែរឹល ឯ.ក
B77: បរិមាណការប្រើប្រាស់ថាមពល ប្រចាំខែ | J77: =$I$6 -> សីហា | K77: =$K$43 -> ឆ្នាំ២០២៦ (USD)
A78: ល.រ | B78: ប្រភេទថាមពល | E78: ឯកតា (Unit) | G78: ឆ្នាំមុន | I78: ប្រចាំខែ......... | K78: សរុបពីដើមឆ្នាំ | O78: ផ្សេងៗ
G79: បរិមាណ | H79: តម្លៃ $ | I79: បរិមាណ | J79: តម្លៃ $ | K79: បរិមាណ | M79: តម្លៃ $
A80: 1 | B80: EDC | E80: KW | I80: 11368 | J80: =0.137*I80 -> 1557.416 | K80: =I80+'7-JUL'!K81:L81 -> 90944 | M80: =J80+'7-JUL'!M81:N81 -> 12459.328 | Q80: =K80+I80 -> 102312 | R80: =M80+J80 -> 14016.744
B81: សរុប | G81: =SUM(G80) -> 0 | H81: =SUM(H80) -> 0 | I81: =SUM(I80) -> 11368 | J81: =SUM(J80) -> 1557.416 | K81: =SUM(K80) -> 90944 | M81: =SUM(M80) -> 12459.328
B83: បរិមាណការប្រើប្រាស់ទឹក​ ប្រចាំខែ | J83: =J77 -> សីហា
A84: ល.រ | B84: ប្រភពទឹក | E84: ឯកតា (Unit) | G84: ឆ្នាំមុន | I84: ប្រចាំខែ......... | K84: សរុបពីដើមឆ្នាំ | O84: ផ្សេងៗ
G85: បរិមាណ | H85: តម្លៃ $ | I85: បរិមាណ | J85: តម្លៃ $ | K85: បរិមាណ | M85: តម្លៃ $
A86: 1 | B86: PPWSA | E86: M3 | I86: 83 | J86: =0.55*I86 -> 45.65 | K86: =I86+'7-JUL'!K87:L87 -> 664 | M86: =J86+'7-JUL'!M87:N87 -> 365.2 | Q86: =K86+I86 -> 747 | R86: =M86+J86 -> 410.85
B87: សរុប | G87: =SUM(G86) -> 0 | H87: =SUM(H86) -> 0 | I87: =SUM(I86) -> 83 | J87: =SUM(J86) -> 45.65 | K87: =SUM(K86) -> 664 | M87: =SUM(M86) -> 365.2
B89: ​ ​បរិមាណសំណល់ ពីដំណើរការខ្សែសង្វាក់ផលិតកម្ម ប្រចាំខែ | J89: =$I$6 -> សីហា | K89: =$K$43 -> ឆ្នាំ២០២៦ (USD)
A90: ល.រ | B90: ប្រភេទសំណល់ | D90: ឯកតា (Unit) | E90: បរិមាណសំណល់សរុប ពីឆ្នាំមុន | G90: បរិមាណសំណល់ប្រចាំខែ......... | K90: បរិមាណសំណល់សរុបពីដើមឆ្នាំ | O90: ផ្សេងៗ
A91: 1 | B91: សំណល់រឹង
A92: 2 | B92: សំណល់រាវ
A93: 3 | B93: សំណល់(ឧស្ម័ន)
A94: 4 | B94: សរុប
A96: =A37 -> ទំនាក់ទំនង : Tel 077 330 279/090 922 237 E-mail : industryaffair.mih@gmail.com : TELEGRAM :077 330 279 | K96: =K30 -> ថ្ងៃទី 15 ខែ សីហា ឆ្នាំ2026 | N96: =N30 -> ថ្ងៃទី 15 ខែ សីហា ឆ្នាំ2026
K97: =K31 -> Date:……./……../…… | N97: =N31 -> Date:……./……../……
K98: =K32 -> នាយក | N98: =N32 -> អ្នកធ្វើរបាយការណ៍
K99: =K34 -> Director | N99: =N69 -> Reportor
K107: =K41 -> NI, CUNLAN | N107: =N75 -> THNIN

Sheet 9-SEP
B1: ព្រះរាជាណាចក្រកម្ពុជា
B2: ជាត​ សានា ព្រះមហាក្សត្រ
G3: 
B4: របាយការណ៍ជូនក្រសួងឧស្សាហកម្ម វិទ្យាសាស្ត្រ បច្ចេកវិទ្យា និងនវានុវត្តន៍
B5: Report for Ministry of Industry, Science, Technology & Innovation
G6: ទិន្នន័យប្រចាំខែ | I6: កញ្ញា | J6: ឆ្នាំ 2026
G7: Monthly Data In September 2026
A9: ឈ្មោះរោងចក្រ:​​​​​​​​​​ ជេអ អឹភែរឹល ឯ.ក អាស័យដ្ឋានរោងចក្រៈ # ផ្លូវលំ ភូមិ កោះខ្នុរ ឃុំ ព្រែករកា ស្រុក កណ្ដាលស្ទឹង ខេត្ត កណ្ដាល ប្រកាសលេខៈ៤១៧ ឧស.កឧ.ប្រក១២ ចុះថ្ងៃទី ២៤​​ ខែ ធ្នូ ឆ្នាំ ២០១៨
A10: Name of Factory: JR APPAREL CO., LTD Factory Address: #LOM ROAD,KAOH KNOR PREAEK ROKA KANDAL STUENG​ KANDAL PROVINCE Prakas Number : 417
A11: ឈ្មោះអ្នកគ្រប់គ្រងរោងចក្រ NI, CUNLAN ទូរស័ព្ទៈ 855-85 441 621 ទូរសារ:.............................. អ៊ីម៉ែលៈ sanashipping8@gmail.com
A12: Manager Name: NI, CUNLAN Tel: 855-85 441 621 Fax:……………………… E-mail: sanashipping8@gmail.com
A13: ចំនួនពលកម្មសរុបៈ​​​ | C13: 148 | D13: ក្នុងនោះមានស្រីៈ | F13: 101 | H13: បៀរវត្សសរុបប្រចាំខែៈ | J13: 50419.75 | L13: USD
A14: Total Number of Employees: Persons Number of Females: Persons Total Salary & Wage of Monthly USD
A15: ទុនសរុបមិនគិតដីធ្លី Total Asset(Land exclude) | D15: 1000000 | F15: ទុនអចលនទ្រព្យមិនគិតដីធ្លី Total Fixed Asset (Land exclude) | J15: 1000000
A16: មុខផលិតផល Products | C16: ឯកតាUnit | D16: បរិមាណ និងតម្លៃផលិតផល Total Output
D17: ឆ្នាំមុន (Data Last Year) | H17: ទិន្នន័យប្រចាំខែ (Monthly Data) | L17: សរុបពីដើមឆ្នាំ (From beginning of the Year )
D18: ​ បរិមាណ Quantity | F18: តម្លៃ Value(USD) | H18: បរិមាណផលិតផល Product Quantity | J18: តម្លៃផលិតផល Product Value(USD) | L18: បរិមាណផលិតផល Product Quantity | N18: តម្លៃផលិតផល Product Value(USD)
D19: ក្នុងស្រុក Domestic | E19: នាំចេញ Export | F19: ក្នុងស្រុក Domestic | G19: នាំចេញ Export | H19: ក្នុងស្រុក Domestic | I19: នាំចេញ Export | J19: ក្នុងស្រុក Domestic | K19: នាំចេញ Export | L19: ក្នុងស្រុក Domestic | M19: នាំចេញ Export | N19: ក្នុងស្រុក Domestic | O19: នាំចេញ Export
A20: LADIES | B20: PANTS | C20: PCS | I20: 147962 | K20: =ROUND(I20*2.02726659547722,2) -> 299958.42 | M20: =I20+'8-AUG'!M20 -> 563295 | O20: =K20+'8-AUG'!O20 -> 1099025.7 | Q20: =M20+I20 -> 711257 | S20: =O20+K20 -> 1398984.1
A21: LADIES | B21: PAJAMAS | C21: PCS | M21: =I21+'8-AUG'!M21 -> 23698 | O21: =K21+'8-AUG'!O21 -> 344904.26
A22: LADIES | B22: SKIRT | C22: PCS | M22: =I22+'8-AUG'!M22 -> 81280 | O22: =K22+'8-AUG'!O22 -> 2855
A23: LADIES | B23: DRESS | C23: PCS | M23: =I23+'8-AUG'!M23 -> 576 | O23: =K23+'8-AUG'!O23 -> 267740.36 | Q23: =M23+I23 -> 576 | S23: =O23+K23 -> 267740.36
A24: LADIES | B24: NIGHT GOWN | C24: PCS | M24: =I24+'8-AUG'!M24 -> 3396 | O24: =K24+'8-AUG'!O24 -> 1532.16 | Q24: =M24+I24 -> 3396 | S24: =O24+K24 -> 1532.16
A25: LADIES | B25: TANK | C25: PCS | M25: =I25+'8-AUG'!M25 -> 1848 | O25: =K25+'8-AUG'!O25 -> 2272.8 | Q25: =M25+I25 -> 1848 | S25: =O25+K25 -> 2272.8
A26: LADIES | B26: SHORT | C26: PCS | M26: =I26+'8-AUG'!M26 -> 565651 | O26: =K26+'8-AUG'!O26 -> 2605.68 | Q26: =M26+I26 -> 565651 | S26: =O26+K26 -> 2605.68
A27: LADIES | B27: SKORT | C27: PCS | M27: =I27+'8-AUG'!M27 -> 1000 | O27: =K27+'8-AUG'!O27 -> 1950
A28: Total | E28: =SUM(E20:E26) -> 0 | G28: =SUM(G20:G26) -> 0 | I28: =SUM(I20:I27) -> 147962 | K28: =SUM(K20:K27) -> 299958.42 | M28: =SUM(M20:M27) -> 1240744 | O28: =SUM(O20:O27) -> 1722886
A29: សំគាល់ :​ ទិន្នន័យនៃរបាយការណ៍នេះត្រូវបានប្រើប្រាស់តែក្នុងគោលបំណង ស្ថិតិឧស្សាហកម្មតែប៉ុណ្ណោះ មិនត្រូវបានយកទៅចែកចាយដើម្បីប្រើប្រាស់
A30: ក្នុងគោលបំណងពាណិជ្ជកម្ម ឬក្នុងការគណនាបង់ពន្ធដារទេ។ | K30: ថ្ងៃទី 15 ខែ កញ្ញា ឆ្នាំ2026 | N30: =K30 -> ថ្ងៃទី 15 ខែ កញ្ញា ឆ្នាំ2026 | Q30: ថ្ងៃទី 15 ខែ កញ្ញា ឆ្នាំ2026
A31: Remark: This report is used for industrial statistic only,​ not for commercial or tax purpose | J31: ​​​​​​​​​​​​​​​​​​​ | K31: Date:……./……../…… | N31: Date:……./……../……
A32: ទុនអចលនទ្រព្យមិនគិតដីធ្លី រួមមាន៖ អគារ និងឧបករណ៍បរិក្ខារដែលភ្ជាប់នឹងអគារ | K32: នាយក | N32: អ្នកធ្វើរបាយការណ៍
A33: Total asset excluding land comprises of : building & material attached.
A34: ទុនសរុបមិនគិតដីធ្លី រួមមាន៖ ទុនអចលនទ្រព្យមិនគិតដីធ្លី, មធ្យោបាយដឹកជញ្ជូន, គ្រឿងចក្រ-ម៉ាស៊ីន និងឧបករណ៍សម្ភារប្រើប្រាស់ក្នុងផលិតកម្ម, សង្ហារឹម និងសម្ភារការិយាល័យ | K34: Director | N34: Reportor
A35: Total fixed asset excluding land comprises of : real estate capital excluding land, transportation, machinery, and instrument utilised in the production line,
A36: furniture and office equiment.
A37: ទំនាក់ទំនង : Tel 077 330 279/090 922 237 E-mail : industryaffair.mih@gmail.com : TELEGRAM :077 330 279
K41: NI, CUNLAN | N41: THNIN
B42: ឈ្មោះរោងចក្រ ជេអ​ អឹភែរឹល ឯ.ក
A43: ទីផ្សារលក់ផលិតផលប្រចាំខែ | J43: =I6 -> កញ្ញា | K43: ឆ្នាំ២០២៦ (USD)
A44: ល.រ | B44: ឈ្មោះផលិតផល | D44: ឯកតា (Unit) | E44: ឈ្មោះប្រទេសនាំចេញផលិតផល | O44: សរុបពីដើមឆ្នាំ
E45: USA | G45: CANADA | I45: CHINA | K45: EU GROUP | M45: ផ្សេងៗ
E46: បរិមាណ | F46: តម្លៃ | G46: បរិមាណ | H46: តម្លៃ | I46: បរិមាណ | J46: តម្លៃ | K46: បរិមាណ | L46: តម្លៃ | M46: បរិមាណ | N46: តម្លៃ | O46: បរិមាណ | P46: តម្លៃ
A47: 1 | B47: =A20 -> LADIES | C47: =B20 -> PANTS | D47: PCS | E47: 141738 | F47: =ROUND(E47*2.02761729388026,2) -> 287390.42 | G47: 6224 | H47: =ROUND(G47*2.01928020565553,2) -> 12568 | O47: =M20 -> 563295 | P47: =O20 -> 1099025.7
A48: 2 | B48: =A21 -> LADIES | C48: =B21 -> PAJAMAS | D48: PCS | O48: =M21 -> 23698 | P48: =O21 -> 344904.26
A49: 3 | B49: =A22 -> LADIES | C49: =B22 -> SKIRT | D49: PCS | O49: =M22 -> 81280 | P49: =O22 -> 2855
A50: 4 | B50: =A23 -> LADIES | C50: =B23 -> DRESS | D50: PCS | O50: =M23 -> 576 | P50: =O23 -> 267740.36
A51: 5 | B51: =A24 -> LADIES | C51: =B24 -> NIGHT GOWN | D51: PCS | O51: =M24 -> 3396 | P51: =O24 -> 1532.16
A52: 6 | B52: =A25 -> LADIES | C52: =B25 -> TANK | D52: PCS | O52: =M25 -> 1848 | P52: =O25 -> 2272.8
A53: 7 | B53: =A26 -> LADIES | C53: =B26 -> SHORT | D53: PCS | O53: =M26 -> 565651 | P53: =O26 -> 2605.68
A54: 8 | B54: =A27 -> LADIES | C54: =B27 -> SKORT | D54: PCS | O54: 1000 | P54: 1950
B55: សរុប | E55: =SUM(E47:E53) -> 141738 | F55: =SUM(F47:F53) -> 287390.42 | G55: =SUM(G47:G53) -> 6224 | H55: =SUM(H47:H53) -> 12568 | I55: =SUM(I47:I53) -> 0 | J55: =SUM(J47:J53) -> 0 | K55: =SUM(K47:K53) -> 0 | L55: =SUM(L47:L53) -> 0 | ... N55: =SUM(N47:N53) -> 0 | O55: =SUM(O47:O54) -> 1240744 | P55: =SUM(P47:P54) -> 1722886 | Q55: =E55+G55 -> 147962 | R55: =F55+H55 -> 299958.42
A57: ប្រភពដើមទំនិញ (វត្ថុធាតុដើម)ប្រចាំខែ | J57: =$I$6 -> កញ្ញា | K57: =$K$43 -> ឆ្នាំ២០២៦ (USD)
A58: ល.រ | B58: ឈ្មោះវត្ថុធាតុដើម | D58: ឯកតា (Unit) | E58: ឈ្មោះប្រទេសនាំចូលវត្ថុធាតុដើម | O58: សរុបពីដើមឆ្នាំ
E59: ចិន | G59: តៃវ៉ាន់ | I59: ហុងកុង | K59: វៀតណាម | M59: ផ្សេងៗ
E60: បរិមាណ | F60: តម្លៃ | G60: បរិមាណ | H60: តម្លៃ | I60: បរិមាណ | J60: តម្លៃ | K60: បរិមាណ | L60: តម្លៃ | M60: បរិមាណ | N60: តម្លៃ | O60: បរិមាណ | P60: តម្លៃ
A61: 1 | B61: I. MACHINERIES &. EQUIPMENTS | D61: SET | O61: ='8-AUG'!O61+E61 -> 1 | P61: ='8-AUG'!P61+F61 -> 11000 | Q61: =E61+G61+I61+K61+M61 -> 0 | R61: =F61+H61+J61+L61+N61 -> 0 | S61: =Q61+O61 -> 1 | T61: =R61+P61 -> 11000
A62: 3 | B62: II. RAW MATERIAL | D62: MTR | E62: 176986.9 | F62: 257603.46 | O62: =E62+'8-AUG'!O62 -> 836020.9 | P62: =F62+'8-AUG'!P62 -> 909451.66 | Q62: =E62+G62+I62+K62+M62 -> 176986.9 | R62: =F62+H62+J62+L62+N62 -> 257603.46 | S62: =Q62+O62 -> 1013007.8 | T62: =R62+P62 -> 1167055.1
A63: 4 | B63: III. ACCESSORY | D63: DZN | E63: 4968.8 | F63: 993.76 | O63: =E63+'8-AUG'!O63 -> 32605.8 | P63: =F63+'8-AUG'!P63 -> 7582.21 | Q63: =E63+G63+I63+K63+M63 -> 4968.8 | R63: =F63+H63+J63+L63+N63 -> 993.76 | S63: =Q63+O63 -> 37574.6 | T63: =R63+P63 -> 8575.97
B64: សរុប | E64: =SUM(E61:E63) -> 181955.7 | F64: =SUM(F61:F63) -> 258597.22 | G64: =SUM(G61:G63) -> 0 | H64: =SUM(H61:H63) -> 0 | I64: =SUM(I61:I63) -> 0 | J64: =SUM(J61:J63) -> 0 | K64: =SUM(K61:K63) -> 0 | L64: =SUM(L61:L63) -> 0 | ... P64: =SUM(P61:P63) -> 928033.87
B66: =A37 -> ទំនាក់ទំនង : Tel 077 330 279/090 922 237 E-mail : industryaffair.mih@gmail.com : TELEGRAM :077 330 279 | K66: =K30 -> ថ្ងៃទី 15 ខែ កញ្ញា ឆ្នាំ2026 | N66: =N30 -> ថ្ងៃទី 15 ខែ កញ្ញា ឆ្នាំ2026
K67: =K31 -> Date:……./……../…… | N67: =N31 -> Date:……./……../……
K68: =K32 -> នាយក | N68: =N32 -> អ្នកធ្វើរបាយការណ៍
K69: =K34 -> Director | N69: =N34 -> Reportor
K75: =K41 -> NI, CUNLAN | N75: =N41 -> THNIN
B76: ឈ្មោះរោងចក្រ ជេអ​ អឹភែរឹល ឯ.ក
B77: បរិមាណការប្រើប្រាស់ថាមពល ប្រចាំខែ | J77: =$I$6 -> កញ្ញា | K77: =$K$43 -> ឆ្នាំ២០២៦ (USD)
A78: ល.រ | B78: ប្រភេទថាមពល | E78: ឯកតា (Unit) | G78: ឆ្នាំមុន | I78: ប្រចាំខែ......... | K78: សរុបពីដើមឆ្នាំ | O78: ផ្សេងៗ
G79: បរិមាណ | H79: តម្លៃ $ | I79: បរិមាណ | J79: តម្លៃ $ | K79: បរិមាណ | M79: តម្លៃ $
A80: 1 | B80: EDC | E80: KW | I80: 11368 | J80: =0.137*I80 -> 1557.416 | K80: =I80+'8-AUG'!K81:L81 -> 102312 | M80: =J80+'8-AUG'!M81:N81 -> 14016.744 | Q80: =K80+I80 -> 113680 | R80: =M80+J80 -> 15574.16
B81: សរុប | G81: =SUM(G80) -> 0 | H81: =SUM(H80) -> 0 | I81: =SUM(I80) -> 11368 | J81: =SUM(J80) -> 1557.416 | K81: =SUM(K80) -> 102312 | M81: =SUM(M80) -> 14016.744
B83: បរិមាណការប្រើប្រាស់ទឹក​ ប្រចាំខែ | J83: =J77 -> កញ្ញា
A84: ល.រ | B84: ប្រភពទឹក | E84: ឯកតា (Unit) | G84: ឆ្នាំមុន | I84: ប្រចាំខែ......... | K84: សរុបពីដើមឆ្នាំ | O84: ផ្សេងៗ
G85: បរិមាណ | H85: តម្លៃ $ | I85: បរិមាណ | J85: តម្លៃ $ | K85: បរិមាណ | M85: តម្លៃ $
A86: 1 | B86: PPWSA | E86: M3 | I86: 83 | J86: =0.55*I86 -> 45.65 | K86: =I86+'8-AUG'!K87:L87 -> 747 | M86: =J86+'8-AUG'!M87:N87 -> 410.85 | Q86: =K86+I86 -> 830 | R86: =M86+J86 -> 456.5
B87: សរុប | G87: =SUM(G86) -> 0 | H87: =SUM(H86) -> 0 | I87: =SUM(I86) -> 83 | J87: =SUM(J86) -> 45.65 | K87: =SUM(K86) -> 747 | M87: =SUM(M86) -> 410.85
B89: ​ ​បរិមាណសំណល់ ពីដំណើរការខ្សែសង្វាក់ផលិតកម្ម ប្រចាំខែ | J89: =$I$6 -> កញ្ញា | K89: =$K$43 -> ឆ្នាំ២០២៦ (USD)
A90: ល.រ | B90: ប្រភេទសំណល់ | D90: ឯកតា (Unit) | E90: បរិមាណសំណល់សរុប ពីឆ្នាំមុន | G90: បរិមាណសំណល់ប្រចាំខែ......... | K90: បរិមាណសំណល់សរុបពីដើមឆ្នាំ | O90: ផ្សេងៗ
A91: 1 | B91: សំណល់រឹង
A92: 2 | B92: សំណល់រាវ
A93: 3 | B93: សំណល់(ឧស្ម័ន)
A94: 4 | B94: សរុប
A96: =A37 -> ទំនាក់ទំនង : Tel 077 330 279/090 922 237 E-mail : industryaffair.mih@gmail.com : TELEGRAM :077 330 279 | K96: =K30 -> ថ្ងៃទី 15 ខែ កញ្ញា ឆ្នាំ2026 | N96: =N30 -> ថ្ងៃទី 15 ខែ កញ្ញា ឆ្នាំ2026
K97: =K31 -> Date:……./……../…… | N97: =N31 -> Date:……./……../……
K98: =K32 -> នាយក | N98: =N32 -> អ្នកធ្វើរបាយការណ៍
K99: =K34 -> Director | N99: =N69 -> Reportor
K107: =K41 -> NI, CUNLAN | N107: =N75 -> THNIN
