Workbook

Sheet 01
A1: PAID | E1: REVENUE & EXPENSE | G1: THC | M1: Saturday
A2: CHEA PAYMENT | B2: PORT NUMBER | C2: PORT CODE | D2: PORT NAME | E2: DECLARE | F2: DATE | G2: CLIENT | H2: INV | I2: DISBURSEMENT | J2: DN | K2: DATE | L2: EXCHANGE RATE | M2: weekday | N2: CLEAR FEE | O2: THC | P2: CM | Q2: INV (REVENUE) | R2: REIM | S2: VAT 10% | T2: DN | U2: NET PROFIT | V2: MARK
A3: PAID | B3: 11 | C3: =INDEX(PORT!$B$2:$B$20,MATCH('01'!B3,PORT!$A$2:$A$20)) -> SHV11 | D3: =INDEX(PORT!$C$2:$C$20,MATCH('01'!B3,PORT!$A$2:$A$20)) -> SHV PORT | E3: I 4718 | F3: 46032 | G3: JR | H3: GS26-017 | I3: DIS017 | J3: JR2601001 | K3: 46034 | L3: 4025 | M3: =TEXT(K3,"dddd") -> Monday | N3: 620.2 | O3: 683 | P3: 5 | Q3: 180 | R3: 778.2 | S3: =ROUND(Q3*10%,2) -> 18 | T3: 620 | U3: =(Q3+R3+T3)-(N3+O3+P3) -> 270
A4: PAID | B4: 11 | C4: =INDEX(PORT!$B$2:$B$20,MATCH('01'!B4,PORT!$A$2:$A$20)) -> SHV11 | D4: =INDEX(PORT!$C$2:$C$20,MATCH('01'!B4,PORT!$A$2:$A$20)) -> SHV PORT | E4: I 4728 | F4: 46032 | G4: JR | K4: 46034 | L4: 4025 | M4: =TEXT(K4,"dddd") -> Monday | S4: =ROUND(Q4*10%,2) -> 0 | U4: =(Q4+R4+T4)-(N4+O4+P4) -> 0
A5: PAID | B5: 11 | C5: =INDEX(PORT!$B$2:$B$20,MATCH('01'!B5,PORT!$A$2:$A$20)) -> SHV11 | D5: =INDEX(PORT!$C$2:$C$20,MATCH('01'!B5,PORT!$A$2:$A$20)) -> SHV PORT | E5: I 14254 | F5: 46050 | G5: JR | H5: GS26-034 | I5: DIS034 | J5: JR2601002 | K5: 46051 | L5: 4027 | M5: =TEXT(K5,"dddd") -> Thursday | N5: 569.45 | O5: 691.5 | P5: 5 | Q5: 200 | R5: 805.95 | S5: =ROUND(Q5*10%,2) -> 20 | T5: 560 | U5: =(Q5+R5+T5)-(N5+O5+P5) -> 300
A6: PAID | B6: 11 | C6: =INDEX(PORT!$B$2:$B$20,MATCH('01'!B6,PORT!$A$2:$A$20)) -> SHV11 | D6: =INDEX(PORT!$C$2:$C$20,MATCH('01'!B6,PORT!$A$2:$A$20)) -> SHV PORT | E6: I 15940 | F6: 46052 | G6: JR | H6: GS26-036 | I6: DIS036 | J6: JR2601003 | K6: 46052 | L6: 4026 | M6: =TEXT(K6,"dddd") -> Friday | N6: 446.45 | O6: 476.5 | P6: 5 | Q6: 180 | R6: 557.95 | S6: =ROUND(Q6*10%,2) -> 18 | T6: 460 | U6: =(Q6+R6+T6)-(N6+O6+P6) -> 270
A7: PAID | B7: 1 | C7: =INDEX(PORT!$B$2:$B$20,MATCH('01'!B7,PORT!$A$2:$A$20)) -> PNH01 | D7: =INDEX(PORT!$C$2:$C$20,MATCH('01'!B7,PORT!$A$2:$A$20)) -> KTI AIR PORT | E7: E 222 | F7: 46025 | G7: JIN YUAN XI | H7: GS26-007 | I7: DIS007 | J7: JYX2601001 | K7: 46027 | L7: 4018 | M7: =TEXT(K7,"dddd") -> Monday | N7: 191.48 | P7: 50 | Q7: 175 | R7: 71.48 | S7: =ROUND(Q7*10%,2) -> 17.5 | T7: 180 | U7: =(Q7+R7+T7)-(N7+O7+P7) -> 185
A8: PAID | B8: 4 | C8: =INDEX(PORT!$B$2:$B$20,MATCH('01'!B8,PORT!$A$2:$A$20)) -> PNH04 | D8: =INDEX(PORT!$C$2:$C$20,MATCH('01'!B8,PORT!$A$2:$A$20)) -> PNH PORT | E8: E 4763 | F8: 46025 | G8: JIN YUAN XI | H8: GS26-008 | I8: DIS008 | J8: JYX2601002 | K8: 46027 | L8: 4018 | M8: =TEXT(K8,"dddd") -> Monday | N8: 538.85 | P8: 50 | Q8: 215 | R8: 93.85 | S8: =ROUND(Q8*10%,2) -> 21.5 | T8: 724 | U8: =(Q8+R8+T8)-(N8+O8+P8) -> 444
A9: PAID | B9: 1 | C9: =INDEX(PORT!$B$2:$B$20,MATCH('01'!B9,PORT!$A$2:$A$20)) -> PNH01 | D9: =INDEX(PORT!$C$2:$C$20,MATCH('01'!B9,PORT!$A$2:$A$20)) -> KTI AIR PORT | E9: I 672 | F9: 46030 | G9: JIN YUAN XI | H9: GS26-013 | I9: DIS013 | J9: JYX2601003 | K9: 46031 | L9: 4021 | M9: =TEXT(K9,"dddd") -> Friday | N9: 222.38 | P9: 50 | Q9: 150 | R9: 27.38 | S9: =ROUND(Q9*10%,2) -> 15 | T9: 195 | U9: =(Q9+R9+T9)-(N9+O9+P9) -> 100
A10: PAID | B10: 11 | C10: =INDEX(PORT!$B$2:$B$20,MATCH('01'!B10,PORT!$A$2:$A$20)) -> SHV11 | D10: =INDEX(PORT!$C$2:$C$20,MATCH('01'!B10,PORT!$A$2:$A$20)) -> SHV PORT | E10: E 7388 | F10: 46031 | G10: JIN YUAN XI | H10: GS26-015 | I10: DIS015 | J10: JYX2601004 | K10: 46034 | L10: 4025 | M10: =TEXT(K10,"dddd") -> Monday | N10: 373.95 | P10: 50 | Q10: 245 | R10: 73.95 | S10: =ROUND(Q10*10%,2) -> 24.5 | T10: 305 | U10: =(Q10+R10+T10)-(N10+O10+P10) -> 200
A11: PAID | B11: 1 | C11: =INDEX(PORT!$B$2:$B$20,MATCH('01'!B11,PORT!$A$2:$A$20)) -> PNH01 | D11: =INDEX(PORT!$C$2:$C$20,MATCH('01'!B11,PORT!$A$2:$A$20)) -> KTI AIR PORT | E11: E 1215 | F11: 46032 | G11: JIN YUAN XI | H11: GS26-016 | I11: DIS016 | J11: JXY2601005 | K11: 46034 | L11: 4025 | M11: =TEXT(K11,"dddd") -> Monday | N11: 308.34 | P11: 50 | Q11: 220 | R11: 188.34 | S11: =ROUND(Q11*10%,2) -> 22 | T11: 180 | U11: =(Q11+R11+T11)-(N11+O11+P11) -> 230
A12: PAID | B12: 1 | C12: =INDEX(PORT!$B$2:$B$20,MATCH('01'!B12,PORT!$A$2:$A$20)) -> PNH01 | D12: =INDEX(PORT!$C$2:$C$20,MATCH('01'!B12,PORT!$A$2:$A$20)) -> KTI AIR PORT | E12: I 1438 | F12: 46037 | G12: JIN YUAN XI | H12: GS26-021 | I12: DIS021 | J12: JYX2601006 | K12: 46038 | L12: 4026 | M12: =TEXT(K12,"dddd") -> Friday | N12: 242.62 | P12: 50 | Q12: 150 | R12: 47.62 | S12: =ROUND(Q12*10%,2) -> 15 | T12: 195 | U12: =(Q12+R12+T12)-(N12+O12+P12) -> 100
A13: PAID | B13: 11 | C13: =INDEX(PORT!$B$2:$B$20,MATCH('01'!B13,PORT!$A$2:$A$20)) -> SHV11 | D13: =INDEX(PORT!$C$2:$C$20,MATCH('01'!B13,PORT!$A$2:$A$20)) -> SHV PORT | E13: E 18060 | F13: 46038 | G13: JIN YUAN XI | H13: GS26-022 | I13: DIS022 | J13: JYX2601007 | K13: 46041 | L13: 4027 | M13: =TEXT(K13,"dddd") -> Monday | N13: 958.54 | P13: 50 | Q13: 490 | R13: 198.55 | S13: =ROUND(Q13*10%,2) -> 49 | T13: 955 | U13: =(Q13+R13+T13)-(N13+O13+P13) -> 635.01
A14: PAID | B14: 11 | C14: =INDEX(PORT!$B$2:$B$20,MATCH('01'!B14,PORT!$A$2:$A$20)) -> SHV11 | D14: =INDEX(PORT!$C$2:$C$20,MATCH('01'!B14,PORT!$A$2:$A$20)) -> SHV PORT | E14: E 19191 | F14: 46039 | G14: JIN YUAN XI | H14: GS26-024 | I14: DIS024 | J14: JYX2601008 | K14: 46041 | L14: 4027 | M14: =TEXT(K14,"dddd") -> Monday | N14: 678.84 | P14: 50 | Q14: 245 | R14: 118.84 | S14: =ROUND(Q14*10%,2) -> 24.5 | T14: 879 | U14: =(Q14+R14+T14)-(N14+O14+P14) -> 514
A15: PAID | B15: 1 | C15: =INDEX(PORT!$B$2:$B$20,MATCH('01'!B15,PORT!$A$2:$A$20)) -> PNH01 | D15: =INDEX(PORT!$C$2:$C$20,MATCH('01'!B15,PORT!$A$2:$A$20)) -> KTI AIR PORT | E15: E 3591 | F15: 46046 | G15: JIN YUAN XI | H15: GS26-030 | I15: DIS030 | J15: JYX2601009 | K15: 46048 | L15: 4029 | M15: =TEXT(K15,"dddd") -> Monday | N15: 344.77 | P15: 50 | Q15: 220 | R15: 224.77 | S15: =ROUND(Q15*10%,2) -> 22 | T15: 180 | U15: =(Q15+R15+T15)-(N15+O15+P15) -> 230
A16: PAID | B16: 1 | C16: =INDEX(PORT!$B$2:$B$20,MATCH('01'!B16,PORT!$A$2:$A$20)) -> PNH01 | D16: =INDEX(PORT!$C$2:$C$20,MATCH('01'!B16,PORT!$A$2:$A$20)) -> KTI AIR PORT | E16: E 3640 | F16: 46046 | G16: JIN YUAN XI | H16: GS26-031 | I16: DIS031 | J16: JYX2601010 | K16: 46048 | L16: 4029 | M16: =TEXT(K16,"dddd") -> Monday | N16: 152.93 | P16: 50 | Q16: 140 | R16: 32.93 | S16: =ROUND(Q16*10%,2) -> 14 | T16: 180 | U16: =(Q16+R16+T16)-(N16+O16+P16) -> 150
A17: PAID | B17: 23 | C17: =INDEX(PORT!$B$2:$B$20,MATCH('01'!B17,PORT!$A$2:$A$20)) -> PNH23 | D17: =INDEX(PORT!$C$2:$C$20,MATCH('01'!B17,PORT!$A$2:$A$20)) -> UNION DRY PORT | E17: I 80 | F17: 46049 | G17: JIN YUAN XI | H17: GS26-032 | I17: DIS032 | J17: JYX2601011 | K17: 46050 | L17: 4025 | M17: =TEXT(K17,"dddd") -> Wednesday | N17: 343.21 | O17: 456.89 | P17: 50 | Q17: 150 | R17: 560.1 | S17: =ROUND(Q17*10%,2) -> 15 | T17: 350 | U17: =(Q17+R17+T17)-(N17+O17+P17) -> 210
A18: PAID | B18: 1 | C18: =INDEX(PORT!$B$2:$B$20,MATCH('01'!B18,PORT!$A$2:$A$20)) -> PNH01 | D18: =INDEX(PORT!$C$2:$C$20,MATCH('01'!B18,PORT!$A$2:$A$20)) -> KTI AIR PORT | E18: I 3142 | F18: 46052 | G18: JIN YUAN XI | H18: GS26-035 | I18: DIS035 | J18: JYX2601012 | K18: 46052 | L18: 4026 | M18: =TEXT(K18,"dddd") -> Friday | N18: 310.38 | P18: 50 | Q18: 185 | R18: 115.38 | S18: =ROUND(Q18*10%,2) -> 18.5 | T18: 195 | U18: =(Q18+R18+T18)-(N18+O18+P18) -> 135
A19: PAID | B19: 21 | C19: =INDEX(PORT!$B$2:$B$20,MATCH('01'!B19,PORT!$A$2:$A$20)) -> PNH21 | D19: =INDEX(PORT!$C$2:$C$20,MATCH('01'!B19,PORT!$A$2:$A$20)) -> OLAIR DRY PORT | E19: I 30 | F19: 46024 | G19: SPORTLINE | H19: GS26-006 | I19: DIS006 | J19: SAK2601001 | K19: 46027 | L19: 4018 | M19: =TEXT(K19,"dddd") -> Monday | N19: 132.58 | P19: 50 | Q19: 150 | R19: 27.58 | S19: =ROUND(Q19*10%,2) -> 15 | T19: 120 | U19: =(Q19+R19+T19)-(N19+O19+P19) -> 115
A20: PAID | B20: 4 | C20: =INDEX(PORT!$B$2:$B$20,MATCH('01'!B20,PORT!$A$2:$A$20)) -> PNH04 | D20: =INDEX(PORT!$C$2:$C$20,MATCH('01'!B20,PORT!$A$2:$A$20)) -> PNH PORT | E20: E 10353 | F20: 46031 | G20: SPORTLINE | H20: GS26-014 | I20: DIS014 | J20: SAK2601002 | K20: 46034 | L20: 4025 | M20: =TEXT(K20,"dddd") -> Monday | N20: 937.76 | P20: 50 | Q20: 490 | R20: 267.76 | S20: =ROUND(Q20*10%,2) -> 49 | T20: 740 | U20: =(Q20+R20+T20)-(N20+O20+P20) -> 510
A21: PAID | B21: 21 | C21: =INDEX(PORT!$B$2:$B$20,MATCH('01'!B21,PORT!$A$2:$A$20)) -> PNH21 | D21: =INDEX(PORT!$C$2:$C$20,MATCH('01'!B21,PORT!$A$2:$A$20)) -> OLAIR DRY PORT | E21: I 242 | F21: 46035 | G21: SPORTLINE | H21: GS26-019 | I21: DIS019 | J21: SAK2601003 | K21: 46036 | L21: 4025 | M21: =TEXT(K21,"dddd") -> Wednesday | N21: 177.18 | O21: 449.63 | P21: 50 | Q21: 150 | R21: 511.81 | S21: =ROUND(Q21*10%,2) -> 15 | T21: 145 | U21: =(Q21+R21+T21)-(N21+O21+P21) -> 130
A22: PAID | D22: HP260134-1/30 | E22: THC | I22: DIS038 | K22: 46053 | O22: 344.43 | R22: 344.43 | U22: =(Q22+R22+T22)-(N22+O22+P22) -> 0
A23: PAID | B23: 1 | C23: =INDEX(PORT!$B$2:$B$20,MATCH('01'!B23,PORT!$A$2:$A$20)) -> PNH01 | D23: =INDEX(PORT!$C$2:$C$20,MATCH('01'!B23,PORT!$A$2:$A$20)) -> KTI AIR PORT | E23: E 94 | F23: 46024 | G23: VFL | H23: GS26-001 | I23: DIS001 | J23: VFL2601001 | K23: 46027 | L23: 4018 | M23: =TEXT(K23,"dddd") -> Monday | N23: 113.76 | P23: 50 | Q23: 150 | R23: 43.76 | S23: =ROUND(Q23*10%,2) -> 15 | T23: 60 | U23: =(Q23+R23+T23)-(N23+O23+P23) -> 90
A24: PAID | B24: 11 | C24: =INDEX(PORT!$B$2:$B$20,MATCH('01'!B24,PORT!$A$2:$A$20)) -> SHV11 | D24: =INDEX(PORT!$C$2:$C$20,MATCH('01'!B24,PORT!$A$2:$A$20)) -> SHV PORT | E24: E 3685 | F24: 46024 | G24: VFL | H24: GS26-002 | I24: DIS002 | J24: VFL2601002 | K24: 46027 | L24: 4018 | M24: =TEXT(K24,"dddd") -> Monday | N24: 400.95 | P24: 50 | Q24: 215 | R24: 95.95 | S24: =ROUND(Q24*10%,2) -> 21.5 | T24: 285 | U24: =(Q24+R24+T24)-(N24+O24+P24) -> 145
A25: PAID | B25: 1 | C25: =INDEX(PORT!$B$2:$B$20,MATCH('01'!B25,PORT!$A$2:$A$20)) -> PNH01 | D25: =INDEX(PORT!$C$2:$C$20,MATCH('01'!B25,PORT!$A$2:$A$20)) -> KTI AIR PORT | E25: I 21 | F25: 46024 | G25: VFL | H25: GS26-003 | I25: DIS003 | J25: VFL2601003 | K25: 46027 | L25: 4018 | M25: =TEXT(K25,"dddd") -> Monday | N25: 151.05 | P25: 50 | Q25: 150 | R25: 9.55 | S25: =ROUND(Q25*10%,2) -> 15 | T25: 106.5 | U25: =(Q25+R25+T25)-(N25+O25+P25) -> 65
A26: PAID | B26: 21 | C26: =INDEX(PORT!$B$2:$B$20,MATCH('01'!B26,PORT!$A$2:$A$20)) -> PNH21 | D26: =INDEX(PORT!$C$2:$C$20,MATCH('01'!B26,PORT!$A$2:$A$20)) -> OLAIR DRY PORT | E26: I 23 | F26: 46024 | G26: VFL | H26: GS26-004 | I26: DIS004 | J26: VFL2601004 | K26: 46027 | L26: 4018 | M26: =TEXT(K26,"dddd") -> Monday | N26: 113.23 | P26: 50 | Q26: 150 | R26: 28.23 | S26: =ROUND(Q26*10%,2) -> 15 | T26: 90 | U26: =(Q26+R26+T26)-(N26+O26+P26) -> 105
A27: PAID | B27: 11 | C27: =INDEX(PORT!$B$2:$B$20,MATCH('01'!B27,PORT!$A$2:$A$20)) -> SHV11 | D27: =INDEX(PORT!$C$2:$C$20,MATCH('01'!B27,PORT!$A$2:$A$20)) -> SHV PORT | E27: I 342 | F27: 46024 | G27: VFL | H27: GS26-005 | I27: DIS005 | J27: VFL2601005 | K27: 46027 | L27: 4018 | M27: =TEXT(K27,"dddd") -> Monday | N27: 164.49 | P27: 50 | Q27: 150 | R27: 17.12 | S27: =ROUND(Q27*10%,2) -> 15 | T27: 106.38 | U27: =(Q27+R27+T27)-(N27+O27+P27) -> 59.01
A28: PAID | B28: 1 | C28: =INDEX(PORT!$B$2:$B$20,MATCH('01'!B28,PORT!$A$2:$A$20)) -> PNH01 | D28: =INDEX(PORT!$C$2:$C$20,MATCH('01'!B28,PORT!$A$2:$A$20)) -> KTI AIR PORT | E28: E 575 | F28: 46028 | G28: VFL | H28: GS26-009 | I28: DIS009 | J28: VFL2601006 | K28: 46030 | L28: 4021 | M28: =TEXT(K28,"dddd") -> Thursday | N28: 102.76 | O28: 60.5 | P28: 50 | Q28: 140 | R28: 32.76 | S28: =ROUND(Q28*10%,2) -> 14 | T28: 60 | U28: =(Q28+R28+T28)-(N28+O28+P28) -> 19.5
A29: PAID | B29: 16 | C29: =INDEX(PORT!$B$2:$B$20,MATCH('01'!B29,PORT!$A$2:$A$20)) -> PNH16 | D29: =INDEX(PORT!$C$2:$C$20,MATCH('01'!B29,PORT!$A$2:$A$20)) -> DRYPORT ROYAL RAILWAY | E29: I 23 | F29: 46028 | G29: VFL | H29: GS26-010 | I29: DIS010 | J29: VFL2601007 | K29: 46030 | L29: 4021 | M29: =TEXT(K29,"dddd") -> Thursday | N29: 150.36 | O29: 194.61 | P29: 50 | Q29: 150 | R29: 259.97 | S29: =ROUND(Q29*10%,2) -> 15 | T29: 90 | U29: =(Q29+R29+T29)-(N29+O29+P29) -> 105
A30: PAID | B30: 1 | C30: =INDEX(PORT!$B$2:$B$20,MATCH('01'!B30,PORT!$A$2:$A$20)) -> PNH01 | D30: =INDEX(PORT!$C$2:$C$20,MATCH('01'!B30,PORT!$A$2:$A$20)) -> KTI AIR PORT | E30: I 432 | F30: 46028 | G30: VFL | H30: GS26-011 | I30: DIS011 | J30: VFL2601008 | K30: 46030 | L30: 4021 | M30: =TEXT(K30,"dddd") -> Thursday | N30: 156.95 | P30: 50 | Q30: 150 | R30: 15.45 | S30: =ROUND(Q30*10%,2) -> 15 | T30: 106.5 | U30: =(Q30+R30+T30)-(N30+O30+P30) -> 65
A31: PAID | B31: 1 | C31: =INDEX(PORT!$B$2:$B$20,MATCH('01'!B31,PORT!$A$2:$A$20)) -> PNH01 | D31: =INDEX(PORT!$C$2:$C$20,MATCH('01'!B31,PORT!$A$2:$A$20)) -> KTI AIR PORT | E31: I 595 | F31: 46030 | G31: VFL | H31: GS26-012 | I31: DIS012 | J31: VFL2601009 | K31: 46031 | L31: 4021 | M31: =TEXT(K31,"dddd") -> Friday | N31: 153.52 | O31: 60.5 | P31: 50 | Q31: 150 | R31: 72.52 | S31: =ROUND(Q31*10%,2) -> 15 | T31: 106.5 | U31: =(Q31+R31+T31)-(N31+O31+P31) -> 65
A32: PAID | B32: 1 | C32: =INDEX(PORT!$B$2:$B$20,MATCH('01'!B32,PORT!$A$2:$A$20)) -> PNH01 | D32: =INDEX(PORT!$C$2:$C$20,MATCH('01'!B32,PORT!$A$2:$A$20)) -> KTI AIR PORT | E32: I 1202 | F32: 46035 | G32: VFL | H32: GS26-018 | I32: DIS018 | J32: VFL2601010 | K32: 46036 | L32: 4025 | M32: =TEXT(K32,"dddd") -> Wednesday | N32: 209.66 | P32: 50 | Q32: 150 | R32: 90.16 | S32: =ROUND(Q32*10%,2) -> 15 | T32: 215 | U32: =(Q32+R32+T32)-(N32+O32+P32) -> 195.5
A33: PAID | B33: 1 | C33: =INDEX(PORT!$B$2:$B$20,MATCH('01'!B33,PORT!$A$2:$A$20)) -> PNH01 | D33: =INDEX(PORT!$C$2:$C$20,MATCH('01'!B33,PORT!$A$2:$A$20)) -> KTI AIR PORT | E33: E 1692 | F33: 46036 | G33: VFL | H33: GS26-020 | I33: DIS020 | J33: VFL2601011 | K33: 46037 | L33: 4026 | M33: =TEXT(K33,"dddd") -> Thursday | N33: 111.47 | P33: 50 | Q33: 150 | R33: 41.47 | S33: =ROUND(Q33*10%,2) -> 15 | T33: 60 | U33: =(Q33+R33+T33)-(N33+O33+P33) -> 90
A34: PAID | B34: 11+ | C34: =INDEX(PORT!$B$2:$B$20,MATCH('01'!B34,PORT!$A$2:$A$20)) -> SVR11 | D34: =INDEX(PORT!$C$2:$C$20,MATCH('01'!B34,PORT!$A$2:$A$20)) -> BAVET CEO | E34: I 1541 | F34: 46039 | G34: VFL | H34: GS26-023 | I34: DIS023 | J34: VFL2601012 | K34: 46041 | L34: 4027 | M34: =TEXT(K34,"dddd") -> Monday | N34: 133.75 | P34: 50 | Q34: 230 | R34: 2.25 | S34: =ROUND(Q34*10%,2) -> 23 | T34: 66.5 | U34: =(Q34+R34+T34)-(N34+O34+P34) -> 115
A35: PAID | B35: 1 | C35: =INDEX(PORT!$B$2:$B$20,MATCH('01'!B35,PORT!$A$2:$A$20)) -> PNH01 | D35: =INDEX(PORT!$C$2:$C$20,MATCH('01'!B35,PORT!$A$2:$A$20)) -> KTI AIR PORT | E35: E 2274 | F35: 46039 | G35: VFL | H35: GS26-025 | I35: DIS025 | J35: VFL2601013 | K35: 46041 | L35: 4027 | M35: =TEXT(K35,"dddd") -> Monday | N35: 90.97 | P35: 50 | Q35: 140 | R35: 20.97 | S35: =ROUND(Q35*10%,2) -> 14 | T35: 60 | U35: =(Q35+R35+T35)-(N35+O35+P35) -> 80
A36: PAID | B36: 1 | C36: =INDEX(PORT!$B$2:$B$20,MATCH('01'!B36,PORT!$A$2:$A$20)) -> PNH01 | D36: =INDEX(PORT!$C$2:$C$20,MATCH('01'!B36,PORT!$A$2:$A$20)) -> KTI AIR PORT | E36: E 2398 | F36: 46041 | G36: VFL | H36: GS26-026 | I36: DIS026 | J36: VFL2601014 | K36: 46042 | L36: 4027 | M36: =TEXT(K36,"dddd") -> Tuesday | N36: 105.4 | P36: 50 | Q36: 140 | R36: 35.4 | S36: =ROUND(Q36*10%,2) -> 14 | T36: 60 | U36: =(Q36+R36+T36)-(N36+O36+P36) -> 80
A37: PAID | B37: 23 | C37: =INDEX(PORT!$B$2:$B$20,MATCH('01'!B37,PORT!$A$2:$A$20)) -> PNH23 | D37: =INDEX(PORT!$C$2:$C$20,MATCH('01'!B37,PORT!$A$2:$A$20)) -> UNION DRY PORT | E37: I 361 | F37: 46043 | G37: VFL | H37: GS26-027 | I37: DIS027 | J37: VFL2601015 | K37: 46044 | L37: 4030 | M37: =TEXT(K37,"dddd") -> Thursday | N37: 218.17 | O37: 674.58 | P37: 50 | Q37: 150 | R37: 772.5 | S37: =ROUND(Q37*10%,2) -> 15 | T37: 150 | U37: =(Q37+R37+T37)-(N37+O37+P37) -> 129.75
A38: PAID | B38: 1 | C38: =INDEX(PORT!$B$2:$B$20,MATCH('01'!B38,PORT!$A$2:$A$20)) -> PNH01 | D38: =INDEX(PORT!$C$2:$C$20,MATCH('01'!B38,PORT!$A$2:$A$20)) -> KTI AIR PORT | E38: E 3105 | F38: 46045 | G38: VFL | H38: GS26-028 | I38: DIS028 | J38: VFL2601016 | K38: 46048 | L38: 4029 | M38: =TEXT(K38,"dddd") -> Monday | N38: 90.17 | P38: 50 | Q38: 140 | R38: 20.17 | S38: =ROUND(Q38*10%,2) -> 14 | T38: 60 | U38: =(Q38+R38+T38)-(N38+O38+P38) -> 80
A39: PAID | B39: 11 | C39: =INDEX(PORT!$B$2:$B$20,MATCH('01'!B39,PORT!$A$2:$A$20)) -> SHV11 | D39: =INDEX(PORT!$C$2:$C$20,MATCH('01'!B39,PORT!$A$2:$A$20)) -> SHV PORT | E39: I 12059 | F39: 46045 | G39: VFL | H39: GS26-029 | I39: DIS029 | J39: VFL2601017 | K39: 46048 | L39: 4029 | M39: =TEXT(K39,"dddd") -> Monday | N39: 140.43 | O39: 299.2 | P39: 50 | Q39: 150 | R39: 314.63 | S39: =ROUND(Q39*10%,2) -> 15 | T39: 106.45 | U39: =(Q39+R39+T39)-(N39+O39+P39) -> 81.45
A40: PAID | B40: 1 | C40: =INDEX(PORT!$B$2:$B$20,MATCH('01'!B40,PORT!$A$2:$A$20)) -> PNH01 | D40: =INDEX(PORT!$C$2:$C$20,MATCH('01'!B40,PORT!$A$2:$A$20)) -> KTI AIR PORT | E40: I 2739 | F40: 46049 | G40: VFL | H40: GS26-033 | I40: DIS033 | J40: VFL2601018 | K40: 46050 | L40: 4025 | M40: =TEXT(K40,"dddd") -> Wednesday | N40: 152.8 | O40: 110 | P40: 50 | Q40: 150 | R40: 132.8 | S40: =ROUND(Q40*10%,2) -> 15 | T40: 95 | U40: =(Q40+R40+T40)-(N40+O40+P40) -> 65
A41: PAID | B41: 4 | C41: =INDEX(PORT!$B$2:$B$20,MATCH('01'!B41,PORT!$A$2:$A$20)) -> PNH04 | D41: =INDEX(PORT!$C$2:$C$20,MATCH('01'!B41,PORT!$A$2:$A$20)) -> PNH PORT | E41: E 327402 | F41: 46052 | G41: VFL | I41: DIS037 | K41: 46052 | L41: 4026 | M41: =TEXT(K41,"dddd") -> Friday | N41: 3.3 | S41: =ROUND(Q41*10%,2) -> 0 | T41: 3.3 | U41: =(Q41+R41+T41)-(N41+O41+P41) -> 0
B57: =SUBTOTAL(3,B3:B56) -> 38 | E57: TOTAL: | H57: =SUBTOTAL(3,H3:H56) -> 36 | I57: =SUBTOTAL(3,I3:I56) -> 38 | J57: =SUBTOTAL(3,J3:J56) -> 36 | N57: =SUBTOTAL(9,N3:N41) -> 10313.1 | O57: =SUBTOTAL(9,O3:O41) -> 4501.34 | P57: =SUBTOTAL(9,P3:P41) -> 1665 | Q57: =SUBTOTAL(9,Q3:Q41) -> 6740 | R57: =SUBTOTAL(9,R3:R41) -> 7052.53 | S57: =SUBTOTAL(9,S3:S41) -> 674 | T57: =SUBTOTAL(9,T3:T41) -> 9050.13 | U57: =SUBTOTAL(9,U3:U45) -> 6363.22
M58: PAID | N58: =SUMIFS($N$3:$N$45,$A$3:$A$45,$M$58) -> 10313.1
M59: NOT YET | N59: =SUMIFS($N$3:$N$45,$A$3:$A$45,$M$59) -> 0

Sheet 02
E1: REVENUE & EXPENSE | M1: Saturday
A2: CHEA PAYMENT | B2: PORT NUMBER | C2: PORT CODE | D2: PORT NAME | E2: DECLARE | F2: DATE | G2: CLIENT | H2: INV | I2: DISBURSEMENT | J2: DN | K2: DATE | L2: EXCHANGE RATE | M2: weekday | N2: CLEAR FEE | O2: THC | P2: CM | Q2: INV (REVENUE) | R2: REIM | S2: VAT 10% | T2: DN | U2: NET PROFIT | V2: MARK
A3: PAID | B3: 1 | C3: =INDEX(PORT!$B$2:$B$20,MATCH('02'!B3,PORT!$A$2:$A$20)) -> PNH01 | D3: =INDEX(PORT!$C$2:$C$20,MATCH('02'!B3,PORT!$A$2:$A$20)) -> KTI AIR PORT | E3: I 3370 | F3: 46055 | G3: JIN YUAN XI | H3: GS26-037 | I3: DIS039 | J3: JYX2602001 | K3: 46056 | L3: =VLOOKUP(K3,'[1]Exchange Rate'!$A$3:$C$15,3,FALSE) -> 4031 | M3: =TEXT(K3,"dddd") -> Tuesday | N3: 312.14 | P3: 50 | Q3: 185 | R3: 117.14 | S3: =ROUND(Q3*10%,2) -> 18.5 | T3: 195 | U3: =(Q3+R3+T3)-(N3+O3+P3) -> 135
A4: PAID | B4: 21 | C4: =INDEX(PORT!$B$2:$B$20,MATCH('02'!B4,PORT!$A$2:$A$20)) -> PNH21 | D4: =INDEX(PORT!$C$2:$C$20,MATCH('02'!B4,PORT!$A$2:$A$20)) -> OLAIR DRY PORT | E4: I 491 | F4: 46055 | G4: SPORTLINE | H4: GS26-038 | I4: DIS040 | J4: SAK2602001 | K4: 46056 | L4: =VLOOKUP(K4,'[1]Exchange Rate'!$A$3:$C$15,3,FALSE) -> 4031 | M4: =TEXT(K4,"dddd") -> Tuesday | N4: 154.34 | O4: 344.43 | P4: 50 | Q4: 150 | R4: 39.34 | S4: =ROUND(Q4*10%,2) -> 15 | T4: 145 | U4: =(Q4+R4+T4)-(N4+P4) -> 130
A5: PAID | B5: 1 | C5: =INDEX(PORT!$B$2:$B$20,MATCH('02'!B5,PORT!$A$2:$A$20)) -> PNH01 | D5: =INDEX(PORT!$C$2:$C$20,MATCH('02'!B5,PORT!$A$2:$A$20)) -> KTI AIR PORT | E5: I 3378 | F5: 46055 | G5: SPORTLINE | H5: GS26-039 | I5: DIS041 | J5: SAK2602002 | K5: 46056 | L5: =VLOOKUP(K5,'[1]Exchange Rate'!$A$3:$C$15,3,FALSE) -> 4031 | M5: =TEXT(K5,"dddd") -> Tuesday | N5: 174.38 | O5: 60.5 | P5: 50 | Q5: 150 | R5: 84.88 | S5: =ROUND(Q5*10%,2) -> 15 | T5: 165 | U5: =(Q5+R5+T5)-(N5+O5+P5) -> 115
A6: PAID | B6: 1 | C6: =INDEX(PORT!$B$2:$B$20,MATCH('02'!B6,PORT!$A$2:$A$20)) -> PNH01 | D6: =INDEX(PORT!$C$2:$C$20,MATCH('02'!B6,PORT!$A$2:$A$20)) -> KTI AIR PORT | E6: E 5316 | F6: 46057 | G6: VFL | H6: GS26-040 | I6: DIS042 | J6: VFL2602001 | K6: 46058 | L6: =VLOOKUP(K6,'[1]Exchange Rate'!$A$3:$C$15,3,FALSE) -> 4033 | M6: =TEXT(K6,"dddd") -> Thursday | N6: 104.43 | O6: 0 | P6: 50 | Q6: 140 | R6: 34.43 | S6: =ROUND(Q6*10%,2) -> 14 | T6: 60 | U6: =(Q6+R6+T6)-(N6+O6+P6) -> 80
A7: PAID | B7: 19 | C7: =INDEX(PORT!$B$2:$B$20,MATCH('02'!B7,PORT!$A$2:$A$20)) -> PNH19 | D7: =INDEX(PORT!$C$2:$C$20,MATCH('02'!B7,PORT!$A$2:$A$20)) -> TEC SRUN DRYPORT | E7: I 420 | F7: 46057 | G7: VFL | H7: GS26-041 | I7: DIS043 | J7: VFL2602002 | K7: 46058 | L7: =VLOOKUP(K7,'[1]Exchange Rate'!$A$3:$C$15,3,FALSE) -> 4033 | M7: =TEXT(K7,"dddd") -> Thursday | N7: 111.1 | O7: 204.97 | P7: 50 | Q7: 150 | R7: 231.07 | S7: =ROUND(Q7*10%,2) -> 15 | T7: 90 | U7: =(Q7+R7+T7)-(N7+O7+P7) -> 105
A8: PAID | B8: 19 | C8: =INDEX(PORT!$B$2:$B$20,MATCH('02'!B8,PORT!$A$2:$A$20)) -> PNH19 | D8: =INDEX(PORT!$C$2:$C$20,MATCH('02'!B8,PORT!$A$2:$A$20)) -> TEC SRUN DRYPORT | E8: I 421 | F8: 46057 | G8: SPORTLINE | H8: GS26-042 | I8: DIS044 | J8: SAK2602003 | K8: 46058 | L8: =VLOOKUP(K8,'[1]Exchange Rate'!$A$3:$C$15,3,FALSE) -> 4033 | M8: =TEXT(K8,"dddd") -> Thursday | N8: 160.06 | O8: 403.19 | P8: 50 | Q8: 150 | R8: 448.25 | S8: =ROUND(Q8*10%,2) -> 15 | T8: 145 | U8: =(Q8+R8+T8)-(N8+O8+P8) -> 130
A9: PAID | B9: 1 | C9: =INDEX(PORT!$B$2:$B$20,MATCH('02'!B9,PORT!$A$2:$A$20)) -> PNH01 | D9: =INDEX(PORT!$C$2:$C$20,MATCH('02'!B9,PORT!$A$2:$A$20)) -> KTI AIR PORT | E9: E 5458 | F9: 46058 | G9: VFL | H9: GS26-043 | I9: DIS045 | J9: VFL2602003 | K9: 46059 | L9: =VLOOKUP(K9,'[1]Exchange Rate'!$A$3:$C$15,3,FALSE) -> 4033 | M9: =TEXT(K9,"dddd") -> Friday | N9: 83.75 | O9: 0 | P9: 50 | Q9: 140 | R9: 2 | S9: =ROUND(Q9*10%,2) -> 14 | T9: 71.75 | U9: =(Q9+R9+T9)-(N9+O9+P9) -> 80
A10: PAID | B10: 1 | C10: =INDEX(PORT!$B$2:$B$20,MATCH('02'!B10,PORT!$A$2:$A$20)) -> PNH01 | D10: =INDEX(PORT!$C$2:$C$20,MATCH('02'!B10,PORT!$A$2:$A$20)) -> KTI AIR PORT | E10: E 5466 | F10: 46058 | G10: VFL | H10: GS26-044 | I10: DIS046 | J10: VFL2602004 | K10: 46059 | L10: =VLOOKUP(K10,'[1]Exchange Rate'!$A$3:$C$15,3,FALSE) -> 4033 | M10: =TEXT(K10,"dddd") -> Friday | N10: 88.24 | O10: 0 | P10: 50 | Q10: 140 | R10: 18.24 | S10: =ROUND(Q10*10%,2) -> 14 | T10: 60 | U10: =(Q10+R10+T10)-(N10+O10+P10) -> 80
A11: PAID | B11: 1 | C11: =INDEX(PORT!$B$2:$B$20,MATCH('02'!B11,PORT!$A$2:$A$20)) -> PNH01 | D11: =INDEX(PORT!$C$2:$C$20,MATCH('02'!B11,PORT!$A$2:$A$20)) -> KTI AIR PORT | E11: E 5467 | F11: 46058 | G11: JIN YUAN XI | H11: GS26-045 | I11: DIS047 | J11: JYX2602002 | K11: 46059 | L11: =VLOOKUP(K11,'[1]Exchange Rate'!$A$3:$C$15,3,FALSE) -> 4033 | M11: =TEXT(K11,"dddd") -> Friday | N11: 182.24 | O11: 0 | P11: 50 | Q11: 175 | R11: 62.24 | S11: =ROUND(Q11*10%,2) -> 17.5 | T11: 180 | U11: =(Q11+R11+T11)-(N11+O11+P11) -> 185
A12: PAID | B12: 1 | C12: =INDEX(PORT!$B$2:$B$20,MATCH('02'!B12,PORT!$A$2:$A$20)) -> PNH01 | D12: =INDEX(PORT!$C$2:$C$20,MATCH('02'!B12,PORT!$A$2:$A$20)) -> KTI AIR PORT | E12: I 3813 | F12: 46058 | G12: JIN YUAN XI | H12: GS26-046 | I12: DIS048 | J12: JYX2602003 | K12: 46059 | L12: =VLOOKUP(K12,'[1]Exchange Rate'!$A$3:$C$15,3,FALSE) -> 4033 | M12: =TEXT(K12,"dddd") -> Friday | N12: 288.02 | O12: 0 | P12: 50 | Q12: 165 | R12: 93.02 | S12: =ROUND(Q12*10%,2) -> 16.5 | T12: 195 | U12: =(Q12+R12+T12)-(N12+O12+P12) -> 115
A13: PAID | B13: 4 | C13: =INDEX(PORT!$B$2:$B$20,MATCH('02'!B13,PORT!$A$2:$A$20)) -> PNH04 | D13: =INDEX(PORT!$C$2:$C$20,MATCH('02'!B13,PORT!$A$2:$A$20)) -> PNH PORT | E13: E 35089 | F13: 46058 | G13: SPORTLINE | H13: GS26-047 | I13: DIS049 | J13: SAK2602004 | K13: 46059 | L13: =VLOOKUP(K13,'[1]Exchange Rate'!$A$3:$C$15,3,FALSE) -> 4033 | M13: =TEXT(K13,"dddd") -> Friday | N13: 495.75 | O13: 0 | P13: 50 | Q13: 245 | R13: 135.75 | S13: =ROUND(Q13*10%,2) -> 24.5 | T13: 405 | U13: =(Q13+R13+T13)-(N13+O13+P13) -> 240
A14: PAID | B14: 11 | C14: =INDEX(PORT!$B$2:$B$20,MATCH('02'!B14,PORT!$A$2:$A$20)) -> SHV11 | D14: =INDEX(PORT!$C$2:$C$20,MATCH('02'!B14,PORT!$A$2:$A$20)) -> SHV PORT | E14: I 21065 | F14: 46062 | G14: JR | H14: GS26-048 | I14: DIS050 | J14: JR2602001 | K14: 46063 | L14: =VLOOKUP(K14,'[1]Exchange Rate'!$A$3:$C$15,3,FALSE) -> 4031 | M14: =TEXT(K14,"dddd") -> Tuesday | N14: 569.45 | O14: 691.5 | P14: 5 | Q14: 200 | R14: 805.95 | S14: =ROUND(Q14*10%,2) -> 20 | T14: 605 | U14: =(Q14+R14+T14)-(N14+O14+P14) -> 345
G15: JR | J15: JR2602002 | K15: 46070 | M15: =TEXT(K15,"dddd") -> Tuesday | N15: 120 | O15: 0 | P15: 0 | T15: 120 | U15: =(Q15+R15+T15)-(N15+O15+P15) -> 0
A16: PAID | B16: 1 | C16: =INDEX(PORT!$B$2:$B$20,MATCH('02'!B16,PORT!$A$2:$A$20)) -> PNH01 | D16: =INDEX(PORT!$C$2:$C$20,MATCH('02'!B16,PORT!$A$2:$A$20)) -> KTI AIR PORT | E16: I 4343 | F16: 46063 | G16: VFL | H16: GS26-049 | I16: DIS051 | J16: VFL2602005 | K16: 46064 | L16: =VLOOKUP(K16,'[1]Exchange Rate'!$A$3:$C$15,3,FALSE) -> 4029 | M16: =TEXT(K16,"dddd") -> Wednesday | N16: 151.92 | O16: 60.5 | P16: 50 | Q16: 150 | R16: 82.42 | S16: =ROUND(Q16*10%,2) -> 15 | T16: 95 | U16: =(Q16+R16+T16)-(N16+O16+P16) -> 65
A17: PAID | B17: 1 | C17: =INDEX(PORT!$B$2:$B$20,MATCH('02'!B17,PORT!$A$2:$A$20)) -> PNH01 | D17: =INDEX(PORT!$C$2:$C$20,MATCH('02'!B17,PORT!$A$2:$A$20)) -> KTI AIR PORT | E17: E 6104 | F17: 46063 | G17: JIN YUAN XI | H17: GS26-050 | I17: DIS052 | J17: JYX2602004 | K17: 46064 | L17: =VLOOKUP(K17,'[1]Exchange Rate'!$A$3:$C$15,3,FALSE) -> 4029 | M17: =TEXT(K17,"dddd") -> Wednesday | N17: 86.48 | O17: 0 | P17: 50 | Q17: 140 | R17: 16.48 | S17: =ROUND(Q17*10%,2) -> 14 | T17: 60 | U17: =(Q17+R17+T17)-(N17+O17+P17) -> 80
A18: PAID | B18: 21 | C18: =INDEX(PORT!$B$2:$B$20,MATCH('02'!B18,PORT!$A$2:$A$20)) -> PNH21 | D18: =INDEX(PORT!$C$2:$C$20,MATCH('02'!B18,PORT!$A$2:$A$20)) -> OLAIR DRY PORT | E18: I 588 | F18: 46063 | G18: SPORTLINE | H18: GS26-051 | I18: DIS053 | J18: SAK2602005 | K18: 46064 | L18: =VLOOKUP(K18,'[1]Exchange Rate'!$A$3:$C$15,3,FALSE) -> 4029 | M18: =TEXT(K18,"dddd") -> Wednesday | N18: 232.82 | O18: 549.18 | P18: 50 | Q18: 150 | R18: 632 | S18: =ROUND(Q18*10%,2) -> 15 | T18: 180 | U18: =(Q18+R18+T18)-(N18+O18+P18) -> 130
A19: PAID | B19: 21 | C19: =INDEX(PORT!$B$2:$B$20,MATCH('02'!B19,PORT!$A$2:$A$20)) -> PNH21 | D19: =INDEX(PORT!$C$2:$C$20,MATCH('02'!B19,PORT!$A$2:$A$20)) -> OLAIR DRY PORT | E19: I 586 | F19: 46063 | G19: VFL | H19: GS26-052 | I19: DIS054 | J19: VFL2602006 | K19: 46064 | L19: =VLOOKUP(K19,'[1]Exchange Rate'!$A$3:$C$15,3,FALSE) -> 4029 | M19: =TEXT(K19,"dddd") -> Wednesday | N19: 218.88 | O19: 647.63 | P19: 50 | Q19: 150 | R19: 746.51 | S19: =ROUND(Q19*10%,2) -> 15 | T19: 150 | U19: =(Q19+R19+T19)-(N19+O19+P19) -> 130
A20: PAID | B20: 1 | C20: =INDEX(PORT!$B$2:$B$20,MATCH('02'!B20,PORT!$A$2:$A$20)) -> PNH01 | D20: =INDEX(PORT!$C$2:$C$20,MATCH('02'!B20,PORT!$A$2:$A$20)) -> KTI AIR PORT | E20: E 6539 | F20: 46066 | G20: JIN YUAN XI | H20: GS26-053 | I20: DIS055 | J20: JYX2602005 | K20: 46069 | L20: =VLOOKUP(K20,'[1]Exchange Rate'!$A$3:$C$15,3,FALSE) -> 4023 | M20: =TEXT(K20,"dddd") -> Monday | N20: 135.67 | O20: 0 | P20: 50 | Q20: 175 | R20: 65.67 | S20: =ROUND(Q20*10%,2) -> 17.5 | T20: 60 | U20: =(Q20+R20+T20)-(N20+O20+P20) -> 115
A21: PAID | B21: 1 | C21: =INDEX(PORT!$B$2:$B$20,MATCH('02'!B21,PORT!$A$2:$A$20)) -> PNH01 | D21: =INDEX(PORT!$C$2:$C$20,MATCH('02'!B21,PORT!$A$2:$A$20)) -> KTI AIR PORT | E21: E 6710 | F21: 46067 | G21: JIN YUAN XI | H21: GS26-054 | I21: DIS056 | J21: JYX2602006 | K21: 46069 | L21: =VLOOKUP(K21,'[1]Exchange Rate'!$A$3:$C$15,3,FALSE) -> 4023 | M21: =TEXT(K21,"dddd") -> Monday | N21: 330.33 | O21: 0 | P21: 50 | Q21: 210 | R21: 260.33 | S21: =ROUND(Q21*10%,2) -> 21 | T21: 60 | U21: =(Q21+R21+T21)-(N21+O21+P21) -> 150
A22: PAID | B22: 11 | C22: =INDEX(PORT!$B$2:$B$20,MATCH('02'!B22,PORT!$A$2:$A$20)) -> SHV11 | D22: =INDEX(PORT!$C$2:$C$20,MATCH('02'!B22,PORT!$A$2:$A$20)) -> SHV PORT | E22: I 26265 | F22: 46071 | G22: VFL | H22: GS26-055 | I22: DIS057 | J22: VFL2602007 | K22: 46072 | L22: =VLOOKUP(K22,'[2]Exchange Rate'!$A$3:$C$23,3,FALSE) -> 4022 | M22: =TEXT(K22,"dddd") -> Thursday | N22: 217.45 | O22: 488.4 | P22: 50 | Q22: 150 | R22: 512.25 | S22: =ROUND(Q22*10%,2) -> 15 | T22: 177.54 | U22: =(Q22+R22+T22)-(N22+O22+P22) -> 83.94
A23: PAID | B23: 11 | C23: =INDEX(PORT!$B$2:$B$20,MATCH('02'!B23,PORT!$A$2:$A$20)) -> SHV11 | D23: =INDEX(PORT!$C$2:$C$20,MATCH('02'!B23,PORT!$A$2:$A$20)) -> SHV PORT | E23: I 26270 | F23: 46071 | G23: VFL | H23: GS26-056 | I23: DIS058 | J23: VFL2602008 | K23: 46072 | L23: =VLOOKUP(K23,'[2]Exchange Rate'!$A$3:$C$23,3,FALSE) -> 4022 | M23: =TEXT(K23,"dddd") -> Thursday | N23: 158.57 | O23: 321.41 | P23: 50 | Q23: 150 | R23: 338.53 | S23: =ROUND(Q23*10%,2) -> 15 | T23: 97.9 | U23: =(Q23+R23+T23)-(N23+O23+P23) -> 56.45
A24: PAID | B24: 23 | C24: =INDEX(PORT!$B$2:$B$20,MATCH('02'!B24,PORT!$A$2:$A$20)) -> PNH23 | D24: =INDEX(PORT!$C$2:$C$20,MATCH('02'!B24,PORT!$A$2:$A$20)) -> UNION DRY PORT | E24: I 123 | F24: 46071 | G24: JIN YUAN XI | H24: GS26-057 | I24: DIS059 | J24: JYX2602007 | K24: 46072 | L24: =VLOOKUP(K24,'[2]Exchange Rate'!$A$3:$C$23,3,FALSE) -> 4022 | M24: =TEXT(K24,"dddd") -> Thursday | N24: 329.75 | O24: 546.26 | P24: 50 | Q24: 150 | R24: 651.01 | S24: =ROUND(Q24*10%,2) -> 15 | T24: 295 | U24: =(Q24+R24+T24)-(N24+O24+P24) -> 170
A25: PAID | B25: 11 | C25: =INDEX(PORT!$B$2:$B$20,MATCH('02'!B25,PORT!$A$2:$A$20)) -> SHV11 | D25: =INDEX(PORT!$C$2:$C$20,MATCH('02'!B25,PORT!$A$2:$A$20)) -> SHV PORT | E25: I 26260 | F25: 46071 | G25: SPORTLINE | H25: GS26-058 | I25: DIS060 | J25: SAK2602006 | K25: 46072 | L25: =VLOOKUP(K25,'[2]Exchange Rate'!$A$3:$C$23,3,FALSE) -> 4022 | M25: =TEXT(K25,"dddd") -> Thursday | N25: 230.25 | O25: 553.08 | P25: 50 | Q25: 150 | R25: 573.56 | S25: =ROUND(Q25*10%,2) -> 15 | T25: 241.05 | U25: =(Q25+R25+T25)-(N25+O25+P25) -> 131.28
A26: PAID | B26: 1 | C26: =INDEX(PORT!$B$2:$B$20,MATCH('02'!B26,PORT!$A$2:$A$20)) -> PNH01 | D26: =INDEX(PORT!$C$2:$C$20,MATCH('02'!B26,PORT!$A$2:$A$20)) -> KTI AIR PORT | E26: E 7265 | F26: 46072 | G26: JIN YUAN XI | H26: GS26-059 | I26: DIS061 | J26: JYX2602008 | K26: 46073 | L26: =VLOOKUP(K26,'[2]Exchange Rate'!$A$3:$C$23,3,FALSE) -> 4021 | M26: =TEXT(K26,"dddd") -> Friday | N26: 151.42 | O26: 0 | P26: 50 | Q26: 175 | R26: 81.42 | S26: =ROUND(Q26*10%,2) -> 17.5 | T26: 60 | U26: =(Q26+R26+T26)-(N26+O26+P26) -> 115
A27: PAID | B27: 11 | C27: =INDEX(PORT!$B$2:$B$20,MATCH('02'!B27,PORT!$A$2:$A$20)) -> SHV11 | D27: =INDEX(PORT!$C$2:$C$20,MATCH('02'!B27,PORT!$A$2:$A$20)) -> SHV PORT | E27: E 51647 | F27: 46073 | G27: JIN YUAN XI | H27: GS26-060 | I27: DIS062 | J27: JYX2602009 | K27: 46076 | L27: =VLOOKUP(K27,'[2]Exchange Rate'!$A$3:$C$23,3,FALSE) -> 4017 | M27: =TEXT(K27,"dddd") -> Monday | N27: 417.7 | O27: 0 | P27: 50 | Q27: 245 | R27: 87.7 | S27: =ROUND(Q27*10%,2) -> 24.5 | T27: 362.5 | U27: =(Q27+R27+T27)-(N27+O27+P27) -> 227.5
A28: PAID | B28: 11 | C28: =INDEX(PORT!$B$2:$B$20,MATCH('02'!B28,PORT!$A$2:$A$20)) -> SHV11 | D28: =INDEX(PORT!$C$2:$C$20,MATCH('02'!B28,PORT!$A$2:$A$20)) -> SHV PORT | E28: E 51619 | F28: 46073 | G28: JIN YUAN XI | H28: PART | S28: =ROUND(Q28*10%,2) -> 0 | U28: =(Q28+R28+T28)-(N28+O28+P28) -> 0
A29: PAID | B29: 11 | C29: =INDEX(PORT!$B$2:$B$20,MATCH('02'!B29,PORT!$A$2:$A$20)) -> SHV11 | D29: =INDEX(PORT!$C$2:$C$20,MATCH('02'!B29,PORT!$A$2:$A$20)) -> SHV PORT | E29: E 52971 | F29: 46073 | G29: JR | H29: GS26-061 | I29: DIS063 | J29: JR2602002 | K29: 46076 | L29: =VLOOKUP(K29,'[2]Exchange Rate'!$A$3:$C$23,3,FALSE) -> 4017 | M29: =TEXT(K29,"dddd") -> Monday | N29: 444.75 | O29: 0 | P29: 5 | Q29: 215 | R29: 64.75 | S29: =ROUND(Q29*10%,2) -> 21.5 | T29: 529 | U29: =(Q29+R29+T29)-(N29+O29+P29) -> 359
A30: PAID | B30: 11 | C30: =INDEX(PORT!$B$2:$B$20,MATCH('02'!B30,PORT!$A$2:$A$20)) -> SHV11 | D30: =INDEX(PORT!$C$2:$C$20,MATCH('02'!B30,PORT!$A$2:$A$20)) -> SHV PORT | E30: I 27779 | F30: 46073 | G30: JR | H30: GS26-062 | I30: DIS064 | J30: JR2602003 | K30: 46076 | L30: =VLOOKUP(K30,'[2]Exchange Rate'!$A$3:$C$23,3,FALSE) -> 4017 | M30: =TEXT(K30,"dddd") -> Monday | N30: 589.45 | O30: 691.5 | P30: 5 | Q30: 200 | R30: 805.95 | S30: =ROUND(Q30*10%,2) -> 20 | T30: 760 | U30: =(Q30+R30+T30)-(N30+O30+P30) -> 480
A31: PAID | B31: 1 | C31: =INDEX(PORT!$B$2:$B$20,MATCH('02'!B31,PORT!$A$2:$A$20)) -> PNH01 | D31: =INDEX(PORT!$C$2:$C$20,MATCH('02'!B31,PORT!$A$2:$A$20)) -> KTI AIR PORT | E31: E 7615 | F31: 46076 | G31: JIN YUAN XI | H31: GS26-063 | I31: DIS065 | J31: JYX2602010 | K31: 46077 | L31: =VLOOKUP(K31,'[2]Exchange Rate'!$A$3:$C$23,3,FALSE) -> 4017 | M31: =TEXT(K31,"dddd") -> Tuesday | N31: 126.08 | O31: 0 | P31: 50 | Q31: 150 | R31: 56.08 | S31: =ROUND(Q31*10%,2) -> 15 | T31: 60 | U31: =(Q31+R31+T31)-(N31+O31+P31) -> 90
A32: PAID | B32: 1 | C32: =INDEX(PORT!$B$2:$B$20,MATCH('02'!B32,PORT!$A$2:$A$20)) -> PNH01 | D32: =INDEX(PORT!$C$2:$C$20,MATCH('02'!B32,PORT!$A$2:$A$20)) -> KTI AIR PORT | E32: E 7616 | F32: 46076 | G32: JIN YUAN XI | H32: GS26-064 | I32: DIS066 | J32: JYX2602011 | K32: 46077 | L32: =VLOOKUP(K32,'[2]Exchange Rate'!$A$3:$C$23,3,FALSE) -> 4017 | M32: =TEXT(K32,"dddd") -> Tuesday | N32: 167 | O32: 0 | P32: 50 | Q32: 175 | R32: 97 | S32: =ROUND(Q32*10%,2) -> 17.5 | T32: 60 | U32: =(Q32+R32+T32)-(N32+O32+P32) -> 115
A33: PAID | B33: 11 | C33: =INDEX(PORT!$B$2:$B$20,MATCH('02'!B33,PORT!$A$2:$A$20)) -> SHV11 | D33: =INDEX(PORT!$C$2:$C$20,MATCH('02'!B33,PORT!$A$2:$A$20)) -> SHV PORT | E33: I 32157 | F33: 46081 | G33: VFL | H33: GS26-069 | I33: DIS071 | J33: VFL2602009 | K33: 46081 | L33: =VLOOKUP(K33,'[2]Exchange Rate'!$A$3:$C$23,3,FALSE) -> 4010 | M33: =TEXT(K33,"dddd") -> Saturday | N33: 179.23 | O33: 335.72 | P33: 50 | Q33: 150 | R33: 354.52 | S33: =ROUND(Q33*10%,2) -> 15 | T33: 116.95 | U33: =(Q33+R33+T33)-(N33+O33+P33) -> 56.52
A34: PAID | B34: 4 | C34: =INDEX(PORT!$B$2:$B$20,MATCH('02'!B34,PORT!$A$2:$A$20)) -> PNH04 | D34: =INDEX(PORT!$C$2:$C$20,MATCH('02'!B34,PORT!$A$2:$A$20)) -> PNH PORT | E34: E 58276 | F34: 46080 | G34: VFL | H34: GS26-071 | I34: DIS073 | J34: VFL2602010 | K34: 46081 | L34: =VLOOKUP(K34,'[2]Exchange Rate'!$A$3:$C$23,3,FALSE) -> 4010 | M34: =TEXT(K34,"dddd") -> Saturday | N34: 359.85 | O34: 0 | P34: 50 | Q34: 215 | R34: 94.85 | S34: =ROUND(Q34*10%,2) -> 21.5 | T34: 255 | U34: =(Q34+R34+T34)-(N34+O34+P34) -> 155
A35: PAID | B35: 4 | C35: =INDEX(PORT!$B$2:$B$20,MATCH('02'!B35,PORT!$A$2:$A$20)) -> PNH04 | D35: =INDEX(PORT!$C$2:$C$20,MATCH('02'!B35,PORT!$A$2:$A$20)) -> PNH PORT | E35: E 55816 | F35: 46080 | G35: SPORTLINE | H35: GS26-067 | I35: DIS069 | J35: SAK2602007 | K35: 46081 | L35: =VLOOKUP(K35,'[2]Exchange Rate'!$A$3:$C$23,3,FALSE) -> 4010 | M35: =TEXT(K35,"dddd") -> Saturday | N35: 930.26 | O35: 0 | P35: 50 | Q35: 490 | R35: 260.26 | S35: =ROUND(Q35*10%,2) -> 49 | T35: 739 | U35: =(Q35+R35+T35)-(N35+O35+P35) -> 509
A36: PAID | B36: 4 | C36: =INDEX(PORT!$B$2:$B$20,MATCH('02'!B36,PORT!$A$2:$A$20)) -> PNH04 | D36: =INDEX(PORT!$C$2:$C$20,MATCH('02'!B36,PORT!$A$2:$A$20)) -> PNH PORT | E36: E 58393 | F36: 46080 | G36: JR | H36: GS26-068 | I36: DIS070 | J36: JR2602004 | K36: 46081 | L36: =VLOOKUP(K36,'[2]Exchange Rate'!$A$3:$C$23,3,FALSE) -> 4010 | M36: =TEXT(K36,"dddd") -> Saturday | N36: 480.75 | O36: 0 | P36: 5 | Q36: 242 | R36: 135.75 | S36: =ROUND(Q36*10%,2) -> 24.2 | T36: 449 | U36: =(Q36+R36+T36)-(N36+O36+P36) -> 341
A37: PAID | B37: 11 | C37: =INDEX(PORT!$B$2:$B$20,MATCH('02'!B37,PORT!$A$2:$A$20)) -> SHV11 | D37: =INDEX(PORT!$C$2:$C$20,MATCH('02'!B37,PORT!$A$2:$A$20)) -> SHV PORT | E37: I 32164 | F37: 46081 | G37: SPORTLINE | H37: GS26-070 | I37: DIS072 | J37: SAK2602008 | K37: 46081 | L37: =VLOOKUP(K37,'[2]Exchange Rate'!$A$3:$C$23,3,FALSE) -> 4010 | M37: =TEXT(K37,"dddd") -> Saturday | N37: 246.18 | O37: 295.24 | P37: 50 | Q37: 150 | R37: 326.11 | S37: =ROUND(Q37*10%,2) -> 15 | T37: 210.15 | U37: =(Q37+R37+T37)-(N37+O37+P37) -> 94.84
A38: PAID | B38: 11 | C38: =INDEX(PORT!$B$2:$B$20,MATCH('02'!B38,PORT!$A$2:$A$20)) -> SHV11 | D38: =INDEX(PORT!$C$2:$C$20,MATCH('02'!B38,PORT!$A$2:$A$20)) -> SHV PORT | E38: I 32162 | F38: 46081 | G38: SPORTLINE | H38: PART | S38: =ROUND(Q38*10%,2) -> 0 | U38: =(Q38+R38+T38)-(N38+O38+P38) -> 0
A39: PAID | B39: 11 | C39: SHV11 | D39: SHV PORT | E39: I 30715 | F39: 46078 | G39: JIN YUAN XI | H39: GS26-065 | I39: DIS067 | J39: JYX2602012 | K39: 46079 | L39: 4011 | M39: =TEXT(K39,"dddd") -> Thursday | N39: 163.75 | P39: 50 | Q39: 150 | R39: 314.75 | S39: =ROUND(Q39*10%,2) -> 15 | T39: 100 | U39: =(Q39+R39+T39)-(N39+O39+P39) -> 351
A40: PAID | B40: 1 | C40: =INDEX(PORT!$B$2:$B$20,MATCH('02'!B40,PORT!$A$2:$A$20)) -> PNH01 | D40: =INDEX(PORT!$C$2:$C$20,MATCH('02'!B40,PORT!$A$2:$A$20)) -> KTI AIR PORT | E40: E 8171 | F40: 46079 | G40: JIN YUAN XI | H40: GS26-066 | I40: DIS068 | J40: JYX2602013 | K40: 46081 | L40: =VLOOKUP(K40,'[2]Exchange Rate'!$A$3:$C$23,3,FALSE) -> 4010 | M40: =TEXT(K40,"dddd") -> Saturday | N40: 181.78 | O40: 0 | P40: 50 | Q40: 210 | R40: 111.78 | S40: =ROUND(Q40*10%,2) -> 21 | T40: 180 | U40: =(Q40+R40+T40)-(N40+O40+P40) -> 270
E41: LOLO
E42: STORAGE
E43: THC
B45: =SUBTOTAL(3,B3:B44) -> 37 | E45: TOTAL: | H45: =SUBTOTAL(3,H3:H44) -> 37 | I45: =SUBTOTAL(3,I3:I44) -> 35 | J45: =SUBTOTAL(3,J3:J44) -> 36 | N45: =SUBTOTAL(9,N3:N39) -> 9192.44 | O45: =SUBTOTAL(9,O3:O39) -> 6193.51 | P45: =SUBTOTAL(9,P3:P39) -> 1520 | Q45: =SUBTOTAL(9,Q3:Q40) -> 6332 | R45: =SUBTOTAL(9,R3:R40) -> 8741.99 | S45: =SUBTOTAL(9,S3:S40) -> 633.2 | T45: =SUBTOTAL(9,T3:T40) -> 7734.84 | U45: =SUBTOTAL(9,U3:U43) -> 6015.53
M46: PAID | N46: =SUMIFS($N$3:$N$40,$A$3:$A$40,$M$46) -> 9254.22
M47: NOT YET | N47: =SUMIFS($N$3:$N$40,$A$3:$A$40,$M$47) -> 0
K49: Lack | L49: $ 0.31 | O49: Shipment VFl (I 342) from Last Month
K50: Should pay | L50: 3,880.31
K51: Paid | L51: 3,880.31 | N51: 46074

Sheet 03
E1: REVENUE & EXPENSE | M1: Saturday
A2: CHEA PAYMENT | B2: PORT NUMBER | C2: PORT CODE | D2: PORT NAME | E2: DECLARE | F2: DATE | G2: CLIENT | H2: INV | I2: DISBURSEMENT | J2: DN | K2: DATE | L2: EXCHANGE RATE | M2: weekday | N2: CLEAR FEE | O2: THC | P2: CM | Q2: INV (REVENUE) | R2: REIM | S2: VAT 10% | T2: DN | U2: NET PROFIT | V2: MARK
A3: PAID | B3: 1 | C3: =INDEX(PORT!$B$2:$B$20,MATCH('03'!B3,PORT!$A$2:$A$20)) -> PNH01 | D3: =INDEX(PORT!$C$2:$C$20,MATCH('03'!B3,PORT!$A$2:$A$20)) -> KTI AIR PORT | E3: E 8725 | F3: 46083 | G3: VFL | H3: GS26-072 | I3: DIS074 | J3: VFL2603001 | K3: 46084 | L3: =VLOOKUP(K3,'[3]Exchange Rate'!$A$3:$C$24,3,FALSE) -> 4013 | M3: =TEXT(K3,"dddd") -> Tuesday | N3: 83.75 | O3: 0 | P3: 50 | Q3: 140 | R3: 13.75 | S3: =ROUND(Q3*10%,2) -> 14 | T3: 60 | U3: =(Q3+R3+T3)-(N3+O3+P3) -> 80
A4: PAID | B4: 1 | C4: =INDEX(PORT!$B$2:$B$20,MATCH('03'!B4,PORT!$A$2:$A$20)) -> PNH01 | D4: =INDEX(PORT!$C$2:$C$20,MATCH('03'!B4,PORT!$A$2:$A$20)) -> KTI AIR PORT | E4: E 8729 | F4: 46083 | G4: VFL | H4: GS26-073 | I4: DIS075 | J4: VFL2603002 | K4: 46084 | L4: =VLOOKUP(K4,'[3]Exchange Rate'!$A$3:$C$24,3,FALSE) -> 4013 | M4: =TEXT(K4,"dddd") -> Tuesday | N4: 83.75 | O4: 0 | P4: 50 | Q4: 140 | R4: 13.75 | S4: =ROUND(Q4*10%,2) -> 14 | T4: 60 | U4: =(Q4+R4+T4)-(N4+O4+P4) -> 80
A5: PAID | B5: 11 | C5: =INDEX(PORT!$B$2:$B$20,MATCH('03'!B5,PORT!$A$2:$A$20)) -> SHV11 | D5: =INDEX(PORT!$C$2:$C$20,MATCH('03'!B5,PORT!$A$2:$A$20)) -> SHV PORT | E5: I 32408 | F5: 46083 | G5: JR | H5: GS26-074 | I5: DIS076 | J5: JR2603001 | K5: 46084 | L5: =VLOOKUP(K5,'[3]Exchange Rate'!$A$3:$C$24,3,FALSE) -> 4013 | M5: =TEXT(K5,"dddd") -> Tuesday | N5: 569.45 | O5: 691.5 | P5: 0 | Q5: 200 | R5: 805.95 | S5: =ROUND(Q5*10%,2) -> 20 | T5: 585 | U5: =(Q5+R5+T5)-(N5+O5+P5) -> 330
A6: PAID | B6: 11 | C6: =INDEX(PORT!$B$2:$B$20,MATCH('03'!B6,PORT!$A$2:$A$20)) -> SHV11 | D6: =INDEX(PORT!$C$2:$C$20,MATCH('03'!B6,PORT!$A$2:$A$20)) -> SHV PORT | E6: I 32429 | F6: 46083 | G6: JR | H6: GS26-075 | I6: DIS077 | J6: JR2603002 | K6: 46084 | L6: =VLOOKUP(K6,'[3]Exchange Rate'!$A$3:$C$24,3,FALSE) -> 4013 | M6: =TEXT(K6,"dddd") -> Tuesday | N6: 526.45 | O6: 476.5 | P6: 0 | Q6: 180 | R6: 557.95 | S6: =ROUND(Q6*10%,2) -> 18 | T6: 485 | U6: =(Q6+R6+T6)-(N6+O6+P6) -> 220
A7: PAID | B7: 1 | C7: =INDEX(PORT!$B$2:$B$20,MATCH('03'!B7,PORT!$A$2:$A$20)) -> PNH01 | D7: =INDEX(PORT!$C$2:$C$20,MATCH('03'!B7,PORT!$A$2:$A$20)) -> KTI AIR PORT | E7: E 9314 | F7: 46088 | G7: VFL | H7: GS26-076 | I7: DIS078 | J7: VFL2603003 | K7: 46090 | L7: =VLOOKUP(K7,'[3]Exchange Rate'!$A$3:$C$24,3,FALSE) -> 4013 | M7: =TEXT(K7,"dddd") -> Monday | N7: 83.75 | O7: 0 | P7: 50 | Q7: 140 | R7: 13.75 | S7: =ROUND(Q7*10%,2) -> 14 | T7: 60 | U7: =(Q7+R7+T7)-(N7+O7+P7) -> 80
A8: PAID | B8: 1 | C8: =INDEX(PORT!$B$2:$B$20,MATCH('03'!B8,PORT!$A$2:$A$20)) -> PNH01 | D8: =INDEX(PORT!$C$2:$C$20,MATCH('03'!B8,PORT!$A$2:$A$20)) -> KTI AIR PORT | E8: E 9095 | F8: 46087 | G8: JIN YUAN XI | H8: GS26-077 | I8: DIS079 | J8: JYX2603001 | K8: 46090 | L8: =VLOOKUP(K8,'[3]Exchange Rate'!$A$3:$C$24,3,FALSE) -> 4013 | M8: =TEXT(K8,"dddd") -> Monday | N8: 128.63 | O8: 0 | P8: 50 | Q8: 175 | R8: 58.63 | S8: =ROUND(Q8*10%,2) -> 17.5 | T8: 60 | U8: =(Q8+R8+T8)-(N8+O8+P8) -> 115
A9: PAID | B9: 1 | C9: =INDEX(PORT!$B$2:$B$20,MATCH('03'!B9,PORT!$A$2:$A$20)) -> PNH01 | D9: =INDEX(PORT!$C$2:$C$20,MATCH('03'!B9,PORT!$A$2:$A$20)) -> KTI AIR PORT | E9: E 9216 | F9: 46087 | G9: JIN YUAN XI | H9: GS26-078 | I9: DIS080 | J9: JYX2603002 | K9: 46090 | L9: =VLOOKUP(K9,'[3]Exchange Rate'!$A$3:$C$24,3,FALSE) -> 4013 | M9: =TEXT(K9,"dddd") -> Monday | N9: 206.42 | O9: 0 | P9: 50 | Q9: 210 | R9: 136.42 | S9: =ROUND(Q9*10%,2) -> 21 | T9: 60 | U9: =(Q9+R9+T9)-(N9+O9+P9) -> 150
A10: PAID | B10: 1 | C10: =INDEX(PORT!$B$2:$B$20,MATCH('03'!B10,PORT!$A$2:$A$20)) -> PNH01 | D10: =INDEX(PORT!$C$2:$C$20,MATCH('03'!B10,PORT!$A$2:$A$20)) -> KTI AIR PORT | E10: E 9303 | F10: 46088 | G10: JIN YUAN XI | H10: GS26-079 | I10: DIS081 | J10: JYX2603003 | K10: 46090 | L10: =VLOOKUP(K10,'[3]Exchange Rate'!$A$3:$C$24,3,FALSE) -> 4013 | M10: =TEXT(K10,"dddd") -> Monday | N10: 604.02 | O10: 0 | P10: 50 | Q10: 230 | R10: 484.02 | S10: =ROUND(Q10*10%,2) -> 23 | T10: 180 | U10: =(Q10+R10+T10)-(N10+O10+P10) -> 240
A11: PAID | B11: 4 | C11: =INDEX(PORT!$B$2:$B$20,MATCH('03'!B11,PORT!$A$2:$A$20)) -> PNH04 | D11: =INDEX(PORT!$C$2:$C$20,MATCH('03'!B11,PORT!$A$2:$A$20)) -> PNH PORT | E11: E 64094 | F11: 46087 | G11: JR | H11: GS26-080 | I11: DIS082 | J11: JR2603003 | K11: 46090 | L11: =VLOOKUP(K11,'[3]Exchange Rate'!$A$3:$C$24,3,FALSE) -> 4013 | M11: =TEXT(K11,"dddd") -> Monday | N11: 517.75 | O11: 528 | P11: 0 | Q11: 242 | R11: =916.45-N12 -> 903.25 | S11: =ROUND(Q11*10%,2) -> 24.2 | T11: 729 | U11: =(Q11+R11+T11)-(N11+O11+P11) -> 828.5 | V11: HBL
A12: PAID | B12: 4 | C12: =INDEX(PORT!$B$2:$B$20,MATCH('03'!B12,PORT!$A$2:$A$20)) -> PNH04 | D12: =INDEX(PORT!$C$2:$C$20,MATCH('03'!B12,PORT!$A$2:$A$20)) -> PNH PORT | E12: E 64094 | F12: 46087 | G12: JR | K12: 46090 | L12: =VLOOKUP(K12,'[3]Exchange Rate'!$A$3:$C$24,3,FALSE) -> 4013 | M12: =TEXT(K12,"dddd") -> Monday | N12: 13.2 | O12: 0 | P12: 0 | R12: 13.2 | S12: =ROUND(Q12*10%,2) -> 0 | U12: =(Q12+R12+T12)-(N12+O12+P12) -> 0 | V12: Lack storage fee
A13: PAID | B13: 4 | C13: =INDEX(PORT!$B$2:$B$20,MATCH('03'!B13,PORT!$A$2:$A$20)) -> PNH04 | D13: =INDEX(PORT!$C$2:$C$20,MATCH('03'!B13,PORT!$A$2:$A$20)) -> PNH PORT | E13: E 65834 | F13: 46087 | G13: JR | H13: GS26-081 | I13: DIS083 | J13: JR2603004 | K13: 46090 | L13: =VLOOKUP(K13,'[3]Exchange Rate'!$A$3:$C$24,3,FALSE) -> 4013 | M13: =TEXT(K13,"dddd") -> Monday | N13: 515.75 | O13: 506 | P13: 0 | Q13: 242 | R13: =691.75-N14 -> 371.75 | S13: =ROUND(Q13*10%,2) -> 24.2 | T13: 1219 | U13: =(Q13+R13+T13)-(N13+O13+P13) -> 811
A14: PAID | B14: 4 | C14: =INDEX(PORT!$B$2:$B$20,MATCH('03'!B14,PORT!$A$2:$A$20)) -> PNH04 | D14: =INDEX(PORT!$C$2:$C$20,MATCH('03'!B14,PORT!$A$2:$A$20)) -> PNH PORT | E14: E 65834 | F14: 46087 | G14: JR | K14: 46090 | L14: =VLOOKUP(K14,'[3]Exchange Rate'!$A$3:$C$24,3,FALSE) -> 4013 | M14: =TEXT(K14,"dddd") -> Monday | N14: 320 | O14: 0 | P14: 0 | R14: 320 | S14: =ROUND(Q14*10%,2) -> 0 | U14: =(Q14+R14+T14)-(N14+O14+P14) -> 0 | V14: Lack
A15: PAID | B15: 1 | C15: =INDEX(PORT!$B$2:$B$20,MATCH('03'!B15,PORT!$A$2:$A$20)) -> PNH01 | D15: =INDEX(PORT!$C$2:$C$20,MATCH('03'!B15,PORT!$A$2:$A$20)) -> KTI AIR PORT | E15: I 6739 | F15: 46090 | G15: VFL | H15: GS26-082 | I15: DIS084 | J15: VFL2603004 | K15: 46091 | L15: =VLOOKUP(K15,'[3]Exchange Rate'!$A$3:$C$24,3,FALSE) -> 4013 | M15: =TEXT(K15,"dddd") -> Tuesday | N15: 172.57 | O15: 60.5 | P15: 50 | Q15: 150 | R15: 93.07 | S15: =ROUND(Q15*10%,2) -> 15 | T15: 119.75 | U15: =(Q15+R15+T15)-(N15+O15+P15) -> 79.75
A16: PAID | B16: 1 | C16: =INDEX(PORT!$B$2:$B$20,MATCH('03'!B16,PORT!$A$2:$A$20)) -> PNH01 | D16: =INDEX(PORT!$C$2:$C$20,MATCH('03'!B16,PORT!$A$2:$A$20)) -> KTI AIR PORT | E16: I 6742 | F16: 46090 | G16: VFL | H16: GS26-083 | I16: DIS085 | J16: VFL2603005 | K16: 46091 | L16: =VLOOKUP(K16,'[3]Exchange Rate'!$A$3:$C$24,3,FALSE) -> 4013 | M16: =TEXT(K16,"dddd") -> Tuesday | N16: 175.14 | O16: 110 | P16: 50 | Q16: 150 | R16: 145.14 | S16: =ROUND(Q16*10%,2) -> 15 | T16: 119.75 | U16: =(Q16+R16+T16)-(N16+O16+P16) -> 79.75
A17: PAID | B17: 21 | C17: =INDEX(PORT!$B$2:$B$20,MATCH('03'!B17,PORT!$A$2:$A$20)) -> PNH21 | D17: =INDEX(PORT!$C$2:$C$20,MATCH('03'!B17,PORT!$A$2:$A$20)) -> OLAIR DRY PORT | E17: I 837 | F17: 46091 | G17: VFL | H17: GS26-084 | I17: DIS086 | J17: VFL2603006 | K17: 46092 | L17: =VLOOKUP(K17,'[3]Exchange Rate'!$A$3:$C$24,3,FALSE) -> 4013 | M17: =TEXT(K17,"dddd") -> Wednesday | N17: 115 | O17: 205.43 | P17: 50 | Q17: 150 | R17: 230.43 | S17: =ROUND(Q17*10%,2) -> 15 | T17: 103.5 | U17: =(Q17+R17+T17)-(N17+O17+P17) -> 113.5
A18: PAID | B18: 21 | C18: =INDEX(PORT!$B$2:$B$20,MATCH('03'!B18,PORT!$A$2:$A$20)) -> PNH21 | D18: =INDEX(PORT!$C$2:$C$20,MATCH('03'!B18,PORT!$A$2:$A$20)) -> OLAIR DRY PORT | E18: I 839 | F18: 46091 | G18: SPORTLINE | H18: GS26-085 | I18: DIS087 | J18: SAK2603001 | K18: 46092 | L18: =VLOOKUP(K18,'[3]Exchange Rate'!$A$3:$C$24,3,FALSE) -> 4013 | M18: =TEXT(K18,"dddd") -> Wednesday | N18: 145 | O18: 176 | P18: 50 | Q18: 150 | R18: 201 | S18: =ROUND(Q18*10%,2) -> 15 | T18: 181 | U18: =(Q18+R18+T18)-(N18+O18+P18) -> 161
A19: PAID | B19: 1 | C19: =INDEX(PORT!$B$2:$B$20,MATCH('03'!B19,PORT!$A$2:$A$20)) -> PNH01 | D19: =INDEX(PORT!$C$2:$C$20,MATCH('03'!B19,PORT!$A$2:$A$20)) -> KTI AIR PORT | E19: E 9849 | F19: 46093 | G19: VFL | H19: GS26-086 | I19: DIS088 | J19: VFL2603007 | K19: 46094 | L19: =VLOOKUP(K19,'[3]Exchange Rate'!$A$3:$C$24,3,FALSE) -> 4013 | M19: =TEXT(K19,"dddd") -> Friday | N19: 85.95 | O19: 0 | P19: 50 | Q19: 140 | R19: 15.95 | S19: =ROUND(Q19*10%,2) -> 14 | T19: 60 | U19: =(Q19+R19+T19)-(N19+O19+P19) -> 80
A20: PAID | B20: 1 | C20: =INDEX(PORT!$B$2:$B$20,MATCH('03'!B20,PORT!$A$2:$A$20)) -> PNH01 | D20: =INDEX(PORT!$C$2:$C$20,MATCH('03'!B20,PORT!$A$2:$A$20)) -> KTI AIR PORT | E20: I 7165 | F20: 46093 | G20: VFL | H20: GS26-087 | I20: DIS089 | J20: VFL2603008 | K20: 46094 | L20: =VLOOKUP(K20,'[3]Exchange Rate'!$A$3:$C$24,3,FALSE) -> 4013 | M20: =TEXT(K20,"dddd") -> Friday | N20: 158.4 | O20: 60.5 | P20: 50 | Q20: 150 | R20: 78.9 | S20: =ROUND(Q20*10%,2) -> 15 | T20: 119.75 | U20: =(Q20+R20+T20)-(N20+O20+P20) -> 79.75
A21: PAID | B21: 11 | C21: =INDEX(PORT!$B$2:$B$20,MATCH('03'!B21,PORT!$A$2:$A$20)) -> SHV11 | D21: =INDEX(PORT!$C$2:$C$20,MATCH('03'!B21,PORT!$A$2:$A$20)) -> SHV PORT | E21: I 35751 | F21: 46093 | G21: SPORTLINE | H21: GS26-088 | I21: DIS090 | J21: SAK2603002 | K21: 46094 | L21: =VLOOKUP(K21,'[3]Exchange Rate'!$A$3:$C$24,3,FALSE) -> 4013 | M21: =TEXT(K21,"dddd") -> Friday | N21: 271.99 | O21: 365.01 | P21: 50 | Q21: 150 | R21: 385.49 | S21: =ROUND(Q21*10%,2) -> 15 | T21: 243.84 | U21: =(Q21+R21+T21)-(N21+O21+P21) -> 92.33
A22: PAID | B22: 11 | C22: =INDEX(PORT!$B$2:$B$20,MATCH('03'!B22,PORT!$A$2:$A$20)) -> SHV11 | D22: =INDEX(PORT!$C$2:$C$20,MATCH('03'!B22,PORT!$A$2:$A$20)) -> SHV PORT | E22: I 35753 | F22: 46093 | G22: SPORTLINE | H22: GS26-089 | I22: DIS091 | J22: SAK2603003 | K22: 46094 | L22: =VLOOKUP(K22,'[3]Exchange Rate'!$A$3:$C$24,3,FALSE) -> 4013 | M22: =TEXT(K22,"dddd") -> Friday | N22: 202.51 | O22: 245.98 | P22: 50 | Q22: 150 | R22: 263.1 | S22: =ROUND(Q22*10%,2) -> 15 | T22: 152.84 | U22: =(Q22+R22+T22)-(N22+O22+P22) -> 67.45
A23: PAID | B23: 1 | C23: =INDEX(PORT!$B$2:$B$20,MATCH('03'!B23,PORT!$A$2:$A$20)) -> PNH01 | D23: =INDEX(PORT!$C$2:$C$20,MATCH('03'!B23,PORT!$A$2:$A$20)) -> KTI AIR PORT | E23: E 10005 | F23: 46094 | G23: VFL | H23: GS26-090 | I23: DIS092 | J23: VFL2603009 | K23: 46097 | L23: =VLOOKUP(K23,'[3]Exchange Rate'!$A$3:$C$24,3,FALSE) -> 4013 | M23: =TEXT(K23,"dddd") -> Monday | N23: 86.83 | O23: 0 | P23: 50 | Q23: 140 | R23: 16.83 | S23: =ROUND(Q23*10%,2) -> 14 | T23: 60 | U23: =(Q23+R23+T23)-(N23+O23+P23) -> 80
A24: PAID | B24: 1 | C24: =INDEX(PORT!$B$2:$B$20,MATCH('03'!B24,PORT!$A$2:$A$20)) -> PNH01 | D24: =INDEX(PORT!$C$2:$C$20,MATCH('03'!B24,PORT!$A$2:$A$20)) -> KTI AIR PORT | E24: E 10184 | F24: 46095 | G24: VFL | H24: GS26-091 | I24: DIS093 | J24: VFL2603010 | K24: 46097 | L24: =VLOOKUP(K24,'[3]Exchange Rate'!$A$3:$C$24,3,FALSE) -> 4013 | M24: =TEXT(K24,"dddd") -> Monday | N24: 90.26 | O24: 0 | P24: 50 | Q24: 140 | R24: 20.26 | S24: =ROUND(Q24*10%,2) -> 14 | T24: 60 | U24: =(Q24+R24+T24)-(N24+O24+P24) -> 80
A25: PAID | B25: 1 | C25: =INDEX(PORT!$B$2:$B$20,MATCH('03'!B25,PORT!$A$2:$A$20)) -> PNH01 | D25: =INDEX(PORT!$C$2:$C$20,MATCH('03'!B25,PORT!$A$2:$A$20)) -> KTI AIR PORT | E25: E 10205 | F25: 46095 | G25: VFL | H25: GS26-092 | I25: DIS094 | J25: VFL2603011 | K25: 46097 | L25: =VLOOKUP(K25,'[3]Exchange Rate'!$A$3:$C$24,3,FALSE) -> 4013 | M25: =TEXT(K25,"dddd") -> Monday | N25: 83.75 | O25: 0 | P25: 50 | Q25: 140 | R25: 13.75 | S25: =ROUND(Q25*10%,2) -> 14 | T25: 60 | U25: =(Q25+R25+T25)-(N25+O25+P25) -> 80
A26: PAID | B26: 11 | C26: =INDEX(PORT!$B$2:$B$20,MATCH('03'!B26,PORT!$A$2:$A$20)) -> SHV11 | D26: =INDEX(PORT!$C$2:$C$20,MATCH('03'!B26,PORT!$A$2:$A$20)) -> SHV PORT | E26: I 36325 | F26: 46095 | G26: VFL | H26: GS26-093 | I26: DIS095 | J26: VFL2603012 | K26: 46097 | L26: =VLOOKUP(K26,'[3]Exchange Rate'!$A$3:$C$24,3,FALSE) -> 4013 | M26: =TEXT(K26,"dddd") -> Monday | N26: 152.45 | O26: 238.92 | P26: 50 | Q26: 150 | R26: 254.35 | S26: =ROUND(Q26*10%,2) -> 15 | T26: 100.15 | U26: =(Q26+R26+T26)-(N26+O26+P26) -> 63.13
... A28: PAID | B28: 1 | C28: =INDEX(PORT!$B$2:$B$20,MATCH('03'!B28,PORT!$A$2:$A$20)) -> PNH01 | D28: =INDEX(PORT!$C$2:$C$20,MATCH('03'!B28,PORT!$A$2:$A$20)) -> KTI AIR PORT | E28: E 9979 | F28: 46094 | G28: JIN YUAN XI | H28: GS26-095 | I28: DIS097 | J28: JYX2603005 | K28: 46097 | L28: =VLOOKUP(K28,'[3]Exchange Rate'!$A$3:$C$24,3,FALSE) -> 4013 | M28: =TEXT(K28,"dddd") -> Monday | N28: 165.41 | O28: 0 | P28: 50 | Q28: 175 | R28: 95.41 | S28: =ROUND(Q28*10%,2) -> 17.5 | T28: 60 | U28: =(Q28+R28+T28)-(N28+O28+P28) -> 115
A29: PAID | B29: 4 | C29: =INDEX(PORT!$B$2:$B$20,MATCH('03'!B29,PORT!$A$2:$A$20)) -> PNH04 | D29: =INDEX(PORT!$C$2:$C$20,MATCH('03'!B29,PORT!$A$2:$A$20)) -> PNH PORT | E29: E 72299 | F29: 46094 | G29: JR | H29: GS26-096 | I29: DIS098 | J29: JR2603005 | K29: 46097 | L29: =VLOOKUP(K29,'[3]Exchange Rate'!$A$3:$C$24,3,FALSE) -> 4013 | M29: =TEXT(K29,"dddd") -> Monday | N29: 516.85 | O29: 466 | P29: 0 | Q29: 213 | R29: 567.85 | S29: =ROUND(Q29*10%,2) -> 21.3 | T29: 621.58 | U29: =(Q29+R29+T29)-(N29+O29+P29) -> 419.58 | V29: HBL
A30: PAID | B30: 11 | C30: =INDEX(PORT!$B$2:$B$20,MATCH('03'!B30,PORT!$A$2:$A$20)) -> SHV11 | D30: =INDEX(PORT!$C$2:$C$20,MATCH('03'!B30,PORT!$A$2:$A$20)) -> SHV PORT | E30: I 36309 | F30: 46095 | G30: SPORTLINE | H30: GS26-097 | I30: DIS099 | J30: SAK2603004 | K30: 46097 | L30: =VLOOKUP(K30,'[3]Exchange Rate'!$A$3:$C$24,3,FALSE) -> 4013 | M30: =TEXT(K30,"dddd") -> Monday | N30: 155.43 | O30: 198.4 | P30: 50 | Q30: 150 | R30: 213.83 | S30: =ROUND(Q30*10%,2) -> 15 | T30: 160.52 | U30: =(Q30+R30+T30)-(N30+O30+P30) -> 120.52
A31: PAID | B31: 19 | C31: =INDEX(PORT!$B$2:$B$20,MATCH('03'!B31,PORT!$A$2:$A$20)) -> PNH19 | D31: =INDEX(PORT!$C$2:$C$20,MATCH('03'!B31,PORT!$A$2:$A$20)) -> TEC SRUN DRYPORT | E31: I 769 | F31: 46097 | G31: VFL | H31: GS26-098 | I31: DIS100 | J31: VFL2603013 | K31: 46098 | L31: =VLOOKUP(K31,'[3]Exchange Rate'!$A$3:$C$24,3,FALSE) -> 4013 | M31: =TEXT(K31,"dddd") -> Tuesday | N31: 116.1 | O31: 194.13 | P31: 50 | Q31: 150 | R31: 220.23 | S31: =ROUND(Q31*10%,2) -> 15 | T31: 108.5 | U31: =(Q31+R31+T31)-(N31+O31+P31) -> 118.5
A32: PAID | B32: 19 | C32: =INDEX(PORT!$B$2:$B$20,MATCH('03'!B32,PORT!$A$2:$A$20)) -> PNH19 | D32: =INDEX(PORT!$C$2:$C$20,MATCH('03'!B32,PORT!$A$2:$A$20)) -> TEC SRUN DRYPORT | E32: I 770 | F32: 46097 | G32: SPORTLINE | H32: GS26-099 | I32: DIS101 | J32: SAK2603005 | K32: 46098 | L32: =VLOOKUP(K32,'[3]Exchange Rate'!$A$3:$C$24,3,FALSE) -> 4013 | M32: =TEXT(K32,"dddd") -> Tuesday | N32: 136.1 | O32: 194.13 | P32: 50 | Q32: 150 | R32: 220.23 | S32: =ROUND(Q32*10%,2) -> 15 | T32: 147 | U32: =(Q32+R32+T32)-(N32+O32+P32) -> 137
A33: PAID | B33: 11 | C33: =INDEX(PORT!$B$2:$B$20,MATCH('03'!B33,PORT!$A$2:$A$20)) -> SHV11 | D33: =INDEX(PORT!$C$2:$C$20,MATCH('03'!B33,PORT!$A$2:$A$20)) -> SHV PORT | E33: I 37892 | F33: 46099 | G33: VFL | H33: GS26-100 | I33: DIS102 | J33: VFL2603014 | K33: 46100 | L33: =VLOOKUP(K33,'[3]Exchange Rate'!$A$3:$C$24,3,FALSE) -> 4013 | M33: =TEXT(K33,"dddd") -> Thursday | N33: 168.06 | O33: 312.74 | P33: 50 | Q33: 150 | R33: 329.86 | S33: =ROUND(Q33*10%,2) -> 15 | T33: 108.64 | U33: =(Q33+R33+T33)-(N33+O33+P33) -> 57.7
A34: PAID | B34: 11 | C34: =INDEX(PORT!$B$2:$B$20,MATCH('03'!B34,PORT!$A$2:$A$20)) -> SHV11 | D34: =INDEX(PORT!$C$2:$C$20,MATCH('03'!B34,PORT!$A$2:$A$20)) -> SHV PORT | E34: I 37893 | F34: 46099 | G34: VFL | H34: GS26-101 | I34: DIS103 | J34: VFL2603015 | K34: 46100 | L34: =VLOOKUP(K34,'[3]Exchange Rate'!$A$3:$C$24,3,FALSE) -> 4013 | M34: =TEXT(K34,"dddd") -> Thursday | N34: 145.43 | O34: 206.25 | P34: 50 | Q34: 150 | R34: 221.68 | S34: =ROUND(Q34*10%,2) -> 15 | T34: 112.31 | U34: =(Q34+R34+T34)-(N34+O34+P34) -> 82.31
A35: PAID | B35: 11 | C35: =INDEX(PORT!$B$2:$B$20,MATCH('03'!B35,PORT!$A$2:$A$20)) -> SHV11 | D35: =INDEX(PORT!$C$2:$C$20,MATCH('03'!B35,PORT!$A$2:$A$20)) -> SHV PORT | E35: I 37897 | F35: 46099 | G35: SPORTLINE | H35: GS26-102 | I35: DIS104 | J35: SAK2603006 | K35: 46100 | L35: =VLOOKUP(K35,'[3]Exchange Rate'!$A$3:$C$24,3,FALSE) -> 4013 | M35: =TEXT(K35,"dddd") -> Thursday | N35: 219.3 | O35: 256.01 | P35: 50 | Q35: 150 | R35: 274.81 | S35: =ROUND(Q35*10%,2) -> 15 | T35: 196.9 | U35: =(Q35+R35+T35)-(N35+O35+P35) -> 96.4
A36: PAID | B36: 4 | C36: =INDEX(PORT!$B$2:$B$20,MATCH('03'!B36,PORT!$A$2:$A$20)) -> PNH04 | D36: =INDEX(PORT!$C$2:$C$20,MATCH('03'!B36,PORT!$A$2:$A$20)) -> PNH PORT | E36: E 74515 | F36: 46100 | G36: SPORTLINE | H36: GS26-103 | I36: DIS105 | J36: SAK2603007 | K36: 46101 | L36: =VLOOKUP(K36,'[3]Exchange Rate'!$A$3:$C$24,3,FALSE) -> 4011 | M36: =TEXT(K36,"dddd") -> Friday | N36: 1108.76 | O36: 0 | P36: 50 | Q36: 490 | R36: 286.75 | S36: =ROUND(Q36*10%,2) -> 49 | T36: 974 | U36: =(Q36+R36+T36)-(N36+O36+P36) -> 591.99
A37: PAID | B37: 1 | C37: =INDEX(PORT!$B$2:$B$20,MATCH('03'!B37,PORT!$A$2:$A$20)) -> PNH01 | D37: =INDEX(PORT!$C$2:$C$20,MATCH('03'!B37,PORT!$A$2:$A$20)) -> KTI AIR PORT | E37: E 11073 | F37: 46102 | G37: JIN YUAN XI | H37: GS26-104 | I37: DIS106 | J37: JYX2603006 | K37: 46104 | L37: =VLOOKUP(K37,'[3]Exchange Rate'!$A$3:$C$24,3,FALSE) -> 4010 | M37: =TEXT(K37,"dddd") -> Monday | N37: 173.35 | O37: 0 | P37: 50 | Q37: 175 | R37: 53.35 | S37: =ROUND(Q37*10%,2) -> 17.5 | T37: 180 | U37: =(Q37+R37+T37)-(N37+O37+P37) -> 185
A38: PAID | B38: 1 | C38: =INDEX(PORT!$B$2:$B$20,MATCH('03'!B38,PORT!$A$2:$A$20)) -> PNH01 | D38: =INDEX(PORT!$C$2:$C$20,MATCH('03'!B38,PORT!$A$2:$A$20)) -> KTI AIR PORT | E38: E 11095 | F38: 46102 | G38: JIN YUAN XI | H38: GS26-105 | I38: DIS107 | J38: JYX2603007 | K38: 46104 | L38: =VLOOKUP(K38,'[3]Exchange Rate'!$A$3:$C$24,3,FALSE) -> 4010 | M38: =TEXT(K38,"dddd") -> Monday | N38: 251.41 | O38: 0 | P38: 50 | Q38: 210 | R38: 131.41 | S38: =ROUND(Q38*10%,2) -> 21 | T38: 180 | U38: =(Q38+R38+T38)-(N38+O38+P38) -> 220
A39: PAID | B39: 4 | C39: =INDEX(PORT!$B$2:$B$20,MATCH('03'!B39,PORT!$A$2:$A$20)) -> PNH04 | D39: =INDEX(PORT!$C$2:$C$20,MATCH('03'!B39,PORT!$A$2:$A$20)) -> PNH PORT | E39: E 78635 | F39: 46101 | G39: SPORTLINE | H39: GS26-106 | I39: DIS108 | J39: SAK2603008 | K39: 46104 | L39: =VLOOKUP(K39,'[3]Exchange Rate'!$A$3:$C$24,3,FALSE) -> 4010 | M39: =TEXT(K39,"dddd") -> Monday | N39: 579.25 | O39: 0 | P39: 50 | Q39: 245 | R39: 143.25 | S39: =ROUND(Q39*10%,2) -> 24.5 | T39: 602 | U39: =(Q39+R39+T39)-(N39+O39+P39) -> 361
A40: PAID | B40: 4 | C40: =INDEX(PORT!$B$2:$B$20,MATCH('03'!B40,PORT!$A$2:$A$20)) -> PNH04 | D40: =INDEX(PORT!$C$2:$C$20,MATCH('03'!B40,PORT!$A$2:$A$20)) -> PNH PORT | E40: E 79749 | F40: 46101 | G40: JR | H40: GS26-107 | I40: DIS109 | J40: JR2603006 | K40: 46104 | L40: =VLOOKUP(K40,'[3]Exchange Rate'!$A$3:$C$24,3,FALSE) -> 4010 | M40: =TEXT(K40,"dddd") -> Monday | N40: 541.85 | O40: 462 | P40: 0 | Q40: 213 | R40: 725.85 | S40: =ROUND(Q40*10%,2) -> 21.3 | T40: 741.5 | U40: =(Q40+R40+T40)-(N40+O40+P40) -> 676.5 | V40: HBL
A41: PAID | B41: 1 | C41: =INDEX(PORT!$B$2:$B$20,MATCH('03'!B41,PORT!$A$2:$A$20)) -> PNH01 | D41: =INDEX(PORT!$C$2:$C$20,MATCH('03'!B41,PORT!$A$2:$A$20)) -> KTI AIR PORT | E41: E 11240 | F41: 46104 | G41: SPORTLINE | H41: GS26-108 | I41: DIS110 | J41: SAK2603009 | K41: 46105 | L41: =VLOOKUP(K41,'[3]Exchange Rate'!$A$3:$C$24,3,FALSE) -> 4007 | M41: =TEXT(K41,"dddd") -> Tuesday | N41: 83.75 | O41: 0 | P41: 50 | Q41: 140 | R41: 13.75 | S41: =ROUND(Q41*10%,2) -> 14 | T41: 60 | U41: =(Q41+R41+T41)-(N41+O41+P41) -> 80
A42: PAID | B42: 1 | C42: =INDEX(PORT!$B$2:$B$20,MATCH('03'!B42,PORT!$A$2:$A$20)) -> PNH01 | D42: =INDEX(PORT!$C$2:$C$20,MATCH('03'!B42,PORT!$A$2:$A$20)) -> KTI AIR PORT | E42: E 11244 | F42: 46104 | G42: SPORTLINE | H42: GS26-109 | I42: DIS111 | J42: SAK2603010 | K42: 46105 | L42: =VLOOKUP(K42,'[3]Exchange Rate'!$A$3:$C$24,3,FALSE) -> 4007 | M42: =TEXT(K42,"dddd") -> Tuesday | N42: 83.75 | O42: 0 | P42: 50 | Q42: 140 | R42: 13.75 | S42: =ROUND(Q42*10%,2) -> 14 | T42: 60 | U42: =(Q42+R42+T42)-(N42+O42+P42) -> 80
A43: PAID | B43: 1 | C43: =INDEX(PORT!$B$2:$B$20,MATCH('03'!B43,PORT!$A$2:$A$20)) -> PNH01 | D43: =INDEX(PORT!$C$2:$C$20,MATCH('03'!B43,PORT!$A$2:$A$20)) -> KTI AIR PORT | E43: I 8428 | F43: 46104 | G43: VFL | H43: GS26-110 | I43: DIS112 | J43: VFL2603016 | K43: 46105 | L43: =VLOOKUP(K43,'[3]Exchange Rate'!$A$3:$C$24,3,FALSE) -> 4007 | M43: =TEXT(K43,"dddd") -> Tuesday | N43: 164.56 | O43: 60.5 | P43: 50 | Q43: 150 | R43: 85.06 | S43: =ROUND(Q43*10%,2) -> 15 | T43: 119.76 | U43: =(Q43+R43+T43)-(N43+O43+P43) -> 79.76
A44: PAID | B44: 21 | C44: =INDEX(PORT!$B$2:$B$20,MATCH('03'!B44,PORT!$A$2:$A$20)) -> PNH21 | D44: =INDEX(PORT!$C$2:$C$20,MATCH('03'!B44,PORT!$A$2:$A$20)) -> OLAIR DRY PORT | E44: I 971 | F44: 46105 | G44: SPORTLINE | H44: GS26-111 | I44: DIS113 | J44: SAK2603011 | K44: 46106 | L44: =VLOOKUP(K44,'[3]Exchange Rate'!$A$3:$C$24,3,FALSE) -> 4006 | M44: =TEXT(K44,"dddd") -> Wednesday | N44: 272.13 | O44: 699.33 | P44: 50 | Q44: 150 | R44: 801.46 | S44: =ROUND(Q44*10%,2) -> 15 | T44: 229.5 | U44: =(Q44+R44+T44)-(N44+O44+P44) -> 159.5
A45: PAID | B45: 11 | C45: =INDEX(PORT!$B$2:$B$20,MATCH('03'!B45,PORT!$A$2:$A$20)) -> SHV11 | D45: =INDEX(PORT!$C$2:$C$20,MATCH('03'!B45,PORT!$A$2:$A$20)) -> SHV PORT | E45: I 40726 | F45: 46106 | G45: VFL | H45: GS26-112 | I45: DIS114 | J45: VFL2603017 | K45: 46107 | L45: =VLOOKUP(K45,'[3]Exchange Rate'!$A$3:$C$24,3,FALSE) -> 4004 | M45: =TEXT(K45,"dddd") -> Thursday | N45: 238.24 | O45: 419.76 | P45: 50 | Q45: 150 | R45: 443.61 | S45: =ROUND(Q45*10%,2) -> 15 | T45: 215.9 | U45: =(Q45+R45+T45)-(N45+O45+P45) -> 101.51
A46: PAID | B46: 19 | C46: =INDEX(PORT!$B$2:$B$20,MATCH('03'!B46,PORT!$A$2:$A$20)) -> PNH19 | D46: =INDEX(PORT!$C$2:$C$20,MATCH('03'!B46,PORT!$A$2:$A$20)) -> TEC SRUN DRYPORT | E46: I 879 | F46: 46108 | G46: VFL | H46: GS26-113 | I46: DIS115 | J46: VFL2603018 | K46: 46111 | L46: =VLOOKUP(K46,'[3]Exchange Rate'!$A$3:$C$24,3,FALSE) -> 4001 | M46: =TEXT(K46,"dddd") -> Monday | N46: 117.11 | O46: 271.62 | P46: 50 | Q46: 150 | R46: 298.73 | S46: =ROUND(Q46*10%,2) -> 15 | T46: 103.5 | U46: =(Q46+R46+T46)-(N46+O46+P46) -> 113.5
A47: PAID | B47: 11 | C47: =INDEX(PORT!$B$2:$B$20,MATCH('03'!B47,PORT!$A$2:$A$20)) -> SHV11 | D47: =INDEX(PORT!$C$2:$C$20,MATCH('03'!B47,PORT!$A$2:$A$20)) -> SHV PORT | E47: I 41824 | F47: 46108 | G47: SPORTLINE | H47: GS26-114 | I47: DIS116 | J47: SAK2603012 | K47: 46111 | L47: =VLOOKUP(K47,'[3]Exchange Rate'!$A$3:$C$24,3,FALSE) -> 4001 | M47: =TEXT(K47,"dddd") -> Monday | N47: 225.31 | O47: 297.92 | P47: 50 | Q47: 150 | R47: 313.35 | S47: =ROUND(Q47*10%,2) -> 15 | T47: 196.73 | U47: =(Q47+R47+T47)-(N47+O47+P47) -> 86.85
A48: PAID | B48: 19 | C48: =INDEX(PORT!$B$2:$B$20,MATCH('03'!B48,PORT!$A$2:$A$20)) -> PNH19 | D48: =INDEX(PORT!$C$2:$C$20,MATCH('03'!B48,PORT!$A$2:$A$20)) -> TEC SRUN DRYPORT | E48: I 881 | F48: 46108 | G48: SPORTLINE | H48: GS26-115 | I48: DIS117 | J48: SAK2603013 | K48: 46111 | L48: =VLOOKUP(K48,'[3]Exchange Rate'!$A$3:$C$24,3,FALSE) -> 4001 | M48: =TEXT(K48,"dddd") -> Monday | N48: 158.22 | O48: 436.69 | P48: 50 | Q48: 150 | R48: 479.91 | S48: =ROUND(Q48*10%,2) -> 15 | T48: 147 | U48: =(Q48+R48+T48)-(N48+O48+P48) -> 132
A49: PAID | B49: 1 | C49: =INDEX(PORT!$B$2:$B$20,MATCH('03'!B49,PORT!$A$2:$A$20)) -> PNH01 | D49: =INDEX(PORT!$C$2:$C$20,MATCH('03'!B49,PORT!$A$2:$A$20)) -> KTI AIR PORT | E49: E 11760 | F49: 46108 | G49: JIN YUAN XI | H49: GS26-116 | I49: DIS118 | J49: JYX2603008 | K49: 46111 | L49: =VLOOKUP(K49,'[3]Exchange Rate'!$A$3:$C$24,3,FALSE) -> 4001 | M49: =TEXT(K49,"dddd") -> Monday | N49: 192.36 | O49: 0 | P49: 50 | Q49: 175 | R49: 72.36 | S49: =ROUND(Q49*10%,2) -> 17.5 | T49: 180 | U49: =(Q49+R49+T49)-(N49+O49+P49) -> 185
B50: 11 | C50: =INDEX(PORT!$B$2:$B$20,MATCH('03'!B50,PORT!$A$2:$A$20)) -> SHV11 | D50: =INDEX(PORT!$C$2:$C$20,MATCH('03'!B50,PORT!$A$2:$A$20)) -> SHV PORT | E50: BLS26-0093 & BLS26-0094 | F50: 46099 | G50: JR | I50: DIS119 | J50: JR2603007 | K50: 46112 | L50: =VLOOKUP(K50,'[3]Exchange Rate'!$A$3:$C$24,3,FALSE) -> 4001 | M50: =TEXT(K50,"dddd") -> Tuesday | N50: 0 | O50: 466 | P50: 0 | Q50: 0 | R50: 466 | S50: =ROUND(Q50*10%,2) -> 0 | T50: 120 | U50: =(Q50+R50+T50)-(N50+O50+P50) -> 120 | V50: E 52971​​​​​-2/20
B51: 4 | C51: =INDEX(PORT!$B$2:$B$20,MATCH('03'!B51,PORT!$A$2:$A$20)) -> PNH04 | D51: =INDEX(PORT!$C$2:$C$20,MATCH('03'!B51,PORT!$A$2:$A$20)) -> PNH PORT | E51: BLS26-0106BLS26-0107 | F51: 46093 | G51: JR | I51: DIS120 | J51: JR2603008 | K51: 46112 | L51: =VLOOKUP(K51,'[3]Exchange Rate'!$A$3:$C$24,3,FALSE) -> 4001 | M51: =TEXT(K51,"dddd") -> Tuesday | N51: 0 | O51: 506 | P51: 0 | Q51: 0 | R51: 506 | S51: =ROUND(Q51*10%,2) -> 0 | T51: 160 | U51: =(Q51+R51+T51)-(N51+O51+P51) -> 160 | V51: E 58393-2/27
B52: 4 | C52: =INDEX(PORT!$B$2:$B$20,MATCH('03'!B52,PORT!$A$2:$A$20)) -> PNH04 | D52: =INDEX(PORT!$C$2:$C$20,MATCH('03'!B52,PORT!$A$2:$A$20)) -> PNH PORT | E52: CGL26-00592 & RM26-00292 | F52: 46099 | G52: JR | I52: DIS121 | J52: JR2603009 | K52: 46112 | L52: =VLOOKUP(K52,'[3]Exchange Rate'!$A$3:$C$24,3,FALSE) -> 4001 | M52: =TEXT(K52,"dddd") -> Tuesday | N52: 0 | O52: 565.4 | P52: 0 | Q52: 0 | R52: 619.4 | S52: =ROUND(Q52*10%,2) -> 0 | T52: 120 | U52: =(Q52+R52+T52)-(N52+O52+P52) -> 174 | V52: E 69968-3/13
B53: 4 | C53: =INDEX(PORT!$B$2:$B$20,MATCH('03'!B53,PORT!$A$2:$A$20)) -> PNH04 | D53: =INDEX(PORT!$C$2:$C$20,MATCH('03'!B53,PORT!$A$2:$A$20)) -> PNH PORT | E53: LAT26-00088 | F53: 46099 | G53: JR | I53: DIS122 | J53: JR2603010 | K53: 46112 | L53: =VLOOKUP(K53,'[3]Exchange Rate'!$A$3:$C$24,3,FALSE) -> 4001 | M53: =TEXT(K53,"dddd") -> Tuesday | N53: 0 | O53: 402.35 | P53: 0 | Q53: 0 | R53: 466.85 | S53: =ROUND(Q53*10%,2) -> 0 | T53: 200 | U53: =(Q53+R53+T53)-(N53+O53+P53) -> 264.5 | V53: E 52039-2/20
B54: 4 | C54: =INDEX(PORT!$B$2:$B$20,MATCH('03'!B54,PORT!$A$2:$A$20)) -> PNH04 | D54: =INDEX(PORT!$C$2:$C$20,MATCH('03'!B54,PORT!$A$2:$A$20)) -> PNH PORT | E54: LAT2026-0047 | F54: 46093 | G54: JR | I54: DIS123 | J54: JR2603011 | K54: 46112 | L54: =VLOOKUP(K54,'[3]Exchange Rate'!$A$3:$C$24,3,FALSE) -> 4001 | M54: =TEXT(K54,"dddd") -> Tuesday | N54: 0 | O54: 439.77 | P54: 0 | Q54: 0 | R54: 515.27 | S54: =ROUND(Q54*10%,2) -> 0 | T54: 160 | U54: =(Q54+R54+T54)-(N54+O54+P54) -> 235.5 | V54: E 56303-2/27
B55: 4 | C55: =INDEX(PORT!$B$2:$B$20,MATCH('03'!B55,PORT!$A$2:$A$20)) -> PNH04 | D55: =INDEX(PORT!$C$2:$C$20,MATCH('03'!B55,PORT!$A$2:$A$20)) -> PNH PORT | E55: BLS26-0130 / RE26-0017 | F55: 46114 | G55: JR | I55: DIS124 | J55: JR2603012 | K55: 46112 | L55: =VLOOKUP(K55,'[3]Exchange Rate'!$A$3:$C$24,3,FALSE) -> 4001 | M55: =TEXT(K55,"dddd") -> Tuesday | N55: 0 | O55: 1260.87 | P55: 0 | Q55: 0 | R55: 1260.87 | S55: =ROUND(Q55*10%,2) -> 0 | T55: 160 | U55: =(Q55+R55+T55)-(N55+O55+P55) -> 160 | V55: E 76799-3/20
A56: paid | B56: 11 | C56: =INDEX(PORT!$B$2:$B$20,MATCH('03'!B56,PORT!$A$2:$A$20)) -> SHV11 | D56: =INDEX(PORT!$C$2:$C$20,MATCH('03'!B56,PORT!$A$2:$A$20)) -> SHV PORT | E56: I 43602 | F56: 46111 | G56: JR | H56: GS26-117 | I56: DIS125 | J56: JR2603013 | K56: 46112 | L56: =VLOOKUP(K56,'[3]Exchange Rate'!$A$3:$C$24,3,FALSE) -> 4001 | M56: =TEXT(K56,"dddd") -> Tuesday | N56: 836.2 | O56: 691.5 | P56: 0 | Q56: 200 | R56: 830.7 | S56: =ROUND(Q56*10%,2) -> 20 | T56: 777 | U56: =(Q56+R56+T56)-(N56+O56+P56) -> 280
B57: 11 | C57: =INDEX(PORT!$B$2:$B$20,MATCH('03'!B57,PORT!$A$2:$A$20)) -> SHV11 | D57: =INDEX(PORT!$C$2:$C$20,MATCH('03'!B57,PORT!$A$2:$A$20)) -> SHV PORT | E57: I 44741 | G57: VFL | I57: DIS126 | K57: 46112 | L57: =VLOOKUP(K57,'[3]Exchange Rate'!$A$3:$C$24,3,FALSE) -> 4001 | M57: =TEXT(K57,"dddd") -> Tuesday | N57: 0 | O57: 803.44 | P57: 0 | Q57: 0 | R57: 803.44 | S57: =ROUND(Q57*10%,2) -> 0 | T57: 0 | U57: =(Q57+R57+T57)-(N57+O57+P57) -> 0
E59: LOLO
E60: STORAGE
E61: THC
B63: =SUBTOTAL(3,B3:B62) -> 55 | E63: TOTAL: | H63: =SUBTOTAL(3,H3:H62) -> 46 | I63: =SUBTOTAL(3,I3:I62) -> 53 | J63: =SUBTOTAL(3,J3:J62) -> 52 | N63: =SUBTOTAL(9,N3:N58) -> 12167.07 | O63: =SUBTOTAL(9,O3:O58) -> 13275.15 | P63: =SUBTOTAL(9,P3:P58) -> 1950 | Q63: =SUBTOTAL(9,Q3:Q58) -> 7985 | R63: =SUBTOTAL(9,R3:R58) -> 16941.08 | S63: =SUBTOTAL(9,S3:S58) -> 798.5 | T63: =SUBTOTAL(9,T3:T58) -> 12260.92 | U63: =SUBTOTAL(9,U3:U61) -> 9794.78
M64: PAID | N64: =SUMIFS($N$3:$N$58,$A$3:$A$58,$M$64) -> 12167.07
M65: NOT YET | N65: =SUMIFS($N$3:$N$58,$A$3:$A$58,$M$65) -> 0

Sheet 04
E1: REVENUE & EXPENSE | M1: Saturday
A2: CHEA PAYMENT | B2: PORT NUMBER | C2: PORT CODE | D2: PORT NAME | E2: DECLARE | F2: DATE | G2: CLIENT | H2: INV | I2: DISBURSEMENT | J2: DN | K2: DATE | L2: EXCHANGE RATE | M2: weekday | N2: CLEAR FEE | O2: THC | P2: CM | Q2: INV (REVENUE) | R2: REIM | S2: VAT 10% | T2: DN | U2: NET PROFIT | V2: MARK
A3: PAID | B3: 11 | C3: =INDEX(PORT!$B$2:$B$20,MATCH('04'!B3,PORT!$A$2:$A$20)) -> SHV11 | D3: =INDEX(PORT!$C$2:$C$20,MATCH('04'!B3,PORT!$A$2:$A$20)) -> SHV PORT | E3: I 44874 | F3: 46113 | G3: JR | H3: GS26-118 | I3: DIS127 | J3: JR2604001 | K3: 46114 | L3: =VLOOKUP(K3,'[4]Exchange Rate'!$A$3:$C$21,3,FALSE) -> 3999 | M3: =TEXT(K3,"dddd") -> Thursday | N3: 925.95 | O3: 721.5 | P3: 0 | Q3: 200 | R3: 835.95 | S3: =ROUND(Q3*10%,2) -> 20 | T3: 869 | U3: =(Q3+R3+T3)-(N3+O3+P3) -> 257.5 | V3: THC PAID ON MAR
A4: PAID | B4: 1 | C4: =INDEX(PORT!$B$2:$B$20,MATCH('04'!B4,PORT!$A$2:$A$20)) -> PNH01 | D4: =INDEX(PORT!$C$2:$C$20,MATCH('04'!B4,PORT!$A$2:$A$20)) -> KTI AIR PORT | E4: E 12322 | F4: 46113 | G4: VFL | H4: GS26-119 | I4: DIS128 | J4: VFL2604001 | K4: 46114 | L4: =VLOOKUP(K4,'[4]Exchange Rate'!$A$3:$C$21,3,FALSE) -> 3999 | M4: =TEXT(K4,"dddd") -> Thursday | N4: 85.95 | O4: 0 | P4: 50 | Q4: 140 | R4: 15.95 | S4: =ROUND(Q4*10%,2) -> 14 | T4: 60 | U4: =(Q4+R4+T4)-(N4+O4+P4) -> 80
A5: PAID | B5: 11 | C5: =INDEX(PORT!$B$2:$B$20,MATCH('04'!B5,PORT!$A$2:$A$20)) -> SHV11 | D5: =INDEX(PORT!$C$2:$C$20,MATCH('04'!B5,PORT!$A$2:$A$20)) -> SHV PORT | E5: I 44741 | F5: 46113 | G5: VFL | H5: GS26-120 | I5: DIS129 | J5: VFL2604002 | K5: 46114 | L5: =VLOOKUP(K5,'[4]Exchange Rate'!$A$3:$C$21,3,FALSE) -> 3999 | M5: =TEXT(K5,"dddd") -> Thursday | N5: 349.01 | O5: 803.44 | P5: 50 | Q5: 150 | R5: 30.58 | S5: =ROUND(Q5*10%,2) -> 15 | T5: 401.12 | U5: =(Q5+R5+T5)-(N5+O5+P5) -> -620.75 | V5: THC PAID ON MAR
A6: PAID | B6: 1 | C6: =INDEX(PORT!$B$2:$B$20,MATCH('04'!B6,PORT!$A$2:$A$20)) -> PNH01 | D6: =INDEX(PORT!$C$2:$C$20,MATCH('04'!B6,PORT!$A$2:$A$20)) -> KTI AIR PORT | E6: E 12666 | F6: 46115 | G6: JIN YUAN XI | H6: GS26-121 | I6: DIS130 | J6: JYX2604001 | K6: 46118 | L6: =VLOOKUP(K6,'[4]Exchange Rate'!$A$3:$C$21,3,FALSE) -> 3999 | M6: =TEXT(K6,"dddd") -> Monday | N6: 204.41 | O6: 0 | P6: 50 | Q6: 175 | R6: 84.41 | S6: =ROUND(Q6*10%,2) -> 17.5 | T6: 180 | U6: =(Q6+R6+T6)-(N6+O6+P6) -> 185
A7: PAID | B7: 1 | C7: =INDEX(PORT!$B$2:$B$20,MATCH('04'!B7,PORT!$A$2:$A$20)) -> PNH01 | D7: =INDEX(PORT!$C$2:$C$20,MATCH('04'!B7,PORT!$A$2:$A$20)) -> KTI AIR PORT | E7: E 12814 | F7: 46116 | G7: JIN YUAN XI | H7: GS26-122 | I7: DIS131 | J7: JYX2604002 | K7: 46118 | L7: =VLOOKUP(K7,'[4]Exchange Rate'!$A$3:$C$21,3,FALSE) -> 3999 | M7: =TEXT(K7,"dddd") -> Monday | N7: 373.39 | O7: 0 | P7: 50 | Q7: 220 | R7: 203.39 | S7: =ROUND(Q7*10%,2) -> 22 | T7: 280 | U7: =(Q7+R7+T7)-(N7+O7+P7) -> 280
A8: PAID | B8: 1 | C8: =INDEX(PORT!$B$2:$B$20,MATCH('04'!B8,PORT!$A$2:$A$20)) -> PNH01 | D8: =INDEX(PORT!$C$2:$C$20,MATCH('04'!B8,PORT!$A$2:$A$20)) -> KTI AIR PORT | E8: E 12839 | F8: 46117 | G8: JIN YUAN XI | H8: GS26-123 | I8: DIS132 | J8: JYX2604003 | K8: 46118 | L8: =VLOOKUP(K8,'[4]Exchange Rate'!$A$3:$C$21,3,FALSE) -> 3999 | M8: =TEXT(K8,"dddd") -> Monday | N8: 224.21 | O8: 0 | P8: 50 | Q8: 175 | R8: 74.21 | S8: =ROUND(Q8*10%,2) -> 17.5 | T8: 230 | U8: =(Q8+R8+T8)-(N8+O8+P8) -> 205
A9: PAID | B9: 1 | C9: =INDEX(PORT!$B$2:$B$20,MATCH('04'!B9,PORT!$A$2:$A$20)) -> PNH01 | D9: =INDEX(PORT!$C$2:$C$20,MATCH('04'!B9,PORT!$A$2:$A$20)) -> KTI AIR PORT | E9: E 12840 | F9: 46117 | G9: JIN YUAN XI | H9: GS26-124 | I9: DIS133 | J9: JYX2604004 | K9: 46118 | L9: =VLOOKUP(K9,'[4]Exchange Rate'!$A$3:$C$21,3,FALSE) -> 3999 | M9: =TEXT(K9,"dddd") -> Monday | N9: 205.9 | O9: 0 | P9: 50 | Q9: 150 | R9: 55.9 | S9: =ROUND(Q9*10%,2) -> 15 | T9: 230 | U9: =(Q9+R9+T9)-(N9+O9+P9) -> 180
A10: PAID | B10: 1 | C10: =INDEX(PORT!$B$2:$B$20,MATCH('04'!B10,PORT!$A$2:$A$20)) -> PNH01 | D10: =INDEX(PORT!$C$2:$C$20,MATCH('04'!B10,PORT!$A$2:$A$20)) -> KTI AIR PORT | E10: E 12841 | F10: 46117 | G10: JIN YUAN XI | H10: GS26-125 | I10: DIS134 | J10: JYX2604005 | K10: 46118 | L10: =VLOOKUP(K10,'[4]Exchange Rate'!$A$3:$C$21,3,FALSE) -> 3999 | M10: =TEXT(K10,"dddd") -> Monday | N10: 187.6 | O10: 0 | P10: 50 | Q10: 150 | R10: 37.6 | S10: =ROUND(Q10*10%,2) -> 15 | T10: 230 | U10: =(Q10+R10+T10)-(N10+O10+P10) -> 180
A11: PAID | B11: 4 | C11: =INDEX(PORT!$B$2:$B$20,MATCH('04'!B11,PORT!$A$2:$A$20)) -> PNH04 | D11: =INDEX(PORT!$C$2:$C$20,MATCH('04'!B11,PORT!$A$2:$A$20)) -> PNH PORT | E11: E 91660 | F11: 46115 | G11: JR | H11: GS26-126 | I11: DIS135 | J11: JR2604002 | K11: 46118 | L11: =VLOOKUP(K11,'[4]Exchange Rate'!$A$3:$C$21,3,FALSE) -> 3999 | M11: =TEXT(K11,"dddd") -> Monday | N11: 578.25 | O11: 528 | P11: 0 | Q11: 242 | R11: 626.25 | S11: =ROUND(Q11*10%,2) -> 24.2 | T11: 1006.5 | U11: =(Q11+R11+T11)-(N11+O11+P11) -> 768.5 | V11: LAT2026-00300
A12: PAID | B12: 4 | C12: =INDEX(PORT!$B$2:$B$20,MATCH('04'!B12,PORT!$A$2:$A$20)) -> PNH04 | D12: =INDEX(PORT!$C$2:$C$20,MATCH('04'!B12,PORT!$A$2:$A$20)) -> PNH PORT | E12: E 92324 | F12: 46115 | G12: JR | H12: GS26-127 | I12: DIS136 | J12: JR2604003 | K12: 46118 | L12: =VLOOKUP(K12,'[4]Exchange Rate'!$A$3:$C$21,3,FALSE) -> 3999 | M12: =TEXT(K12,"dddd") -> Monday | N12: 607.75 | O12: 506 | P12: 0 | Q12: 242 | R12: 604.25 | S12: =ROUND(Q12*10%,2) -> 24.2 | T12: 947.5 | U12: =(Q12+R12+T12)-(N12+O12+P12) -> 680 | V12: BLS26-0158 & BLS26-0159
A13: PAID | B13: 1 | C13: =INDEX(PORT!$B$2:$B$20,MATCH('04'!B13,PORT!$A$2:$A$20)) -> PNH01 | D13: =INDEX(PORT!$C$2:$C$20,MATCH('04'!B13,PORT!$A$2:$A$20)) -> KTI AIR PORT | E13: I 10151 | F13: 46119 | G13: SPORTLINE | H13: GS26-128 | I13: DIS137 | J13: SAK2604001 | K13: 46120 | L13: =VLOOKUP(K13,'[4]Exchange Rate'!$A$3:$C$21,3,FALSE) -> 3999 | M13: =TEXT(K13,"dddd") -> Wednesday | N13: 105.95 | O13: 0 | P13: 50 | Q13: 150 | R13: 4.45 | S13: =ROUND(Q13*10%,2) -> 15 | T13: 46.75 | U13: =(Q13+R13+T13)-(N13+O13+P13) -> 45.25
A14: PAID | B14: 4 | C14: =INDEX(PORT!$B$2:$B$20,MATCH('04'!B14,PORT!$A$2:$A$20)) -> PNH04 | D14: =INDEX(PORT!$C$2:$C$20,MATCH('04'!B14,PORT!$A$2:$A$20)) -> PNH PORT | E14: E 94582 | F14: 46119 | G14: VFL | H14: GS26-129 | I14: DIS138 | J14: VFL2604003 | K14: 46120 | L14: =VLOOKUP(K14,'[4]Exchange Rate'!$A$3:$C$21,3,FALSE) -> 3999 | M14: =TEXT(K14,"dddd") -> Wednesday | N14: 462.65 | O14: 0 | P14: 50 | Q14: 245 | R14: 152.05 | S14: =ROUND(Q14*10%,2) -> 24.5 | T14: 411.5 | U14: =(Q14+R14+T14)-(N14+O14+P14) -> 295.9
A15: PAID | B15: 11 | C15: =INDEX(PORT!$B$2:$B$20,MATCH('04'!B15,PORT!$A$2:$A$20)) -> SHV11 | D15: =INDEX(PORT!$C$2:$C$20,MATCH('04'!B15,PORT!$A$2:$A$20)) -> SHV PORT | E15: I 48322 | F15: 46120 | G15: JR | H15: GS26-130 | I15: DIS139 | J15: JR2604004 | K15: 46121 | L15: =VLOOKUP(K15,'[4]Exchange Rate'!$A$3:$C$21,3,FALSE) -> 3999 | M15: =TEXT(K15,"dddd") -> Thursday | N15: 697.95 | O15: 491.5 | P15: 0 | Q15: 180 | R15: 572.95 | S15: =ROUND(Q15*10%,2) -> 18 | T15: 733.5 | U15: =(Q15+R15+T15)-(N15+O15+P15) -> 297
A16: PAID | B16: 1 | C16: =INDEX(PORT!$B$2:$B$20,MATCH('04'!B16,PORT!$A$2:$A$20)) -> PNH01 | D16: =INDEX(PORT!$C$2:$C$20,MATCH('04'!B16,PORT!$A$2:$A$20)) -> KTI AIR PORT | E16: E 13592 | F16: 46121 | G16: JIN YUAN XI | H16: GS26-131 | I16: DIS140 | J16: JYX2604006 | K16: 46122 | L16: =VLOOKUP(K16,'[4]Exchange Rate'!$A$3:$C$21,3,FALSE) -> 4000 | M16: =TEXT(K16,"dddd") -> Friday | N16: 186.99 | O16: 0 | P16: 50 | Q16: 175 | R16: 66.99 | S16: =ROUND(Q16*10%,2) -> 17.5 | T16: 180 | U16: =(Q16+R16+T16)-(N16+O16+P16) -> 185
A17: PAID | B17: 4 | C17: =INDEX(PORT!$B$2:$B$20,MATCH('04'!B17,PORT!$A$2:$A$20)) -> PNH04 | D17: =INDEX(PORT!$C$2:$C$20,MATCH('04'!B17,PORT!$A$2:$A$20)) -> PNH PORT | E17: E 95300 | F17: 46121 | G17: SPORTLINE | H17: GS26-132 | I17: DIS141 | J17: SAK2604002 | K17: 46122 | L17: =VLOOKUP(K17,'[4]Exchange Rate'!$A$3:$C$21,3,FALSE) -> 4000 | M17: =TEXT(K17,"dddd") -> Friday | N17: 1132.76 | O17: 0 | P17: 50 | Q17: 490 | R17: 282.75 | S17: =ROUND(Q17*10%,2) -> 49 | T17: 1078 | U17: =(Q17+R17+T17)-(N17+O17+P17) -> 667.99
A18: PAID | B18: 1 | C18: =INDEX(PORT!$B$2:$B$20,MATCH('04'!B18,PORT!$A$2:$A$20)) -> PNH01 | D18: =INDEX(PORT!$C$2:$C$20,MATCH('04'!B18,PORT!$A$2:$A$20)) -> KTI AIR PORT | E18: I 10534 | F18: 46121 | G18: SPORTLINE | H18: GS26-133 | I18: DIS142 | J18: SAK2604003 | K18: 46122 | L18: =VLOOKUP(K18,'[4]Exchange Rate'!$A$3:$C$21,3,FALSE) -> 4000 | M18: =TEXT(K18,"dddd") -> Friday | N18: 168.4 | O18: 104.5 | P18: 50 | Q18: 150 | R18: 122.9 | S18: =ROUND(Q18*10%,2) -> 15 | T18: 196.75 | U18: =(Q18+R18+T18)-(N18+O18+P18) -> 146.75
A19: PAID | B19: 4 | C19: =INDEX(PORT!$B$2:$B$20,MATCH('04'!B19,PORT!$A$2:$A$20)) -> PNH04 | D19: =INDEX(PORT!$C$2:$C$20,MATCH('04'!B19,PORT!$A$2:$A$20)) -> PNH PORT | E19: E 95135 | F19: 46121 | G19: VFL | H19: GS26-134 | I19: DIS143 | J19: VFL2604004 | K19: 46122 | L19: =VLOOKUP(K19,'[4]Exchange Rate'!$A$3:$C$21,3,FALSE) -> 4000 | M19: =TEXT(K19,"dddd") -> Friday | N19: 462.65 | O19: 0 | P19: 50 | Q19: 245 | R19: 152.05 | S19: =ROUND(Q19*10%,2) -> 24.5 | T19: 411.5 | U19: =(Q19+R19+T19)-(N19+O19+P19) -> 295.9
A20: PAID | B20: 1 | C20: =INDEX(PORT!$B$2:$B$20,MATCH('04'!B20,PORT!$A$2:$A$20)) -> PNH01 | D20: =INDEX(PORT!$C$2:$C$20,MATCH('04'!B20,PORT!$A$2:$A$20)) -> KTI AIR PORT | E20: E 14148 | F20: 46124 | G20: JIN YUAN XI | H20: GS26-135 | I20: DIS144 | J20: JYX2604007 | K20: 46125 | L20: =VLOOKUP(K20,'[4]Exchange Rate'!$A$3:$C$21,3,FALSE) -> 4000 | M20: =TEXT(K20,"dddd") -> Monday | N20: 251.4 | O20: 0 | P20: 50 | Q20: 175 | R20: 101.4 | S20: =ROUND(Q20*10%,2) -> 17.5 | T20: 230 | U20: =(Q20+R20+T20)-(N20+O20+P20) -> 205
A21: PAID | B21: 1 | C21: =INDEX(PORT!$B$2:$B$20,MATCH('04'!B21,PORT!$A$2:$A$20)) -> PNH01 | D21: =INDEX(PORT!$C$2:$C$20,MATCH('04'!B21,PORT!$A$2:$A$20)) -> KTI AIR PORT | E21: E 14154 | F21: 46124 | G21: JIN YUAN XI | H21: GS26-136 | I21: DIS145 | J21: JYX2604008 | K21: 46125 | L21: =VLOOKUP(K21,'[4]Exchange Rate'!$A$3:$C$21,3,FALSE) -> 4000 | M21: =TEXT(K21,"dddd") -> Monday | N21: 406.98 | O21: 0 | P21: 50 | Q21: 230 | R21: 256.98 | S21: =ROUND(Q21*10%,2) -> 23 | T21: 230 | U21: =(Q21+R21+T21)-(N21+O21+P21) -> 260
A22: PAID | B22: 1 | C22: =INDEX(PORT!$B$2:$B$20,MATCH('04'!B22,PORT!$A$2:$A$20)) -> PNH01 | D22: =INDEX(PORT!$C$2:$C$20,MATCH('04'!B22,PORT!$A$2:$A$20)) -> KTI AIR PORT | E22: E 14158 | F22: 46124 | G22: JIN YUAN XI | H22: GS26-137 | I22: DIS146 | J22: JYX2604009 | K22: 46125 | L22: =VLOOKUP(K22,'[4]Exchange Rate'!$A$3:$C$21,3,FALSE) -> 4000 | M22: =TEXT(K22,"dddd") -> Monday | N22: 203.35 | O22: 0 | P22: 50 | Q22: 150 | R22: 53.35 | S22: =ROUND(Q22*10%,2) -> 15 | T22: 230 | U22: =(Q22+R22+T22)-(N22+O22+P22) -> 180
A23: PAID | B23: 1 | C23: =INDEX(PORT!$B$2:$B$20,MATCH('04'!B23,PORT!$A$2:$A$20)) -> PNH01 | D23: =INDEX(PORT!$C$2:$C$20,MATCH('04'!B23,PORT!$A$2:$A$20)) -> KTI AIR PORT | E23: E 14162 | F23: 46124 | G23: JIN YUAN XI | H23: GS26-138 | I23: DIS147 | J23: JYX2604010 | K23: 46125 | L23: =VLOOKUP(K23,'[4]Exchange Rate'!$A$3:$C$21,3,FALSE) -> 4000 | M23: =TEXT(K23,"dddd") -> Monday | N23: 398.71 | O23: 0 | P23: 50 | Q23: 230 | R23: 248.71 | S23: =ROUND(Q23*10%,2) -> 23 | T23: 230 | U23: =(Q23+R23+T23)-(N23+O23+P23) -> 260
A24: PAID | B24: 4 | C24: =INDEX(PORT!$B$2:$B$20,MATCH('04'!B24,PORT!$A$2:$A$20)) -> PNH04 | D24: =INDEX(PORT!$C$2:$C$20,MATCH('04'!B24,PORT!$A$2:$A$20)) -> PNH PORT | E24: E 98669 | F24: 46122 | G24: SPORTLINE | H24: GS26-139 | I24: DIS148 | J24: SAK2604004 | K24: 46125 | L24: =VLOOKUP(K24,'[4]Exchange Rate'!$A$3:$C$21,3,FALSE) -> 4000 | M24: =TEXT(K24,"dddd") -> Monday | N24: 1106.36 | O24: 0 | P24: 50 | Q24: 460 | R24: 256.35 | S24: =ROUND(Q24*10%,2) -> 46 | T24: 1051.5 | U24: =(Q24+R24+T24)-(N24+O24+P24) -> 611.49
A25: PAID | B25: 4 | C25: =INDEX(PORT!$B$2:$B$20,MATCH('04'!B25,PORT!$A$2:$A$20)) -> PNH04 | D25: =INDEX(PORT!$C$2:$C$20,MATCH('04'!B25,PORT!$A$2:$A$20)) -> PNH PORT | E25: E 99067 | F25: 46122 | G25: JR | H25: GS26-140 | I25: DIS149 | J25: JR2604005 | K25: 46125 | L25: =VLOOKUP(K25,'[4]Exchange Rate'!$A$3:$C$21,3,FALSE) -> 4000 | M25: =TEXT(K25,"dddd") -> Monday | N25: 582.75 | O25: 506 | P25: 0 | Q25: 242 | R25: 604.25 | S25: =ROUND(Q25*10%,2) -> 24.2 | T25: 787.5 | U25: =(Q25+R25+T25)-(N25+O25+P25) -> 545 | V25: BLS26-0160 & BLS26-0161
A26: PAID | B26: 1 | C26: =INDEX(PORT!$B$2:$B$20,MATCH('04'!B26,PORT!$A$2:$A$20)) -> PNH01 | D26: =INDEX(PORT!$C$2:$C$20,MATCH('04'!B26,PORT!$A$2:$A$20)) -> KTI AIR PORT | E26: E 13648 | F26: 46122 | G26: VFL | H26: GS26-141 | I26: DIS150 | J26: VFL2604005 | K26: 46125 | L26: =VLOOKUP(K26,'[4]Exchange Rate'!$A$3:$C$21,3,FALSE) -> 4000 | M26: =TEXT(K26,"dddd") -> Monday | N26: 88.77 | O26: 0 | P26: 50 | Q26: 140 | R26: 18.77 | S26: =ROUND(Q26*10%,2) -> 14 | T26: 60 | U26: =(Q26+R26+T26)-(N26+O26+P26) -> 80
A27: PAID | B27: 4 | C27: =INDEX(PORT!$B$2:$B$20,MATCH('04'!B27,PORT!$A$2:$A$20)) -> PNH04 | D27: =INDEX(PORT!$C$2:$C$20,MATCH('04'!B27,PORT!$A$2:$A$20)) -> PNH PORT | E27: E 98786 | F27: 46122 | G27: VFL | H27: GS26-142 | I27: DIS151 | J27: VFL2604006 | K27: 46125 | L27: =VLOOKUP(K27,'[4]Exchange Rate'!$A$3:$C$21,3,FALSE) -> 4000 | M27: =TEXT(K27,"dddd") -> Monday | N27: 453.85 | O27: 0 | P27: 50 | Q27: 245 | R27: 143.25 | S27: =ROUND(Q27*10%,2) -> 24.5 | T27: 411.5 | U27: =(Q27+R27+T27)-(N27+O27+P27) -> 295.9
A28: PAID | B28: 21 | C28: =INDEX(PORT!$B$2:$B$20,MATCH('04'!B28,PORT!$A$2:$A$20)) -> PNH21 | D28: =INDEX(PORT!$C$2:$C$20,MATCH('04'!B28,PORT!$A$2:$A$20)) -> OLAIR DRY PORT | E28: I 1211 | F28: 46132 | G28: SPORTLINE | H28: GS26-143 | I28: DIS152 | J28: SAK2604005 | K28: 46133 | L28: =VLOOKUP(K28,'[4]Exchange Rate'!$A$3:$C$21,3,FALSE) -> 3998 | M28: =TEXT(K28,"dddd") -> Tuesday | N28: 158.5 | O28: 303.88 | P28: 50 | Q28: 150 | R28: 352.38 | S28: =ROUND(Q28*10%,2) -> 15 | T28: 159 | U28: =(Q28+R28+T28)-(N28+O28+P28) -> 149
A29: PAID | B29: 11 | C29: =INDEX(PORT!$B$2:$B$20,MATCH('04'!B29,PORT!$A$2:$A$20)) -> SHV11 | D29: =INDEX(PORT!$C$2:$C$20,MATCH('04'!B29,PORT!$A$2:$A$20)) -> SHV PORT | E29: I 53023 | F29: 46132 | G29: SPORTLINE | H29: GS26-144 | I29: DIS153 | J29: SAK2604006 | K29: 46133 | L29: =VLOOKUP(K29,'[4]Exchange Rate'!$A$3:$C$21,3,FALSE) -> 3998 | M29: =TEXT(K29,"dddd") -> Tuesday | N29: 192.73 | O29: 227.03 | P29: 50 | Q29: 150 | R29: 243.34 | S29: =ROUND(Q29*10%,2) -> 15 | T29: 159.5 | U29: =(Q29+R29+T29)-(N29+O29+P29) -> 83.08
A30: PAID | B30: 11 | C30: =INDEX(PORT!$B$2:$B$20,MATCH('04'!B30,PORT!$A$2:$A$20)) -> SHV11 | D30: =INDEX(PORT!$C$2:$C$20,MATCH('04'!B30,PORT!$A$2:$A$20)) -> SHV PORT | E30: I 52781 | F30: 46132 | G30: VFL | H30: GS26-145 | I30: DIS154 | J30: VFL2604007 | K30: 46133 | L30: =VLOOKUP(K30,'[4]Exchange Rate'!$A$3:$C$21,3,FALSE) -> 3998 | M30: =TEXT(K30,"dddd") -> Tuesday | N30: 166.621 | O30: 348.05 | P30: 50 | Q30: 150 | R30: 365.17 | S30: =ROUND(Q30*10%,2) -> 15 | T30: 109.5 | U30: =(Q30+R30+T30)-(N30+O30+P30) -> 59.999
A31: PAID | B31: 11 | C31: =INDEX(PORT!$B$2:$B$20,MATCH('04'!B31,PORT!$A$2:$A$20)) -> SHV11 | D31: =INDEX(PORT!$C$2:$C$20,MATCH('04'!B31,PORT!$A$2:$A$20)) -> SHV PORT | E31: I 52998 | F31: 46132 | G31: VFL | H31: GS26-146 | I31: DIS155 | J31: VFL2604008 | K31: 46133 | L31: =VLOOKUP(K31,'[4]Exchange Rate'!$A$3:$C$21,3,FALSE) -> 3998 | M31: =TEXT(K31,"dddd") -> Tuesday | N31: 145.43 | O31: 198 | P31: 50 | Q31: 150 | R31: 213.43 | S31: =ROUND(Q31*10%,2) -> 15 | T31: 114.5 | U31: =(Q31+R31+T31)-(N31+O31+P31) -> 84.5
A32: PAID | B32: 11 | C32: =INDEX(PORT!$B$2:$B$20,MATCH('04'!B32,PORT!$A$2:$A$20)) -> SHV11 | D32: =INDEX(PORT!$C$2:$C$20,MATCH('04'!B32,PORT!$A$2:$A$20)) -> SHV PORT | E32: I 54125 | F32: 46133 | G32: JR | H32: GS26-147 | I32: DIS156 | J32: JR2604006 | K32: 46134 | L32: =VLOOKUP(K32,'[4]Exchange Rate'!$A$3:$C$21,3,FALSE) -> 3999 | M32: =TEXT(K32,"dddd") -> Wednesday | N32: 898.45 | O32: 691.5 | P32: 0 | Q32: 200 | R32: 805.95 | S32: =ROUND(Q32*10%,2) -> 20 | T32: 1091.5 | U32: =(Q32+R32+T32)-(N32+O32+P32) -> 507.5
A33: PAID | B33: 1 | C33: =INDEX(PORT!$B$2:$B$20,MATCH('04'!B33,PORT!$A$2:$A$20)) -> PNH01 | D33: =INDEX(PORT!$C$2:$C$20,MATCH('04'!B33,PORT!$A$2:$A$20)) -> KTI AIR PORT | E33: I 11292 | F33: 46133 | G33: VFL | H33: GS26-148 | I33: DIS157 | J33: VFL2604009 | K33: 46134 | L33: =VLOOKUP(K33,'[4]Exchange Rate'!$A$3:$C$21,3,FALSE) -> 3999 | M33: =TEXT(K33,"dddd") -> Wednesday | N33: 153.4 | O33: 71.5 | P33: 50 | Q33: 150 | R33: 89.9 | S33: =ROUND(Q33*10%,2) -> 15 | T33: 130.75 | U33: =(Q33+R33+T33)-(N33+O33+P33) -> 95.75
A34: PAID | B34: 11 | C34: =INDEX(PORT!$B$2:$B$20,MATCH('04'!B34,PORT!$A$2:$A$20)) -> SHV11 | D34: =INDEX(PORT!$C$2:$C$20,MATCH('04'!B34,PORT!$A$2:$A$20)) -> SHV PORT | E34: I 54535 | F34: 46134 | G34: JR | H34: GS26-149 | I34: DIS158 | J34: JR2604007 | K34: 46135 | L34: =VLOOKUP(K34,'[4]Exchange Rate'!$A$3:$C$21,3,FALSE) -> 3999 | M34: =TEXT(K34,"dddd") -> Thursday | N34: 746.45 | O34: 485.5 | P34: 0 | Q34: 180 | R34: 566.95 | S34: =ROUND(Q34*10%,2) -> 18 | T34: 732 | U34: =(Q34+R34+T34)-(N34+O34+P34) -> 247
A35: PAID | B35: 1 | C35: =INDEX(PORT!$B$2:$B$20,MATCH('04'!B35,PORT!$A$2:$A$20)) -> PNH01 | D35: =INDEX(PORT!$C$2:$C$20,MATCH('04'!B35,PORT!$A$2:$A$20)) -> KTI AIR PORT | E35: I 11660 | F35: 46135 | G35: JIN YUAN XI | H35: GS26-150 | I35: DIS159 | J35: JYX2604011 | K35: 46136 | L35: =VLOOKUP(K35,'[4]Exchange Rate'!$A$3:$C$21,3,FALSE) -> 4001 | M35: =TEXT(K35,"dddd") -> Friday | N35: 333.12 | O35: 0 | P35: 50 | Q35: 185 | R35: 123.12 | S35: =ROUND(Q35*10%,2) -> 18.5 | T35: 219.75 | U35: =(Q35+R35+T35)-(N35+O35+P35) -> 144.75
A36: PAID | B36: 4 | C36: =INDEX(PORT!$B$2:$B$20,MATCH('04'!B36,PORT!$A$2:$A$20)) -> PNH04 | D36: =INDEX(PORT!$C$2:$C$20,MATCH('04'!B36,PORT!$A$2:$A$20)) -> PNH PORT | E36: E 106314 | F36: 46135 | G36: SPORTLINE | H36: GS26-151 | I36: DIS160 | J36: SAK2604007 | K36: 46136 | L36: =VLOOKUP(K36,'[4]Exchange Rate'!$A$3:$C$21,3,FALSE) -> 4001 | M36: =TEXT(K36,"dddd") -> Friday | N36: 369.28 | O36: 0 | P36: 50 | Q36: 146.2 | R36: 143.25 | S36: =ROUND(Q36*10%,2) -> 14.62 | T36: 350.69 | U36: =(Q36+R36+T36)-(N36+O36+P36) -> 220.86
A37: PAID | B37: 4 | C37: =INDEX(PORT!$B$2:$B$20,MATCH('04'!B37,PORT!$A$2:$A$20)) -> PNH04 | D37: =INDEX(PORT!$C$2:$C$20,MATCH('04'!B37,PORT!$A$2:$A$20)) -> PNH PORT | E37: E 106324 | F37: 46135 | G37: VFL | H37: GS26-152 | I37: DIS161 | J37: VFL2604010 | K37: 46136 | L37: =VLOOKUP(K37,'[4]Exchange Rate'!$A$3:$C$21,3,FALSE) -> 4001 | M37: =TEXT(K37,"dddd") -> Friday | N37: 199.88 | O37: 0 | P37: 50 | Q37: 98.82 | R37: 13.75 | S37: =ROUND(Q37*10%,2) -> 9.88 | T37: 261.58 | U37: =(Q37+R37+T37)-(N37+O37+P37) -> 124.27
... A42: PAID | B42: 19 | C42: =INDEX(PORT!$B$2:$B$20,MATCH('04'!B42,PORT!$A$2:$A$20)) -> PNH19 | D42: =INDEX(PORT!$C$2:$C$20,MATCH('04'!B42,PORT!$A$2:$A$20)) -> TEC SRUN DRYPORT | E42: I 1157 | F42: 46136 | G42: VFL | H42: GS26-157 | I42: DIS166 | J42: VFL2604012 | K42: 46139 | L42: =VLOOKUP(K42,'[4]Exchange Rate'!$A$3:$C$21,3,FALSE) -> 4002 | M42: =TEXT(K42,"dddd") -> Monday | N42: 116.1 | O42: 193.6 | P42: 50 | Q42: 150 | R42: 219.7 | S42: =ROUND(Q42*10%,2) -> 15 | T42: 109.5 | U42: =(Q42+R42+T42)-(N42+O42+P42) -> 119.5
A43: PAID | B43: 11+ | C43: =INDEX(PORT!$B$2:$B$20,MATCH('04'!B43,PORT!$A$2:$A$20)) -> SVR11 | D43: =INDEX(PORT!$C$2:$C$20,MATCH('04'!B43,PORT!$A$2:$A$20)) -> BAVET CEO | E43: I 10242 | F43: 46137 | G43: VFL | H43: GS26-158 | I43: DIS167 | J43: VFL2604013 | K43: 46139 | L43: =VLOOKUP(K43,'[4]Exchange Rate'!$A$3:$C$21,3,FALSE) -> 4002 | M43: =TEXT(K43,"dddd") -> Monday | N43: 133.75 | O43: 0 | P43: 50 | Q43: 230 | R43: 2.25 | S43: =ROUND(Q43*10%,2) -> 23 | T43: 66.5 | U43: =(Q43+R43+T43)-(N43+O43+P43) -> 115
A44: PAID | B44: 1 | C44: =INDEX(PORT!$B$2:$B$20,MATCH('04'!B44,PORT!$A$2:$A$20)) -> PNH01 | D44: =INDEX(PORT!$C$2:$C$20,MATCH('04'!B44,PORT!$A$2:$A$20)) -> KTI AIR PORT | E44: E 15217 | F44: 46138 | G44: JIN YUAN XI | H44: GS26-159 | I44: DIS168 | J44: JYX2604014 | K44: 46139 | L44: =VLOOKUP(K44,'[4]Exchange Rate'!$A$3:$C$21,3,FALSE) -> 4002 | M44: =TEXT(K44,"dddd") -> Monday | N44: 354.01 | O44: 0 | P44: 50 | Q44: 220 | R44: 204.01 | S44: =ROUND(Q44*10%,2) -> 22 | T44: 230 | U44: =(Q44+R44+T44)-(N44+O44+P44) -> 250
A45: PAID | B45: 1 | C45: =INDEX(PORT!$B$2:$B$20,MATCH('04'!B45,PORT!$A$2:$A$20)) -> PNH01 | D45: =INDEX(PORT!$C$2:$C$20,MATCH('04'!B45,PORT!$A$2:$A$20)) -> KTI AIR PORT | E45: I 12076 | F45: 46139 | G45: SPORTLINE | H45: GS26-160 | I45: DIS169 | J45: SAK2604009 | K45: 46140 | L45: =VLOOKUP(K45,'[4]Exchange Rate'!$A$3:$C$21,3,FALSE) -> 4004 | M45: =TEXT(K45,"dddd") -> Tuesday | N45: 168.15 | O45: 60.5 | P45: 50 | Q45: 150 | R45: 67.15 | S45: =ROUND(Q45*10%,2) -> 15 | T45: 208.25 | U45: =(Q45+R45+T45)-(N45+O45+P45) -> 146.75
A46: PAID | B46: 4 | C46: =INDEX(PORT!$B$2:$B$20,MATCH('04'!B46,PORT!$A$2:$A$20)) -> PNH04 | D46: =INDEX(PORT!$C$2:$C$20,MATCH('04'!B46,PORT!$A$2:$A$20)) -> PNH PORT | E46: E 115285 | F46: 46142 | G46: JR | H46: GS26-161 | I46: DIS170 | J46: JR2604008 | K46: 46142 | L46: =VLOOKUP(K46,'[4]Exchange Rate'!$A$3:$C$21,3,FALSE) -> 4007 | M46: =TEXT(K46,"dddd") -> Thursday | N46: 952.14 | O46: 0 | P46: 0 | Q46: 213 | R46: 544.45 | S46: =ROUND(Q46*10%,2) -> 21.3 | T46: 1065.69 | U46: =(Q46+R46+T46)-(N46+O46+P46) -> 871 | V46: Original 945.54 + 6.6 STORAGE FEE 'E 79749 = 952.14
A47: PAID | B47: 4 | C47: =INDEX(PORT!$B$2:$B$20,MATCH('04'!B47,PORT!$A$2:$A$20)) -> PNH04 | D47: =INDEX(PORT!$C$2:$C$20,MATCH('04'!B47,PORT!$A$2:$A$20)) -> PNH PORT | E47: E 115341 | F47: 46142 | G47: JR | H47: GS26-162 | I47: DIS171 | J47: JR2604009 | K47: 46142 | L47: =VLOOKUP(K47,'[4]Exchange Rate'!$A$3:$C$21,3,FALSE) -> 4007 | M47: =TEXT(K47,"dddd") -> Thursday | N47: 519.85 | O47: 0 | P47: 0 | Q47: 213 | R47: 71.85 | S47: =ROUND(Q47*10%,2) -> 21.3 | T47: 590 | U47: =(Q47+R47+T47)-(N47+O47+P47) -> 355
A48: PAID | B48: 1 | C48: =INDEX(PORT!$B$2:$B$20,MATCH('04'!B48,PORT!$A$2:$A$20)) -> PNH01 | D48: =INDEX(PORT!$C$2:$C$20,MATCH('04'!B48,PORT!$A$2:$A$20)) -> KTI AIR PORT | E48: E 15672 | F48: 46142 | G48: VFL | H48: GS26-163 | I48: DIS172 | J48: VFL2604014 | K48: 46142 | L48: =VLOOKUP(K48,'[4]Exchange Rate'!$A$3:$C$21,3,FALSE) -> 4007 | M48: =TEXT(K48,"dddd") -> Thursday | N48: 85.95 | O48: 0 | P48: 50 | Q48: 140 | R48: 4.2 | S48: =ROUND(Q48*10%,2) -> 14 | T48: 66.75 | U48: =(Q48+R48+T48)-(N48+O48+P48) -> 75
A49: PAID | B49: 1 | C49: =INDEX(PORT!$B$2:$B$20,MATCH('04'!B49,PORT!$A$2:$A$20)) -> PNH01 | D49: =INDEX(PORT!$C$2:$C$20,MATCH('04'!B49,PORT!$A$2:$A$20)) -> KTI AIR PORT | E49: E 15984 | F49: 46142 | G49: JIN YUAN XI | H49: GS26-164 | I49: DIS173 | J49: JYX2604015 | K49: 46142 | L49: =VLOOKUP(K49,'[4]Exchange Rate'!$A$3:$C$21,3,FALSE) -> 4007 | M49: =TEXT(K49,"dddd") -> Thursday | N49: 219.99 | O49: 0 | P49: 50 | Q49: 175 | R49: 99.99 | S49: =ROUND(Q49*10%,2) -> 17.5 | T49: 180 | U49: =(Q49+R49+T49)-(N49+O49+P49) -> 185
A50: PAID | B50: 11 | C50: =INDEX(PORT!$B$2:$B$20,MATCH('04'!B50,PORT!$A$2:$A$20)) -> SHV11 | D50: =INDEX(PORT!$C$2:$C$20,MATCH('04'!B50,PORT!$A$2:$A$20)) -> SHV PORT | E50: I 60060 | F50: 46141 | G50: SPORTLINE | H50: GS26-165 | I50: DIS174 | J50: SAK2604010 | K50: 46142 | L50: =VLOOKUP(K50,'[4]Exchange Rate'!$A$3:$C$21,3,FALSE) -> 4007 | M50: =TEXT(K50,"dddd") -> Thursday | N50: 250.8 | O50: 390.72 | P50: 50 | Q50: 150 | R50: 411.2 | S50: =ROUND(Q50*10%,2) -> 15 | T50: 231.16 | U50: =(Q50+R50+T50)-(N50+O50+P50) -> 100.84
A51: PAID | B51: 11 | C51: =INDEX(PORT!$B$2:$B$20,MATCH('04'!B51,PORT!$A$2:$A$20)) -> SHV11 | D51: =INDEX(PORT!$C$2:$C$20,MATCH('04'!B51,PORT!$A$2:$A$20)) -> SHV PORT | E51: I 60109 | F51: 46141 | G51: SPORTLINE | H51: GS26-166 | I51: DIS175 | J51: SAK2604011 | K51: 46142 | L51: =VLOOKUP(K51,'[4]Exchange Rate'!$A$3:$C$21,3,FALSE) -> 4007 | M51: =TEXT(K51,"dddd") -> Thursday | N51: 188.35 | O51: 207.11 | P51: 50 | Q51: 150 | R51: 222.54 | S51: =ROUND(Q51*10%,2) -> 15 | T51: 159.5 | U51: =(Q51+R51+T51)-(N51+O51+P51) -> 86.58
A52: PAID | B52: 1 | C52: =INDEX(PORT!$B$2:$B$20,MATCH('04'!B52,PORT!$A$2:$A$20)) -> PNH01 | D52: =INDEX(PORT!$C$2:$C$20,MATCH('04'!B52,PORT!$A$2:$A$20)) -> KTI AIR PORT | E52: I 12297 | F52: 46141 | G52: JIN YUAN XI | H52: GS26-167 | I52: DIS176 | J52: JYX2604016 | K52: 46142 | L52: =VLOOKUP(K52,'[4]Exchange Rate'!$A$3:$C$21,3,FALSE) -> 4007 | M52: =TEXT(K52,"dddd") -> Thursday | N52: 351.46 | O52: 0 | P52: 50 | Q52: 185 | R52: 151.46 | S52: =ROUND(Q52*10%,2) -> 18.5 | T52: 219.75 | U52: =(Q52+R52+T52)-(N52+O52+P52) -> 154.75
B53: 4 | C53: =INDEX(PORT!$B$2:$B$20,MATCH('04'!B53,PORT!$A$2:$A$20)) -> PNH04 | D53: =INDEX(PORT!$C$2:$C$20,MATCH('04'!B53,PORT!$A$2:$A$20)) -> PNH PORT | E53: LAT2026-00379 & RE260012 | F53: 46141 | G53: JR | I53: DIS177 | J53: JR2604010 | K53: 46142 | L53: =VLOOKUP(K53,'[4]Exchange Rate'!$A$3:$C$21,3,FALSE) -> 4007 | M53: =TEXT(K53,"dddd") -> Thursday | N53: 0 | O53: 836.14 | P53: 0 | Q53: 0 | R53: 836.14 | S53: =ROUND(Q53*10%,2) -> 0 | T53: 203 | U53: =(Q53+R53+T53)-(N53+O53+P53) -> 203 | V53: E 110436-4/24
B54: 4 | C54: =INDEX(PORT!$B$2:$B$20,MATCH('04'!B54,PORT!$A$2:$A$20)) -> PNH04 | D54: =INDEX(PORT!$C$2:$C$20,MATCH('04'!B54,PORT!$A$2:$A$20)) -> PNH PORT | E54: LAT2026-00358 & LAT2026-00359 | F54: 46135 | G54: JR | I54: DIS178 | J54: JR2604011 | K54: 46142 | L54: =VLOOKUP(K54,'[4]Exchange Rate'!$A$3:$C$21,3,FALSE) -> 4007 | M54: =TEXT(K54,"dddd") -> Thursday | N54: 0 | O54: 638.34 | P54: 0 | Q54: 0 | R54: 638.24 | S54: =ROUND(Q54*10%,2) -> 0 | T54: 203 | U54: =(Q54+R54+T54)-(N54+O54+P54) -> 202.9 | V54: E 98601-4/10
E55: LOLO
E56: STORAGE
E57: THC
B59: =SUBTOTAL(3,B3:B58) -> 52 | E59: TOTAL: | H59: =SUBTOTAL(3,H3:H58) -> 50 | I59: =SUBTOTAL(3,I3:I58) -> 52 | J59: =SUBTOTAL(3,J3:J58) -> 52 | N59: =SUM(N3:N54) -> 17949.121 | O59: =SUBTOTAL(9,O3:O54) -> 8815.35 | P59: =SUBTOTAL(9,P3:P54) -> 2050 | Q59: =SUBTOTAL(9,Q3:Q54) -> 9537.02 | R59: =SUBTOTAL(9,R3:R54) -> 12796.42 | S59: =SUBTOTAL(9,S3:S54) -> 953.7 | T59: =SUBTOTAL(9,T3:T54) -> 18261.24 | U59: =SUBTOTAL(9,U3:U57) -> 11780.209
M60: PAID | N60: =SUMIFS($N$3:$N$54,$A$3:$A$54,$M$60) -> 17949.121 | U60: =Q59+S59 -> 10490.72
M61: NOT YET | N61: =SUMIFS($N$3:$N$54,$A$3:$A$54,$M$61) -> 0
L63: Should Pay | M63: =N61 -> 0
L64: PAID | M64: 5000 | N64: 46139
L65: PAID | M65: 4000 | N65: 46151
L66: PAID | M66: 6000 | N66: 46154
L67: PAID | M67: 2949.12 | N67: 46155
L68: Total | M68: =M64+M65+M66+M67 -> 17949.12 | N68: PAID DONE ALL

Sheet 05
E1: REVENUE & EXPENSE | M1: Saturday
A2: CHEA PAYMENT | B2: PORT NUMBER | C2: PORT CODE | D2: PORT NAME | E2: DECLARE | F2: DATE | G2: CLIENT | H2: INV | I2: DISBURSEMENT | J2: DN | K2: DATE | L2: EXCHANGE RATE | M2: weekday | N2: CLEAR FEE | O2: THC | P2: CM | Q2: INV (REVENUE) | R2: REIM | S2: VAT 10% | T2: DN | U2: NET PROFIT | V2: MARK
A3: PAID | B3: 1 | C3: =INDEX(PORT!$B$2:$B$20,MATCH('05'!B3,PORT!$A$2:$A$20)) -> PNH01 | D3: =INDEX(PORT!$C$2:$C$20,MATCH('05'!B3,PORT!$A$2:$A$20)) -> KTI AIR PORT | E3: E 16039 | F3: 46144 | G3: JIN YUAN XI | H3: GS26-168 | I3: DIS179 | J3: JYX2605001 | K3: 46146 | L3: =VLOOKUP(K3,'[5]Exchange Rate'!$A$3:$C$21,3,FALSE) -> 4005 | M3: =TEXT(K3,"dddd") -> Monday | N3: 253.87 | O3: 0 | P3: 50 | Q3: 210 | R3: 133.87 | S3: =ROUND(Q3*10%,2) -> 21 | T3: 180 | U3: =(Q3+R3+T3)-(N3+O3+P3) -> 220
A4: PAID | B4: 1 | C4: =INDEX(PORT!$B$2:$B$20,MATCH('05'!B4,PORT!$A$2:$A$20)) -> PNH01 | D4: =INDEX(PORT!$C$2:$C$20,MATCH('05'!B4,PORT!$A$2:$A$20)) -> KTI AIR PORT | E4: E 16045 | F4: 46144 | G4: JIN YUAN XI | H4: GS26-169 | I4: DIS180 | J4: JYX2605002 | K4: 46146 | L4: =VLOOKUP(K4,'[5]Exchange Rate'!$A$3:$C$21,3,FALSE) -> 4005 | M4: =TEXT(K4,"dddd") -> Monday | N4: 266.89 | O4: 0 | P4: 50 | Q4: 220 | R4: 146.89 | S4: =ROUND(Q4*10%,2) -> 22 | T4: 180 | U4: =(Q4+R4+T4)-(N4+O4+P4) -> 230
A5: PAID | B5: 4 | C5: =INDEX(PORT!$B$2:$B$20,MATCH('05'!B5,PORT!$A$2:$A$20)) -> PNH04 | D5: =INDEX(PORT!$C$2:$C$20,MATCH('05'!B5,PORT!$A$2:$A$20)) -> PNH PORT | E5: E 118697 | F5: 46144 | G5: JR | H5: GS26-170 | I5: DIS181 | J5: JR2605001 | K5: 46146 | L5: =VLOOKUP(K5,'[5]Exchange Rate'!$A$3:$C$21,3,FALSE) -> 4005 | M5: =TEXT(K5,"dddd") -> Monday | N5: 715.25 | O5: 506 | P5: 0 | Q5: 242 | R5: 606.75 | S5: =ROUND(Q5*10%,2) -> 24.2 | T5: 1227.5 | U5: =(Q5+R5+T5)-(N5+O5+P5) -> 855 | V5: BLS26-0193 & BLS26-0194
A6: PAID | B6: 1 | C6: =INDEX(PORT!$B$2:$B$20,MATCH('05'!B6,PORT!$A$2:$A$20)) -> PNH01 | D6: =INDEX(PORT!$C$2:$C$20,MATCH('05'!B6,PORT!$A$2:$A$20)) -> KTI AIR PORT | E6: I 12592 | F6: 46144 | G6: SPORTLINE | H6: GS26-171 | I6: DIS182 | J6: SAK2605001 | K6: 46146 | L6: =VLOOKUP(K6,'[5]Exchange Rate'!$A$3:$C$21,3,FALSE) -> 4005 | M6: =TEXT(K6,"dddd") -> Monday | N6: 181 | O6: 0 | P6: 50 | Q6: 150 | R6: 36 | S6: =ROUND(Q6*10%,2) -> 15 | T6: 196.75 | U6: =(Q6+R6+T6)-(N6+O6+P6) -> 151.75
A7: PAID | B7: 1 | C7: =INDEX(PORT!$B$2:$B$20,MATCH('05'!B7,PORT!$A$2:$A$20)) -> PNH01 | D7: =INDEX(PORT!$C$2:$C$20,MATCH('05'!B7,PORT!$A$2:$A$20)) -> KTI AIR PORT | E7: E 16485 | F7: 46148 | G7: JIN YUAN XI | H7: GS26-172 | I7: DIS183 | J7: JYX2605003 | K7: 46149 | L7: =VLOOKUP(K7,'[5]Exchange Rate'!$A$3:$C$21,3,FALSE) -> 4011 | M7: =TEXT(K7,"dddd") -> Thursday | N7: 90 | O7: 0 | P7: 50 | Q7: 140 | R7: 20 | S7: =ROUND(Q7*10%,2) -> 14 | T7: 60 | U7: =(Q7+R7+T7)-(N7+O7+P7) -> 80
A8: PAID | B8: 1 | C8: =INDEX(PORT!$B$2:$B$20,MATCH('05'!B8,PORT!$A$2:$A$20)) -> PNH01 | D8: =INDEX(PORT!$C$2:$C$20,MATCH('05'!B8,PORT!$A$2:$A$20)) -> KTI AIR PORT | E8: E 16521 | F8: 46148 | G8: VFL | H8: GS26-173 | I8: DIS184 | J8: VFL2605001 | K8: 46149 | L8: =VLOOKUP(K8,'[5]Exchange Rate'!$A$3:$C$21,3,FALSE) -> 4011 | M8: =TEXT(K8,"dddd") -> Thursday | N8: 88.06 | O8: 0 | P8: 50 | Q8: 140 | R8: 18.06 | S8: =ROUND(Q8*10%,2) -> 14 | T8: 60 | U8: =(Q8+R8+T8)-(N8+O8+P8) -> 80
A9: PAID | B9: 4 | C9: =INDEX(PORT!$B$2:$B$20,MATCH('05'!B9,PORT!$A$2:$A$20)) -> PNH04 | D9: =INDEX(PORT!$C$2:$C$20,MATCH('05'!B9,PORT!$A$2:$A$20)) -> PNH PORT | E9: E 119429 | F9: 46149 | G9: SPORTLINE | H9: GS26-174 | I9: DIS185 | J9: SAK2605002 | K9: 46150 | L9: =VLOOKUP(K9,'[5]Exchange Rate'!$A$3:$C$21,3,FALSE) -> 4012 | M9: =TEXT(K9,"dddd") -> Friday | N9: 1145.75 | O9: 0 | P9: 50 | Q9: 490 | R9: 295.75 | S9: =ROUND(Q9*10%,2) -> 49 | T9: 1078 | U9: =(Q9+R9+T9)-(N9+O9+P9) -> 668 | W9: FINISHED SAT WEEK 1 DATE 9/5/26
A10: PAID | B10: 1 | C10: =INDEX(PORT!$B$2:$B$20,MATCH('05'!B10,PORT!$A$2:$A$20)) -> PNH01 | D10: =INDEX(PORT!$C$2:$C$20,MATCH('05'!B10,PORT!$A$2:$A$20)) -> KTI AIR PORT | E10: E 16803 | F10: 46149 | G10: JIN YUAN XI | H10: GS26-175 | I10: DIS186 | J10: JYX2605004 | K10: 46150 | L10: =VLOOKUP(K10,'[5]Exchange Rate'!$A$3:$C$21,3,FALSE) -> 4012 | M10: =TEXT(K10,"dddd") -> Friday | N10: 294 | O10: 0 | P10: 50 | Q10: 220 | R10: 174 | S10: =ROUND(Q10*10%,2) -> 22 | T10: 180 | U10: =(Q10+R10+T10)-(N10+O10+P10) -> 230
A11: PAID | B11: 1 | C11: =INDEX(PORT!$B$2:$B$20,MATCH('05'!B11,PORT!$A$2:$A$20)) -> PNH01 | D11: =INDEX(PORT!$C$2:$C$20,MATCH('05'!B11,PORT!$A$2:$A$20)) -> KTI AIR PORT | E11: E 16818 | F11: 46149 | G11: JIN YUAN XI | H11: GS26-176 | I11: DIS187 | J11: JYX2605005 | K11: 46150 | L11: =VLOOKUP(K11,'[5]Exchange Rate'!$A$3:$C$21,3,FALSE) -> 4012 | M11: =TEXT(K11,"dddd") -> Friday | N11: 176.08 | O11: 0 | P11: 50 | Q11: 150 | R11: 56.08 | S11: =ROUND(Q11*10%,2) -> 15 | T11: 180 | U11: =(Q11+R11+T11)-(N11+O11+P11) -> 160
A12: PAID | B12: 11 | C12: =INDEX(PORT!$B$2:$B$20,MATCH('05'!B12,PORT!$A$2:$A$20)) -> SHV11 | D12: =INDEX(PORT!$C$2:$C$20,MATCH('05'!B12,PORT!$A$2:$A$20)) -> SHV PORT | E12: I 64252 | F12: 46149 | G12: JIN YUAN XI | H12: GS26-177 | I12: DIS188 | J12: JYX2605006 | K12: 46150 | L12: =VLOOKUP(K12,'[5]Exchange Rate'!$A$3:$C$21,3,FALSE) -> 4012 | M12: =TEXT(K12,"dddd") -> Friday | N12: 408.92 | O12: 582.82 | P12: 50 | Q12: 150 | R12: 606.67 | S12: =ROUND(Q12*10%,2) -> 15 | T12: 509.99 | U12: =(Q12+R12+T12)-(N12+O12+P12) -> 224.92
A13: PAID | B13: 19 | C13: =INDEX(PORT!$B$2:$B$20,MATCH('05'!B13,PORT!$A$2:$A$20)) -> PNH19 | D13: =INDEX(PORT!$C$2:$C$20,MATCH('05'!B13,PORT!$A$2:$A$20)) -> TEC SRUN DRYPORT | E13: I 1299 | F13: 46149 | G13: SPORTLINE | H13: GS26-178 | I13: DIS189 | J13: SAK2605003 | K13: 46150 | L13: =VLOOKUP(K13,'[5]Exchange Rate'!$A$3:$C$21,3,FALSE) -> 4012 | M13: =TEXT(K13,"dddd") -> Friday | N13: 143.18 | O13: 333.86 | P13: 50 | Q13: 150 | R13: 367.04 | S13: =ROUND(Q13*10%,2) -> 15 | T13: 159 | U13: =(Q13+R13+T13)-(N13+O13+P13) -> 149
A14: PAID | B14: 11 | C14: =INDEX(PORT!$B$2:$B$20,MATCH('05'!B14,PORT!$A$2:$A$20)) -> SHV11 | D14: =INDEX(PORT!$C$2:$C$20,MATCH('05'!B14,PORT!$A$2:$A$20)) -> SHV PORT | E14: I 64223 | F14: 46149 | G14: SPORTLINE | H14: GS26-179 | I14: DIS190 | J14: SAK2605004 | K14: 46150 | L14: =VLOOKUP(K14,'[5]Exchange Rate'!$A$3:$C$21,3,FALSE) -> 4012 | M14: =TEXT(K14,"dddd") -> Friday | N14: 247.8 | O14: 346.7 | P14: 50 | Q14: 150 | R14: 365.5 | S14: =ROUND(Q14*10%,2) -> 15 | T14: 234.21 | U14: =(Q14+R14+T14)-(N14+O14+P14) -> 105.21
A15: PAID | B15: 11 | C15: =INDEX(PORT!$B$2:$B$20,MATCH('05'!B15,PORT!$A$2:$A$20)) -> SHV11 | D15: =INDEX(PORT!$C$2:$C$20,MATCH('05'!B15,PORT!$A$2:$A$20)) -> SHV PORT | E15: I 64230 | F15: 46149 | G15: SPORTLINE | H15: GS26-180 | I15: DIS191 | J15: SAK2605005 | K15: 46150 | L15: =VLOOKUP(K15,'[5]Exchange Rate'!$A$3:$C$21,3,FALSE) -> 4012 | M15: =TEXT(K15,"dddd") -> Friday | N15: 177.12 | O15: 208.12 | P15: 50 | Q15: 150 | R15: 225.24 | S15: =ROUND(Q15*10%,2) -> 15 | T15: 156.96 | U15: =(Q15+R15+T15)-(N15+O15+P15) -> 96.96
A16: PAID | B16: 19 | C16: =INDEX(PORT!$B$2:$B$20,MATCH('05'!B16,PORT!$A$2:$A$20)) -> PNH19 | D16: =INDEX(PORT!$C$2:$C$20,MATCH('05'!B16,PORT!$A$2:$A$20)) -> TEC SRUN DRYPORT | E16: I 1298 | F16: 46149 | G16: VFL | H16: GS26-181 | I16: DIS192 | J16: VFL2605002 | K16: 46150 | L16: =VLOOKUP(K16,'[5]Exchange Rate'!$A$3:$C$21,3,FALSE) -> 4012 | M16: =TEXT(K16,"dddd") -> Friday | N16: 113.1 | O16: 254.03 | P16: 50 | Q16: 150 | R16: 280.04 | S16: =ROUND(Q16*10%,2) -> 15 | T16: 109.5 | U16: =(Q16+R16+T16)-(N16+O16+P16) -> 122.41
A17: PAID | B17: 11 | C17: =INDEX(PORT!$B$2:$B$20,MATCH('05'!B17,PORT!$A$2:$A$20)) -> SHV11 | D17: =INDEX(PORT!$C$2:$C$20,MATCH('05'!B17,PORT!$A$2:$A$20)) -> SHV PORT | E17: I 64237 | F17: 46149 | G17: VFL | H17: GS26-182 | I17: DIS193 | J17: VFL2605003 | K17: 46150 | L17: =VLOOKUP(K17,'[5]Exchange Rate'!$A$3:$C$21,3,FALSE) -> 4012 | M17: =TEXT(K17,"dddd") -> Friday | N17: 160.72 | O17: 259.6 | P17: 50 | Q17: 150 | R17: 276.72 | S17: =ROUND(Q17*10%,2) -> 15 | T17: 111.28 | U17: =(Q17+R17+T17)-(N17+O17+P17) -> 67.68
A18: PAID | B18: 1 | C18: =INDEX(PORT!$B$2:$B$20,MATCH('05'!B18,PORT!$A$2:$A$20)) -> PNH01 | D18: =INDEX(PORT!$C$2:$C$20,MATCH('05'!B18,PORT!$A$2:$A$20)) -> KTI AIR PORT | E18: E 17265 | F18: 46152 | G18: JIN YUAN XI | H18: GS26-183 | I18: DIS194 | J18: JYX2605007 | K18: 46153 | L18: =VLOOKUP(K18,'[5]Exchange Rate'!$A$3:$C$21,3,FALSE) -> 4012 | M18: =TEXT(K18,"dddd") -> Monday | N18: 179.59 | O18: 0 | P18: 50 | Q18: 140 | R18: 29.59 | S18: =ROUND(Q18*10%,2) -> 14 | T18: 330 | U18: =(Q18+R18+T18)-(N18+O18+P18) -> 270
A19: PAID | B19: 4 | C19: =INDEX(PORT!$B$2:$B$20,MATCH('05'!B19,PORT!$A$2:$A$20)) -> PNH04 | D19: =INDEX(PORT!$C$2:$C$20,MATCH('05'!B19,PORT!$A$2:$A$20)) -> PNH PORT | E19: E 126330 | F19: 46151 | G19: JR | H19: GS26-184 | I19: DIS195 | J19: JR2605002 | K19: 46153 | L19: =VLOOKUP(K19,'[5]Exchange Rate'!$A$3:$C$21,3,FALSE) -> 4012 | M19: =TEXT(K19,"dddd") -> Monday | N19: 652.35 | O19: 466 | P19: 0 | Q19: 213 | R19: 540.35 | S19: =ROUND(Q19*10%,2) -> 21.3 | T19: 1224.5 | U19: =(Q19+R19+T19)-(N19+O19+P19) -> 859.5 | V19: BLS26-0209 & BLS26-0210
A20: PAID | B20: 21 | C20: =INDEX(PORT!$B$2:$B$20,MATCH('05'!B20,PORT!$A$2:$A$20)) -> PNH21 | D20: =INDEX(PORT!$C$2:$C$20,MATCH('05'!B20,PORT!$A$2:$A$20)) -> OLAIR DRY PORT | E20: I 1561 | F20: 46154 | G20: SPORTLINE | H20: GS26-185 | I20: DIS196 | J20: SAK2605006 | K20: 46155 | L20: =VLOOKUP(K20,'[5]Exchange Rate'!$A$3:$C$21,3,FALSE) -> 4012 | M20: =TEXT(K20,"dddd") -> Wednesday | N20: 137.86 | O20: 235.13 | P20: 50 | Q20: 150 | R20: 262.99 | S20: =ROUND(Q20*10%,2) -> 15 | T20: 159 | U20: =(Q20+R20+T20)-(N20+O20+P20) -> 149
A21: PAID | B21: 21 | C21: =INDEX(PORT!$B$2:$B$20,MATCH('05'!B21,PORT!$A$2:$A$20)) -> PNH21 | D21: =INDEX(PORT!$C$2:$C$20,MATCH('05'!B21,PORT!$A$2:$A$20)) -> OLAIR DRY PORT | E21: I 1557 | F21: 46154 | G21: VFL | H21: GS26-186 | I21: DIS197 | J21: VFL2605004 | K21: 46155 | L21: =VLOOKUP(K21,'[5]Exchange Rate'!$A$3:$C$21,3,FALSE) -> 4012 | M21: =TEXT(K21,"dddd") -> Wednesday | N21: 112 | O21: 207.63 | P21: 50 | Q21: 150 | R21: 232.63 | S21: =ROUND(Q21*10%,2) -> 15 | T21: 109.5 | U21: =(Q21+R21+T21)-(N21+O21+P21) -> 122.5
A22: PAID | B22: 1 | C22: =INDEX(PORT!$B$2:$B$20,MATCH('05'!B22,PORT!$A$2:$A$20)) -> PNH01 | D22: =INDEX(PORT!$C$2:$C$20,MATCH('05'!B22,PORT!$A$2:$A$20)) -> KTI AIR PORT | E22: E 18690 | F22: 46158 | G22: JIN YUAN XI | H22: GS26-187 | I22: DIS198 | J22: JYX2605008 | K22: 46160 | L22: =VLOOKUP(K22,'[5]Exchange Rate'!$A$3:$C$21,3,FALSE) -> 4014 | M22: =TEXT(K22,"dddd") -> Monday | N22: 358.33 | O22: 0 | P22: 50 | Q22: 230 | R22: 238.33 | S22: =ROUND(Q22*10%,2) -> 23 | T22: 180 | U22: =(Q22+R22+T22)-(N22+O22+P22) -> 240
A23: PAID | B23: 4 | C23: =INDEX(PORT!$B$2:$B$20,MATCH('05'!B23,PORT!$A$2:$A$20)) -> PNH04 | D23: =INDEX(PORT!$C$2:$C$20,MATCH('05'!B23,PORT!$A$2:$A$20)) -> PNH PORT | E23: E 129471 | F23: 46157 | G23: JR | H23: GS26-188 | I23: DIS199 | J23: JR2605003 | K23: 46160 | L23: =VLOOKUP(K23,'[5]Exchange Rate'!$A$3:$C$21,3,FALSE) -> 4014 | M23: =TEXT(K23,"dddd") -> Monday | N23: 562.75 | O23: 506 | P23: 0 | Q23: 242 | R23: 654.25 | S23: =ROUND(Q23*10%,2) -> 24.2 | T23: 707.5 | U23: =(Q23+R23+T23)-(N23+O23+P23) -> 535 | V23: BLS26-0221 & BLS26-0222
A24: PAID | B24: 19 | C24: =INDEX(PORT!$B$2:$B$20,MATCH('05'!B24,PORT!$A$2:$A$20)) -> PNH19 | D24: =INDEX(PORT!$C$2:$C$20,MATCH('05'!B24,PORT!$A$2:$A$20)) -> TEC SRUN DRYPORT | E24: I 1522 | F24: 46160 | G24: SPORTLINE | H24: GS26-189 | I24: DIS200 | J24: SAK2605007 | K24: 46161 | L24: =VLOOKUP(K24,'[5]Exchange Rate'!$A$3:$C$21,3,FALSE) -> 4019 | M24: =TEXT(K24,"dddd") -> Tuesday | N24: 136.1 | O24: 207.13 | P24: 50 | Q24: 150 | R24: 233.23 | S24: =ROUND(Q24*10%,2) -> 15 | T24: 159 | U24: =(Q24+R24+T24)-(N24+O24+P24) -> 149
A25: PAID | B25: 19 | C25: =INDEX(PORT!$B$2:$B$20,MATCH('05'!B25,PORT!$A$2:$A$20)) -> PNH19 | D25: =INDEX(PORT!$C$2:$C$20,MATCH('05'!B25,PORT!$A$2:$A$20)) -> TEC SRUN DRYPORT | E25: I 1521 | F25: 46160 | G25: VFL | H25: GS26-190 | I25: DIS201 | J25: VFL2605005 | K25: 46161 | L25: =VLOOKUP(K25,'[5]Exchange Rate'!$A$3:$C$21,3,FALSE) -> 4019 | M25: =TEXT(K25,"dddd") -> Tuesday | N25: 113.1 | O25: 194.05 | P25: 50 | Q25: 150 | R25: 220.15 | S25: =ROUND(Q25*10%,2) -> 15 | T25: 109.5 | U25: =(Q25+R25+T25)-(N25+O25+P25) -> 122.5 | W25: FINISHED SAT WEEK3 DATE 23/5/26
A26: PAID | B26: 1 | C26: =INDEX(PORT!$B$2:$B$20,MATCH('05'!B26,PORT!$A$2:$A$20)) -> PNH01 | D26: =INDEX(PORT!$C$2:$C$20,MATCH('05'!B26,PORT!$A$2:$A$20)) -> KTI AIR PORT | E26: I 14562 | F26: 46162 | G26: JIN YUAN XI | H26: GS26-191 | I26: DIS202 | J26: JYX2605009 | K26: 46163 | L26: =VLOOKUP(K26,'[5]Exchange Rate'!$A$3:$C$21,3,FALSE) -> 4023 | M26: =TEXT(K26,"dddd") -> Thursday | N26: 269.36 | O26: 0 | P26: 50 | Q26: 165 | R26: 99.36 | S26: =ROUND(Q26*10%,2) -> 16.5 | T26: 175.75 | U26: =(Q26+R26+T26)-(N26+O26+P26) -> 120.75
A27: PAID | B27: 4 | C27: =INDEX(PORT!$B$2:$B$20,MATCH('05'!B27,PORT!$A$2:$A$20)) -> PNH04 | D27: =INDEX(PORT!$C$2:$C$20,MATCH('05'!B27,PORT!$A$2:$A$20)) -> PNH PORT | E27: E 135354 | F27: 46163 | G27: SPORTLINE | H27: GS26-192 | I27: DIS203 | J27: SAK2605008 | K27: 46164 | L27: =VLOOKUP(K27,'[5]Exchange Rate'!$A$3:$C$21,3,FALSE) -> 4024 | M27: =TEXT(K27,"dddd") -> Friday | N27: 597.75 | O27: 0 | P27: 50 | Q27: 245 | R27: 147.75 | S27: =ROUND(Q27*10%,2) -> 24.5 | T27: 574 | U27: =(Q27+R27+T27)-(N27+O27+P27) -> 319
A28: PAID | B28: 11 | C28: =INDEX(PORT!$B$2:$B$20,MATCH('05'!B28,PORT!$A$2:$A$20)) -> SHV11 | D28: =INDEX(PORT!$C$2:$C$20,MATCH('05'!B28,PORT!$A$2:$A$20)) -> SHV PORT | E28: E 135368 | F28: 46163 | G28: SPORTLINE | H28: GS26-193 | I28: DIS204 | J28: SAK2605009 | K28: 46164 | L28: =VLOOKUP(K28,'[5]Exchange Rate'!$A$3:$C$21,3,FALSE) -> 4024 | M28: =TEXT(K28,"dddd") -> Friday | N28: 529.75 | O28: 0 | P28: 50 | Q28: 215 | R28: 70.75 | S28: =ROUND(Q28*10%,2) -> 21.5 | T28: 580.5 | U28: =(Q28+R28+T28)-(N28+O28+P28) -> 286.5
A29: PAID | B29: 11 | C29: =INDEX(PORT!$B$2:$B$20,MATCH('05'!B29,PORT!$A$2:$A$20)) -> SHV11 | D29: =INDEX(PORT!$C$2:$C$20,MATCH('05'!B29,PORT!$A$2:$A$20)) -> SHV PORT | E29: I 71890 | F29: 46163 | G29: SPORTLINE | H29: GS26-194 | I29: DIS205 | J29: SAK2605010 | K29: 46164 | L29: =VLOOKUP(K29,'[5]Exchange Rate'!$A$3:$C$21,3,FALSE) -> 4024 | M29: =TEXT(K29,"dddd") -> Friday | N29: 195.12 | O29: 221.1 | P29: 50 | Q29: 150 | R29: 238.22 | S29: =ROUND(Q29*10%,2) -> 15 | T29: 157.8 | U29: =(Q29+R29+T29)-(N29+O29+P29) -> 79.8
A30: PAID | B30: 11 | C30: =INDEX(PORT!$B$2:$B$20,MATCH('05'!B30,PORT!$A$2:$A$20)) -> SHV11 | D30: =INDEX(PORT!$C$2:$C$20,MATCH('05'!B30,PORT!$A$2:$A$20)) -> SHV PORT | E30: I 72096 | F30: 46163 | G30: VFL | H30: GS26-195 | I30: DIS206 | J30: VFL2605006 | K30: 46164 | L30: =VLOOKUP(K30,'[5]Exchange Rate'!$A$3:$C$21,3,FALSE) -> 4024 | M30: =TEXT(K30,"dddd") -> Friday | N30: 170.1 | O30: 283.58 | P30: 50 | Q30: 150 | R30: 300.7 | S30: =ROUND(Q30*10%,2) -> 15 | T30: 126.99 | U30: =(Q30+R30+T30)-(N30+O30+P30) -> 74.01
A31: PAID | B31: 1 | C31: =INDEX(PORT!$B$2:$B$20,MATCH('05'!B31,PORT!$A$2:$A$20)) -> PNH01 | D31: =INDEX(PORT!$C$2:$C$20,MATCH('05'!B31,PORT!$A$2:$A$20)) -> KTI AIR PORT | E31: E 19991 | F31: 46164 | G31: VFL | H31: GS26-196 | I31: DIS207 | J31: VFL2605007 | K31: 46167 | L31: =VLOOKUP(K31,'[5]Exchange Rate'!$A$3:$C$21,3,FALSE) -> 4025 | M31: =TEXT(K31,"dddd") -> Monday | N31: 135.95 | O31: 0 | P31: 50 | Q31: 140 | R31: 15.95 | S31: =ROUND(Q31*10%,2) -> 14 | T31: 180 | U31: =(Q31+R31+T31)-(N31+O31+P31) -> 150
A32: PAID | B32: 1 | C32: =INDEX(PORT!$B$2:$B$20,MATCH('05'!B32,PORT!$A$2:$A$20)) -> PNH01 | D32: =INDEX(PORT!$C$2:$C$20,MATCH('05'!B32,PORT!$A$2:$A$20)) -> KTI AIR PORT | E32: E 19970 | F32: 46164 | G32: VFL | H32: GS26-197 | I32: DIS208 | J32: VFL2605008 | K32: 46167 | L32: =VLOOKUP(K32,'[5]Exchange Rate'!$A$3:$C$21,3,FALSE) -> 4025 | M32: =TEXT(K32,"dddd") -> Monday | N32: 135.95 | O32: 0 | P32: 50 | Q32: 140 | R32: 4.2 | S32: =ROUND(Q32*10%,2) -> 14 | T32: 191.75 | U32: =(Q32+R32+T32)-(N32+O32+P32) -> 150
A33: PAID | B33: 1 | C33: =INDEX(PORT!$B$2:$B$20,MATCH('05'!B33,PORT!$A$2:$A$20)) -> PNH01 | D33: =INDEX(PORT!$C$2:$C$20,MATCH('05'!B33,PORT!$A$2:$A$20)) -> KTI AIR PORT | E33: E 19977 | F33: 46164 | G33: VFL | H33: GS26-198 | I33: DIS209 | J33: VFL2605009 | K33: 46167 | L33: =VLOOKUP(K33,'[5]Exchange Rate'!$A$3:$C$21,3,FALSE) -> 4025 | M33: =TEXT(K33,"dddd") -> Monday | N33: 139.29 | O33: 0 | P33: 50 | Q33: 140 | R33: 19.29 | S33: =ROUND(Q33*10%,2) -> 14 | T33: 180 | U33: =(Q33+R33+T33)-(N33+O33+P33) -> 150
A34: PAID | B34: 1 | C34: =INDEX(PORT!$B$2:$B$20,MATCH('05'!B34,PORT!$A$2:$A$20)) -> PNH01 | D34: =INDEX(PORT!$C$2:$C$20,MATCH('05'!B34,PORT!$A$2:$A$20)) -> KTI AIR PORT | E34: E 19998 | F34: 46164 | G34: VFL | H34: GS26-199 | I34: DIS210 | J34: VFL2605010 | K34: 46167 | L34: =VLOOKUP(K34,'[5]Exchange Rate'!$A$3:$C$21,3,FALSE) -> 4025 | M34: =TEXT(K34,"dddd") -> Monday | N34: 135.95 | O34: 0 | P34: 50 | Q34: 140 | R34: 15.95 | S34: =ROUND(Q34*10%,2) -> 14 | T34: 180 | U34: =(Q34+R34+T34)-(N34+O34+P34) -> 150
A35: PAID | B35: 1 | C35: =INDEX(PORT!$B$2:$B$20,MATCH('05'!B35,PORT!$A$2:$A$20)) -> PNH01 | D35: =INDEX(PORT!$C$2:$C$20,MATCH('05'!B35,PORT!$A$2:$A$20)) -> KTI AIR PORT | E35: E 2007 | F35: 46164 | G35: VFL | H35: GS26-200 | I35: DIS211 | J35: VFL2605011 | K35: 46167 | L35: =VLOOKUP(K35,'[5]Exchange Rate'!$A$3:$C$21,3,FALSE) -> 4025 | M35: =TEXT(K35,"dddd") -> Monday | N35: 135.95 | O35: 0 | P35: 50 | Q35: 140 | R35: 15.95 | S35: =ROUND(Q35*10%,2) -> 14 | T35: 180 | U35: =(Q35+R35+T35)-(N35+O35+P35) -> 150
A36: PAID | B36: 1 | C36: =INDEX(PORT!$B$2:$B$20,MATCH('05'!B36,PORT!$A$2:$A$20)) -> PNH01 | D36: =INDEX(PORT!$C$2:$C$20,MATCH('05'!B36,PORT!$A$2:$A$20)) -> KTI AIR PORT | E36: E 20021 | F36: 46164 | G36: SPORTLINE | H36: GS26-201 | I36: DIS212 | J36: SAK2605011 | K36: 46167 | L36: =VLOOKUP(K36,'[5]Exchange Rate'!$A$3:$C$21,3,FALSE) -> 4025 | M36: =TEXT(K36,"dddd") -> Monday | N36: 137.45 | O36: 0 | P36: 50 | Q36: 140 | R36: 17.45 | S36: =ROUND(Q36*10%,2) -> 14 | T36: 180 | U36: =(Q36+R36+T36)-(N36+O36+P36) -> 150
A37: PAID | B37: 1 | C37: =INDEX(PORT!$B$2:$B$20,MATCH('05'!B37,PORT!$A$2:$A$20)) -> PNH01 | D37: =INDEX(PORT!$C$2:$C$20,MATCH('05'!B37,PORT!$A$2:$A$20)) -> KTI AIR PORT | E37: E 20012 | F37: 46164 | G37: SPORTLINE | H37: GS26-202 | I37: DIS213 | J37: SAK2605012 | K37: 46167 | L37: =VLOOKUP(K37,'[5]Exchange Rate'!$A$3:$C$21,3,FALSE) -> 4025 | M37: =TEXT(K37,"dddd") -> Monday | N37: 135.95 | O37: 0 | P37: 50 | Q37: 140 | R37: 15.95 | S37: =ROUND(Q37*10%,2) -> 14 | T37: 180 | U37: =(Q37+R37+T37)-(N37+O37+P37) -> 150
... A44: PAID | B44: 4 | C44: =INDEX(PORT!$B$2:$B$20,MATCH('05'!B44,PORT!$A$2:$A$20)) -> PNH04 | D44: =INDEX(PORT!$C$2:$C$20,MATCH('05'!B44,PORT!$A$2:$A$20)) -> PNH PORT | E44: E 143483 | F44: 46170 | G44: SPORTLINE | H44: GS26-209 | I44: DIS220 | J44: SAK2605015 | K44: 46171 | L44: =VLOOKUP(K44,'[5]Exchange Rate'!$A$3:$C$21,3,FALSE) -> 4026 | M44: =TEXT(K44,"dddd") -> Friday | N44: 563.25 | O44: 0 | P44: 50 | Q44: 245 | R44: 143.25 | S44: =ROUND(Q44*10%,2) -> 24.5 | T44: 574 | U44: =(Q44+R44+T44)-(N44+O44+P44) -> 349
B45: 4 | C45: =INDEX(PORT!$B$2:$B$20,MATCH('05'!B45,PORT!$A$2:$A$20)) -> PNH04 | D45: =INDEX(PORT!$C$2:$C$20,MATCH('05'!B45,PORT!$A$2:$A$20)) -> PNH PORT | E45: LAT2026-00417 | F45: 46149 | G45: JR | I45: DIS221 | J45: JR2605004 | K45: 46171 | L45: =VLOOKUP(K45,'[5]Exchange Rate'!$A$3:$C$21,3,FALSE) -> 4026 | M45: =TEXT(K45,"dddd") -> Friday | N45: 0 | O45: 462 | P45: 0 | Q45: 0 | R45: 462 | S45: =ROUND(Q45*10%,2) -> 0 | T45: 94 | U45: =(Q45+R45+T45)-(N45+O45+P45) -> 94 | V45: E 115341-4/30/26
B46: 19 | C46: =INDEX(PORT!$B$2:$B$20,MATCH('05'!B46,PORT!$A$2:$A$20)) -> PNH19 | D46: =INDEX(PORT!$C$2:$C$20,MATCH('05'!B46,PORT!$A$2:$A$20)) -> TEC SRUN DRYPORT | E46: I 1733 | G46: VFL | I46: DIS222 | K46: 46173 | L46: =VLOOKUP(K46,'[5]Exchange Rate'!$A$3:$C$21,3,FALSE) -> 4026 | M46: =TEXT(K46,"dddd") -> Sunday | N46: 0 | O46: 193.6 | P46: 0 | Q46: 0 | R46: 193.6 | T46: 0 | U46: =(Q46+R46+T46)-(N46+O46+P46) -> 0
B47: 4 | C47: =INDEX(PORT!$B$2:$B$20,MATCH('05'!B48,PORT!$A$2:$A$20)) -> PNH04 | D47: =INDEX(PORT!$C$2:$C$20,MATCH('05'!B48,PORT!$A$2:$A$20)) -> PNH PORT | E47: LAT2026-00486 & RE260015 | F47: 46157 | G47: JR | I47: DIS223 | J47: JR2605006 | K47: 46171 | L47: =VLOOKUP(K47,'[5]Exchange Rate'!$A$3:$C$21,3,FALSE) -> 4026 | M47: =TEXT(K47,"dddd") -> Friday | N47: 0 | O47: 575.72 | P47: 0 | Q47: 0 | R47: 575.72 | S47: =ROUND(Q47*10%,2) -> 0 | T47: 203 | U47: =(Q47+R47+T47)-(N47+O47+P47) -> 203 | V47: E 121009-5/8/26
B48: 4 | C48: =INDEX(PORT!$B$2:$B$20,MATCH('05'!B49,PORT!$A$2:$A$20)) -> PNH04 | D48: =INDEX(PORT!$C$2:$C$20,MATCH('05'!B49,PORT!$A$2:$A$20)) -> PNH PORT | E48: LAT2026-00491 & LAT2026-00492 | F48: 46160 | G48: JR | I48: DIS224 | J48: JR2605007 | K48: 46171 | L48: =VLOOKUP(K48,'[5]Exchange Rate'!$A$3:$C$21,3,FALSE) -> 4026 | M48: =TEXT(K48,"dddd") -> Friday | N48: 0 | O48: 451.2 | P48: 0 | Q48: 0 | R48: 451.2 | S48: =ROUND(Q48*10%,2) -> 0 | T48: 141.5 | U48: =(Q48+R48+T48)-(N48+O48+P48) -> 141.5 | V48: E 122248-5/8/26
B49: 4 | C49: =INDEX(PORT!$B$2:$B$20,MATCH('05'!B50,PORT!$A$2:$A$20)) -> PNH04 | D49: =INDEX(PORT!$C$2:$C$20,MATCH('05'!B50,PORT!$A$2:$A$20)) -> PNH PORT | E49: 5612521921 | F49: 46162 | G49: JR | I49: DIS225 | J49: JR2605008 | K49: 46171 | L49: =VLOOKUP(K49,'[5]Exchange Rate'!$A$3:$C$21,3,FALSE) -> 4026 | M49: =TEXT(K49,"dddd") -> Friday | N49: 0 | O49: 240.03 | P49: 0 | Q49: 0 | R49: 240.03 | S49: =ROUND(Q49*10%,2) -> 0 | T49: 141.5 | U49: =(Q49+R49+T49)-(N49+O49+P49) -> 141.5 | V49: E 131163-15/5/26
B50: 4 | C50: =INDEX(PORT!$B$2:$B$20,MATCH('05'!B51,PORT!$A$2:$A$20)) -> PNH04 | D50: =INDEX(PORT!$C$2:$C$20,MATCH('05'!B51,PORT!$A$2:$A$20)) -> PNH PORT | E50: CGL26-00972&CGL26-00973&RM26-00499 | F50: 46168 | G50: JR | I50: DIS226 | J50: JR2605009 | K50: 46171 | L50: =VLOOKUP(K50,'[5]Exchange Rate'!$A$3:$C$21,3,FALSE) -> 4026 | M50: =TEXT(K50,"dddd") -> Friday | N50: 0 | O50: 1453.65 | P50: 0 | Q50: 0 | R50: 1453.65 | S50: =ROUND(Q50*10%,2) -> 0 | T50: 268 | U50: =(Q50+R50+T50)-(N50+O50+P50) -> 268 | V50: E 141994-5/25/26
B51: 4 | C51: =INDEX(PORT!$B$2:$B$20,MATCH('05'!B52,PORT!$A$2:$A$20)) -> PNH04 | D51: =INDEX(PORT!$C$2:$C$20,MATCH('05'!B52,PORT!$A$2:$A$20)) -> PNH PORT | E51: LAT2026-00564 & RE260016 | F51: 46170 | G51: JR | I51: DIS227 | J51: JR2605010 | K51: 46171 | L51: =VLOOKUP(K51,'[5]Exchange Rate'!$A$3:$C$21,3,FALSE) -> 4026 | M51: =TEXT(K51,"dddd") -> Friday | N51: 0 | O51: 729.88 | P51: 0 | Q51: 0 | R51: 729.88 | S51: =ROUND(Q51*10%,2) -> 0 | T51: 160 | U51: =(Q51+R51+T51)-(N51+O51+P51) -> 160 | V51: E 140456-5/22/26
B52: 4 | C52: =INDEX(PORT!$B$2:$B$20,MATCH('05'!B53,PORT!$A$2:$A$20)) -> PNH19 | D52: =INDEX(PORT!$C$2:$C$20,MATCH('05'!B53,PORT!$A$2:$A$20)) -> TEC SRUN DRYPORT | E52: CGL26-00991&CGL26-00992&RM26-00506 | F52: 46174 | G52: JR | I52: DIS228 | J52: JR2605012 | K52: 46171 | L52: =VLOOKUP(K52,'[5]Exchange Rate'!$A$3:$C$21,3,FALSE) -> 4026 | M52: =TEXT(K52,"dddd") -> Friday | N52: 0 | O52: 1317.36 | P52: 0 | Q52: 0 | R52: 1317.36 | S52: =ROUND(Q52*10%,2) -> 0 | T52: 174 | U52: =(Q52+R52+T52)-(N52+O52+P52) -> 174 | V52: E 149931-5/31/26
B53: 19 | C53: =INDEX(PORT!$B$2:$B$20,MATCH('05'!B54,PORT!$A$2:$A$20)) -> PNH04 | D53: =INDEX(PORT!$C$2:$C$20,MATCH('05'!B54,PORT!$A$2:$A$20)) -> PNH PORT | E53: I 1735 | G53: SPORTLINE | I53: DIS229 | K53: 46173 | L53: =VLOOKUP(K53,'[5]Exchange Rate'!$A$3:$C$21,3,FALSE) -> 4026 | M53: =TEXT(K53,"dddd") -> Sunday | N53: 0 | O53: 231.48 | P53: 0 | Q53: 0 | R53: 231.48 | S53: =ROUND(Q53*10%,2) -> 0 | T53: 0 | U53: =(Q53+R53+T53)-(N53+O53+P53) -> 0
B54: 4 | C54: =INDEX(PORT!$B$2:$B$20,MATCH('05'!B47,PORT!$A$2:$A$20)) -> PNH04 | D54: =INDEX(PORT!$C$2:$C$20,MATCH('05'!B47,PORT!$A$2:$A$20)) -> PNH PORT | G54: JR | J54: JR2605005 | K54: 46171 | L54: =VLOOKUP(K54,'[5]Exchange Rate'!$A$3:$C$21,3,FALSE) -> 4026 | M54: =TEXT(K54,"dddd") -> Friday | N54: 0 | O54: 0 | P54: 0 | Q54: 0 | R54: 0 | S54: =ROUND(Q54*10%,2) -> 0 | T54: 40 | U54: =(Q54+R54+T54)-(N54+O54+P54) -> 40
G55: JR | J55: JR2605011 | K55: 46171 | L55: =VLOOKUP(K55,'[5]Exchange Rate'!$A$3:$C$21,3,FALSE) -> 4026 | M55: =TEXT(K55,"dddd") -> Friday | N55: 0 | O55: 1720 | P55: 0 | Q55: 0 | R55: 0 | S55: =ROUND(Q55*10%,2) -> 0 | T55: 1930 | U55: =(Q55+R55+T55)-(N55+O55+P55) -> 210 | V55: APPLY EXTENSION CDC TO JR APPAREL
A56: PAID | E56: LOLO | N56: 52.8 | V56: lacking lolo E 94582 & E 95135 (26.40*2)
E57: STORAGE
E58: THC
B60: =SUBTOTAL(3,B3:B59) -> 52 | E60: TOTAL: | H60: =SUBTOTAL(3,H3:H59) -> 42 | I60: =SUBTOTAL(3,I3:I59) -> 51 | J60: =SUBTOTAL(3,J3:J59) -> 51 | N60: =SUM(N3:N58) -> 11274.78 | O60: =SUBTOTAL(9,O3:O52) -> 10235.19 | P60: =SUBTOTAL(9,P3:P56) -> 1950 | Q60: =SUBTOTAL(9,Q3:Q53) -> 7477 | R60: =SUBTOTAL(9,R3:R55) -> 13174.41 | S60: =SUBTOTAL(9,S3:S53) -> 747.7 | T60: =SUBTOTAL(9,T3:T55) -> 15477.48 | U60: =SUBTOTAL(9,U3:U58) -> 10770.24
M61: PAID | N61: =SUMIFS($N$3:$N$58,$A$3:$A$58,$M$61)-O62 -> 11274.47
M62: NOT YET | N62: =SUMIFS($N$3:$N$57,$A$3:$A$57,$M$62) -> 0 | O62: 0.31 | P62: Exceed warehouse last month (I 1211)
R64: =SUM(Q60+S60) -> 8224.7
M68: PAID | N68: 5000 | O68: 46157
M69: PAID | N69: 6274.47 | O69: 46182
M70: TOTAL PAID | N70: =SUM(N68:N69) -> 11274.47

Sheet 06
E1: REVENUE & EXPENSE | M1: Saturday
A2: CHEA PAYMENT | B2: PORT NUMBER | C2: PORT CODE | D2: PORT NAME | E2: DECLARE | F2: DATE | G2: CLIENT | H2: INV | I2: DISBURSEMENT | J2: DN | K2: DATE | L2: EXCHANGE RATE | M2: weekday | N2: CLEAR FEE | O2: THC | P2: OTHER PAY | Q2: CM | R2: INV (REVENUE) | S2: REIM | T2: VAT 10% | U2: DN | V2: NET PROFIT | W2: MARK
A3: PAID | B3: 19 | C3: =INDEX(PORT!$B$2:$B$20,MATCH('06'!B3,PORT!$A$2:$A$20)) -> PNH19 | D3: =INDEX(PORT!$C$2:$C$20,MATCH('06'!B3,PORT!$A$2:$A$20)) -> TEC SRUN DRYPORT | E3: I 1733 | F3: 46174 | G3: VFL | H3: GS26-210 | I3: DIS230 | J3: VFL2606001 | K3: 46175 | L3: =VLOOKUP(K3,'[6]Exchange Rate'!$A$3:$D$22,3,FALSE) -> 4026 | M3: =TEXT(K3,"dddd") -> Tuesday | N3: 113.1 | O3: 193.6 | P3: 0 | Q3: 50 | R3: 150 | S3: 26.1 | T3: =ROUND(R3*10%,2) -> 15 | U3: 109.5 | V3: =(R3+S3+U3)-(N3+O3+Q3+P3) -> -71.1 | W3: THC PAID ON MAY
A4: PAID | B4: 19 | C4: =INDEX(PORT!$B$2:$B$20,MATCH('06'!B4,PORT!$A$2:$A$20)) -> PNH19 | D4: =INDEX(PORT!$C$2:$C$20,MATCH('06'!B4,PORT!$A$2:$A$20)) -> TEC SRUN DRYPORT | E4: I 1735 | F4: 46174 | G4: SPORTLINE | H4: GS26-211 | I4: DIS231 | J4: SAK2606001 | K4: 46175 | L4: =VLOOKUP(K4,'[6]Exchange Rate'!$A$3:$D$22,3,FALSE) -> 4026 | M4: =TEXT(K4,"dddd") -> Tuesday | N4: 136.1 | O4: 231.48 | P4: 0 | Q4: 50 | R4: 150 | S4: 26.1 | T4: =ROUND(R4*10%,2) -> 15 | U4: 159 | V4: =(R4+S4+U4)-(N4+O4+Q4+P4) -> -82.48 | W4: THC PAID ON MAY
A5: PAID | B5: 11+ | C5: =INDEX(PORT!$B$2:$B$20,MATCH('06'!B5,PORT!$A$2:$A$20)) -> SVR11 | D5: =INDEX(PORT!$C$2:$C$20,MATCH('06'!B5,PORT!$A$2:$A$20)) -> BAVET CEO | E5: E 150950 | F5: 46174 | G5: JR | H5: GS26-212 | I5: DIS232 | J5: JR2606001 | K5: 46175 | L5: =VLOOKUP(K5,'[6]Exchange Rate'!$A$3:$D$22,3,FALSE) -> 4026 | M5: =TEXT(K5,"dddd") -> Tuesday | N5: 616.25 | O5: 0 | P5: 1507 | Q5: 0 | R5: 330 | S5: 21.25 | T5: =ROUND(R5*10%,2) -> 33 | U5: 2474 | V5: =(R5+S5+U5)-(N5+O5+Q5+P5) -> 702
A6: PAID | B6: 1 | C6: =INDEX(PORT!$B$2:$B$20,MATCH('06'!B6,PORT!$A$2:$A$20)) -> PNH01 | D6: =INDEX(PORT!$C$2:$C$20,MATCH('06'!B6,PORT!$A$2:$A$20)) -> KTI AIR PORT | E6: I 15967 | F6: 46175 | G6: JIN YUAN XI | H6: GS26-213 | I6: DIS233 | J6: JYX2606001 | K6: 46176 | L6: =VLOOKUP(K6,'[6]Exchange Rate'!$A$3:$D$22,3,FALSE) -> 4026 | M6: =TEXT(K6,"dddd") -> Wednesday | N6: 242.08 | O6: 0 | P6: 0 | Q6: 50 | R6: 165 | S6: 72.08 | T6: =ROUND(R6*10%,2) -> 16.5 | U6: 225.75 | V6: =(R6+S6+U6)-(N6+O6+Q6+P6) -> 170.75
A7: PAID | B7: 4 | C7: =INDEX(PORT!$B$2:$B$20,MATCH('06'!B7,PORT!$A$2:$A$20)) -> PNH04 | D7: =INDEX(PORT!$C$2:$C$20,MATCH('06'!B7,PORT!$A$2:$A$20)) -> PNH PORT | E7: E 151650 | F7: 46177 | G7: VFL | H7: GS26-214 | I7: DIS234 | J7: VFL2606002 | K7: 46178 | L7: =VLOOKUP(K7,'[6]Exchange Rate'!$A$3:$D$22,3,FALSE) -> 4027 | M7: =TEXT(K7,"dddd") -> Friday | N7: 484.75 | O7: 0 | P7: 0 | Q7: 50 | R7: 245 | S7: 147.75 | T7: =ROUND(R7*10%,2) -> 24.5 | U7: 411.5 | V7: =(R7+S7+U7)-(N7+O7+Q7+P7) -> 269.5
A8: PAID | B8: 4 | C8: =INDEX(PORT!$B$2:$B$20,MATCH('06'!B8,PORT!$A$2:$A$20)) -> PNH04 | D8: =INDEX(PORT!$C$2:$C$20,MATCH('06'!B8,PORT!$A$2:$A$20)) -> PNH PORT | E8: E 152290 | F8: 46177 | G8: SPORTLINE | H8: GS26-215 | I8: DIS235 | J8: SAK2606002 | K8: 46178 | L8: =VLOOKUP(K8,'[6]Exchange Rate'!$A$3:$D$22,3,FALSE) -> 4027 | M8: =TEXT(K8,"dddd") -> Friday | N8: 593.25 | O8: 0 | P8: 0 | Q8: 50 | R8: 245 | S8: 98.25 | T8: =ROUND(R8*10%,2) -> 24.5 | U8: 619 | V8: =(R8+S8+U8)-(N8+O8+Q8+P8) -> 319
A9: PAID | B9: 1 | C9: =INDEX(PORT!$B$2:$B$20,MATCH('06'!B9,PORT!$A$2:$A$20)) -> PNH01 | D9: =INDEX(PORT!$C$2:$C$20,MATCH('06'!B9,PORT!$A$2:$A$20)) -> KTI AIR PORT | E9: E 22236 | F9: 46177 | G9: JIN YUAN XI | H9: GS26-216 | I9: DIS236 | J9: JYX2606002 | K9: 46178 | L9: =VLOOKUP(K9,'[6]Exchange Rate'!$A$3:$D$22,3,FALSE) -> 4027 | M9: =TEXT(K9,"dddd") -> Friday | N9: 239.73 | O9: 0 | P9: 0 | Q9: 50 | R9: 175 | S9: 99.73 | T9: =ROUND(R9*10%,2) -> 17.5 | U9: 280 | V9: =(R9+S9+U9)-(N9+O9+Q9+P9) -> 265
A10: PAID | B10: 1 | C10: =INDEX(PORT!$B$2:$B$20,MATCH('06'!B10,PORT!$A$2:$A$20)) -> PNH01 | D10: =INDEX(PORT!$C$2:$C$20,MATCH('06'!B10,PORT!$A$2:$A$20)) -> KTI AIR PORT | E10: E 22401 | F10: 46178 | G10: VFL | H10: GS26-217 | I10: DIS237 | J10: VFL2606003 | K10: 46181 | L10: =VLOOKUP(K10,'[6]Exchange Rate'!$A$3:$D$22,3,FALSE) -> 4027 | M10: =TEXT(K10,"dddd") -> Monday | N10: 85.95 | O10: 0 | P10: 0 | Q10: 50 | R10: 140 | S10: 4.2 | T10: =ROUND(R10*10%,2) -> 14 | U10: 71.75 | V10: =(R10+S10+U10)-(N10+O10+Q10+P10) -> 80
A11: PAID | B11: 1 | C11: =INDEX(PORT!$B$2:$B$20,MATCH('06'!B11,PORT!$A$2:$A$20)) -> PNH01 | D11: =INDEX(PORT!$C$2:$C$20,MATCH('06'!B11,PORT!$A$2:$A$20)) -> KTI AIR PORT | E11: E 22413 | F11: 46178 | G11: VFL | H11: GS26-218 | I11: DIS238 | J11: VFL2606004 | K11: 46181 | L11: =VLOOKUP(K11,'[6]Exchange Rate'!$A$3:$D$22,3,FALSE) -> 4027 | M11: =TEXT(K11,"dddd") -> Monday | N11: 85.95 | O11: 0 | P11: 0 | Q11: 50 | R11: 140 | S11: 15.95 | T11: =ROUND(R11*10%,2) -> 14 | U11: 60 | V11: =(R11+S11+U11)-(N11+O11+Q11+P11) -> 80
A12: PAID | B12: 1 | C12: =INDEX(PORT!$B$2:$B$20,MATCH('06'!B12,PORT!$A$2:$A$20)) -> PNH01 | D12: =INDEX(PORT!$C$2:$C$20,MATCH('06'!B12,PORT!$A$2:$A$20)) -> KTI AIR PORT | E12: E 22600 | F12: 46179 | G12: JR | H12: GS26-219 | I12: DIS239 | J12: JR2606002 | K12: 46181 | L12: =VLOOKUP(K12,'[6]Exchange Rate'!$A$3:$D$22,3,FALSE) -> 4027 | M12: =TEXT(K12,"dddd") -> Monday | N12: 180.95 | O12: 77 | P12: 248 | Q12: 0 | R12: 120 | S12: 81.2 | T12: =ROUND(R12*10%,2) -> 12 | U12: 908.25 | V12: =(R12+S12+U12)-(N12+O12+Q12+P12) -> 603.5 | W12: TI-26-008
A13: PAID | B13: 4 | C13: =INDEX(PORT!$B$2:$B$20,MATCH('06'!B13,PORT!$A$2:$A$20)) -> PNH04 | D13: =INDEX(PORT!$C$2:$C$20,MATCH('06'!B13,PORT!$A$2:$A$20)) -> PNH PORT | E13: E 155508 | F13: 46178 | G13: JR | H13: GS26-220 | I13: DIS240 | J13: JR2606003 | K13: 46181 | L13: =VLOOKUP(K13,'[6]Exchange Rate'!$A$3:$D$22,3,FALSE) -> 4027 | M13: =TEXT(K13,"dddd") -> Monday | N13: 558.25 | O13: 588 | P13: 0 | Q13: 0 | R13: 242 | S13: 686.25 | T13: =ROUND(R13*10%,2) -> 24.2 | U13: 757 | V13: =(R13+S13+U13)-(N13+O13+Q13+P13) -> 539 | W13: TIDM260483&TIDM260484
A14: PAID | B14: 11 | C14: =INDEX(PORT!$B$2:$B$20,MATCH('06'!B14,PORT!$A$2:$A$20)) -> SHV11 | D14: =INDEX(PORT!$C$2:$C$20,MATCH('06'!B14,PORT!$A$2:$A$20)) -> SHV PORT | E14: E 158594 | F14: 46179 | G14: JIN YUAN XI | H14: GS26-221 | I14: DIS241 | J14: JYX2606003 | K14: 46181 | L14: =VLOOKUP(K14,'[6]Exchange Rate'!$A$3:$D$22,3,FALSE) -> 4027 | M14: =TEXT(K14,"dddd") -> Monday | N14: 851.38 | O14: 0 | P14: 0 | Q14: 50 | R14: 245 | S14: 69.88 | T14: =ROUND(R14*10%,2) -> 24.5 | U14: 1202 | V14: =(R14+S14+U14)-(N14+O14+Q14+P14) -> 615.5
A15: PAID | B15: 4 | C15: =INDEX(PORT!$B$2:$B$20,MATCH('06'!B15,PORT!$A$2:$A$20)) -> PNH04 | D15: =INDEX(PORT!$C$2:$C$20,MATCH('06'!B15,PORT!$A$2:$A$20)) -> PNH PORT | E15: E 158607 | F15: 46179 | G15: JR | H15: GS26-222 | I15: DIS242 | J15: JR2606004 | K15: 46181 | L15: =VLOOKUP(K15,'[6]Exchange Rate'!$A$3:$D$22,3,FALSE) -> 4027 | M15: =TEXT(K15,"dddd") -> Monday | N15: 842.75 | O15: 556 | P15: 0 | Q15: 0 | R15: 242 | S15: 654.25 | T15: =ROUND(R15*10%,2) -> 24.2 | U15: 1537.5 | V15: =(R15+S15+U15)-(N15+O15+Q15+P15) -> 1035 | W15: BLS26-0264 & BLS26-0265
A16: PAID | B16: 1 | C16: =INDEX(PORT!$B$2:$B$20,MATCH('06'!B16,PORT!$A$2:$A$20)) -> PNH01 | D16: =INDEX(PORT!$C$2:$C$20,MATCH('06'!B16,PORT!$A$2:$A$20)) -> KTI AIR PORT | E16: E 23449 | F16: 46184 | G16: VFL | H16: GS26-223 | I16: DIS243 | J16: VFL2606005 | K16: 46185 | L16: =VLOOKUP(K16,'[6]Exchange Rate'!$A$3:$D$22,3,FALSE) -> 4026 | M16: =TEXT(K16,"dddd") -> Friday | N16: 85.95 | O16: 0 | P16: 0 | Q16: 50 | R16: 140 | S16: 4.2 | T16: =ROUND(R16*10%,2) -> 14 | U16: 71.75 | V16: =(R16+S16+U16)-(N16+O16+Q16+P16) -> 80
A17: PAID | B17: 1 | C17: =INDEX(PORT!$B$2:$B$20,MATCH('06'!B17,PORT!$A$2:$A$20)) -> PNH01 | D17: =INDEX(PORT!$C$2:$C$20,MATCH('06'!B17,PORT!$A$2:$A$20)) -> KTI AIR PORT | E17: E 23451 | F17: 46184 | G17: VFL | H17: GS26-224 | I17: DIS244 | J17: VFL2606006 | K17: 46185 | L17: =VLOOKUP(K17,'[6]Exchange Rate'!$A$3:$D$22,3,FALSE) -> 4026 | M17: =TEXT(K17,"dddd") -> Friday | N17: 85.95 | O17: 0 | P17: 0 | Q17: 50 | R17: 140 | S17: 15.95 | T17: =ROUND(R17*10%,2) -> 14 | U17: 60 | V17: =(R17+S17+U17)-(N17+O17+Q17+P17) -> 80
A18: PAID | B18: 1 | C18: =INDEX(PORT!$B$2:$B$20,MATCH('06'!B18,PORT!$A$2:$A$20)) -> PNH01 | D18: =INDEX(PORT!$C$2:$C$20,MATCH('06'!B18,PORT!$A$2:$A$20)) -> KTI AIR PORT | E18: E 23455 | F18: 46184 | G18: VFL | H18: GS26-225 | I18: DIS245 | J18: VFL2606007 | K18: 46185 | L18: =VLOOKUP(K18,'[6]Exchange Rate'!$A$3:$D$22,3,FALSE) -> 4026 | M18: =TEXT(K18,"dddd") -> Friday | N18: 85.95 | O18: 0 | P18: 0 | Q18: 50 | R18: 140 | S18: 4.2 | T18: =ROUND(R18*10%,2) -> 14 | U18: 71.75 | V18: =(R18+S18+U18)-(N18+O18+Q18+P18) -> 80
A19: PAID | B19: 1 | C19: =INDEX(PORT!$B$2:$B$20,MATCH('06'!B19,PORT!$A$2:$A$20)) -> PNH01 | D19: =INDEX(PORT!$C$2:$C$20,MATCH('06'!B19,PORT!$A$2:$A$20)) -> KTI AIR PORT | E19: E 23458 | F19: 46184 | G19: VFL | H19: GS26-226 | I19: DIS246 | J19: VFL2606008 | K19: 46185 | L19: =VLOOKUP(K19,'[6]Exchange Rate'!$A$3:$D$22,3,FALSE) -> 4026 | M19: =TEXT(K19,"dddd") -> Friday | N19: 85.95 | O19: 0 | P19: 0 | Q19: 50 | R19: 140 | S19: 4.2 | T19: =ROUND(R19*10%,2) -> 14 | U19: 71.75 | V19: =(R19+S19+U19)-(N19+O19+Q19+P19) -> 80
A20: PAID | B20: 1 | C20: =INDEX(PORT!$B$2:$B$20,MATCH('06'!B20,PORT!$A$2:$A$20)) -> PNH01 | D20: =INDEX(PORT!$C$2:$C$20,MATCH('06'!B20,PORT!$A$2:$A$20)) -> KTI AIR PORT | E20: E 23464 | F20: 46184 | G20: VFL | H20: GS26-227 | I20: DIS247 | J20: VFL2606009 | K20: 46185 | L20: =VLOOKUP(K20,'[6]Exchange Rate'!$A$3:$D$22,3,FALSE) -> 4026 | M20: =TEXT(K20,"dddd") -> Friday | N20: 85.95 | O20: 0 | P20: 0 | Q20: 50 | R20: 140 | S20: 4.2 | T20: =ROUND(R20*10%,2) -> 14 | U20: 71.75 | V20: =(R20+S20+U20)-(N20+O20+Q20+P20) -> 80
A21: PAID | B21: 1 | C21: =INDEX(PORT!$B$2:$B$20,MATCH('06'!B21,PORT!$A$2:$A$20)) -> PNH01 | D21: =INDEX(PORT!$C$2:$C$20,MATCH('06'!B21,PORT!$A$2:$A$20)) -> KTI AIR PORT | E21: E 23474 | F21: 46184 | G21: VFL | H21: GS26-228 | I21: DIS248 | J21: VFL2606010 | K21: 46185 | L21: =VLOOKUP(K21,'[6]Exchange Rate'!$A$3:$D$22,3,FALSE) -> 4026 | M21: =TEXT(K21,"dddd") -> Friday | N21: 85.95 | O21: 0 | P21: 0 | Q21: 50 | R21: 140 | S21: 4.2 | T21: =ROUND(R21*10%,2) -> 14 | U21: 71.75 | V21: =(R21+S21+U21)-(N21+O21+Q21+P21) -> 80
A22: PAID | B22: 11 | C22: =INDEX(PORT!$B$2:$B$20,MATCH('06'!B22,PORT!$A$2:$A$20)) -> SHV11 | D22: =INDEX(PORT!$C$2:$C$20,MATCH('06'!B22,PORT!$A$2:$A$20)) -> SHV PORT | E22: E 160433 | F22: 46184 | G22: VFL | H22: GS26-229 | I22: DIS249 | J22: VFL2606011 | K22: 46185 | L22: =VLOOKUP(K22,'[6]Exchange Rate'!$A$3:$D$22,3,FALSE) -> 4026 | M22: =TEXT(K22,"dddd") -> Friday | N22: 278 | O22: 0 | P22: 0 | Q22: 50 | R22: 110.94 | S22: 84.95 | T22: =ROUND(R22*10%,2) -> 11.09 | U22: 303.23 | V22: =(R22+S22+U22)-(N22+O22+Q22+P22) -> 171.12
A23: PAID | B23: 1 | C23: =INDEX(PORT!$B$2:$B$20,MATCH('06'!B23,PORT!$A$2:$A$20)) -> PNH01 | D23: =INDEX(PORT!$C$2:$C$20,MATCH('06'!B23,PORT!$A$2:$A$20)) -> KTI AIR PORT | E23: E 23460 | F23: 46184 | G23: VFL | H23: GS26-230 | I23: DIS250 | J23: VFL2606012 | K23: 46185 | L23: =VLOOKUP(K23,'[6]Exchange Rate'!$A$3:$D$22,3,FALSE) -> 4026 | M23: =TEXT(K23,"dddd") -> Friday | N23: 85.95 | O23: 0 | P23: 0 | Q23: 50 | R23: 140 | S23: 4.2 | T23: =ROUND(R23*10%,2) -> 14 | U23: 71.75 | V23: =(R23+S23+U23)-(N23+O23+Q23+P23) -> 80
A24: PAID | B24: 11 | C24: =INDEX(PORT!$B$2:$B$20,MATCH('06'!B24,PORT!$A$2:$A$20)) -> SHV11 | D24: =INDEX(PORT!$C$2:$C$20,MATCH('06'!B24,PORT!$A$2:$A$20)) -> SHV PORT | E24: E 160452 | F24: 46184 | G24: SPORTLINE | H24: GS26-231 | I24: DIS251 | J24: SAK2606003 | K24: 46185 | L24: =VLOOKUP(K24,'[6]Exchange Rate'!$A$3:$D$22,3,FALSE) -> 4026 | M24: =TEXT(K24,"dddd") -> Friday | N24: 210.38 | O24: 0 | P24: 0 | Q24: 50 | R24: 99.11 | S24: 13.75 | T24: =ROUND(R24*10%,2) -> 9.91 | U24: 274.78 | V24: =(R24+S24+U24)-(N24+O24+Q24+P24) -> 127.26
A25: PAID | B25: 1 | C25: =INDEX(PORT!$B$2:$B$20,MATCH('06'!B25,PORT!$A$2:$A$20)) -> PNH01 | D25: =INDEX(PORT!$C$2:$C$20,MATCH('06'!B25,PORT!$A$2:$A$20)) -> KTI AIR PORT | E25: E 23668 | F25: 46185 | G25: VFL | H25: GS26-232 | I25: DIS252 | J25: VFL2606013 | K25: 46188 | L25: =VLOOKUP(K25,'[6]Exchange Rate'!$A$3:$D$22,3,FALSE) -> 4025 | M25: =TEXT(K25,"dddd") -> Monday | N25: 92.99 | O25: 0 | P25: 0 | Q25: 50 | R25: 140 | S25: 22.99 | T25: =ROUND(R25*10%,2) -> 14 | U25: 180 | V25: =(R25+S25+U25)-(N25+O25+Q25+P25) -> 200
A26: PAID | B26: 4 | C26: =INDEX(PORT!$B$2:$B$20,MATCH('06'!B26,PORT!$A$2:$A$20)) -> PNH04 | D26: =INDEX(PORT!$C$2:$C$20,MATCH('06'!B26,PORT!$A$2:$A$20)) -> PNH PORT | E26: E 162796 | F26: 46185 | G26: SPORTLINE | H26: GS26-233 | I26: DIS253 | J26: SAK2606004 | K26: 46188 | L26: =VLOOKUP(K26,'[6]Exchange Rate'!$A$3:$D$22,3,FALSE) -> 4025 | M26: =TEXT(K26,"dddd") -> Monday | N26: 551.85 | O26: 0 | P26: 0 | Q26: 50 | R26: 215 | S26: 101.85 | T26: =ROUND(R26*10%,2) -> 21.5 | U26: 547.5 | V26: =(R26+S26+U26)-(N26+O26+Q26+P26) -> 262.5
A27: PAID | B27: 4 | C27: =INDEX(PORT!$B$2:$B$20,MATCH('06'!B27,PORT!$A$2:$A$20)) -> PNH04 | D27: =INDEX(PORT!$C$2:$C$20,MATCH('06'!B27,PORT!$A$2:$A$20)) -> PNH PORT | E27: E 165484 | F27: 46185 | G27: JR | H27: GS26-234 | I27: DIS254 | J27: JR2606005 | K27: 46188 | L27: =VLOOKUP(K27,'[6]Exchange Rate'!$A$3:$D$22,3,FALSE) -> 4025 | M27: =TEXT(K27,"dddd") -> Monday | N27: 562.75 | O27: 476.5 | P27: 0 | Q27: 0 | R27: 242 | S27: 574.75 | T27: =ROUND(R27*10%,2) -> 24.2 | U27: 903 | V27: =(R27+S27+U27)-(N27+O27+Q27+P27) -> 680.5 | W27: TICF20261610&TICF20261611
A28: PAID | B28: 11 | C28: =INDEX(PORT!$B$2:$B$20,MATCH('06'!B28,PORT!$A$2:$A$20)) -> SHV11 | D28: =INDEX(PORT!$C$2:$C$20,MATCH('06'!B28,PORT!$A$2:$A$20)) -> SHV PORT | E28: I 86496 | F28: 46188 | G28: SPORTLINE | H28: GS26-235 | I28: DIS255 | J28: SAK2606005 | K28: 46189 | L28: =VLOOKUP(K28,'[6]Exchange Rate'!$A$3:$D$22,3,FALSE) -> 4025 | M28: =TEXT(K28,"dddd") -> Tuesday | N28: 168.96 | O28: 262.9 | P28: 0 | Q28: 50 | R28: 150 | S28: 280.46 | T28: =ROUND(R28*10%,2) -> 15 | U28: 165.97 | V28: =(R28+S28+U28)-(N28+O28+Q28+P28) -> 114.57
A29: PAID | B29: 11 | C29: =INDEX(PORT!$B$2:$B$20,MATCH('06'!B29,PORT!$A$2:$A$20)) -> SHV11 | D29: =INDEX(PORT!$C$2:$C$20,MATCH('06'!B29,PORT!$A$2:$A$20)) -> SHV PORT | E29: E 168235 | F29: 46190 | G29: SPORTLINE | H29: GS26-236 | I29: DIS256 | J29: SAK2606006 | K29: 46192 | L29: =VLOOKUP(K29,'[6]Exchange Rate'!$A$3:$D$22,3,FALSE) -> 4024 | M29: =TEXT(K29,"dddd") -> Friday | N29: 531.75 | O29: 0 | P29: 0 | Q29: 50 | R29: 215 | S29: 67.75 | T29: =ROUND(R29*10%,2) -> 21.5 | U29: 580.5 | V29: =(R29+S29+U29)-(N29+O29+Q29+P29) -> 281.5
A30: PAID | B30: 1 | C30: =INDEX(PORT!$B$2:$B$20,MATCH('06'!B30,PORT!$A$2:$A$20)) -> PNH01 | D30: =INDEX(PORT!$C$2:$C$20,MATCH('06'!B30,PORT!$A$2:$A$20)) -> KTI AIR PORT | E30: E 24809 | F30: 46190 | G30: VFL | H30: GS26-237 | I30: DIS257 | J30: VFL2606014 | K30: 46192 | L30: =VLOOKUP(K30,'[6]Exchange Rate'!$A$3:$D$22,3,FALSE) -> 4024 | M30: =TEXT(K30,"dddd") -> Friday | N30: 90.88 | O30: 0 | P30: 0 | Q30: 50 | R30: 140 | S30: 20.88 | T30: =ROUND(R30*10%,2) -> 14 | U30: 60 | V30: =(R30+S30+U30)-(N30+O30+Q30+P30) -> 80
A31: PAID | B31: 19 | C31: =INDEX(PORT!$B$2:$B$20,MATCH('06'!B31,PORT!$A$2:$A$20)) -> PNH19 | D31: =INDEX(PORT!$C$2:$C$20,MATCH('06'!B31,PORT!$A$2:$A$20)) -> TEC SRUN DRYPORT | E31: I 2091 | F31: 46196 | G31: SPORTLINE | H31: GS26-238 | I31: DIS258 | J31: SAK2606007 | K31: 46197 | L31: =VLOOKUP(K31,'[6]Exchange Rate'!$A$3:$D$22,3,FALSE) -> 4024 | M31: =TEXT(K31,"dddd") -> Wednesday | N31: 147.13 | O31: 262.9 | P31: 0 | Q31: 50 | R31: 150 | S31: 386.33 | T31: =ROUND(R31*10%,2) -> 15 | U31: 159 | V31: =(R31+S31+U31)-(N31+O31+Q31+P31) -> 235.3
A32: PAID | B32: 11 | C32: =INDEX(PORT!$B$2:$B$20,MATCH('06'!B32,PORT!$A$2:$A$20)) -> SHV11 | D32: =INDEX(PORT!$C$2:$C$20,MATCH('06'!B32,PORT!$A$2:$A$20)) -> SHV PORT | E32: I 91062 | F32: 46196 | G32: SPORTLINE | H32: GS26-239 | I32: DIS259 | J32: SAK2606008 | K32: 46197 | L32: =VLOOKUP(K32,'[6]Exchange Rate'!$A$3:$D$22,3,FALSE) -> 4024 | M32: =TEXT(K32,"dddd") -> Wednesday | N32: 194.43 | O32: 251.89 | P32: 0 | Q32: 50 | R32: 150 | S32: 267.32 | T32: =ROUND(R32*10%,2) -> 15 | U32: 166.75 | V32: =(R32+S32+U32)-(N32+O32+Q32+P32) -> 87.75
A33: PAID | B33: 11 | C33: =INDEX(PORT!$B$2:$B$20,MATCH('06'!B33,PORT!$A$2:$A$20)) -> SHV11 | D33: =INDEX(PORT!$C$2:$C$20,MATCH('06'!B33,PORT!$A$2:$A$20)) -> SHV PORT | E33: I 91069 | F33: 46196 | G33: SPORTLINE | H33: GS26-240 | I33: DIS260 | J33: SAK2606009 | K33: 46197 | L33: =VLOOKUP(K33,'[6]Exchange Rate'!$A$3:$D$22,3,FALSE) -> 4024 | M33: =TEXT(K33,"dddd") -> Wednesday | N33: 170.43 | O33: 192.5 | P33: 0 | Q33: 50 | R33: 150 | S33: 207.93 | T33: =ROUND(R33*10%,2) -> 15 | U33: 156.5 | V33: =(R33+S33+U33)-(N33+O33+Q33+P33) -> 101.5
A34: PAID | B34: 11 | C34: =INDEX(PORT!$B$2:$B$20,MATCH('06'!B34,PORT!$A$2:$A$20)) -> SHV11 | D34: =INDEX(PORT!$C$2:$C$20,MATCH('06'!B34,PORT!$A$2:$A$20)) -> SHV PORT | E34: I 91080 | F34: 46196 | G34: VFL | H34: GS26-241 | I34: DIS261 | J34: VFL2606015 | K34: 46197 | L34: =VLOOKUP(K34,'[6]Exchange Rate'!$A$3:$D$22,3,FALSE) -> 4024 | M34: =TEXT(K34,"dddd") -> Wednesday | N34: 301.4 | O34: 698.5 | P34: 0 | Q34: 50 | R34: 150 | S34: 727.4 | T34: =ROUND(R34*10%,2) -> 15 | U34: 348.13 | V34: =(R34+S34+U34)-(N34+O34+Q34+P34) -> 175.63
A35: PAID | C35: =INDEX(PORT!$B$2:$B$20,MATCH('06'!B35,PORT!$A$2:$A$20)) -> #N/A | D35: =INDEX(PORT!$C$2:$C$20,MATCH('06'!B35,PORT!$A$2:$A$20)) -> #N/A | E35: I 626 | F35: 46197 | G35: SPORTLINE | H35: GS26-242 | I35: DIS262 | J35: SAK2606010 | K35: 46198 | L35: =VLOOKUP(K35,'[6]Exchange Rate'!$A$3:$D$22,3,FALSE) -> 4024 | M35: =TEXT(K35,"dddd") -> Thursday | N35: 141.16 | O35: 255.75 | P35: 0 | Q35: 50 | R35: 150 | S35: 286.91 | T35: =ROUND(R35*10%,2) -> 15 | U35: 159 | V35: =(R35+S35+U35)-(N35+O35+Q35+P35) -> 149
A36: PAID | C36: =INDEX(PORT!$B$2:$B$20,MATCH('06'!B36,PORT!$A$2:$A$20)) -> #N/A | D36: =INDEX(PORT!$C$2:$C$20,MATCH('06'!B36,PORT!$A$2:$A$20)) -> #N/A | E36: I 625 | F36: 46197 | G36: VFL | H36: GS26-243 | I36: DIS263 | J36: VFL2606016 | K36: 46198 | L36: =VLOOKUP(K36,'[6]Exchange Rate'!$A$3:$D$22,3,FALSE) -> 4024 | M36: =TEXT(K36,"dddd") -> Thursday | N36: 112 | O36: 203.5 | P36: 0 | Q36: 50 | R36: 150 | S36: 228.5 | T36: =ROUND(R36*10%,2) -> 15 | U36: 109.5 | V36: =(R36+S36+U36)-(N36+O36+Q36+P36) -> 122.5
A37: PAID | B37: 1 | C37: =INDEX(PORT!$B$2:$B$20,MATCH('06'!B37,PORT!$A$2:$A$20)) -> PNH01 | D37: =INDEX(PORT!$C$2:$C$20,MATCH('06'!B37,PORT!$A$2:$A$20)) -> KTI AIR PORT | E37: I 18502 | F37: 46198 | G37: SPORTLINE | H37: GS26-244 | I37: DIS264 | J37: SAK2606011 | K37: 46199 | L37: =VLOOKUP(K37,'[6]Exchange Rate'!$A$3:$D$22,3,FALSE) -> 4024 | M37: =TEXT(K37,"dddd") -> Friday | N37: 164.7 | O37: 104.5 | P37: 0 | Q37: 50 | R37: 150 | S37: 124.2 | T37: =ROUND(R37*10%,2) -> 15 | U37: 196.75 | V37: =(R37+S37+U37)-(N37+O37+Q37+P37) -> 151.75
A38: PAID | B38: 1 | C38: =INDEX(PORT!$B$2:$B$20,MATCH('06'!B38,PORT!$A$2:$A$20)) -> PNH01 | D38: =INDEX(PORT!$C$2:$C$20,MATCH('06'!B38,PORT!$A$2:$A$20)) -> KTI AIR PORT | E38: E 26895 | F38: 46200 | G38: JIN YUAN XI | H38: GS26-245 | I38: DIS265 | J38: JYX2606004 | K38: 46202 | L38: =VLOOKUP(K38,'[6]Exchange Rate'!$A$3:$D$22,3,FALSE) -> 4026 | M38: =TEXT(K38,"dddd") -> Monday | N38: 153.81 | O38: 0 | P38: 0 | Q38: 50 | R38: 140 | S38: 33.81 | T38: =ROUND(R38*10%,2) -> 14 | U38: 180 | V38: =(R38+S38+U38)-(N38+O38+Q38+P38) -> 150
A39: PAID | B39: 11 | C39: =INDEX(PORT!$B$2:$B$20,MATCH('06'!B39,PORT!$A$2:$A$20)) -> SHV11 | D39: =INDEX(PORT!$C$2:$C$20,MATCH('06'!B39,PORT!$A$2:$A$20)) -> SHV PORT | E39: E 184114 | F39: 46200 | G39: JIN YUAN XI | H39: GS26-246 | I39: DIS266 | J39: JYX2606005 | K39: 46202 | L39: =VLOOKUP(K39,'[6]Exchange Rate'!$A$3:$D$22,3,FALSE) -> 4026 | M39: =TEXT(K39,"dddd") -> Monday | N39: 838.88 | O39: 0 | P39: 0 | Q39: 50 | R39: 245 | S39: 72.38 | T39: =ROUND(R39*10%,2) -> 24.5 | U39: 1282 | V39: =(R39+S39+U39)-(N39+O39+Q39+P39) -> 710.5
A40: PAID | B40: 4 | C40: =INDEX(PORT!$B$2:$B$20,MATCH('06'!B40,PORT!$A$2:$A$20)) -> PNH04 | D40: =INDEX(PORT!$C$2:$C$20,MATCH('06'!B40,PORT!$A$2:$A$20)) -> PNH PORT | E40: E 178756 | F40: 46564 | G40: SPORTLINE | H40: GS26-247 | I40: DIS267 | J40: SAK2606012 | K40: 46202 | L40: =VLOOKUP(K40,'[6]Exchange Rate'!$A$3:$D$22,3,FALSE) -> 4026 | M40: =TEXT(K40,"dddd") -> Monday | N40: 1153.95 | O40: 0 | P40: 0 | Q40: 50 | R40: 490 | S40: 302.75 | T40: =ROUND(R40*10%,2) -> 49 | U40: 1078 | V40: =(R40+S40+U40)-(N40+O40+Q40+P40) -> 666.8 | W40: LACKING STORAGE (13.20)
A41: PAID | B41: 11 | C41: =INDEX(PORT!$B$2:$B$20,MATCH('06'!B41,PORT!$A$2:$A$20)) -> SHV11 | D41: =INDEX(PORT!$C$2:$C$20,MATCH('06'!B41,PORT!$A$2:$A$20)) -> SHV PORT | E41: I 92883 | F41: 46199 | G41: VFL | H41: GS26-248 | I41: DIS268 | J41: VFL2606017 | K41: 46202 | L41: =VLOOKUP(K41,'[6]Exchange Rate'!$A$3:$D$22,3,FALSE) -> 4026 | M41: =TEXT(K41,"dddd") -> Monday | N41: 208.48 | O41: 331.23 | P41: 0 | Q41: 50 | R41: 150 | S41: 351.71 | T41: =ROUND(R41*10%,2) -> 15 | U41: 186.79 | V41: =(R41+S41+U41)-(N41+O41+Q41+P41) -> 98.79
B42: 4 | C42: =INDEX(PORT!$B$2:$B$20,MATCH('06'!B42,PORT!$A$2:$A$20)) -> PNH04 | D42: =INDEX(PORT!$C$2:$C$20,MATCH('06'!B42,PORT!$A$2:$A$20)) -> PNH PORT | E42: E 157509 | F42: 46178 | G42: JR | I42: DIS269 | J42: JR2606006 | K42: 46203 | L42: =VLOOKUP(K42,'[6]Exchange Rate'!$A$3:$D$22,3,FALSE) -> 4026 | M42: =TEXT(K42,"dddd") -> Tuesday | N42: 0 | O42: 2123.44 | P42: 0 | Q42: 0 | R42: 0 | S42: 2123.44 | T42: =ROUND(R42*10%,2) -> 0 | U42: 174 | V42: =(R42+S42+U42)-(N42+O42+Q42+P42) -> 174 | W42: CGL26-01103-1104-1107&RM26-00571
B43: 4 | C43: =INDEX(PORT!$B$2:$B$20,MATCH('06'!B43,PORT!$A$2:$A$20)) -> PNH04 | D43: =INDEX(PORT!$C$2:$C$20,MATCH('06'!B43,PORT!$A$2:$A$20)) -> PNH PORT | E43: E 166063 | F43: 46185 | G43: JR | I43: DIS270 | J43: JR2606007 | K43: 46203 | L43: =VLOOKUP(K43,'[6]Exchange Rate'!$A$3:$D$22,3,FALSE) -> 4026 | M43: =TEXT(K43,"dddd") -> Tuesday | N43: 0 | O43: 1618.96 | P43: 0 | Q43: 0 | R43: 0 | S43: 1618.96 | T43: =ROUND(R43*10%,2) -> 0 | U43: 174 | V43: =(R43+S43+U43)-(N43+O43+Q43+P43) -> 174 | W43: CGL26-01170-1171&RM26-00604
B44: 4 | C44: =INDEX(PORT!$B$2:$B$20,MATCH('06'!B44,PORT!$A$2:$A$20)) -> PNH04 | D44: =INDEX(PORT!$C$2:$C$20,MATCH('06'!B44,PORT!$A$2:$A$20)) -> PNH PORT | E44: E 167278 | F44: 46186 | G44: JR | I44: DIS271 | J44: JR2606008 | K44: 46203 | L44: =VLOOKUP(K44,'[6]Exchange Rate'!$A$3:$D$22,3,FALSE) -> 4026 | M44: =TEXT(K44,"dddd") -> Tuesday | N44: 0 | O44: 1648.55 | P44: 0 | Q44: 0 | R44: 0 | S44: 1648.55 | T44: =ROUND(R44*10%,2) -> 0 | U44: 174 | V44: =(R44+S44+U44)-(N44+O44+Q44+P44) -> 174 | W44: CGL26-01166-1167-RM26-00602
B45: 11 | C45: =INDEX(PORT!$B$2:$B$20,MATCH('06'!B45,PORT!$A$2:$A$20)) -> SHV11 | D45: =INDEX(PORT!$C$2:$C$20,MATCH('06'!B45,PORT!$A$2:$A$20)) -> SHV PORT | E45: E 168899 | F45: 46191 | G45: JR | I45: DIS272 | J45: JR2606009 | K45: 46203 | L45: =VLOOKUP(K45,'[6]Exchange Rate'!$A$3:$D$22,3,FALSE) -> 4026 | M45: =TEXT(K45,"dddd") -> Tuesday | N45: 0 | O45: 452.93 | P45: 0 | Q45: 0 | R45: 0 | S45: 452.93 | T45: =ROUND(R45*10%,2) -> 0 | U45: 120 | V45: =(R45+S45+U45)-(N45+O45+Q45+P45) -> 120 | W45: APLL26007073
B46: 11 | C46: =INDEX(PORT!$B$2:$B$20,MATCH('06'!B46,PORT!$A$2:$A$20)) -> SHV11 | D46: =INDEX(PORT!$C$2:$C$20,MATCH('06'!B46,PORT!$A$2:$A$20)) -> SHV PORT | E46: E 168958 | F46: 46191 | G46: JR | I46: DIS273 | J46: JR2606010 | K46: 46203 | L46: =VLOOKUP(K46,'[6]Exchange Rate'!$A$3:$D$22,3,FALSE) -> 4026 | M46: =TEXT(K46,"dddd") -> Tuesday | N46: 0 | O46: 529.86 | P46: 0 | Q46: 0 | R46: 0 | S46: 529.86 | T46: =ROUND(R46*10%,2) -> 0 | U46: 174 | V46: =(R46+S46+U46)-(N46+O46+Q46+P46) -> 174 | W46: APLL26007021
B47: 4 | C47: =INDEX(PORT!$B$2:$B$20,MATCH('06'!B47,PORT!$A$2:$A$20)) -> PNH04 | D47: =INDEX(PORT!$C$2:$C$20,MATCH('06'!B47,PORT!$A$2:$A$20)) -> PNH PORT | E47: E 173249 | F47: 46192 | G47: JR | I47: DIS274 | J47: JR2606011 | K47: 46203 | L47: =VLOOKUP(K47,'[6]Exchange Rate'!$A$3:$D$22,3,FALSE) -> 4026 | M47: =TEXT(K47,"dddd") -> Tuesday | N47: 0 | O47: 1386.77 | P47: 0 | Q47: 0 | R47: 0 | S47: 1386.77 | T47: =ROUND(R47*10%,2) -> 0 | U47: 120 | V47: =(R47+S47+U47)-(N47+O47+Q47+P47) -> 120 | W47: BLS26-0281&BLS26-0282&RM26-0039
B48: 4 | C48: =INDEX(PORT!$B$2:$B$20,MATCH('06'!B48,PORT!$A$2:$A$20)) -> PNH04 | D48: =INDEX(PORT!$C$2:$C$20,MATCH('06'!B48,PORT!$A$2:$A$20)) -> PNH PORT | E48: E 175464 | F48: 46193 | G48: JR | I48: DIS275 | J48: JR2606012 | K48: 46203 | L48: =VLOOKUP(K48,'[6]Exchange Rate'!$A$3:$D$22,3,FALSE) -> 4026 | M48: =TEXT(K48,"dddd") -> Tuesday | N48: 0 | O48: 1719.08 | P48: 0 | Q48: 0 | R48: 0 | S48: 1719.08 | T48: =ROUND(R48*10%,2) -> 0 | U48: 174 | V48: =(R48+S48+U48)-(N48+O48+Q48+P48) -> 174 | W48: CGL26-01240-01241&RM26-00642
A49: PAID | B49: 1 | C49: =INDEX(PORT!$B$2:$B$20,MATCH('06'!B49,PORT!$A$2:$A$20)) -> PNH01 | D49: =INDEX(PORT!$C$2:$C$20,MATCH('06'!B49,PORT!$A$2:$A$20)) -> KTI AIR PORT | E49: I 18959 | F49: 46202 | G49: JIN YUAN XI | H49: GS26-249 | I49: DIS276 | J49: JYX2606006 | K49: 46203 | L49: =VLOOKUP(K49,'[6]Exchange Rate'!$A$3:$D$22,3,FALSE) -> 4026 | M49: =TEXT(K49,"dddd") -> Tuesday | N49: 274.29 | O49: 0 | P49: 0 | Q49: 50 | R49: 185 | S49: 104.29 | T49: =ROUND(R49*10%,2) -> 18.5 | U49: 225.75 | V49: =(R49+S49+U49)-(N49+O49+Q49+P49) -> 190.75
A50: PAID | B50: 1 | C50: =INDEX(PORT!$B$2:$B$20,MATCH('06'!B50,PORT!$A$2:$A$20)) -> PNH01 | D50: =INDEX(PORT!$C$2:$C$20,MATCH('06'!B50,PORT!$A$2:$A$20)) -> KTI AIR PORT | E50: I 18962 | F50: 46202 | G50: JIN YUAN XI | H50: GS26-250 | I50: DIS277 | J50: JYX2606007 | K50: 46203 | L50: =VLOOKUP(K50,'[6]Exchange Rate'!$A$3:$D$22,3,FALSE) -> 4026 | M50: =TEXT(K50,"dddd") -> Tuesday | N50: 353.88 | O50: 0 | P50: 0 | Q50: 50 | R50: 185 | S50: 168.88 | T50: =ROUND(R50*10%,2) -> 18.5 | U50: 272 | V50: =(R50+S50+U50)-(N50+O50+Q50+P50) -> 222
A51: PAID | B51: 1 | C51: =INDEX(PORT!$B$2:$B$20,MATCH('06'!B51,PORT!$A$2:$A$20)) -> PNH01 | D51: =INDEX(PORT!$C$2:$C$20,MATCH('06'!B51,PORT!$A$2:$A$20)) -> KTI AIR PORT | E51: I 19067 | F51: 46203 | G51: SPORTLINE | H51: GS26-251 | I51: DIS278 | J51: SAK2606013 | K51: 46203 | L51: =VLOOKUP(K51,'[6]Exchange Rate'!$A$3:$D$22,3,FALSE) -> 4026 | M51: =TEXT(K51,"dddd") -> Tuesday | N51: 176.17 | O51: 60.5 | P51: 0 | Q51: 50 | R51: 150 | S51: 91.67 | T51: =ROUND(R51*10%,2) -> 15 | U51: 196.75 | V51: =(R51+S51+U51)-(N51+O51+Q51+P51) -> 151.75
A52: PAID | B52: 11 | C52: =INDEX(PORT!$B$2:$B$20,MATCH('06'!B52,PORT!$A$2:$A$20)) -> SHV11 | D52: =INDEX(PORT!$C$2:$C$20,MATCH('06'!B52,PORT!$A$2:$A$20)) -> SHV PORT | E52: I 95338 | F52: 46203 | G52: VFL | H52: GS26-252 | I52: DIS279 | J52: VFL2606018 | K52: 46203 | L52: =VLOOKUP(K52,'[6]Exchange Rate'!$A$3:$D$22,3,FALSE) -> 4026 | M52: =TEXT(K52,"dddd") -> Tuesday | N52: 140.43 | O52: 183.7 | P52: 0 | Q52: 50 | R52: 150 | S52: 199.13 | T52: =ROUND(R52*10%,2) -> 15 | U52: 109.5 | V52: =(R52+S52+U52)-(N52+O52+Q52+P52) -> 84.5
B53: 11 | C53: =INDEX(PORT!$B$2:$B$20,MATCH('06'!B53,PORT!$A$2:$A$20)) -> SHV11 | D53: =INDEX(PORT!$C$2:$C$20,MATCH('06'!B53,PORT!$A$2:$A$20)) -> SHV PORT | E53: I 96700 | G53: SPORTLINE | I53: DIS280 | K53: 46203 | L53: =VLOOKUP(K53,'[6]Exchange Rate'!$A$3:$D$22,3,FALSE) -> 4026 | M53: =TEXT(K53,"dddd") -> Tuesday | N53: 0 | O53: 222.72 | P53: 0 | Q53: 0 | R53: 0 | S53: 222.72 | T53: =ROUND(R53*10%,2) -> 0 | U53: 0 | V53: =(R53+S53+U53)-(N53+O53+Q53+P53) -> 0
B54: 11 | C54: =INDEX(PORT!$B$2:$B$20,MATCH('06'!B54,PORT!$A$2:$A$20)) -> SHV11 | D54: =INDEX(PORT!$C$2:$C$20,MATCH('06'!B54,PORT!$A$2:$A$20)) -> SHV PORT | E54: I 95925 | G54: SPORTLINE | I54: DIS281 | K54: 46203 | L54: =VLOOKUP(K54,'[6]Exchange Rate'!$A$3:$D$22,3,FALSE) -> 4026 | M54: =TEXT(K54,"dddd") -> Tuesday | N54: 0 | O54: 602.36 | P54: 0 | Q54: 0 | R54: 0 | S54: 602.36 | T54: =ROUND(R54*10%,2) -> 0 | U54: 0 | V54: =(R54+S54+U54)-(N54+O54+Q54+P54) -> 0
B55: 19 | C55: =INDEX(PORT!$B$2:$B$20,MATCH('06'!B55,PORT!$A$2:$A$20)) -> PNH19 | D55: =INDEX(PORT!$C$2:$C$20,MATCH('06'!B55,PORT!$A$2:$A$20)) -> TEC SRUN DRYPORT | E55: I 2335 | G55: SPORTLINE | I55: DIS282 | K55: 46203 | L55: =VLOOKUP(K55,'[6]Exchange Rate'!$A$3:$D$22,3,FALSE) -> 4026 | M55: =TEXT(K55,"dddd") -> Tuesday | N55: 0 | O55: 285.6 | P55: 0 | Q55: 0 | R55: 0 | S55: 285.6 | T55: =ROUND(R55*10%,2) -> 0 | U55: 0 | V55: =(R55+S55+U55)-(N55+O55+Q55+P55) -> 0
B56: 19 | C56: =INDEX(PORT!$B$2:$B$20,MATCH('06'!B56,PORT!$A$2:$A$20)) -> PNH19 | D56: =INDEX(PORT!$C$2:$C$20,MATCH('06'!B56,PORT!$A$2:$A$20)) -> TEC SRUN DRYPORT | G56: VFL | I56: DIS283 | K56: 46203 | L56: =VLOOKUP(K56,'[6]Exchange Rate'!$A$3:$D$22,3,FALSE) -> 4026 | M56: =TEXT(K56,"dddd") -> Tuesday | N56: 0 | O56: 198.56 | P56: 0 | Q56: 0 | R56: 0 | S56: 198.56 | T56: =ROUND(R56*10%,2) -> 0 | U56: 0 | V56: =(R56+S56+U56)-(N56+O56+Q56+P56) -> 0
B57: 11 | C57: =INDEX(PORT!$B$2:$B$20,MATCH('06'!B57,PORT!$A$2:$A$20)) -> SHV11 | D57: =INDEX(PORT!$C$2:$C$20,MATCH('06'!B57,PORT!$A$2:$A$20)) -> SHV PORT | G57: VFL | I57: DIS284 | K57: 46203 | L57: =VLOOKUP(K57,'[6]Exchange Rate'!$A$3:$D$22,3,FALSE) -> 4026 | M57: =TEXT(K57,"dddd") -> Tuesday | N57: 0 | O57: 272.25 | P57: 0 | Q57: 0 | R57: 0 | S57: 272.25 | T57: =ROUND(R57*10%,2) -> 0 | U57: 0 | V57: =(R57+S57+U57)-(N57+O57+Q57+P57) -> 0
A58: PAID | B58: 11 | C58: =INDEX(PORT!$B$2:$B$20,MATCH('06'!B58,PORT!$A$2:$A$20)) -> SHV11 | D58: =INDEX(PORT!$C$2:$C$20,MATCH('06'!B58,PORT!$A$2:$A$20)) -> SHV PORT | E58: I 95352 | F58: 46203 | G58: JIN YUAN XI | H58: GS26-253 | I58: DIS285 | J58: JYX2606008 | K58: 46203 | L58: =VLOOKUP(K58,'[6]Exchange Rate'!$A$3:$D$22,3,FALSE) -> 4026 | M58: =TEXT(K58,"dddd") -> Tuesday | N58: 450.45 | O58: 401 | P58: 0 | Q58: 50 | R58: 150 | S58: 510.45 | T58: =ROUND(R58*10%,2) -> 15 | U58: 592.45 | V58: =(R58+S58+U58)-(N58+O58+Q58+P58) -> 351.45
A59: PAID | B59: 11 | C59: =INDEX(PORT!$B$2:$B$20,MATCH('06'!B59,PORT!$A$2:$A$20)) -> SHV11 | D59: =INDEX(PORT!$C$2:$C$20,MATCH('06'!B59,PORT!$A$2:$A$20)) -> SHV PORT | E59: E 165443 | F59: 46185 | G59: JIN YUAN XI | H59: GS26-254 | I59: DIS286 | J59: JYX2606009 | K59: 46203 | L59: =VLOOKUP(K59,'[6]Exchange Rate'!$A$3:$D$22,3,FALSE) -> 4026 | M59: =TEXT(K59,"dddd") -> Tuesday | N59: 451.45 | O59: 0 | P59: 0 | Q59: 50 | R59: 245 | S59: 39.95 | T59: =ROUND(R59*10%,2) -> 24.5 | U59: 499.5 | V59: =(R59+S59+U59)-(N59+O59+Q59+P59) -> 283
A60: PAID | B60: 23 | C60: =INDEX(PORT!$B$2:$B$20,MATCH('06'!B60,PORT!$A$2:$A$20)) -> PNH23 | D60: =INDEX(PORT!$C$2:$C$20,MATCH('06'!B60,PORT!$A$2:$A$20)) -> UNION DRY PORT | E60: I 487 | F60: 46185 | G60: JIN YUAN XI | H60: GS26-255 | I60: DIS287 | J60: JYX2606010 | K60: 46203 | L60: =VLOOKUP(K60,'[6]Exchange Rate'!$A$3:$D$22,3,FALSE) -> 4026 | M60: =TEXT(K60,"dddd") -> Tuesday | N60: 345.35 | O60: 774.62 | P60: 0 | Q60: 50 | R60: 150 | S60: 949.97 | T60: =ROUND(R60*10%,2) -> 15 | U60: 227 | V60: =(R60+S60+U60)-(N60+O60+Q60+P60) -> 157
A61: PAID | B61: 11 | C61: =INDEX(PORT!$B$2:$B$20,MATCH('06'!B61,PORT!$A$2:$A$20)) -> SHV11 | D61: =INDEX(PORT!$C$2:$C$20,MATCH('06'!B61,PORT!$A$2:$A$20)) -> SHV PORT | E61: E 174326 | F61: 46192 | G61: JIN YUAN XI | H61: GS26-256 | I61: DIS288 | J61: JYX2606011 | K61: 46203 | L61: =VLOOKUP(K61,'[6]Exchange Rate'!$A$3:$D$22,3,FALSE) -> 4026 | M61: =TEXT(K61,"dddd") -> Tuesday | N61: 899.28 | O61: 0 | P61: 0 | Q61: 50 | R61: 245 | S61: 107.28 | T61: =ROUND(R61*10%,2) -> 24.5 | U61: 1157.5 | V61: =(R61+S61+U61)-(N61+O61+Q61+P61) -> 560.5
A62: PAID | B62: 1 | C62: =INDEX(PORT!$B$2:$B$20,MATCH('06'!B62,PORT!$A$2:$A$20)) -> PNH01 | D62: =INDEX(PORT!$C$2:$C$20,MATCH('06'!B62,PORT!$A$2:$A$20)) -> KTI AIR PORT | E62: E 26037 | F62: 46196 | G62: JIN YUAN XI | H62: GS26-257 | I62: DIS289 | J62: JYX2606012 | K62: 46203 | L62: =VLOOKUP(K62,'[6]Exchange Rate'!$A$3:$D$22,3,FALSE) -> 4026 | M62: =TEXT(K62,"dddd") -> Tuesday | N62: 167.28 | O62: 0 | P62: 0 | Q62: 50 | R62: 150 | S62: 47.28 | T62: =ROUND(R62*10%,2) -> 15 | U62: 180 | V62: =(R62+S62+U62)-(N62+O62+Q62+P62) -> 160
A63: PAID | B63: 1 | C63: =INDEX(PORT!$B$2:$B$20,MATCH('06'!B63,PORT!$A$2:$A$20)) -> PNH01 | D63: =INDEX(PORT!$C$2:$C$20,MATCH('06'!B63,PORT!$A$2:$A$20)) -> KTI AIR PORT | E63: I 18748 | F63: 46199 | G63: JIN YUAN XI | H63: GS26-258 | I63: DIS290 | J63: JYX2606013 | K63: 46203 | L63: =VLOOKUP(K63,'[6]Exchange Rate'!$A$3:$D$22,3,FALSE) -> 4026 | M63: =TEXT(K63,"dddd") -> Tuesday | N63: 244.19 | O63: 0 | P63: 0 | Q63: 50 | R63: 165 | S63: 74.19 | T63: =ROUND(R63*10%,2) -> 16.5 | U63: 175.75 | V63: =(R63+S63+U63)-(N63+O63+Q63+P63) -> 120.75
G64: JR | J64: JR2606013 | K64: 46203 | L64: =VLOOKUP(K64,'[6]Exchange Rate'!$A$3:$D$22,3,FALSE) -> 4026 | M64: =TEXT(K64,"dddd") -> Tuesday | N64: 0 | O64: 0 | P64: 920 | Q64: 0 | R64: 0 | S64: 0 | T64: =ROUND(R64*10%,2) -> 0 | U64: 1240 | V64: =(R64+S64+U64)-(N64+O64+Q64+P64) -> 320 | W64: INVENTORY FROM JAN TO JUN2026
G65: JR | J65: JR2606014 | K65: 46203 | L65: =VLOOKUP(K65,'[6]Exchange Rate'!$A$3:$D$22,3,FALSE) -> 4026 | M65: =TEXT(K65,"dddd") -> Tuesday | N65: 0 | O65: 0 | P65: 1492.75 | Q65: 0 | R65: 0 | S65: 0 | T65: =ROUND(R65*10%,2) -> 0 | U65: 1652.75 | V65: =(R65+S65+U65)-(N65+O65+Q65+P65) -> 160 | W65: PAID TO BRILLIANT LINE SERVICE
E66: LOLO
E67: STORAGE
E68: THC
B70: =SUBTOTAL(3,B3:B69) -> 59 | E70: TOTAL: | H70: =SUBTOTAL(3,H3:H69) -> 49 | I70: =SUBTOTAL(3,I3:I69) -> 61 | J70: =SUBTOTAL(3,J3:J69) -> 58 | N70: =SUM(N3:N68) -> 15208.84 | O70: =SUBTOTAL(9,O3:O65) -> 17167.15 | P70: =SUBTOTAL(9,P3:P65) -> 4167.75 | Q70: =SUBTOTAL(9,Q3:Q66) -> 2200 | R70: =SUBTOTAL(9,R3:R65) -> 8731.05 | S70: =SUBTOTAL(9,S3:S65) -> 19554.93 | T70: =SUBTOTAL(9,T3:T65) -> 873.1 | U70: =SUBTOTAL(9,U3:U65) -> 23982.1 | V70: =SUBTOTAL(9,V3:V68) -> 13524.34
M71: PAID | N71: =SUMIFS($N$3:$N$68,$A$3:$A$68,$M$71)-O72 -> 15208.84
M72: NOT YET | N72: =SUMIFS($N$3:$N$67,$A$3:$A$67,$M$72) -> 0
K80: PAID ON: 20-JUN-26 | M80: 6003.13
K81: PAID ON: 08-JUL-26 | M81: 6000 | N81: PAID FOR NEXT MONTH
K82: PAID ON: 17-JUL-27 | M82: 9205.71
K83: TOTAL: | M83: =SUM(M80:M82) -> 21208.84
K84: SHOULD PAY: | M84: =N70-M83 -> -6000

Sheet 07
E1: REVENUE & EXPENSE | M1: Saturday
A2: CHEA PAYMENT | B2: PORT NUMBER | C2: PORT CODE | D2: PORT NAME | E2: DECLARE | F2: DATE | G2: CLIENT | H2: INV | I2: DISBURSEMENT | J2: DN | K2: DATE | L2: EXCHANGE RATE | M2: weekday | N2: CLEAR FEE | O2: THC | P2: OTHER PAY | Q2: CM | R2: INV (REVENUE) | S2: REIM | T2: VAT 10% | U2: DN | V2: NET PROFIT | W2: MARK
A3: PAID | B3: 11 | C3: =INDEX(PORT!$B$2:$B$20,MATCH('07'!B3,PORT!$A$2:$A$20)) -> SHV11 | D3: =INDEX(PORT!$C$2:$C$20,MATCH('07'!B3,PORT!$A$2:$A$20)) -> SHV PORT | E3: I 95925 | F3: 46204 | G3: SPORTLINE | H3: GS26-259 | I3: DIS291 | J3: SAK2607001 | K3: 46205 | L3: =VLOOKUP(K3,'[7]Exchange Rate'!$A$3:$D$25,3,FALSE) -> 4030 | M3: =TEXT(K3,"dddd") -> Thursday | N3: 285.53 | O3: 0 | P3: 0 | Q3: 50 | R3: 150 | S3: 25.53 | T3: =ROUND(R3*10%,2) -> 15 | U3: 347.11 | V3: =(R3+S3+U3)-(N3+O3+Q3+P3) -> 187.11
A4: PAID | B4: 1 | C4: =INDEX(PORT!$B$2:$B$20,MATCH('07'!B4,PORT!$A$2:$A$20)) -> PNH01 | D4: =INDEX(PORT!$C$2:$C$20,MATCH('07'!B4,PORT!$A$2:$A$20)) -> KTI AIR PORT | E4: E 28011 | F4: 46205 | G4: JIN YUAN XI | H4: GS26-260 | I4: DIS292 | J4: JYX2607001 | K4: 46206 | L4: =VLOOKUP(K4,'[7]Exchange Rate'!$A$3:$D$25,3,FALSE) -> 4033 | M4: =TEXT(K4,"dddd") -> Friday | N4: 153.11 | O4: 0 | P4: 0 | Q4: 50 | R4: 140 | S4: 33.11 | T4: =ROUND(R4*10%,2) -> 14 | U4: 180 | V4: =(R4+S4+U4)-(N4+O4+Q4+P4) -> 150
A5: PAID | B5: 1 | C5: =INDEX(PORT!$B$2:$B$20,MATCH('07'!B5,PORT!$A$2:$A$20)) -> PNH01 | D5: =INDEX(PORT!$C$2:$C$20,MATCH('07'!B5,PORT!$A$2:$A$20)) -> KTI AIR PORT | E5: E 28017 | F5: 46205 | G5: JIN YUAN XI | H5: GS26-261 | I5: DIS293 | J5: JYX2607002 | K5: 46206 | L5: =VLOOKUP(K5,'[7]Exchange Rate'!$A$3:$D$25,3,FALSE) -> 4033 | M5: =TEXT(K5,"dddd") -> Friday | N5: 155.13 | O5: 0 | P5: 0 | Q5: 50 | R5: 150 | S5: 35.13 | T5: =ROUND(R5*10%,2) -> 15 | U5: 180 | V5: =(R5+S5+U5)-(N5+O5+Q5+P5) -> 160
A6: PAID | B6: 1 | C6: =INDEX(PORT!$B$2:$B$20,MATCH('07'!B6,PORT!$A$2:$A$20)) -> PNH01 | D6: =INDEX(PORT!$C$2:$C$20,MATCH('07'!B6,PORT!$A$2:$A$20)) -> KTI AIR PORT | E6: E 27975 | F6: 46205 | G6: SPORTLINE | H6: GS26-262 | I6: DIS294 | J6: SAK2607002 | K6: 46206 | L6: =VLOOKUP(K6,'[7]Exchange Rate'!$A$3:$D$25,3,FALSE) -> 4033 | M6: =TEXT(K6,"dddd") -> Friday | N6: 114.55 | O6: 0 | P6: 0 | Q6: 50 | R6: 150 | S6: 44.55 | T6: =ROUND(R6*10%,2) -> 15 | U6: 60 | V6: =(R6+S6+U6)-(N6+O6+Q6+P6) -> 90
A7: PAID | B7: 11 | C7: =INDEX(PORT!$B$2:$B$20,MATCH('07'!B7,PORT!$A$2:$A$20)) -> SHV11 | D7: =INDEX(PORT!$C$2:$C$20,MATCH('07'!B7,PORT!$A$2:$A$20)) -> SHV PORT | E7: I 96700 | F7: 46205 | G7: SPORTLINE | H7: GS26-263 | I7: DIS295 | J7: SAK2607003 | K7: 46206 | L7: =VLOOKUP(K7,'[7]Exchange Rate'!$A$3:$D$25,3,FALSE) -> 4033 | M7: =TEXT(K7,"dddd") -> Friday | N7: 181.12 | O7: 0 | P7: 0 | Q7: 50 | R7: 150 | S7: 17.12 | T7: =ROUND(R7*10%,2) -> 15 | U7: 158 | V7: =(R7+S7+U7)-(N7+O7+Q7+P7) -> 94
A8: PAID | B8: 11 | C8: =INDEX(PORT!$B$2:$B$20,MATCH('07'!B8,PORT!$A$2:$A$20)) -> SHV11 | D8: =INDEX(PORT!$C$2:$C$20,MATCH('07'!B8,PORT!$A$2:$A$20)) -> SHV PORT | E8: I 96707 | F8: 46205 | G8: JR | H8: GS26-264 | I8: DIS296 | J8: JR2607001 | K8: 46206 | L8: =VLOOKUP(K8,'[7]Exchange Rate'!$A$3:$D$25,3,FALSE) -> 4033 | M8: =TEXT(K8,"dddd") -> Friday | N8: 631.95 | O8: 691.5 | P8: 0 | Q8: 0 | R8: 200 | S8: 805.95 | T8: =ROUND(R8*10%,2) -> 20 | U8: 921.5 | V8: =(R8+S8+U8)-(N8+O8+Q8+P8) -> 604
A9: PAID | B9: 1 | C9: =INDEX(PORT!$B$2:$B$20,MATCH('07'!B9,PORT!$A$2:$A$20)) -> PNH01 | D9: =INDEX(PORT!$C$2:$C$20,MATCH('07'!B9,PORT!$A$2:$A$20)) -> KTI AIR PORT | E9: E 27979 | F9: 46205 | G9: VFL | H9: GS26-265 | I9: DIS297 | J9: VFL2607001 | K9: 46206 | L9: =VLOOKUP(K9,'[7]Exchange Rate'!$A$3:$D$25,3,FALSE) -> 4033 | M9: =TEXT(K9,"dddd") -> Friday | N9: 88.77 | O9: 0 | P9: 0 | Q9: 50 | R9: 140 | S9: 18.77 | T9: =ROUND(R9*10%,2) -> 14 | U9: 60 | V9: =(R9+S9+U9)-(N9+O9+Q9+P9) -> 80
A10: PAID | B10: 1 | C10: =INDEX(PORT!$B$2:$B$20,MATCH('07'!B10,PORT!$A$2:$A$20)) -> PNH01 | D10: =INDEX(PORT!$C$2:$C$20,MATCH('07'!B10,PORT!$A$2:$A$20)) -> KTI AIR PORT | E10: E 27991 | F10: 46205 | G10: VFL | H10: GS26-266 | I10: DIS298 | J10: VFL2607002 | K10: 46206 | L10: =VLOOKUP(K10,'[7]Exchange Rate'!$A$3:$D$25,3,FALSE) -> 4033 | M10: =TEXT(K10,"dddd") -> Friday | N10: 101.09 | O10: 0 | P10: 0 | Q10: 50 | R10: 140 | S10: 31.09 | T10: =ROUND(R10*10%,2) -> 14 | U10: 60 | V10: =(R10+S10+U10)-(N10+O10+Q10+P10) -> 80
A11: PAID | B11: 1 | C11: =INDEX(PORT!$B$2:$B$20,MATCH('07'!B11,PORT!$A$2:$A$20)) -> PNH01 | D11: =INDEX(PORT!$C$2:$C$20,MATCH('07'!B11,PORT!$A$2:$A$20)) -> KTI AIR PORT | E11: E 27998 | F11: 46205 | G11: VFL | H11: GS26-267 | I11: DIS299 | J11: VFL2607003 | K11: 46206 | L11: =VLOOKUP(K11,'[7]Exchange Rate'!$A$3:$D$25,3,FALSE) -> 4033 | M11: =TEXT(K11,"dddd") -> Friday | N11: 87.09 | O11: 0 | P11: 0 | Q11: 50 | R11: 140 | S11: 17.09 | T11: =ROUND(R11*10%,2) -> 14 | U11: 160 | V11: =(R11+S11+U11)-(N11+O11+Q11+P11) -> 180
A12: PAID | B12: 1 | C12: =INDEX(PORT!$B$2:$B$20,MATCH('07'!B12,PORT!$A$2:$A$20)) -> PNH01 | D12: =INDEX(PORT!$C$2:$C$20,MATCH('07'!B12,PORT!$A$2:$A$20)) -> KTI AIR PORT | E12: I 19496 | F12: 46206 | G12: JIN YUAN XI | H12: GS26-268 | I12: DIS300 | J12: JYX2607003 | K12: 46209 | L12: =VLOOKUP(K12,'[7]Exchange Rate'!$A$3:$D$25,3,FALSE) -> 4034 | M12: =TEXT(K12,"dddd") -> Monday | N12: 291.64 | O12: 0 | P12: 0 | Q12: 50 | R12: 185 | S12: 126.64 | T12: =ROUND(R12*10%,2) -> 18.5 | U12: 175.75 | V12: =(R12+S12+U12)-(N12+O12+Q12+P12) -> 145.75
A13: PAID | B13: 1 | C13: =INDEX(PORT!$B$2:$B$20,MATCH('07'!B13,PORT!$A$2:$A$20)) -> PNH01 | D13: =INDEX(PORT!$C$2:$C$20,MATCH('07'!B13,PORT!$A$2:$A$20)) -> KTI AIR PORT | E13: E 28287 | F13: 46206 | G13: SPORTLINE | H13: GS26-269 | I13: DIS301 | J13: SAK2607004 | K13: 46209 | L13: =VLOOKUP(K13,'[7]Exchange Rate'!$A$3:$D$25,3,FALSE) -> 4034 | M13: =TEXT(K13,"dddd") -> Monday | N13: 106.19 | O13: 0 | P13: 0 | Q13: 50 | R13: 150 | S13: 36.19 | T13: =ROUND(R13*10%,2) -> 15 | U13: 60 | V13: =(R13+S13+U13)-(N13+O13+Q13+P13) -> 90
A14: PAID | B14: 4 | C14: =INDEX(PORT!$B$2:$B$20,MATCH('07'!B14,PORT!$A$2:$A$20)) -> PNH04 | D14: =INDEX(PORT!$C$2:$C$20,MATCH('07'!B14,PORT!$A$2:$A$20)) -> PNH PORT | E14: E 191506 | F14: 46206 | G14: SPORTLINE | H14: GS26-270 | I14: DIS302 | J14: SAK2607005 | K14: 46209 | L14: =VLOOKUP(K14,'[7]Exchange Rate'!$A$3:$D$25,3,FALSE) -> 4034 | M14: =TEXT(K14,"dddd") -> Monday | N14: 453.25 | O14: 0 | P14: 0 | Q14: 50 | R14: 245 | S14: 143.25 | T14: =ROUND(R14*10%,2) -> 24.5 | U14: 504 | V14: =(R14+S14+U14)-(N14+O14+Q14+P14) -> 389
... A24: PAID | B24: 21 | C24: =INDEX(PORT!$B$2:$B$20,MATCH('07'!B24,PORT!$A$2:$A$20)) -> PNH21 | D24: =INDEX(PORT!$C$2:$C$20,MATCH('07'!B24,PORT!$A$2:$A$20)) -> OLAIR DRY PORT | E24: I 1767 | F24: 46211 | G24: SPORTLINE | H24: GS26-280 | I24: DIS312 | J24: SAK2607008 | K24: 46212 | L24: =VLOOKUP(K24,'[7]Exchange Rate'!$A$3:$D$25,3,FALSE) -> 4036 | M24: =TEXT(K24,"dddd") -> Thursday | N24: 130 | O24: 176 | P24: 0 | Q24: 50 | R24: 150 | S24: 201 | T24: =ROUND(R24*10%,2) -> 15 | U24: 159 | V24: =(R24+S24+U24)-(N24+O24+Q24+P24) -> 154
A25: PAID | B25: 11 | C25: =INDEX(PORT!$B$2:$B$20,MATCH('07'!B25,PORT!$A$2:$A$20)) -> SHV11 | D25: =INDEX(PORT!$C$2:$C$20,MATCH('07'!B25,PORT!$A$2:$A$20)) -> SHV PORT | E25: I 99578 | F25: 46211 | G25: JIN YUAN XI | H25: GS26-281 | I25: DIS313 | J25: JYX2607006 | K25: 46212 | L25: =VLOOKUP(K25,'[7]Exchange Rate'!$A$3:$D$25,3,FALSE) -> 4036 | M25: =TEXT(K25,"dddd") -> Thursday | N25: 453.75 | O25: 281 | P25: 0 | Q25: 50 | R25: 170 | S25: 339.59 | T25: =ROUND(R25*10%,2) -> 17 | U25: 576 | V25: =(R25+S25+U25)-(N25+O25+Q25+P25) -> 300.84 | W25: AOTAI Clear
A26: PAID | B26: 1 | C26: =INDEX(PORT!$B$2:$B$20,MATCH('07'!B26,PORT!$A$2:$A$20)) -> PNH01 | D26: =INDEX(PORT!$C$2:$C$20,MATCH('07'!B26,PORT!$A$2:$A$20)) -> KTI AIR PORT | E26: I 20128 | F26: 46212 | G26: VFL | H26: GS26-282 | I26: DIS314 | J26: VFL2607009 | K26: 46213 | L26: =VLOOKUP(K26,'[7]Exchange Rate'!$A$3:$D$25,3,FALSE) -> 4036 | M26: =TEXT(K26,"dddd") -> Friday | N26: 152.8 | O26: 60.5 | P26: 0 | Q26: 50 | R26: 150 | S26: 83.3 | T26: =ROUND(R26*10%,2) -> 15 | U26: 130.75 | V26: =(R26+S26+U26)-(N26+O26+Q26+P26) -> 100.75
A27: PAID | B27: 1 | C27: =INDEX(PORT!$B$2:$B$20,MATCH('07'!B27,PORT!$A$2:$A$20)) -> PNH01 | D27: =INDEX(PORT!$C$2:$C$20,MATCH('07'!B27,PORT!$A$2:$A$20)) -> KTI AIR PORT | E27: E 29708 | F27: 46212 | G27: JIN YUAN XI | H27: GS26-283 | I27: DIS315 | J27: JYX2607007 | K27: 46213 | L27: =VLOOKUP(K27,'[7]Exchange Rate'!$A$3:$D$25,3,FALSE) -> 4036 | M27: =TEXT(K27,"dddd") -> Friday | N27: 103.99 | O27: 0 | P27: 0 | Q27: 50 | R27: 140 | S27: 33.99 | T27: =ROUND(R27*10%,2) -> 14 | U27: 180 | V27: =(R27+S27+U27)-(N27+O27+Q27+P27) -> 200
A28: PAID | B28: 11 | C28: =INDEX(PORT!$B$2:$B$20,MATCH('07'!B28,PORT!$A$2:$A$20)) -> SHV11 | D28: =INDEX(PORT!$C$2:$C$20,MATCH('07'!B28,PORT!$A$2:$A$20)) -> SHV PORT | E28: E 200982 | F28: 46213 | G28: JIN YUAN XI | H28: GS26-284 | I28: DIS316 | J28: JYX2607008 | K28: 46216 | L28: =VLOOKUP(K28,'[7]Exchange Rate'!$A$3:$D$25,3,FALSE) -> 4037 | M28: =TEXT(K28,"dddd") -> Monday | N28: 767.44 | O28: 0 | P28: 0 | Q28: 50 | R28: 245 | S28: 117.44 | T28: =ROUND(R28*10%,2) -> 24.5 | U28: 1007 | V28: =(R28+S28+U28)-(N28+O28+Q28+P28) -> 552
A29: PAID | B29: 1 | C29: =INDEX(PORT!$B$2:$B$20,MATCH('07'!B29,PORT!$A$2:$A$20)) -> PNH01 | D29: =INDEX(PORT!$C$2:$C$20,MATCH('07'!B29,PORT!$A$2:$A$20)) -> KTI AIR PORT | E29: E 30246 | F29: 46214 | G29: JIN YUAN XI | H29: GS26-285 | I29: DIS317 | J29: JYX2607009 | K29: 46216 | L29: =VLOOKUP(K29,'[7]Exchange Rate'!$A$3:$D$25,3,FALSE) -> 4037 | M29: =TEXT(K29,"dddd") -> Monday | N29: 114.55 | O29: 0 | P29: 0 | Q29: 50 | R29: 150 | S29: 44.55 | T29: =ROUND(R29*10%,2) -> 15 | U29: 180 | V29: =(R29+S29+U29)-(N29+O29+Q29+P29) -> 210
A30: PAID | B30: 1 | C30: =INDEX(PORT!$B$2:$B$20,MATCH('07'!B30,PORT!$A$2:$A$20)) -> PNH01 | D30: =INDEX(PORT!$C$2:$C$20,MATCH('07'!B30,PORT!$A$2:$A$20)) -> KTI AIR PORT | E30: I 20586 | F30: 46217 | G30: VFL | H30: GS26-286 | I30: DIS318 | J30: VFL2607010 | K30: 46218 | L30: =VLOOKUP(K30,'[7]Exchange Rate'!$A$3:$D$25,3,FALSE) -> 4037 | M30: =TEXT(K30,"dddd") -> Wednesday | N30: 152.89 | O30: 60.5 | P30: 0 | Q30: 50 | R30: 150 | S30: 83.39 | T30: =ROUND(R30*10%,2) -> 15 | U30: 130.75 | V30: =(R30+S30+U30)-(N30+O30+Q30+P30) -> 100.75
A31: PAID | B31: 11+ | C31: =INDEX(PORT!$B$2:$B$20,MATCH('07'!B31,PORT!$A$2:$A$20)) -> SVR11 | D31: =INDEX(PORT!$C$2:$C$20,MATCH('07'!B31,PORT!$A$2:$A$20)) -> BAVET CEO | E31: E 202564 | F31: 46217 | G31: JR | H31: GS26-287 | I31: DIS319 | J31: JR2607002 | K31: 46218 | L31: =VLOOKUP(K31,'[7]Exchange Rate'!$A$3:$D$25,3,FALSE) -> 4037 | M31: =TEXT(K31,"dddd") -> Wednesday | N31: 611.25 | O31: 1299.5 | P31: 0 | Q31: 0 | R31: 213 | S31: 1320.75 | T31: =ROUND(R31*10%,2) -> 21.3 | U31: 950.5 | V31: =(R31+S31+U31)-(N31+O31+Q31+P31) -> 573.5
A32: PAID | B32: 11 | C32: =INDEX(PORT!$B$2:$B$20,MATCH('07'!B32,PORT!$A$2:$A$20)) -> SHV11 | D32: =INDEX(PORT!$C$2:$C$20,MATCH('07'!B32,PORT!$A$2:$A$20)) -> SHV PORT | E32: I 102722 | F32: 46217 | G32: JIN YUAN XI | H32: GS26-288 | I32: DIS320 | J32: JYX2607010 | K32: 46218 | L32: =VLOOKUP(K32,'[7]Exchange Rate'!$A$3:$D$25,3,FALSE) -> 4037 | M32: =TEXT(K32,"dddd") -> Wednesday | N32: 158.75 | O32: 401 | P32: 0 | Q32: 50 | R32: 150 | S32: 414.75 | T32: =ROUND(R32*10%,2) -> 15 | U32: 100 | V32: =(R32+S32+U32)-(N32+O32+Q32+P32) -> 55
A33: PAID | B33: 19 | C33: =INDEX(PORT!$B$2:$B$20,MATCH('07'!B33,PORT!$A$2:$A$20)) -> PNH19 | D33: =INDEX(PORT!$C$2:$C$20,MATCH('07'!B33,PORT!$A$2:$A$20)) -> TEC SRUN DRYPORT | E33: I 2482 | F33: 46218 | G33: VFL | H33: GS26-289 | I33: DIS321 | J33: VFL2607011 | K33: 46219 | L33: =VLOOKUP(K33,'[7]Exchange Rate'!$A$3:$D$25,3,FALSE) -> 4037 | M33: =TEXT(K33,"dddd") -> Thursday | N33: 111.1 | O33: 193.6 | P33: 0 | Q33: 50 | R33: 150 | S33: 219.7 | T33: =ROUND(R33*10%,2) -> 15 | U33: 109.5 | V33: =(R33+S33+U33)-(N33+O33+Q33+P33) -> 124.5
A34: PAID | B34: 19 | C34: =INDEX(PORT!$B$2:$B$20,MATCH('07'!B34,PORT!$A$2:$A$20)) -> PNH19 | D34: =INDEX(PORT!$C$2:$C$20,MATCH('07'!B34,PORT!$A$2:$A$20)) -> TEC SRUN DRYPORT | E34: I 2483 | F34: 46218 | G34: SPORTLINE | H34: GS26-290 | I34: DIS322 | J34: SAK2607009 | K34: 46219 | L34: =VLOOKUP(K34,'[7]Exchange Rate'!$A$3:$D$25,3,FALSE) -> 4037 | M34: =TEXT(K34,"dddd") -> Thursday | N34: 131.1 | O34: 193.6 | P34: 0 | Q34: 50 | R34: 150 | S34: 219.7 | T34: =ROUND(R34*10%,2) -> 15 | U34: 159 | V34: =(R34+S34+U34)-(N34+O34+Q34+P34) -> 154
A35: PAID | B35: 1 | C35: =INDEX(PORT!$B$2:$B$20,MATCH('07'!B35,PORT!$A$2:$A$20)) -> PNH01 | D35: =INDEX(PORT!$C$2:$C$20,MATCH('07'!B35,PORT!$A$2:$A$20)) -> KTI AIR PORT | E35: E 30999 | F35: 46218 | G35: JIN YUAN XI | H35: GS26-291 | I35: DIS323 | J35: JYX2607011 | K35: 46219 | L35: =VLOOKUP(K35,'[7]Exchange Rate'!$A$3:$D$25,3,FALSE) -> 4037 | M35: =TEXT(K35,"dddd") -> Thursday | N35: 105.75 | O35: 0 | P35: 0 | Q35: 50 | R35: 140 | S35: 35.75 | T35: =ROUND(R35*10%,2) -> 14 | U35: 60 | V35: =(R35+S35+U35)-(N35+O35+Q35+P35) -> 80
A36: PAID | B36: 11 | C36: =INDEX(PORT!$B$2:$B$20,MATCH('07'!B36,PORT!$A$2:$A$20)) -> SHV11 | D36: =INDEX(PORT!$C$2:$C$20,MATCH('07'!B36,PORT!$A$2:$A$20)) -> SHV PORT | E36: I 104042 | F36: 46219 | G36: SPORTLINE | H36: GS26-292 | I36: DIS324 | J36: SAK2607010 | K36: 46220 | L36: =VLOOKUP(K36,'[7]Exchange Rate'!$A$3:$D$25,3,FALSE) -> 4037 | M36: =TEXT(K36,"dddd") -> Friday | N36: 194.8 | O36: 248.29 | P36: 0 | Q36: 50 | R36: 150 | S36: 267.09 | T36: =ROUND(R36*10%,2) -> 15 | U36: 180.97 | V36: =(R36+S36+U36)-(N36+O36+Q36+P36) -> 104.97
A37: PAID | B37: 11 | C37: =INDEX(PORT!$B$2:$B$20,MATCH('07'!B37,PORT!$A$2:$A$20)) -> SHV11 | D37: =INDEX(PORT!$C$2:$C$20,MATCH('07'!B37,PORT!$A$2:$A$20)) -> SHV PORT | E37: I 104056 | F37: 46219 | G37: VFL | H37: GS26-293 | I37: DIS325 | J37: VFL2607012 | K37: 46220 | L37: =VLOOKUP(K37,'[7]Exchange Rate'!$A$3:$D$25,3,FALSE) -> 4037 | M37: =TEXT(K37,"dddd") -> Friday | N37: 214.48 | O37: 358.4 | P37: 0 | Q37: 50 | R37: 150 | S37: 378.88 | T37: =ROUND(R37*10%,2) -> 15 | U37: 209.07 | V37: =(R37+S37+U37)-(N37+O37+Q37+P37) -> 115.07
A38: PAID | B38: 1 | C38: =INDEX(PORT!$B$2:$B$20,MATCH('07'!B38,PORT!$A$2:$A$20)) -> PNH01 | D38: =INDEX(PORT!$C$2:$C$20,MATCH('07'!B38,PORT!$A$2:$A$20)) -> KTI AIR PORT | E38: E 31674 | F38: 46220 | G38: SPORTLINE | H38: GS26-294 | I38: DIS326 | J38: SAK2607011 | K38: 46223 | L38: =VLOOKUP(K38,'[7]Exchange Rate'!$A$3:$D$25,3,FALSE) -> 4036 | M38: =TEXT(K38,"dddd") -> Monday | N38: 85.95 | O38: 0 | P38: 0 | Q38: 50 | R38: 140 | S38: 4.2 | T38: =ROUND(R38*10%,2) -> 14 | U38: 71.75 | V38: =(R38+S38+U38)-(N38+O38+Q38+P38) -> 80
A39: PAID | B39: 1 | C39: =INDEX(PORT!$B$2:$B$20,MATCH('07'!B39,PORT!$A$2:$A$20)) -> PNH01 | D39: =INDEX(PORT!$C$2:$C$20,MATCH('07'!B39,PORT!$A$2:$A$20)) -> KTI AIR PORT | E39: E 31681 | F39: 46220 | G39: JIN YUAN XI | H39: GS26-295 | I39: DIS327 | J39: JYX2607012 | K39: 46223 | L39: =VLOOKUP(K39,'[7]Exchange Rate'!$A$3:$D$25,3,FALSE) -> 4036 | M39: =TEXT(K39,"dddd") -> Monday | N39: 411.48 | O39: 0 | P39: 0 | Q39: 50 | R39: 220 | S39: 291.48 | T39: =ROUND(R39*10%,2) -> 22 | U39: 180 | V39: =(R39+S39+U39)-(N39+O39+Q39+P39) -> 230
A40: PAID | B40: 4 | C40: =INDEX(PORT!$B$2:$B$20,MATCH('07'!B40,PORT!$A$2:$A$20)) -> PNH04 | D40: =INDEX(PORT!$C$2:$C$20,MATCH('07'!B40,PORT!$A$2:$A$20)) -> PNH PORT | E40: E 209077 | F40: 46220 | G40: VFL | H40: GS26-296 | I40: DIS328 | J40: VFL2607013 | K40: 46223 | L40: =VLOOKUP(K40,'[7]Exchange Rate'!$A$3:$D$25,3,FALSE) -> 4036 | M40: =TEXT(K40,"dddd") -> Monday | N40: 416.25 | O40: 0 | P40: 0 | Q40: 50 | R40: 245 | S40: 151.25 | T40: =ROUND(R40*10%,2) -> 24.5 | U40: 411.5 | V40: =(R40+S40+U40)-(N40+O40+Q40+P40) -> 341.5
A41: PAID | B41: 1 | C41: =INDEX(PORT!$B$2:$B$20,MATCH('07'!B41,PORT!$A$2:$A$20)) -> PNH01 | D41: =INDEX(PORT!$C$2:$C$20,MATCH('07'!B41,PORT!$A$2:$A$20)) -> KTI AIR PORT | E41: E 31867 | F41: 46221 | G41: JIN YUAN XI | H41: GS26-297 | I41: DIS329 | J41: JYX2607013 | K41: 46223 | L41: =VLOOKUP(K41,'[7]Exchange Rate'!$A$3:$D$25,3,FALSE) -> 4036 | M41: =TEXT(K41,"dddd") -> Monday | N41: 304.65 | O41: 0 | P41: 0 | Q41: 50 | R41: 220 | S41: 184.65 | T41: =ROUND(R41*10%,2) -> 22 | U41: 180 | V41: =(R41+S41+U41)-(N41+O41+Q41+P41) -> 230
A42: PAID | B42: 1 | C42: =INDEX(PORT!$B$2:$B$20,MATCH('07'!B42,PORT!$A$2:$A$20)) -> PNH01 | D42: =INDEX(PORT!$C$2:$C$20,MATCH('07'!B42,PORT!$A$2:$A$20)) -> KTI AIR PORT | E42: E 31871 | F42: 46221 | G42: JIN YUAN XI | H42: GS26-298 | I42: DIS330 | J42: JYX2607014 | K42: 46223 | L42: =VLOOKUP(K42,'[7]Exchange Rate'!$A$3:$D$25,3,FALSE) -> 4036 | M42: =TEXT(K42,"dddd") -> Monday | N42: 265.49 | O42: 0 | P42: 0 | Q42: 50 | R42: 210 | S42: 145.49 | T42: =ROUND(R42*10%,2) -> 21 | U42: 180 | V42: =(R42+S42+U42)-(N42+O42+Q42+P42) -> 220
A43: PAID | B43: 1 | C43: =INDEX(PORT!$B$2:$B$20,MATCH('07'!B43,PORT!$A$2:$A$20)) -> PNH01 | D43: =INDEX(PORT!$C$2:$C$20,MATCH('07'!B43,PORT!$A$2:$A$20)) -> KTI AIR PORT | E43: I 21349 | F43: 46223 | G43: VFL | H43: GS26-299 | I43: DIS331 | J43: VFL2607014 | K43: 46224 | L43: =VLOOKUP(K43,'[7]Exchange Rate'!$A$3:$D$25,3,FALSE) -> 4040 | M43: =TEXT(K43,"dddd") -> Tuesday | N43: 152.62 | O43: 71.5 | P43: 0 | Q43: 50 | R43: 150 | S43: 94.12 | T43: =ROUND(R43*10%,2) -> 15 | U43: 130.75 | V43: =(R43+S43+U43)-(N43+O43+Q43+P43) -> 100.75
... A69: PAID | B69: 1 | C69: =INDEX(PORT!$B$2:$B$20,MATCH('07'!B69,PORT!$A$2:$A$20)) -> PNH01 | D69: =INDEX(PORT!$C$2:$C$20,MATCH('07'!B69,PORT!$A$2:$A$20)) -> KTI AIR PORT | E69: E 35115 | F69: 46234 | G69: VFL | H69: GS26-325 | I69: DIS357 | J69: VFL2607019 | K69: 46234 | L69: =VLOOKUP(K69,'[7]Exchange Rate'!$A$3:$D$25,3,FALSE) -> 4043 | M69: =TEXT(K69,"dddd") -> Friday | N69: 85.95 | O69: 0 | P69: 0 | Q69: 50 | R69: 140 | S69: 15.95 | T69: =ROUND(R69*10%,2) -> 14 | U69: 60 | V69: =(R69+S69+U69)-(N69+O69+Q69+P69) -> 80
A70: PAID | B70: 11 | C70: =INDEX(PORT!$B$2:$B$20,MATCH('07'!B70,PORT!$A$2:$A$20)) -> SHV11 | D70: =INDEX(PORT!$C$2:$C$20,MATCH('07'!B70,PORT!$A$2:$A$20)) -> SHV PORT | E70: I 111738 | G70: VFL | I70: DIS358 | K70: 46234 | L70: =VLOOKUP(K70,'[7]Exchange Rate'!$A$3:$D$25,3,FALSE) -> 4043 | M70: =TEXT(K70,"dddd") -> Friday | N70: 0 | O70: 654.29 | P70: 0 | Q70: 0 | R70: 0 | S70: 654.29 | T70: =ROUND(R70*10%,2) -> 0 | U70: 0 | V70: =(R70+S70+U70)-(N70+O70+Q70+P70) -> 0
A71: PAID | B71: 1 | C71: =INDEX(PORT!$B$2:$B$20,MATCH('07'!B71,PORT!$A$2:$A$20)) -> PNH01 | D71: =INDEX(PORT!$C$2:$C$20,MATCH('07'!B71,PORT!$A$2:$A$20)) -> KTI AIR PORT | G71: SPORTLINE | I71: DIS359 | K71: 46234 | L71: =VLOOKUP(K71,'[7]Exchange Rate'!$A$3:$D$25,3,FALSE) -> 4043 | M71: =TEXT(K71,"dddd") -> Friday | N71: 0 | O71: 60.5 | P71: 0 | Q71: 0 | R71: 0 | S71: 60.5 | T71: =ROUND(R71*10%,2) -> 0 | U71: 0 | V71: =(R71+S71+U71)-(N71+O71+Q71+P71) -> 0
A72: PAID | B72: 4 | C72: =INDEX(PORT!$B$2:$B$20,MATCH('07'!B72,PORT!$A$2:$A$20)) -> PNH04 | D72: =INDEX(PORT!$C$2:$C$20,MATCH('07'!B72,PORT!$A$2:$A$20)) -> PNH PORT | E72: E 189000 | F72: 46206 | G72: JR | I72: DIS360 | J72: JR2607006 | K72: 46234 | L72: =VLOOKUP(K72,'[7]Exchange Rate'!$A$3:$D$25,3,FALSE) -> 4043 | M72: =TEXT(K72,"dddd") -> Friday | N72: 0 | O72: 916.8 | P72: 0 | Q72: 0 | R72: 0 | S72: 916.8 | T72: =ROUND(R72*10%,2) -> 0 | U72: 174 | V72: =(R72+S72+U72)-(N72+O72+Q72+P72) -> 174 | W72: TIDM260564/565
A73: PAID | B73: 4 | C73: =INDEX(PORT!$B$2:$B$20,MATCH('07'!B73,PORT!$A$2:$A$20)) -> PNH04 | D73: =INDEX(PORT!$C$2:$C$20,MATCH('07'!B73,PORT!$A$2:$A$20)) -> PNH PORT | E73: E 195384 | F73: 46212 | G73: JR | I73: DIS361 | J73: JR2607007 | K73: 46234 | L73: =VLOOKUP(K73,'[7]Exchange Rate'!$A$3:$D$25,3,FALSE) -> 4043 | M73: =TEXT(K73,"dddd") -> Friday | N73: 0 | O73: 701.84 | P73: 0 | Q73: 0 | R73: 0 | S73: 701.84 | T73: =ROUND(R73*10%,2) -> 0 | U73: 174 | V73: =(R73+S73+U73)-(N73+O73+Q73+P73) -> 174 | W73: CGL26-01448&RM26-00743
A74: PAID | B74: 4 | C74: =INDEX(PORT!$B$2:$B$20,MATCH('07'!B74,PORT!$A$2:$A$20)) -> PNH04 | D74: =INDEX(PORT!$C$2:$C$20,MATCH('07'!B74,PORT!$A$2:$A$20)) -> PNH PORT | E74: E 208779 | F74: 46220 | G74: JR | I74: DIS362 | J74: JR2607008 | K74: 46234 | L74: =VLOOKUP(K74,'[7]Exchange Rate'!$A$3:$D$25,3,FALSE) -> 4043 | M74: =TEXT(K74,"dddd") -> Friday | N74: 0 | O74: 1059.92 | P74: 0 | Q74: 0 | R74: 0 | S74: 1059.92 | T74: =ROUND(R74*10%,2) -> 0 | U74: 141.5 | V74: =(R74+S74+U74)-(N74+O74+Q74+P74) -> 141.5 | W74: CGL26-01529-1530&RM26-00786
A75: PAID | B75: 4 | C75: =INDEX(PORT!$B$2:$B$20,MATCH('07'!B75,PORT!$A$2:$A$20)) -> PNH04 | D75: =INDEX(PORT!$C$2:$C$20,MATCH('07'!B75,PORT!$A$2:$A$20)) -> PNH PORT | E75: E 214571 | F75: 46227 | G75: JR | I75: DIS363 | J75: JR2607009 | K75: 46234 | L75: =VLOOKUP(K75,'[7]Exchange Rate'!$A$3:$D$25,3,FALSE) -> 4043 | M75: =TEXT(K75,"dddd") -> Friday | N75: 0 | O75: 518.94 | P75: 0 | Q75: 0 | R75: 0 | S75: 518.94 | T75: =ROUND(R75*10%,2) -> 0 | U75: 141.5 | V75: =(R75+S75+U75)-(N75+O75+Q75+P75) -> 141.5 | W75: CGL26-01574&RM26-00802
A76: PAID | B76: 4 | C76: =INDEX(PORT!$B$2:$B$20,MATCH('07'!B76,PORT!$A$2:$A$20)) -> PNH04 | D76: =INDEX(PORT!$C$2:$C$20,MATCH('07'!B76,PORT!$A$2:$A$20)) -> PNH PORT | E76: E 225809 | G76: JR | I76: DIS364 | J76: JR2607010 | K76: 46234 | L76: =VLOOKUP(K76,'[7]Exchange Rate'!$A$3:$D$25,3,FALSE) -> 4043 | M76: =TEXT(K76,"dddd") -> Friday | N76: 0 | O76: 1213.72 | P76: 0 | Q76: 0 | R76: 0 | S76: 1213.72 | T76: =ROUND(R76*10%,2) -> 0 | U76: 160 | V76: =(R76+S76+U76)-(N76+O76+Q76+P76) -> 160
E77: LOLO
E78: STORAGE
A79: PAID | E79: PERMIT FE | N79: 35 | W79: Lack charge in ship I95352, but charge to factory done
B81: =SUBTOTAL(3,B3:B80) -> 74 | E81: TOTAL: | H81: =SUBTOTAL(3,H3:H80) -> 67 | I81: =SUBTOTAL(3,I3:I80) -> 74 | J81: =SUBTOTAL(3,J3:J80) -> 72 | N81: =SUM(N3:N80) -> 18011.03 | O81: =SUBTOTAL(9,O3:O76) -> 14290.73 | P81: =SUBTOTAL(9,P3:P76) -> 0 | Q81: =SUBTOTAL(9,Q3:Q77) -> 3100 | R81: =SUBTOTAL(9,R3:R76) -> 11678 | S81: =SUBTOTAL(9,S3:S76) -> 18644.08 | T81: =SUBTOTAL(9,T3:T76) -> 1167.8 | U81: =SUBTOTAL(9,U3:U76) -> 20358.76 | V81: =SUBTOTAL(9,V3:V79) -> 15314.08
M82: PAID | N82: =SUMIFS($N$3:$N$79,$A$3:$A$79,$M$82)-O83 -> 18011.03
M83: NOT YET | N83: =SUMIFS($N$3:$N$79,$A$3:$A$79,$M$83) -> 0
K86: PAID ON: 08-JUL-26 | M86: 6000 | R86: =SUM(R81+T81) -> 12845.8
K87: PAID ON: 24-JUL-27 | M87: 6000
K88: PAID ON: 10-AUG-28 | M88: 6011.03
K89: TOTAL: | M89: =SUM(M86:M88) -> 18011.03

Sheet 08
E1: REVENUE & EXPENSE | M1: Saturday
A2: CHEA PAYMENT | B2: PORT NUMBER | C2: PORT CODE | D2: PORT NAME | E2: DECLARE/ INV F.W NO | F2: DATE | G2: CLIENT | H2: INV | I2: DISBURSEMENT | J2: DN | K2: DATE | L2: EXCHANGE RATE | M2: weekday | N2: CLEAR FEE | O2: THC | P2: OTHER PAY | Q2: CM | R2: INV (REVENUE) | S2: REIM | T2: VAT 10% | U2: DN | V2: NET PROFIT | W2: MARK
A3: PAID | B3: 11 | C3: =INDEX(PORT!$B$2:$B$20,MATCH('08'!B3,PORT!$A$2:$A$20)) -> SHV11 | D3: =INDEX(PORT!$C$2:$C$20,MATCH('08'!B3,PORT!$A$2:$A$20)) -> SHV PORT | E3: I 111738 | F3: 46235 | G3: VFL | H3: GS26-326 | I3: DIS365 | J3: VFL2608001 | K3: 46237 | L3: =VLOOKUP(K3,'[8]Exchange Rate'!$A$3:$D$23,3,FALSE) -> 4047 | M3: =TEXT(K3,"dddd") -> Monday | N3: 280.21 | O3: 0 | P3: 0 | Q3: 50 | R3: 150 | S3: 27.21 | T3: =ROUND(R3*10%,2) -> 15 | U3: 324.68 | V3: =(R3+S3+U3)-(N3+O3+Q3+P3) -> 171.68
A4: PAID | B4: 1 | C4: =INDEX(PORT!$B$2:$B$20,MATCH('08'!B4,PORT!$A$2:$A$20)) -> PNH01 | D4: =INDEX(PORT!$C$2:$C$20,MATCH('08'!B4,PORT!$A$2:$A$20)) -> KTI AIR PORT | E4: E 35466 | F4: 46235 | G4: JIN YUAN XI | H4: GS26-327 | I4: DIS366 | J4: JYX2608001 | K4: 46237 | L4: =VLOOKUP(K4,'[8]Exchange Rate'!$A$3:$D$23,3,FALSE) -> 4047 | M4: =TEXT(K4,"dddd") -> Monday | N4: 262.49 | O4: 0 | P4: 0 | Q4: 50 | R4: 210 | S4: 142.49 | T4: =ROUND(R4*10%,2) -> 21 | U4: 180 | V4: =(R4+S4+U4)-(N4+O4+Q4+P4) -> 220
A5: PAID | B5: 21 | C5: =INDEX(PORT!$B$2:$B$20,MATCH('08'!B5,PORT!$A$2:$A$20)) -> PNH21 | D5: =INDEX(PORT!$C$2:$C$20,MATCH('08'!B5,PORT!$A$2:$A$20)) -> OLAIR DRY PORT | E5: I 1960 | F5: 46238 | G5: SPORTLINE | H5: GS26-328 | I5: DIS367 | J5: SAK2608001 | K5: 46239 | L5: =VLOOKUP(K5,'[8]Exchange Rate'!$A$3:$D$23,3,FALSE) -> 4053 | M5: =TEXT(K5,"dddd") -> Wednesday | N5: 135 | O5: 176 | P5: 0 | Q5: 50 | R5: 150 | S5: 201 | T5: =ROUND(R5*10%,2) -> 15 | U5: 159 | V5: =(R5+S5+U5)-(N5+O5+Q5+P5) -> 149
A6: PAID | B6: 21 | C6: =INDEX(PORT!$B$2:$B$20,MATCH('08'!B6,PORT!$A$2:$A$20)) -> PNH21 | D6: =INDEX(PORT!$C$2:$C$20,MATCH('08'!B6,PORT!$A$2:$A$20)) -> OLAIR DRY PORT | E6: I 1961 | F6: 46238 | G6: VFL | H6: GS26-329 | I6: DIS368 | J6: VFL2608002 | K6: 46239 | L6: =VLOOKUP(K6,'[8]Exchange Rate'!$A$3:$D$23,3,FALSE) -> 4053 | M6: =TEXT(K6,"dddd") -> Wednesday | N6: 112.7 | O6: 221.65 | P6: 0 | Q6: 50 | R6: 150 | S6: 247.35 | T6: =ROUND(R6*10%,2) -> 15 | U6: 109.5 | V6: =(R6+S6+U6)-(N6+O6+Q6+P6) -> 122.5
A7: PAID | B7: 1 | C7: =INDEX(PORT!$B$2:$B$20,MATCH('08'!B7,PORT!$A$2:$A$20)) -> PNH01 | D7: =INDEX(PORT!$C$2:$C$20,MATCH('08'!B7,PORT!$A$2:$A$20)) -> KTI AIR PORT | E7: I 23070 | F7: 46238 | G7: VFL | H7: GS26-330 | I7: DIS369 | J7: VFL2608003 | K7: 46239 | L7: =VLOOKUP(K7,'[8]Exchange Rate'!$A$3:$D$23,3,FALSE) -> 4053 | M7: =TEXT(K7,"dddd") -> Wednesday | N7: 481.52 | O7: 77 | P7: 0 | Q7: 50 | R7: 265 | S7: 363.52 | T7: =ROUND(R7*10%,2) -> 26.5 | U7: 314 | V7: =(R7+S7+U7)-(N7+O7+Q7+P7) -> 334
A8: PAID | B8: 1 | C8: =INDEX(PORT!$B$2:$B$20,MATCH('08'!B8,PORT!$A$2:$A$20)) -> PNH01 | D8: =INDEX(PORT!$C$2:$C$20,MATCH('08'!B8,PORT!$A$2:$A$20)) -> KTI AIR PORT | E8: E 36275 | F8: 46239 | G8: SPORTLINE | H8: GS26-331 | I8: DIS370 | J8: SAK2608002 | K8: 46240 | L8: =VLOOKUP(K8,'[8]Exchange Rate'!$A$3:$D$23,3,FALSE) -> 4055 | M8: =TEXT(K8,"dddd") -> Thursday | N8: 116.22 | O8: 0 | P8: 0 | Q8: 50 | R8: 150 | S8: 46.22 | T8: =ROUND(R8*10%,2) -> 15 | U8: 60 | V8: =(R8+S8+U8)-(N8+O8+Q8+P8) -> 90
A9: PAID | B9: 1 | C9: =INDEX(PORT!$B$2:$B$20,MATCH('08'!B9,PORT!$A$2:$A$20)) -> PNH01 | D9: =INDEX(PORT!$C$2:$C$20,MATCH('08'!B9,PORT!$A$2:$A$20)) -> KTI AIR PORT | E9: E 36285 | F9: 46239 | G9: SPORTLINE | H9: GS26-332 | I9: DIS371 | J9: SAK2608003 | K9: 46240 | L9: =VLOOKUP(K9,'[8]Exchange Rate'!$A$3:$D$23,3,FALSE) -> 4055 | M9: =TEXT(K9,"dddd") -> Thursday | N9: 106.89 | O9: 0 | P9: 0 | Q9: 50 | R9: 150 | S9: 36.89 | T9: =ROUND(R9*10%,2) -> 15 | U9: 60 | V9: =(R9+S9+U9)-(N9+O9+Q9+P9) -> 90
A10: PAID | B10: 1 | C10: =INDEX(PORT!$B$2:$B$20,MATCH('08'!B10,PORT!$A$2:$A$20)) -> PNH01 | D10: =INDEX(PORT!$C$2:$C$20,MATCH('08'!B10,PORT!$A$2:$A$20)) -> KTI AIR PORT | E10: I 23221 | F10: 46239 | G10: SPORTLINE | H10: GS26-333 | I10: DIS372 | J10: SAK2608004 | K10: 46240 | L10: =VLOOKUP(K10,'[8]Exchange Rate'!$A$3:$D$23,3,FALSE) -> 4055 | M10: =TEXT(K10,"dddd") -> Thursday | N10: 166.74 | O10: 0 | P10: 0 | Q10: 50 | R10: 150 | S10: 21.74 | T10: =ROUND(R10*10%,2) -> 15 | U10: 196.75 | V10: =(R10+S10+U10)-(N10+O10+Q10+P10) -> 151.75
A11: PAID | B11: 1 | C11: =INDEX(PORT!$B$2:$B$20,MATCH('08'!B11,PORT!$A$2:$A$20)) -> PNH01 | D11: =INDEX(PORT!$C$2:$C$20,MATCH('08'!B11,PORT!$A$2:$A$20)) -> KTI AIR PORT | E11: I 23273 | F11: 46239 | G11: VFL | H11: GS26-334 | I11: DIS373 | J11: VFL2608004 | K11: 46240 | L11: =VLOOKUP(K11,'[8]Exchange Rate'!$A$3:$D$23,3,FALSE) -> 4055 | M11: =TEXT(K11,"dddd") -> Thursday | N11: 158.5 | O11: 0 | P11: 0 | Q11: 50 | R11: 150 | S11: 23.5 | T11: =ROUND(R11*10%,2) -> 15 | U11: 130.75 | V11: =(R11+S11+U11)-(N11+O11+Q11+P11) -> 95.75
A12: PAID | B12: 1 | C12: =INDEX(PORT!$B$2:$B$20,MATCH('08'!B12,PORT!$A$2:$A$20)) -> PNH01 | D12: =INDEX(PORT!$C$2:$C$20,MATCH('08'!B12,PORT!$A$2:$A$20)) -> KTI AIR PORT | E12: E 36706 | F12: 46240 | G12: JIN YUAN XI | H12: GS26-335 | I12: DIS374 | J12: JYX2608002 | K12: 46241 | L12: =VLOOKUP(K12,'[8]Exchange Rate'!$A$3:$D$23,3,FALSE) -> 4054 | M12: =TEXT(K12,"dddd") -> Friday | N12: 252.2 | O12: 0 | P12: 0 | Q12: 50 | R12: 210 | S12: 132.2 | T12: =ROUND(R12*10%,2) -> 21 | U12: 180 | V12: =(R12+S12+U12)-(N12+O12+Q12+P12) -> 220
A13: PAID | B13: 11+ | C13: =INDEX(PORT!$B$2:$B$20,MATCH('08'!B13,PORT!$A$2:$A$20)) -> SVR11 | D13: =INDEX(PORT!$C$2:$C$20,MATCH('08'!B13,PORT!$A$2:$A$20)) -> BAVET CEO | E13: I 21609 | F13: 46242 | G13: VFL | H13: GS26-336 | I13: DIS375 | J13: VFL2608005 | K13: 46244 | L13: =VLOOKUP(K13,'[8]Exchange Rate'!$A$3:$D$23,3,FALSE) -> 4053 | M13: =TEXT(K13,"dddd") -> Monday | N13: 134 | O13: 0 | P13: 0 | Q13: 50 | R13: 230 | S13: 14 | T13: =ROUND(R13*10%,2) -> 23 | U13: 55 | V13: =(R13+S13+U13)-(N13+O13+Q13+P13) -> 115
A14: PAID | B14: 19 | C14: =INDEX(PORT!$B$2:$B$20,MATCH('08'!B14,PORT!$A$2:$A$20)) -> PNH19 | D14: =INDEX(PORT!$C$2:$C$20,MATCH('08'!B14,PORT!$A$2:$A$20)) -> TEC SRUN DRYPORT | E14: I 2792 | F14: 46244 | G14: VFL | H14: GS26-337 | I14: DIS376 | J14: VFL2608006 | K14: 46245 | L14: =VLOOKUP(K14,'[8]Exchange Rate'!$A$3:$D$23,3,FALSE) -> 4051 | M14: =TEXT(K14,"dddd") -> Tuesday | N14: 113.1 | O14: 222.92 | P14: 0 | Q14: 50 | R14: 150 | S14: 249.02 | T14: =ROUND(R14*10%,2) -> 15 | U14: 109.5 | V14: =(R14+S14+U14)-(N14+O14+Q14+P14) -> 122.5
A15: PAID | B15: 19 | C15: =INDEX(PORT!$B$2:$B$20,MATCH('08'!B15,PORT!$A$2:$A$20)) -> PNH19 | D15: =INDEX(PORT!$C$2:$C$20,MATCH('08'!B15,PORT!$A$2:$A$20)) -> TEC SRUN DRYPORT | E15: I 2793 | F15: 46244 | G15: SPORTLINE | H15: GS26-338 | I15: DIS377 | J15: SAK2608005 | K15: 46245 | L15: =VLOOKUP(K15,'[8]Exchange Rate'!$A$3:$D$23,3,FALSE) -> 4051 | M15: =TEXT(K15,"dddd") -> Tuesday | N15: 136.1 | O15: 193.6 | P15: 0 | Q15: 50 | R15: 150 | S15: 219.7 | T15: =ROUND(R15*10%,2) -> 15 | U15: 159 | V15: =(R15+S15+U15)-(N15+O15+Q15+P15) -> 149
A16: PAID | B16: 1 | C16: =INDEX(PORT!$B$2:$B$20,MATCH('08'!B16,PORT!$A$2:$A$20)) -> PNH01 | D16: =INDEX(PORT!$C$2:$C$20,MATCH('08'!B16,PORT!$A$2:$A$20)) -> KTI AIR PORT | E16: E 38165 | F16: 46246 | G16: JIN YUAN XI | H16: GS26-339 | I16: DIS378 | J16: JYX2608003 | K16: 46247 | L16: =VLOOKUP(K16,'[8]Exchange Rate'!$A$3:$D$23,3,FALSE) -> 4046 | M16: =TEXT(K16,"dddd") -> Thursday | N16: 143.06 | O16: 0 | P16: 0 | Q16: 50 | R16: 175 | S16: 72.8 | T16: =ROUND(R16*10%,2) -> 17.5 | U16: 180 | V16: =(R16+S16+U16)-(N16+O16+Q16+P16) -> 234.74
A17: PAID | B17: 1 | C17: =INDEX(PORT!$B$2:$B$20,MATCH('08'!B17,PORT!$A$2:$A$20)) -> PNH01 | D17: =INDEX(PORT!$C$2:$C$20,MATCH('08'!B17,PORT!$A$2:$A$20)) -> KTI AIR PORT | E17: E 38185 | F17: 46246 | G17: JIN YUAN XI | H17: GS26-340 | I17: DIS379 | J17: JYX2608004 | K17: 46247 | L17: =VLOOKUP(K17,'[8]Exchange Rate'!$A$3:$D$23,3,FALSE) -> 4046 | M17: =TEXT(K17,"dddd") -> Thursday | N17: 143.06 | O17: 0 | P17: 0 | Q17: 50 | R17: 175 | S17: 73.06 | T17: =ROUND(R17*10%,2) -> 17.5 | U17: 60 | V17: =(R17+S17+U17)-(N17+O17+Q17+P17) -> 115
A18: PAID | B18: 11 | C18: =INDEX(PORT!$B$2:$B$20,MATCH('08'!B18,PORT!$A$2:$A$20)) -> SHV11 | D18: =INDEX(PORT!$C$2:$C$20,MATCH('08'!B18,PORT!$A$2:$A$20)) -> SHV PORT | E18: I 117276 | F18: 46246 | G18: VFL | H18: GS26-341 | I18: DIS380 | J18: VFL2608007 | K18: 46247 | L18: =VLOOKUP(K18,'[8]Exchange Rate'!$A$3:$D$23,3,FALSE) -> 4046 | M18: =TEXT(K18,"dddd") -> Thursday | N18: 262.17 | O18: 577.06 | P18: 0 | Q18: 50 | R18: 150 | S18: 599.23 | T18: =ROUND(R18*10%,2) -> 15 | U18: 283.4 | V18: =(R18+S18+U18)-(N18+O18+Q18+P18) -> 143.4
A19: PAID | B19: 4 | C19: =INDEX(PORT!$B$2:$B$20,MATCH('08'!B19,PORT!$A$2:$A$20)) -> PNH04 | D19: =INDEX(PORT!$C$2:$C$20,MATCH('08'!B19,PORT!$A$2:$A$20)) -> PNH PORT | E19: E 241907 | F19: 46248 | G19: SPORTLINE | H19: GS26-342 | I19: DIS381 | J19: SAK2608006 | K19: 46251 | L19: =VLOOKUP(K19,'[8]Exchange Rate'!$A$3:$D$23,3,FALSE) -> 4044 | M19: =TEXT(K19,"dddd") -> Monday | N19: 995.85 | O19: 0 | P19: 0 | Q19: 50 | R19: 460 | S19: 245.85 | T19: =ROUND(R19*10%,2) -> 46 | U19: 1051.5 | V19: =(R19+S19+U19)-(N19+O19+Q19+P19) -> 711.5
A20: PAID | B20: 4 | C20: =INDEX(PORT!$B$2:$B$20,MATCH('08'!B20,PORT!$A$2:$A$20)) -> PNH04 | D20: =INDEX(PORT!$C$2:$C$20,MATCH('08'!B20,PORT!$A$2:$A$20)) -> PNH PORT | E20: E 245475 | F20: 46248 | G20: VFL | H20: GS26-343 | I20: DIS382 | J20: VFL2608008 | K20: 46251 | L20: =VLOOKUP(K20,'[8]Exchange Rate'!$A$3:$D$23,3,FALSE) -> 4044 | M20: =TEXT(K20,"dddd") -> Monday | N20: 408.75 | O20: 0 | P20: 0 | Q20: 50 | R20: 215 | S20: 111.75 | T20: =ROUND(R20*10%,2) -> 21.5 | U20: 465 | V20: =(R20+S20+U20)-(N20+O20+Q20+P20) -> 333
A21: PAID | B21: 1 | C21: =INDEX(PORT!$B$2:$B$20,MATCH('08'!B21,PORT!$A$2:$A$20)) -> PNH01 | D21: =INDEX(PORT!$C$2:$C$20,MATCH('08'!B21,PORT!$A$2:$A$20)) -> KTI AIR PORT | E21: E 39116 | F21: 46249 | G21: JIN YUAN XI | H21: GS26-344 | I21: DIS383 | J21: JYX2608005 | K21: 46251 | L21: =VLOOKUP(K21,'[8]Exchange Rate'!$A$3:$D$23,3,FALSE) -> 4044 | M21: =TEXT(K21,"dddd") -> Monday | N21: 142.53 | O21: 0 | P21: 0 | Q21: 50 | R21: 175 | S21: 72.53 | T21: =ROUND(R21*10%,2) -> 17.5 | U21: 60 | V21: =(R21+S21+U21)-(N21+O21+Q21+P21) -> 115
A22: PAID | B22: 21 | C22: =INDEX(PORT!$B$2:$B$20,MATCH('08'!B22,PORT!$A$2:$A$20)) -> PNH21 | D22: =INDEX(PORT!$C$2:$C$20,MATCH('08'!B22,PORT!$A$2:$A$20)) -> OLAIR DRY PORT | E22: I 2063 | F22: 46252 | G22: VFL | H22: GS26-345 | I22: DIS384 | J22: VFL2608009 | K22: 46253 | L22: =VLOOKUP(K22,'[8]Exchange Rate'!$A$3:$D$23,3,FALSE) -> 4043 | M22: =TEXT(K22,"dddd") -> Wednesday | N22: 117.08 | O22: 242 | P22: 0 | Q22: 50 | R22: 150 | S22: 272.08 | T22: =ROUND(R22*10%,2) -> 15 | U22: 109.5 | V22: =(R22+S22+U22)-(N22+O22+Q22+P22) -> 122.5
A23: PAID | B23: 1 | C23: =INDEX(PORT!$B$2:$B$20,MATCH('08'!B23,PORT!$A$2:$A$20)) -> PNH01 | D23: =INDEX(PORT!$C$2:$C$20,MATCH('08'!B23,PORT!$A$2:$A$20)) -> KTI AIR PORT | E23: E 40020 | F23: 46253 | G23: JIN YUAN XI | H23: GS26-346 | I23: DIS385 | J23: JYX2608006 | K23: 46254 | L23: =VLOOKUP(K23,'[8]Exchange Rate'!$A$3:$D$23,3,FALSE) -> 4044 | M23: =TEXT(K23,"dddd") -> Thursday | N23: 182.41 | O23: 0 | P23: 0 | Q23: 50 | R23: 175 | S23: 62.41 | T23: =ROUND(R23*10%,2) -> 17.5 | U23: 180 | V23: =(R23+S23+U23)-(N23+O23+Q23+P23) -> 185
A24: PAID | B24: 11 | C24: =INDEX(PORT!$B$2:$B$20,MATCH('08'!B24,PORT!$A$2:$A$20)) -> SHV11 | D24: =INDEX(PORT!$C$2:$C$20,MATCH('08'!B24,PORT!$A$2:$A$20)) -> SHV PORT | E24: I 120893 | F24: 46254 | G24: JR | H24: GS26-347 | I24: DIS386 | J24: JR2608001 | K24: 46255 | L24: =VLOOKUP(K24,'[8]Exchange Rate'!$A$3:$D$23,3,FALSE) -> 4046 | M24: =TEXT(K24,"dddd") -> Friday | N24: 612.45 | O24: 464 | P24: 0 | Q24: 0 | R24: 180 | S24: 545.45 | T24: =ROUND(R24*10%,2) -> 18 | U24: 687 | V24: =(R24+S24+U24)-(N24+O24+Q24+P24) -> 336
A25: PAID | B25: 11 | C25: =INDEX(PORT!$B$2:$B$20,MATCH('08'!B25,PORT!$A$2:$A$20)) -> SHV11 | D25: =INDEX(PORT!$C$2:$C$20,MATCH('08'!B25,PORT!$A$2:$A$20)) -> SHV PORT | E25: I 122050 | F25: 46255 | G25: JR | H25: GS26-348 | I25: DIS387 | J25: JR2608002 | K25: 46258 | L25: =VLOOKUP(K25,'[8]Exchange Rate'!$A$3:$D$23,3,FALSE) -> 4047 | M25: =TEXT(K25,"dddd") -> Monday | N25: 982.45 | O25: 355 | P25: 0 | Q25: 0 | R25: 180 | S25: 436.45 | T25: =ROUND(R25*10%,2) -> 18 | U25: 1202 | V25: =(R25+S25+U25)-(N25+O25+Q25+P25) -> 481
... A28: PAID | B28: 1 | C28: =INDEX(PORT!$B$2:$B$20,MATCH('08'!B28,PORT!$A$2:$A$20)) -> PNH01 | D28: =INDEX(PORT!$C$2:$C$20,MATCH('08'!B28,PORT!$A$2:$A$20)) -> KTI AIR PORT | E28: I 25544 | F28: 46259 | G28: VFL | H28: GS26-351 | I28: DIS390 | J28: VFL2608011 | K28: 46260 | L28: =VLOOKUP(K28,'[8]Exchange Rate'!$A$3:$D$23,3,FALSE) -> 4047 | M28: =TEXT(K28,"dddd") -> Wednesday | N28: 178.48 | O28: 0 | P28: 0 | Q28: 50 | R28: 150 | S28: 43.48 | T28: =ROUND(R28*10%,2) -> 15 | U28: 130.75 | V28: =(R28+S28+U28)-(N28+O28+Q28+P28) -> 95.75
A29: PAID | B29: 4 | C29: =INDEX(PORT!$B$2:$B$20,MATCH('08'!B29,PORT!$A$2:$A$20)) -> PNH04 | D29: =INDEX(PORT!$C$2:$C$20,MATCH('08'!B29,PORT!$A$2:$A$20)) -> PNH PORT | E29: E 256765 | F29: 46260 | G29: JR | H29: GS26-352 | I29: DIS391 | J29: JR2608004 | K29: 46261 | L29: =VLOOKUP(K29,'[8]Exchange Rate'!$A$3:$D$23,3,FALSE) -> 4046 | M29: =TEXT(K29,"dddd") -> Thursday | N29: 528.25 | O29: 505.5 | P29: 0 | Q29: 0 | R29: 242 | S29: 603.75 | T29: =ROUND(R29*10%,2) -> 24.2 | U29: 703 | V29: =(R29+S29+U29)-(N29+O29+Q29+P29) -> 515 | W29: PENDING BILL FEE FROM OPERATION
A30: PAID | B30: 1 | C30: =INDEX(PORT!$B$2:$B$20,MATCH('08'!B30,PORT!$A$2:$A$20)) -> PNH01 | D30: =INDEX(PORT!$C$2:$C$20,MATCH('08'!B30,PORT!$A$2:$A$20)) -> KTI AIR PORT | E30: E 41922 | F30: 46260 | G30: JIN YUAN XI | H30: GS26-353 | I30: DIS392 | J30: JYX2608007 | K30: 46261 | L30: =VLOOKUP(K30,'[8]Exchange Rate'!$A$3:$D$23,3,FALSE) -> 4046 | M30: =TEXT(K30,"dddd") -> Thursday | N30: 132.41 | O30: 0 | P30: 0 | Q30: 50 | R30: 175 | S30: 62.41 | T30: =ROUND(R30*10%,2) -> 17.5 | U30: 60 | V30: =(R30+S30+U30)-(N30+O30+Q30+P30) -> 115
A31: PAID | B31: 4 | C31: =INDEX(PORT!$B$2:$B$20,MATCH('08'!B31,PORT!$A$2:$A$20)) -> PNH04 | D31: =INDEX(PORT!$C$2:$C$20,MATCH('08'!B31,PORT!$A$2:$A$20)) -> PNH PORT | E31: E 257554 | F31: 46261 | G31: SPORTLINE | H31: GS26-354 | I31: DIS393 | J31: SAK2608007 | K31: 46262 | L31: =VLOOKUP(K31,'[8]Exchange Rate'!$A$3:$D$23,3,FALSE) -> 4046 | M31: =TEXT(K31,"dddd") -> Friday | N31: 547.75 | O31: 0 | P31: 0 | Q31: 50 | R31: 245 | S31: 147.75 | T31: =ROUND(R31*10%,2) -> 24.5 | U31: 574 | V31: =(R31+S31+U31)-(N31+O31+Q31+P31) -> 369
A32: PAID | B32: 11 | C32: =INDEX(PORT!$B$2:$B$20,MATCH('08'!B32,PORT!$A$2:$A$20)) -> SHV11 | D32: =INDEX(PORT!$C$2:$C$20,MATCH('08'!B32,PORT!$A$2:$A$20)) -> SHV PORT | E32: I 125081 | F32: 46262 | G32: VFL | H32: GS26-355 | I32: DIS394 | J32: VFL2608012 | K32: 46265 | L32: =VLOOKUP(K32,'[8]Exchange Rate'!$A$3:$D$23,3,FALSE) -> 4047 | M32: =TEXT(K32,"dddd") -> Monday | N32: 179.12 | O32: 292.12 | P32: 0 | Q32: 50 | R32: 150 | S32: 309.24 | T32: =ROUND(R32*10%,2) -> 15 | U32: 145.05 | V32: =(R32+S32+U32)-(N32+O32+Q32+P32) -> 83.05
A33: PAID | B33: 1 | C33: =INDEX(PORT!$B$2:$B$20,MATCH('08'!B33,PORT!$A$2:$A$20)) -> PNH01 | D33: =INDEX(PORT!$C$2:$C$20,MATCH('08'!B33,PORT!$A$2:$A$20)) -> KTI AIR PORT | E33: I 25898 | F33: 46262 | G33: JIN YUAN XI | H33: GS26-356 | I33: DIS395 | J33: JYX2608008 | K33: 46265 | L33: =VLOOKUP(K33,'[8]Exchange Rate'!$A$3:$D$23,3,FALSE) -> 4047 | M33: =TEXT(K33,"dddd") -> Monday | N33: 249.38 | O33: 0 | P33: 0 | Q33: 50 | R33: 150 | S33: 49.38 | T33: =ROUND(R33*10%,2) -> 15 | U33: 230.75 | V33: =(R33+S33+U33)-(N33+O33+Q33+P33) -> 130.75 | W33: 112-09026533
A34: PAID | B34: 1 | C34: =INDEX(PORT!$B$2:$B$20,MATCH('08'!B34,PORT!$A$2:$A$20)) -> PNH01 | D34: =INDEX(PORT!$C$2:$C$20,MATCH('08'!B34,PORT!$A$2:$A$20)) -> KTI AIR PORT | E34: E 42843 | F34: 46265 | G34: SPORTLINE | H34: GS26-357 | I34: DIS396 | J34: SAK2608008 | K34: 46265 | L34: =VLOOKUP(K34,'[8]Exchange Rate'!$A$3:$D$23,3,FALSE) -> 4047 | M34: =TEXT(K34,"dddd") -> Monday | N34: 95.81 | O34: 0 | P34: 0 | Q34: 50 | R34: 140 | S34: 25.81 | T34: =ROUND(R34*10%,2) -> 14 | U34: 60 | V34: =(R34+S34+U34)-(N34+O34+Q34+P34) -> 80
B35: 4 | C35: =INDEX(PORT!$B$2:$B$20,MATCH('08'!B35,PORT!$A$2:$A$20)) -> PNH04 | D35: =INDEX(PORT!$C$2:$C$20,MATCH('08'!B35,PORT!$A$2:$A$20)) -> PNH PORT | E35: E 241838 | F35: 46248 | G35: JR | I35: DIS397 | J35: JR2608005 | K35: 46265 | L35: =VLOOKUP(K35,'[8]Exchange Rate'!$A$3:$D$23,3,FALSE) -> 4047 | M35: =TEXT(K35,"dddd") -> Monday | N35: 0 | O35: 1280.01 | P35: 0 | Q35: 0 | R35: 0 | S35: 1280.01 | T35: =ROUND(R35*10%,2) -> 0 | U35: 174 | V35: =(R35+S35+U35)-(N35+O35+Q35+P35) -> 174
B36: 4 | C36: =INDEX(PORT!$B$2:$B$20,MATCH('08'!B36,PORT!$A$2:$A$20)) -> PNH04 | D36: =INDEX(PORT!$C$2:$C$20,MATCH('08'!B36,PORT!$A$2:$A$20)) -> PNH PORT | E36: E 245477 | F36: 46248 | G36: JR | I36: DIS398 | J36: JR2608006 | K36: 46265 | L36: =VLOOKUP(K36,'[8]Exchange Rate'!$A$3:$D$23,3,FALSE) -> 4047 | M36: =TEXT(K36,"dddd") -> Monday | N36: 0 | O36: 557.75 | P36: 0 | Q36: 0 | R36: 0 | S36: 557.75 | T36: =ROUND(R36*10%,2) -> 0 | U36: 160 | V36: =(R36+S36+U36)-(N36+O36+Q36+P36) -> 160
B37: 4 | C37: =INDEX(PORT!$B$2:$B$20,MATCH('08'!B37,PORT!$A$2:$A$20)) -> PNH04 | D37: =INDEX(PORT!$C$2:$C$20,MATCH('08'!B37,PORT!$A$2:$A$20)) -> PNH PORT | E37: E 251185 | F37: 46255 | G37: JR | I37: DIS399 | J37: JR2608007 | K37: 46265 | L37: =VLOOKUP(K37,'[8]Exchange Rate'!$A$3:$D$23,3,FALSE) -> 4047 | M37: =TEXT(K37,"dddd") -> Monday | N37: 0 | O37: 708.15 | P37: 100 | Q37: 0 | R37: 0 | S37: 708.15 | T37: =ROUND(R37*10%,2) -> 0 | U37: 529.5 | V37: =(R37+S37+U37)-(N37+O37+Q37+P37) -> 429.5 | W37: pay to moc OFFICER 100 this invoice wrong q'ty of PCS
B38: 4 | C38: =INDEX(PORT!$B$2:$B$20,MATCH('08'!B38,PORT!$A$2:$A$20)) -> PNH04 | D38: =INDEX(PORT!$C$2:$C$20,MATCH('08'!B38,PORT!$A$2:$A$20)) -> PNH PORT | E38: E 259225 | G38: JR | I38: DIS400 | J38: JR2608008 | K38: 46265 | L38: =VLOOKUP(K38,'[8]Exchange Rate'!$A$3:$D$23,3,FALSE) -> 4047 | M38: =TEXT(K38,"dddd") -> Monday | N38: 0 | O38: 374.65 | P38: 0 | Q38: 0 | R38: 0 | S38: 374.65 | T38: =ROUND(R38*10%,2) -> 0 | U38: 141.5 | V38: =(R38+S38+U38)-(N38+O38+Q38+P38) -> 141.5
G39: JR | J39: JR2608009 | K39: 46265 | L39: =VLOOKUP(K39,'[8]Exchange Rate'!$A$3:$D$23,3,FALSE) -> 4047 | M39: =TEXT(K39,"dddd") -> Monday | N39: 0 | O39: 0 | P39: 0 | Q39: 0 | R39: 0 | S39: 0 | T39: =ROUND(R39*10%,2) -> 0 | U39: 265 | V39: =(R39+S39+U39)-(N39+O39+Q39+P39) -> 265 | W39: MIH CHARGE FROM JAN TO AUG-2026
E40: LOLO
E41: STORAGE
E42: THC
B44: =SUBTOTAL(3,B3:B43) -> 36 | E44: TOTAL: | H44: =SUBTOTAL(3,H3:H43) -> 32 | I44: =SUBTOTAL(3,I3:I43) -> 36 | J44: =SUBTOTAL(3,J3:J43) -> 37 | N44: =SUM(N3:N43) -> 9131.6 | O44: =SUBTOTAL(9,O3:O39) -> 7347.22 | P44: =SUBTOTAL(9,P3:P39) -> 100 | Q44: =SUBTOTAL(9,Q3:Q40) -> 1400 | R44: =SUBTOTAL(9,R3:R38) -> 5902 | S44: =SUBTOTAL(9,S3:S39) -> 9630.81 | T44: =SUBTOTAL(9,T3:T39) -> 590.2 | U44: =SUBTOTAL(9,U3:U39) -> 10513.38 | V44: =SUBTOTAL(9,V3:V40) -> 8067.37
M45: PAID | N45: =SUMIFS($N$3:$N$41,$A$3:$A$41,$M$45)-O46 -> 9131.6
M46: NOT YET | N46: =SUMIFS($N$3:$N$41,$A$3:$A$41,$M$46) -> 0
J51: PAID ON: 13/8/26 | L51: 10000
J52: OVERPAYMENT: | L52: =L51-N45 -> 868.4
J53: SHOULD PAY | L53: =N46-L51 -> -10000

Sheet 09
E1: REVENUE & EXPENSE | M1: Saturday
A2: CHEA PAYMENT | B2: PORT NUMBER | C2: PORT CODE | D2: PORT NAME | E2: DECLARE | F2: DATE | G2: CLIENT | H2: INV | I2: DISBURSEMENT | J2: DN | K2: INV, DIS, DN DATE | L2: EXCHANGE RATE | M2: weekday | N2: CLEAR FEE | O2: THC | P2: OTHER PAY | Q2: CM | R2: INV (REVENUE) | S2: REIM | T2: VAT 10% | U2: DN | V2: NET PROFIT | W2: MARK
A3: NOT YET | B3: 1 | C3: =INDEX(PORT!$B$2:$B$20,MATCH('09'!B3,PORT!$A$2:$A$20)) -> PNH01 | D3: =INDEX(PORT!$C$2:$C$20,MATCH('09'!B3,PORT!$A$2:$A$20)) -> KTI AIR PORT | E3: I 26400 | F3: 46267 | G3: VFL | H3: GS26-358 | I3: DIS401 | J3: VFL2609001 | K3: 46268 | L3: =VLOOKUP(K3,'[9]Exchange Rate'!$A$3:$D$26,3,FALSE) -> 4047 | M3: =TEXT(K3,"dddd") -> Thursday | N3: 172.23 | O3: 0 | P3: 0 | Q3: 50 | V3: =(R3+S3+U3)-(N3+O3+Q3+P3) -> -222.23
A4: NOT YET | B4: 4 | C4: =INDEX(PORT!$B$2:$B$20,MATCH('09'!B4,PORT!$A$2:$A$20)) -> PNH04 | D4: =INDEX(PORT!$C$2:$C$20,MATCH('09'!B4,PORT!$A$2:$A$20)) -> PNH PORT | E4: E 264560 | F4: 46267 | G4: VFL | H4: GS26-359 | I4: DIS402 | J4: VFL2609002 | K4: 46268 | L4: =VLOOKUP(K4,'[9]Exchange Rate'!$A$3:$D$26,3,FALSE) -> 4047 | M4: =TEXT(K4,"dddd") -> Thursday | N4: 440.25 | O4: 0 | Q4: 50 | V4: =(R4+S4+U4)-(N4+O4+Q4+P4) -> -490.25
A5: NOT YET | B5: 4 | C5: =INDEX(PORT!$B$2:$B$20,MATCH('09'!B5,PORT!$A$2:$A$20)) -> PNH04 | D5: =INDEX(PORT!$C$2:$C$20,MATCH('09'!B5,PORT!$A$2:$A$20)) -> PNH PORT | E5: E 264562 | F5: 46267 | G5: JR | H5: GS26-360 | I5: DIS403 | J5: JR2609001 | K5: 46268 | L5: =VLOOKUP(K5,'[9]Exchange Rate'!$A$3:$D$26,3,FALSE) -> 4047 | M5: =TEXT(K5,"dddd") -> Thursday | N5: 532.75 | O5: 539 | P5: 0 | Q5: 0 | V5: =(R5+S5+U5)-(N5+O5+Q5+P5) -> -1071.75
A6: NOT YET | B6: 1 | C6: =INDEX(PORT!$B$2:$B$20,MATCH('09'!B6,PORT!$A$2:$A$20)) -> PNH01 | D6: =INDEX(PORT!$C$2:$C$20,MATCH('09'!B6,PORT!$A$2:$A$20)) -> KTI AIR PORT | E6: E 44677 | F6: 46272 | G6: SPORTLINE | H6: GS26-361 | I6: DIS404 | J6: SAK2609001 | K6: 46273 | L6: =VLOOKUP(K6,'[9]Exchange Rate'!$A$3:$D$26,3,FALSE) -> 4050 | M6: =TEXT(K6,"dddd") -> Tuesday | N6: 122.29 | O6: 0 | P6: 0 | Q6: 50 | V6: =(R6+S6+U6)-(N6+O6+Q6+P6) -> -172.29
A7: NOT YET | B7: 1 | C7: =INDEX(PORT!$B$2:$B$20,MATCH('09'!B7,PORT!$A$2:$A$20)) -> PNH01 | D7: =INDEX(PORT!$C$2:$C$20,MATCH('09'!B7,PORT!$A$2:$A$20)) -> KTI AIR PORT | E7: E 44700 | F7: 46272 | G7: SPORTLINE | H7: GS26-362 | I7: DIS405 | J7: SAK2609002 | K7: 46273 | L7: =VLOOKUP(K7,'[9]Exchange Rate'!$A$3:$D$26,3,FALSE) -> 4050 | M7: =TEXT(K7,"dddd") -> Tuesday | N7: 120.45 | O7: 0 | Q7: 50 | V7: =(R7+S7+U7)-(N7+O7+Q7+P7) -> -170.45
A8: NOT YET | D8: CHAY DA CEO | E8: I 1970 | F8: 46272 | G8: SPORTLINE | H8: GS26-363 | I8: DIS406 | J8: SAK2609003 | K8: 46273 | L8: =VLOOKUP(K8,'[9]Exchange Rate'!$A$3:$D$26,3,FALSE) -> 4050 | M8: =TEXT(K8,"dddd") -> Tuesday | N8: 165.56 | O8: 235.29 | Q8: 50 | V8: =(R8+S8+U8)-(N8+O8+Q8+P8) -> -450.85
A9: NOT YET | D9: CHAY DA CEO | E9: I 1971 | F9: 46272 | G9: VFL | H9: GS26-364 | I9: DIS407 | J9: VFL2609003 | K9: 46273 | L9: =VLOOKUP(K9,'[9]Exchange Rate'!$A$3:$D$26,3,FALSE) -> 4050 | M9: =TEXT(K9,"dddd") -> Tuesday | N9: 142.93 | O9: 247.17 | Q9: 50 | V9: =(R9+S9+U9)-(N9+O9+Q9+P9) -> -440.1
A10: NOT YET | B10: 11 | C10: =INDEX(PORT!$B$2:$B$20,MATCH('09'!B10,PORT!$A$2:$A$20)) -> SHV11 | D10: =INDEX(PORT!$C$2:$C$20,MATCH('09'!B10,PORT!$A$2:$A$20)) -> SHV PORT | E10: I 129538 | F10: 46272 | G10: VFL | H10: GS26-365 | I10: DIS408 | J10: VFL2609004 | K10: 46273 | L10: =VLOOKUP(K10,'[9]Exchange Rate'!$A$3:$D$26,3,FALSE) -> 4050 | M10: =TEXT(K10,"dddd") -> Tuesday | N10: 155.12 | O10: 298.08 | Q10: 50 | V10: =(R10+S10+U10)-(N10+O10+Q10+P10) -> -503.2
A11: NOT YET | B11: 4 | C11: =INDEX(PORT!$B$2:$B$20,MATCH('09'!B11,PORT!$A$2:$A$20)) -> PNH04 | D11: =INDEX(PORT!$C$2:$C$20,MATCH('09'!B11,PORT!$A$2:$A$20)) -> PNH PORT | E11: E 272714 | F11: 46274 | G11: JR | H11: GS26-366 | I11: DIS409 | J11: JR2609002 | K11: 46275 | L11: =VLOOKUP(K11,'[9]Exchange Rate'!$A$3:$D$26,3,FALSE) -> 4052 | M11: =TEXT(K11,"dddd") -> Thursday | N11: 532.75 | O11: 266.2 | P11: 0 | Q11: 0 | V11: =(R11+S11+U11)-(N11+O11+Q11+P11) -> -798.95
A12: NOT YET | B12: 11 | C12: =INDEX(PORT!$B$2:$B$20,MATCH('09'!B12,PORT!$A$2:$A$20)) -> SHV11 | D12: =INDEX(PORT!$C$2:$C$20,MATCH('09'!B12,PORT!$A$2:$A$20)) -> SHV PORT | E12: I 130973 | F12: 46274 | G12: VFL | H12: GS26-367 | I12: DIS410 | J12: VFL2609005 | K12: 46275 | L12: =VLOOKUP(K12,'[9]Exchange Rate'!$A$3:$D$26,3,FALSE) -> 4052 | M12: =TEXT(K12,"dddd") -> Thursday | N12: 336.58 | O12: 747.34 | Q12: 50 | V12: =(R12+S12+U12)-(N12+O12+Q12+P12) -> -1133.92
A13: NOT YET | B13: 4 | C13: =INDEX(PORT!$B$2:$B$20,MATCH('09'!B13,PORT!$A$2:$A$20)) -> PNH04 | D13: =INDEX(PORT!$C$2:$C$20,MATCH('09'!B13,PORT!$A$2:$A$20)) -> PNH PORT | E13: E 273634 | F13: 46275 | G13: SPORTLINE | H13: GS26-368 | I13: DIS411 | J13: SAK2609004 | K13: 46276 | L13: =VLOOKUP(K13,'[9]Exchange Rate'!$A$3:$D$26,3,FALSE) -> 4052 | M13: =TEXT(K13,"dddd") -> Friday | N13: 547.75 | O13: 0 | Q13: 50 | V13: =(R13+S13+U13)-(N13+O13+Q13+P13) -> -597.75
A14: NOT YET | B14: 4 | C14: =INDEX(PORT!$B$2:$B$20,MATCH('09'!B14,PORT!$A$2:$A$20)) -> PNH04 | D14: =INDEX(PORT!$C$2:$C$20,MATCH('09'!B14,PORT!$A$2:$A$20)) -> PNH PORT | E14: E 273293 | F14: 46275 | G14: VFL | H14: GS26-369 | I14: DIS412 | J14: VFL2609006 | K14: 46276 | L14: =VLOOKUP(K14,'[9]Exchange Rate'!$A$3:$D$26,3,FALSE) -> 4052 | M14: =TEXT(K14,"dddd") -> Friday | N14: 440.25 | O14: 0 | Q14: 50 | V14: =(R14+S14+U14)-(N14+O14+Q14+P14) -> -490.25
A15: NOT YET | B15: 4 | C15: =INDEX(PORT!$B$2:$B$20,MATCH('09'!B15,PORT!$A$2:$A$20)) -> PNH04 | D15: =INDEX(PORT!$C$2:$C$20,MATCH('09'!B15,PORT!$A$2:$A$20)) -> PNH PORT | E15: E 275226 | F15: 46276 | G15: JR | H15: GS26-370 | I15: DIS413 | J15: JR2609003 | K15: 46279 | L15: =VLOOKUP(K15,'[9]Exchange Rate'!$A$3:$D$26,3,FALSE) -> 4052 | M15: =TEXT(K15,"dddd") -> Monday | N15: 532.75 | O15: 539 | P15: 0 | Q15: 0 | V15: =(R15+S15+U15)-(N15+O15+Q15+P15) -> -1071.75
A16: NOT YET | B16: 1 | C16: =INDEX(PORT!$B$2:$B$20,MATCH('09'!B16,PORT!$A$2:$A$20)) -> PNH01 | D16: =INDEX(PORT!$C$2:$C$20,MATCH('09'!B16,PORT!$A$2:$A$20)) -> KTI AIR PORT | E16: I 27394 | F16: 46276 | G16: VFL | H16: GS26-371 | I16: DIS414 | J16: VFL2609007 | K16: 46279 | L16: =VLOOKUP(K16,'[9]Exchange Rate'!$A$3:$D$26,3,FALSE) -> 4052 | M16: =TEXT(K16,"dddd") -> Monday | N16: 108.15 | O16: 0 | Q16: 50 | V16: =(R16+S16+U16)-(N16+O16+Q16+P16) -> -158.15
